Workbook

Sheet Planejamento
B1: | PROGRAMAÇÃO DA ESTAÇÃO REPRODUTIVA
AI2: Estação | AM2: Nasacimento | AS2: Desmama | AW2: Seca
B3: Programação da estação | E3: CALENDÁRIO REPRODUTIVO PROGRAMADO | AH3: =MONTH(AI3) -> 11 | AI3: =C6 -> 45597 | AJ3: =IF(AND(AI3>=$C$6,AI3<=$C$8),"Ok","Não") -> Ok | AL3: =MONTH(AM3) -> 8 | AM3: =C9 -> 45877 | AN3: =IF(AND(AM3>=$C$9,AM3<=$C$10),"Ok","Não") -> Ok | AR3: =MONTH(AS3) -> 3 | AS3: =C11 -> 46087 | AT3: =IF(AND(AS3>=$C$11,AS3<=$C$12),"Ok","Não") -> Ok | AV3: =MONTH(AW3) -> 4 | AW3: =C4 -> 45383 | AX3: =IF(AND(AW3>=$C$4,AW3<=$C$5),"Ok","Não") -> Ok
B4: Início da seca | C4: 45383 | E4: Meses | F4: J | G4: A | H4: S | I4: O | J4: N | K4: D | L4: J | M4: F | N4: M | O4: A | P4: M | Q4: J | AH4: =MONTH(AI4) -> 11 | AI4: =AI3+1 -> 45598 | AJ4: =IF(AND(AI4>=$C$6,AI4<=$C$8),"Ok","Não") -> Ok | AL4: =MONTH(AM4) -> 8 | AM4: =AM3+1 -> 45878 | AN4: =IF(AND(AM4>=$C$9,AM4<=$C$10),"Ok","Não") -> Ok | AR4: =MONTH(AS4) -> 3 | AS4: =AS3+1 -> 46088 | AT4: =IF(AND(AS4>=$C$11,AS4<=$C$12),"Ok","Não") -> Ok | AV4: =MONTH(AW4) -> 4 | AW4: =AW3+1 -> 45384 | AX4: =IF(AND(AW4>=$C$4,AW4<=$C$5),"Ok","Não") -> Ok
B5: Final da seca | C5: 45580 | E5: Chuva/seca | F5: =VLOOKUP(S6,$S$8:$W$19,5,0) -> Ok | G5: =VLOOKUP(T6,$S$8:$W$19,5,0) -> Ok | H5: =VLOOKUP(U6,$S$8:$W$19,5,0) -> Ok | I5: =VLOOKUP(V6,$S$8:$W$19,5,0) -> Ok | J5: =VLOOKUP(W6,$S$8:$W$19,5,0) -> Não | K5: =VLOOKUP(X6,$S$8:$W$19,5,0) -> Não | L5: =VLOOKUP(Y6,$S$8:$W$19,5,0) -> Não | M5: =VLOOKUP(Z6,$S$8:$W$19,5,0) -> Não | ... Q5: =VLOOKUP(AD6,$S$8:$W$19,5,0) -> Ok | AH5: =MONTH(AI5) -> 11 | AI5: =AI4+1 -> 45599 | AJ5: =IF(AND(AI5>=$C$6,AI5<=$C$8),"Ok","Não") -> Ok | AL5: =MONTH(AM5) -> 8 | AM5: =AM4+1 -> 45879 | AN5: =IF(AND(AM5>=$C$9,AM5<=$C$10),"Ok","Não") -> Ok | AR5: =MONTH(AS5) -> 3 | AS5: =AS4+1 -> 46089 | AT5: =IF(AND(AS5>=$C$11,AS5<=$C$12),"Ok","Não") -> Ok | AV5: =MONTH(AW5) -> 4 | AW5: =AW4+1 -> 45385 | AX5: =IF(AND(AW5>=$C$4,AW5<=$C$5),"Ok","Não") -> Ok
B6: Data de início da estação | C6: 45597 | E6: "Estação" | F6: =VLOOKUP(S6,$S$8:$T$19,2,0) -> Não | G6: =VLOOKUP(T6,$S$8:$T$19,2,0) -> Não | H6: =VLOOKUP(U6,$S$8:$T$19,2,0) -> Não | I6: =VLOOKUP(V6,$S$8:$T$19,2,0) -> Não | J6: =VLOOKUP(W6,$S$8:$T$19,2,0) -> Ok | K6: =VLOOKUP(X6,$S$8:$T$19,2,0) -> Ok | L6: =VLOOKUP(Y6,$S$8:$T$19,2,0) -> Ok | M6: =VLOOKUP(Z6,$S$8:$T$19,2,0) -> Não | ... Q6: =VLOOKUP(AD6,$S$8:$T$19,2,0) -> Não | S6: 7 | T6: 8 | U6: 9 | V6: 10 | W6: 11 | X6: 12 | Y6: 1 | Z6: 2 | AA6: 3 | AB6: 4 | AC6: 5 | AD6: 6 | AH6: =MONTH(AI6) -> 11 | AI6: =AI5+1 -> 45600 | AJ6: =IF(AND(AI6>=$C$6,AI6<=$C$8),"Ok","Não") -> Ok | AL6: =MONTH(AM6) -> 8 | AM6: =AM5+1 -> 45880 | AN6: =IF(AND(AM6>=$C$9,AM6<=$C$10),"Ok","Não") -> Ok | AR6: =MONTH(AS6) -> 3 | AS6: =AS5+1 -> 46090 | AT6: =IF(AND(AS6>=$C$11,AS6<=$C$12),"Ok","Não") -> Ok | AV6: =MONTH(AW6) -> 4 | AW6: =AW5+1 -> 45386 | AX6: =IF(AND(AW6>=$C$4,AW6<=$C$5),"Ok","Não") -> Ok
B7: Duração planejada (dias) | C7: 90 | E7: Nascimento | F7: =VLOOKUP(S6,$S$8:$V$19,3,0) -> Não | G7: =VLOOKUP(T6,$S$8:$V$19,3,0) -> Ok | H7: =VLOOKUP(U6,$S$8:$V$19,3,0) -> Ok | I7: =VLOOKUP(V6,$S$8:$V$19,3,0) -> Ok | J7: =VLOOKUP(W6,$S$8:$V$19,3,0) -> Ok | K7: =VLOOKUP(X6,$S$8:$V$19,3,0) -> Não | L7: =VLOOKUP(Y6,$S$8:$V$19,3,0) -> Não | M7: =VLOOKUP(Z6,$S$8:$V$19,3,0) -> Não | ... Q7: =VLOOKUP(AD6,$S$8:$V$19,3,0) -> Não | T7: Estação | U7: Nascimento | V7: Desmama | W7: Seca | AH7: =MONTH(AI7) -> 11 | AI7: =AI6+1 -> 45601 | AJ7: =IF(AND(AI7>=$C$6,AI7<=$C$8),"Ok","Não") -> Ok | AL7: =MONTH(AM7) -> 8 | AM7: =AM6+1 -> 45881 | AN7: =IF(AND(AM7>=$C$9,AM7<=$C$10),"Ok","Não") -> Ok | AR7: =MONTH(AS7) -> 3 | AS7: =AS6+1 -> 46091 | AT7: =IF(AND(AS7>=$C$11,AS7<=$C$12),"Ok","Não") -> Ok | AV7: =MONTH(AW7) -> 4 | AW7: =AW6+1 -> 45387 | AX7: =IF(AND(AW7>=$C$4,AW7<=$C$5),"Ok","Não") -> Ok
B8: Data final | C8: =C7+C6 -> 45687 | E8: Desmama | F8: =VLOOKUP(S6,$S$8:$V$19,4,0) -> Não | G8: =VLOOKUP(T6,$S$8:$V$19,4,0) -> Não | H8: =VLOOKUP(U6,$S$8:$V$19,4,0) -> Não | I8: =VLOOKUP(V6,$S$8:$V$19,4,0) -> Não | J8: =VLOOKUP(W6,$S$8:$V$19,4,0) -> Não | K8: =VLOOKUP(X6,$S$8:$V$19,4,0) -> Não | L8: =VLOOKUP(Y6,$S$8:$V$19,4,0) -> Não | M8: =VLOOKUP(Z6,$S$8:$V$19,4,0) -> Não | ... Q8: =VLOOKUP(AD6,$S$8:$V$19,4,0) -> Ok | S8: 1 | T8: =VLOOKUP(S8,$AH$3:$AJ$584,3,0) -> Ok | U8: =VLOOKUP(S8,$AL$3:$AN$584,3,0) -> Não | V8: =VLOOKUP(S8,$AR$3:$AT$584,3,0) -> Não | W8: =VLOOKUP(S8,$AV$3:$AX$584,3,0) -> Não | AH8: =MONTH(AI8) -> 11 | AI8: =AI7+1 -> 45602 | AJ8: =IF(AND(AI8>=$C$6,AI8<=$C$8),"Ok","Não") -> Ok | AL8: =MONTH(AM8) -> 8 | AM8: =AM7+1 -> 45882 | AN8: =IF(AND(AM8>=$C$9,AM8<=$C$10),"Ok","Não") -> Ok | AR8: =MONTH(AS8) -> 3 | AS8: =AS7+1 -> 46092 | AT8: =IF(AND(AS8>=$C$11,AS8<=$C$12),"Ok","Não") -> Ok | AV8: =MONTH(AW8) -> 4 | AW8: =AW7+1 -> 45388 | AX8: =IF(AND(AW8>=$C$4,AW8<=$C$5),"Ok","Não") -> Ok
B9: Início dos nascimentos | C9: =C6+280 -> 45877 | S9: 2 | T9: =VLOOKUP(S9,$AH$3:$AJ$584,3,0) -> Não | U9: =VLOOKUP(S9,$AL$3:$AN$584,3,0) -> Não | V9: =VLOOKUP(S9,$AR$3:$AT$584,3,0) -> Não | W9: =VLOOKUP(S9,$AV$3:$AX$584,3,0) -> Não | AH9: =MONTH(AI9) -> 11 | AI9: =AI8+1 -> 45603 | AJ9: =IF(AND(AI9>=$C$6,AI9<=$C$8),"Ok","Não") -> Ok | AL9: =MONTH(AM9) -> 8 | AM9: =AM8+1 -> 45883 | AN9: =IF(AND(AM9>=$C$9,AM9<=$C$10),"Ok","Não") -> Ok | AR9: =MONTH(AS9) -> 3 | AS9: =AS8+1 -> 46093 | AT9: =IF(AND(AS9>=$C$11,AS9<=$C$12),"Ok","Não") -> Ok | AV9: =MONTH(AW9) -> 4 | AW9: =AW8+1 -> 45389 | AX9: =IF(AND(AW9>=$C$4,AW9<=$C$5),"Ok","Não") -> Ok
B10: Final dos nascimentos | C10: =C9+C7 -> 45967 | S10: 3 | T10: =VLOOKUP(S10,$AH$3:$AJ$584,3,0) -> Não | U10: =VLOOKUP(S10,$AL$3:$AN$584,3,0) -> Não | V10: =VLOOKUP(S10,$AR$3:$AT$584,3,0) -> Ok | W10: =VLOOKUP(S10,$AV$3:$AX$584,3,0) -> Não | AH10: =MONTH(AI10) -> 11 | AI10: =AI9+1 -> 45604 | AJ10: =IF(AND(AI10>=$C$6,AI10<=$C$8),"Ok","Não") -> Ok | AL10: =MONTH(AM10) -> 8 | AM10: =AM9+1 -> 45884 | AN10: =IF(AND(AM10>=$C$9,AM10<=$C$10),"Ok","Não") -> Ok | AR10: =MONTH(AS10) -> 3 | AS10: =AS9+1 -> 46094 | AT10: =IF(AND(AS10>=$C$11,AS10<=$C$12),"Ok","Não") -> Ok | AV10: =MONTH(AW10) -> 4 | AW10: =AW9+1 -> 45390 | AX10: =IF(AND(AW10>=$C$4,AW10<=$C$5),"Ok","Não") -> Ok
B11: Início da desmama | C11: =C9+210 -> 46087 | S11: 4 | T11: =VLOOKUP(S11,$AH$3:$AJ$584,3,0) -> Não | U11: =VLOOKUP(S11,$AL$3:$AN$584,3,0) -> Não | V11: =VLOOKUP(S11,$AR$3:$AT$584,3,0) -> Ok | W11: =VLOOKUP(S11,$AV$3:$AX$584,3,0) -> Ok | AH11: =MONTH(AI11) -> 11 | AI11: =AI10+1 -> 45605 | AJ11: =IF(AND(AI11>=$C$6,AI11<=$C$8),"Ok","Não") -> Ok | AL11: =MONTH(AM11) -> 8 | AM11: =AM10+1 -> 45885 | AN11: =IF(AND(AM11>=$C$9,AM11<=$C$10),"Ok","Não") -> Ok | AR11: =MONTH(AS11) -> 3 | AS11: =AS10+1 -> 46095 | AT11: =IF(AND(AS11>=$C$11,AS11<=$C$12),"Ok","Não") -> Ok | AV11: =MONTH(AW11) -> 4 | AW11: =AW10+1 -> 45391 | AX11: =IF(AND(AW11>=$C$4,AW11<=$C$5),"Ok","Não") -> Ok
B12: Final da desmama | C12: =C10+210 -> 46177 | S12: 5 | T12: =VLOOKUP(S12,$AH$3:$AJ$584,3,0) -> Não | U12: =VLOOKUP(S12,$AL$3:$AN$584,3,0) -> Não | V12: =VLOOKUP(S12,$AR$3:$AT$584,3,0) -> Ok | W12: =VLOOKUP(S12,$AV$3:$AX$584,3,0) -> Ok | AH12: =MONTH(AI12) -> 11 | AI12: =AI11+1 -> 45606 | AJ12: =IF(AND(AI12>=$C$6,AI12<=$C$8),"Ok","Não") -> Ok | AL12: =MONTH(AM12) -> 8 | AM12: =AM11+1 -> 45886 | AN12: =IF(AND(AM12>=$C$9,AM12<=$C$10),"Ok","Não") -> Ok | AR12: =MONTH(AS12) -> 3 | AS12: =AS11+1 -> 46096 | AT12: =IF(AND(AS12>=$C$11,AS12<=$C$12),"Ok","Não") -> Ok | AV12: =MONTH(AW12) -> 4 | AW12: =AW11+1 -> 45392 | AX12: =IF(AND(AW12>=$C$4,AW12<=$C$5),"Ok","Não") -> Ok
B13: Dias até início da próxima estação | C13: =C6+365-C9 -> 85 | S13: 6 | T13: =VLOOKUP(S13,$AH$3:$AJ$584,3,0) -> Não | U13: =VLOOKUP(S13,$AL$3:$AN$584,3,0) -> Não | V13: =VLOOKUP(S13,$AR$3:$AT$584,3,0) -> Ok | W13: =VLOOKUP(S13,$AV$3:$AX$584,3,0) -> Ok | AH13: =MONTH(AI13) -> 11 | AI13: =AI12+1 -> 45607 | AJ13: =IF(AND(AI13>=$C$6,AI13<=$C$8),"Ok","Não") -> Ok | AL13: =MONTH(AM13) -> 8 | AM13: =AM12+1 -> 45887 | AN13: =IF(AND(AM13>=$C$9,AM13<=$C$10),"Ok","Não") -> Ok | AR13: =MONTH(AS13) -> 3 | AS13: =AS12+1 -> 46097 | AT13: =IF(AND(AS13>=$C$11,AS13<=$C$12),"Ok","Não") -> Ok | AV13: =MONTH(AW13) -> 4 | AW13: =AW12+1 -> 45393 | AX13: =IF(AND(AW13>=$C$4,AW13<=$C$5),"Ok","Não") -> Ok
B14: Início da próxima estação | C14: =C13+C9 -> 45962 | S14: 7 | T14: =VLOOKUP(S14,$AH$3:$AJ$584,3,0) -> Não | U14: =VLOOKUP(S14,$AL$3:$AN$584,3,0) -> Não | V14: =VLOOKUP(S14,$AR$3:$AT$584,3,0) -> Não | W14: =VLOOKUP(S14,$AV$3:$AX$584,3,0) -> Ok | AH14: =MONTH(AI14) -> 11 | AI14: =AI13+1 -> 45608 | AJ14: =IF(AND(AI14>=$C$6,AI14<=$C$8),"Ok","Não") -> Ok | AL14: =MONTH(AM14) -> 8 | AM14: =AM13+1 -> 45888 | AN14: =IF(AND(AM14>=$C$9,AM14<=$C$10),"Ok","Não") -> Ok | AR14: =MONTH(AS14) -> 3 | AS14: =AS13+1 -> 46098 | AT14: =IF(AND(AS14>=$C$11,AS14<=$C$12),"Ok","Não") -> Ok | AV14: =MONTH(AW14) -> 4 | AW14: =AW13+1 -> 45394 | AX14: =IF(AND(AW14>=$C$4,AW14<=$C$5),"Ok","Não") -> Ok
S15: 8 | T15: =VLOOKUP(S15,$AH$3:$AJ$584,3,0) -> Não | U15: =VLOOKUP(S15,$AL$3:$AN$584,3,0) -> Ok | V15: =VLOOKUP(S15,$AR$3:$AT$584,3,0) -> Não | W15: =VLOOKUP(S15,$AV$3:$AX$584,3,0) -> Ok | AH15: =MONTH(AI15) -> 11 | AI15: =AI14+1 -> 45609 | AJ15: =IF(AND(AI15>=$C$6,AI15<=$C$8),"Ok","Não") -> Ok | AL15: =MONTH(AM15) -> 8 | AM15: =AM14+1 -> 45889 | AN15: =IF(AND(AM15>=$C$9,AM15<=$C$10),"Ok","Não") -> Ok | AR15: =MONTH(AS15) -> 3 | AS15: =AS14+1 -> 46099 | AT15: =IF(AND(AS15>=$C$11,AS15<=$C$12),"Ok","Não") -> Ok | AV15: =MONTH(AW15) -> 4 | AW15: =AW14+1 -> 45395 | AX15: =IF(AND(AW15>=$C$4,AW15<=$C$5),"Ok","Não") -> Ok
S16: 9 | T16: =VLOOKUP(S16,$AH$3:$AJ$584,3,0) -> Não | U16: =VLOOKUP(S16,$AL$3:$AN$584,3,0) -> Ok | V16: =VLOOKUP(S16,$AR$3:$AT$584,3,0) -> Não | W16: =VLOOKUP(S16,$AV$3:$AX$584,3,0) -> Ok | AH16: =MONTH(AI16) -> 11 | AI16: =AI15+1 -> 45610 | AJ16: =IF(AND(AI16>=$C$6,AI16<=$C$8),"Ok","Não") -> Ok | AL16: =MONTH(AM16) -> 8 | AM16: =AM15+1 -> 45890 | AN16: =IF(AND(AM16>=$C$9,AM16<=$C$10),"Ok","Não") -> Ok | AR16: =MONTH(AS16) -> 3 | AS16: =AS15+1 -> 46100 | AT16: =IF(AND(AS16>=$C$11,AS16<=$C$12),"Ok","Não") -> Ok | AV16: =MONTH(AW16) -> 4 | AW16: =AW15+1 -> 45396 | AX16: =IF(AND(AW16>=$C$4,AW16<=$C$5),"Ok","Não") -> Ok
S17: 10 | T17: =VLOOKUP(S17,$AH$3:$AJ$584,3,0) -> Não | U17: =VLOOKUP(S17,$AL$3:$AN$584,3,0) -> Ok | V17: =VLOOKUP(S17,$AR$3:$AT$584,3,0) -> Não | W17: =VLOOKUP(S17,$AV$3:$AX$584,3,0) -> Ok | AH17: =MONTH(AI17) -> 11 | AI17: =AI16+1 -> 45611 | AJ17: =IF(AND(AI17>=$C$6,AI17<=$C$8),"Ok","Não") -> Ok | AL17: =MONTH(AM17) -> 8 | AM17: =AM16+1 -> 45891 | AN17: =IF(AND(AM17>=$C$9,AM17<=$C$10),"Ok","Não") -> Ok | AR17: =MONTH(AS17) -> 3 | AS17: =AS16+1 -> 46101 | AT17: =IF(AND(AS17>=$C$11,AS17<=$C$12),"Ok","Não") -> Ok | AV17: =MONTH(AW17) -> 4 | AW17: =AW16+1 -> 45397 | AX17: =IF(AND(AW17>=$C$4,AW17<=$C$5),"Ok","Não") -> Ok
S18: 11 | T18: =VLOOKUP(S18,$AH$3:$AJ$584,3,0) -> Ok | U18: =VLOOKUP(S18,$AL$3:$AN$584,3,0) -> Ok | V18: =VLOOKUP(S18,$AR$3:$AT$584,3,0) -> Não | W18: =VLOOKUP(S18,$AV$3:$AX$584,3,0) -> Não | AH18: =MONTH(AI18) -> 11 | AI18: =AI17+1 -> 45612 | AJ18: =IF(AND(AI18>=$C$6,AI18<=$C$8),"Ok","Não") -> Ok | AL18: =MONTH(AM18) -> 8 | AM18: =AM17+1 -> 45892 | AN18: =IF(AND(AM18>=$C$9,AM18<=$C$10),"Ok","Não") -> Ok | AR18: =MONTH(AS18) -> 3 | AS18: =AS17+1 -> 46102 | AT18: =IF(AND(AS18>=$C$11,AS18<=$C$12),"Ok","Não") -> Ok | AV18: =MONTH(AW18) -> 4 | AW18: =AW17+1 -> 45398 | AX18: =IF(AND(AW18>=$C$4,AW18<=$C$5),"Ok","Não") -> Ok
S19: 12 | T19: =VLOOKUP(S19,$AH$3:$AJ$584,3,0) -> Ok | U19: =VLOOKUP(S19,$AL$3:$AN$584,3,0) -> Não | V19: =VLOOKUP(S19,$AR$3:$AT$584,3,0) -> Não | W19: =VLOOKUP(S19,$AV$3:$AX$584,3,0) -> Não | AH19: =MONTH(AI19) -> 11 | AI19: =AI18+1 -> 45613 | AJ19: =IF(AND(AI19>=$C$6,AI19<=$C$8),"Ok","Não") -> Ok | AL19: =MONTH(AM19) -> 8 | AM19: =AM18+1 -> 45893 | AN19: =IF(AND(AM19>=$C$9,AM19<=$C$10),"Ok","Não") -> Ok | AR19: =MONTH(AS19) -> 3 | AS19: =AS18+1 -> 46103 | AT19: =IF(AND(AS19>=$C$11,AS19<=$C$12),"Ok","Não") -> Ok | AV19: =MONTH(AW19) -> 4 | AW19: =AW18+1 -> 45399 | AX19: =IF(AND(AW19>=$C$4,AW19<=$C$5),"Ok","Não") -> Ok
AH20: =MONTH(AI20) -> 11 | AI20: =AI19+1 -> 45614 | AJ20: =IF(AND(AI20>=$C$6,AI20<=$C$8),"Ok","Não") -> Ok | AL20: =MONTH(AM20) -> 8 | AM20: =AM19+1 -> 45894 | AN20: =IF(AND(AM20>=$C$9,AM20<=$C$10),"Ok","Não") -> Ok | AR20: =MONTH(AS20) -> 3 | AS20: =AS19+1 -> 46104 | AT20: =IF(AND(AS20>=$C$11,AS20<=$C$12),"Ok","Não") -> Ok | AV20: =MONTH(AW20) -> 4 | AW20: =AW19+1 -> 45400 | AX20: =IF(AND(AW20>=$C$4,AW20<=$C$5),"Ok","Não") -> Ok
AH21: =MONTH(AI21) -> 11 | AI21: =AI20+1 -> 45615 | AJ21: =IF(AND(AI21>=$C$6,AI21<=$C$8),"Ok","Não") -> Ok | AL21: =MONTH(AM21) -> 8 | AM21: =AM20+1 -> 45895 | AN21: =IF(AND(AM21>=$C$9,AM21<=$C$10),"Ok","Não") -> Ok | AR21: =MONTH(AS21) -> 3 | AS21: =AS20+1 -> 46105 | AT21: =IF(AND(AS21>=$C$11,AS21<=$C$12),"Ok","Não") -> Ok | AV21: =MONTH(AW21) -> 4 | AW21: =AW20+1 -> 45401 | AX21: =IF(AND(AW21>=$C$4,AW21<=$C$5),"Ok","Não") -> Ok
AH22: =MONTH(AI22) -> 11 | AI22: =AI21+1 -> 45616 | AJ22: =IF(AND(AI22>=$C$6,AI22<=$C$8),"Ok","Não") -> Ok | AL22: =MONTH(AM22) -> 8 | AM22: =AM21+1 -> 45896 | AN22: =IF(AND(AM22>=$C$9,AM22<=$C$10),"Ok","Não") -> Ok | AR22: =MONTH(AS22) -> 3 | AS22: =AS21+1 -> 46106 | AT22: =IF(AND(AS22>=$C$11,AS22<=$C$12),"Ok","Não") -> Ok | AV22: =MONTH(AW22) -> 4 | AW22: =AW21+1 -> 45402 | AX22: =IF(AND(AW22>=$C$4,AW22<=$C$5),"Ok","Não") -> Ok
AH23: =MONTH(AI23) -> 11 | AI23: =AI22+1 -> 45617 | AJ23: =IF(AND(AI23>=$C$6,AI23<=$C$8),"Ok","Não") -> Ok | AL23: =MONTH(AM23) -> 8 | AM23: =AM22+1 -> 45897 | AN23: =IF(AND(AM23>=$C$9,AM23<=$C$10),"Ok","Não") -> Ok | AR23: =MONTH(AS23) -> 3 | AS23: =AS22+1 -> 46107 | AT23: =IF(AND(AS23>=$C$11,AS23<=$C$12),"Ok","Não") -> Ok | AV23: =MONTH(AW23) -> 4 | AW23: =AW22+1 -> 45403 | AX23: =IF(AND(AW23>=$C$4,AW23<=$C$5),"Ok","Não") -> Ok
AH24: =MONTH(AI24) -> 11 | AI24: =AI23+1 -> 45618 | AJ24: =IF(AND(AI24>=$C$6,AI24<=$C$8),"Ok","Não") -> Ok | AL24: =MONTH(AM24) -> 8 | AM24: =AM23+1 -> 45898 | AN24: =IF(AND(AM24>=$C$9,AM24<=$C$10),"Ok","Não") -> Ok | AR24: =MONTH(AS24) -> 3 | AS24: =AS23+1 -> 46108 | AT24: =IF(AND(AS24>=$C$11,AS24<=$C$12),"Ok","Não") -> Ok | AV24: =MONTH(AW24) -> 4 | AW24: =AW23+1 -> 45404 | AX24: =IF(AND(AW24>=$C$4,AW24<=$C$5),"Ok","Não") -> Ok
AH25: =MONTH(AI25) -> 11 | AI25: =AI24+1 -> 45619 | AJ25: =IF(AND(AI25>=$C$6,AI25<=$C$8),"Ok","Não") -> Ok | AL25: =MONTH(AM25) -> 8 | AM25: =AM24+1 -> 45899 | AN25: =IF(AND(AM25>=$C$9,AM25<=$C$10),"Ok","Não") -> Ok | AR25: =MONTH(AS25) -> 3 | AS25: =AS24+1 -> 46109 | AT25: =IF(AND(AS25>=$C$11,AS25<=$C$12),"Ok","Não") -> Ok | AV25: =MONTH(AW25) -> 4 | AW25: =AW24+1 -> 45405 | AX25: =IF(AND(AW25>=$C$4,AW25<=$C$5),"Ok","Não") -> Ok
AH26: =MONTH(AI26) -> 11 | AI26: =AI25+1 -> 45620 | AJ26: =IF(AND(AI26>=$C$6,AI26<=$C$8),"Ok","Não") -> Ok | AL26: =MONTH(AM26) -> 8 | AM26: =AM25+1 -> 45900 | AN26: =IF(AND(AM26>=$C$9,AM26<=$C$10),"Ok","Não") -> Ok | AR26: =MONTH(AS26) -> 3 | AS26: =AS25+1 -> 46110 | AT26: =IF(AND(AS26>=$C$11,AS26<=$C$12),"Ok","Não") -> Ok | AV26: =MONTH(AW26) -> 4 | AW26: =AW25+1 -> 45406 | AX26: =IF(AND(AW26>=$C$4,AW26<=$C$5),"Ok","Não") -> Ok
AH27: =MONTH(AI27) -> 11 | AI27: =AI26+1 -> 45621 | AJ27: =IF(AND(AI27>=$C$6,AI27<=$C$8),"Ok","Não") -> Ok | AL27: =MONTH(AM27) -> 9 | AM27: =AM26+1 -> 45901 | AN27: =IF(AND(AM27>=$C$9,AM27<=$C$10),"Ok","Não") -> Ok | AR27: =MONTH(AS27) -> 3 | AS27: =AS26+1 -> 46111 | AT27: =IF(AND(AS27>=$C$11,AS27<=$C$12),"Ok","Não") -> Ok | AV27: =MONTH(AW27) -> 4 | AW27: =AW26+1 -> 45407 | AX27: =IF(AND(AW27>=$C$4,AW27<=$C$5),"Ok","Não") -> Ok
AH28: =MONTH(AI28) -> 11 | AI28: =AI27+1 -> 45622 | AJ28: =IF(AND(AI28>=$C$6,AI28<=$C$8),"Ok","Não") -> Ok | AL28: =MONTH(AM28) -> 9 | AM28: =AM27+1 -> 45902 | AN28: =IF(AND(AM28>=$C$9,AM28<=$C$10),"Ok","Não") -> Ok | AR28: =MONTH(AS28) -> 3 | AS28: =AS27+1 -> 46112 | AT28: =IF(AND(AS28>=$C$11,AS28<=$C$12),"Ok","Não") -> Ok | AV28: =MONTH(AW28) -> 4 | AW28: =AW27+1 -> 45408 | AX28: =IF(AND(AW28>=$C$4,AW28<=$C$5),"Ok","Não") -> Ok
AH29: =MONTH(AI29) -> 11 | AI29: =AI28+1 -> 45623 | AJ29: =IF(AND(AI29>=$C$6,AI29<=$C$8),"Ok","Não") -> Ok | AL29: =MONTH(AM29) -> 9 | AM29: =AM28+1 -> 45903 | AN29: =IF(AND(AM29>=$C$9,AM29<=$C$10),"Ok","Não") -> Ok | AR29: =MONTH(AS29) -> 4 | AS29: =AS28+1 -> 46113 | AT29: =IF(AND(AS29>=$C$11,AS29<=$C$12),"Ok","Não") -> Ok | AV29: =MONTH(AW29) -> 4 | AW29: =AW28+1 -> 45409 | AX29: =IF(AND(AW29>=$C$4,AW29<=$C$5),"Ok","Não") -> Ok
AH30: =MONTH(AI30) -> 11 | AI30: =AI29+1 -> 45624 | AJ30: =IF(AND(AI30>=$C$6,AI30<=$C$8),"Ok","Não") -> Ok | AL30: =MONTH(AM30) -> 9 | AM30: =AM29+1 -> 45904 | AN30: =IF(AND(AM30>=$C$9,AM30<=$C$10),"Ok","Não") -> Ok | AR30: =MONTH(AS30) -> 4 | AS30: =AS29+1 -> 46114 | AT30: =IF(AND(AS30>=$C$11,AS30<=$C$12),"Ok","Não") -> Ok | AV30: =MONTH(AW30) -> 4 | AW30: =AW29+1 -> 45410 | AX30: =IF(AND(AW30>=$C$4,AW30<=$C$5),"Ok","Não") -> Ok
AH31: =MONTH(AI31) -> 11 | AI31: =AI30+1 -> 45625 | AJ31: =IF(AND(AI31>=$C$6,AI31<=$C$8),"Ok","Não") -> Ok | AL31: =MONTH(AM31) -> 9 | AM31: =AM30+1 -> 45905 | AN31: =IF(AND(AM31>=$C$9,AM31<=$C$10),"Ok","Não") -> Ok | AR31: =MONTH(AS31) -> 4 | AS31: =AS30+1 -> 46115 | AT31: =IF(AND(AS31>=$C$11,AS31<=$C$12),"Ok","Não") -> Ok | AV31: =MONTH(AW31) -> 4 | AW31: =AW30+1 -> 45411 | AX31: =IF(AND(AW31>=$C$4,AW31<=$C$5),"Ok","Não") -> Ok
... AH584: =MONTH(AI584) -> 6 | AI584: =AI583+1 -> 46178 | AJ584: =IF(AND(AI584>=$C$6,AI584<=$C$8),"Ok","Não") -> Não | AL584: =MONTH(AM584) -> 3 | AM584: =AM583+1 -> 46458 | AN584: =IF(AND(AM584>=$C$9,AM584<=$C$10),"Ok","Não") -> Não | AR584: =MONTH(AS584) -> 10 | AS584: =AS583+1 -> 46668 | AT584: =IF(AND(AS584>=$C$11,AS584<=$C$12),"Ok","Não") -> Não | AV584: =MONTH(AW584) -> 11 | AW584: =AW583+1 -> 45964 | AX584: =IF(AND(AW584>=$C$4,AW584<=$C$5),"Ok","Não") -> Não

Sheet Indicadores
B2: Informações
B3: N° de vacas para entrar na estação | C3: 1300
B4: Prenhas no final da estação | C4: 1100
B5: Bezerros(as) desmamados(as) | C5: 1000
B6: Peso médio de desmama | C6: 200
B7: Área útil (ha) | C7: 500
B9: Resultados
B10: Taxa de prenhez | C10: =C4/C3 -> 0.84615385
B11: Taxa de desmame | C11: =C5/C3 -> 0.76923077
B12: Kg de bezerro desmamado/vaca | C12: =(C6*C5)/C3 -> 153.84615
B13: Kg de bezerro desmamado/hectare | C13: =(C6*C5)/C7 -> 400
B14: Bezerros desmamados/hectare | C14: =C5/C7 -> 2

Sheet IATF x Touro
B1: TOURO x IATF
C4: TOURO | H4: IATF
C6: Informações | H6: Informações
C7: Preço compra do touro | D7: 13000 | H7: R$/protocolo | I7: 70
C8: Vida útil (anos) | D8: 5 | H8: % prenhez do protocolo | I8: 0.5
C9: Bezerros por ano | D9: 25
C10: R$/cab/mês | D10: 50 | H10: Resultados
C11: Exames anuais | D11: 300 | H11: Custo/prenhez | I11: =I7/I8 -> 140
C12: % inviabilidade | D12: 0.3
C13: R$ de "revenda" | D13: 4000
C15: Resultados
C16: Custo anual do touro | D16: =((12*D10)+D11)*(1+D12) -> 1170
C17: Custo total do touro | D17: =D7+(D16*D8) -> 18850
C18: Custo - revenda | D18: =D17-D13 -> 14850
C19: Custo/prenhez | D19: =D18/(D9*D8) -> 118.8
C23: Simulação de custos Touro | H23: Simulação de custos IATF
C24: Qnt. De vacas | D24: 125 | H24: Qnt. De vacas | I24: 500
C25: Relação touro x vaca | D25: 25 | H25: R$/protocolo | I25: 70
C26: n° de touros necessários | D26: =D24/D25 -> 5 | H26: % prenhez 1° IATF | I26: 0.5
C27: Prenhez | D27: 0.4 | H27: % prenhez 2° IATF | I27: 0.5
C28: n° de prenhas | D28: =D27*D24 -> 50 | H28: n° de prenhas | I28: =ROUND((I24*I26)+(I24-(I24*I26))*I27,0) -> 375
C29: R$ compra de touros | D29: =D26*D7 -> 65000 | H29: R$ com protocolos | I29: =(I24+(I24*(1-I26)))*I25 -> 52500
C30: R$ anual touros | D30: =D26*D16+((D29-(D13*D26))/D8) -> 14850 | H30: R$/prenhez | I30: =I29/I28 -> 140
C31: R$/prenhez | D31: =D30/(D28) -> 297

Sheet 1 IATF + Touro
B1: PROGRAMAÇÃO DA ESTAÇÃO REPRODUTIVA
B3: Mês | C3: J | D3: A | E3: S | F3: O | G3: N | H3: D | I3: J | J3: F | K3: M | L3: A | M3: M | N3: J | O3: J | P3: A | Q3: S | R3: O | S3: N | T3: D | U3: J | V3: F | W3: M | X3: A | Y3: M | Z3: J
B4: Nascimentos | D4: 100 | E4: 80 | F4: 50 | G4: 30
B5: 1° mandada | E5: =IF(C4="","",C4) | F5: =IF(D4="","",D4) -> 100 | G5: =IF(E4="","",E4) -> 80 | H5: =IF(F4="","",F4) -> 50 | I5: =IF(G4="","",G4) -> 30 | J5: =IF(H4="","",H4) | K5: =IF(I4="","",I4) | L5: =IF(J4="","",J4) | ... Z5: =IF(X4="","",X4)
B6: Prenhez 1° IATF | F6: 0.5 | G6: 0.5 | H6: 0.5 | I6: 0.5
B7: Touro | E7: =IF(D5="","",ROUND(D5*(1-D6),0)) | F7: =IF(E5="","",ROUND(E5*(1-E6),0)) | G7: =IF(F5="","",ROUND(F5*(1-F6),0)) -> 50 | H7: =IF(G5="","",ROUND(G5*(1-G6),0)) -> 40 | I7: =IF(H5="","",ROUND(H5*(1-H6),0)) -> 25 | J7: =IF(I5="","",ROUND(I5*(1-I6),0)) -> 15 | K7: =IF(J5="","",ROUND(J5*(1-J6),0)) | L7: =IF(K5="","",ROUND(K5*(1-K6),0)) | ... Z7: =IF(Y5="","",ROUND(Y5*(1-Y6),0))
B8: Prenhez touro | G8: 0.7 | H8: 0.7 | I8: 0.7 | J8: 0.7
B9: 1° Nascimentos | J9: =IF(A5="","",ROUND(A5*A6,0)) | L9: =IF(C5="","",ROUND(C5*C6,0)) | M9: =IF(D5="","",ROUND(D5*D6,0)) | N9: =IF(E5="","",ROUND(E5*E6,0)) | O9: =IF(F5="","",ROUND(F5*F6,0)) -> 50 | P9: =IF(G5="","",ROUND(G5*G6,0)) -> 40 | Q9: =IF(H5="","",ROUND(H5*H6,0)) -> 25 | R9: =IF(I5="","",ROUND(I5*I6,0)) -> 15 | S9: =IF(J5="","",ROUND(J5*J6,0)) | ... Z9: =IF(Q5="","",ROUND(Q5*Q6,0))
B10: Nascimentos Touro | L10: =IF(C7="","",ROUND(C7*C8,0)) | M10: =IF(D7="","",ROUND(D7*D8,0)) | N10: =IF(E7="","",ROUND(E7*E8,0)) | O10: =IF(F7="","",ROUND(F7*F8,0)) | P10: =IF(G7="","",ROUND(G7*G8,0)) -> 35 | Q10: =IF(H7="","",ROUND(H7*H8,0)) -> 28 | R10: =IF(I7="","",ROUND(I7*I8,0)) -> 18 | S10: =IF(J7="","",ROUND(J7*J8,0)) -> 11 | ... Z10: =IF(Q7="","",ROUND(Q7*Q8,0))
B12: Total de bezerros de IATF | D12: =SUM(C9:Z9) -> 130
B13: Total de bezerros de Touro | D13: =SUM(C10:Z10) -> 92
B14: Vacas expostas | D14: =SUM(C4:Z4) -> 260
B15: % prenhez | D15: =(D12+D13)/D14 -> 0.85384615
B16: Inseminações | D16: =SUM(C5:Z5) -> 260

Sheet 2 IATF + Touro
B1: PROGRAMAÇÃO DA ESTAÇÃO REPRODUTIVA
B3: Mês | C3: J | D3: A | E3: S | F3: O | G3: N | H3: D | I3: J | J3: F | K3: M | L3: A | M3: M | N3: J | O3: J | P3: A | Q3: S | R3: O | S3: N | T3: D | U3: J | V3: F | W3: M | X3: A | Y3: M | Z3: J
B4: Nascimentos | D4: 100 | E4: 80 | F4: 50 | G4: 30
B5: 1° mandada | E5: =IF(C4="","",C4) | F5: =IF(D4="","",D4) -> 100 | G5: =IF(E4="","",E4) -> 80 | H5: =IF(F4="","",F4) -> 50 | I5: =IF(G4="","",G4) -> 30 | J5: =IF(H4="","",H4) | K5: =IF(I4="","",I4) | L5: =IF(J4="","",J4) | ... N5: =IF(L4="","",L4) | O5: =IF(L4="","",L4) | P5: =IF(M4="","",M4) | Q5: =IF(N4="","",N4) | R5: =IF(O4="","",O4) | S5: =IF(P4="","",P4) | T5: =IF(Q4="","",Q4) | U5: =IF(R4="","",R4) | V5: =IF(S4="","",S4) | ... Z5: =IF(W4="","",W4)
B6: Prenhez | F6: 0.5 | G6: 0.5 | H6: 0.5 | I6: 0.5
B7: 2° mandada | G7: =IF(F5="","",ROUND(F5*(1-F6),0)) -> 50 | H7: =IF(G5="","",ROUND(G5*(1-G6),0)) -> 40 | I7: =IF(H5="","",ROUND(H5*(1-H6),0)) -> 25 | J7: =IF(I5="","",ROUND(I5*(1-I6),0)) -> 15 | K7: =IF(J5="","",ROUND(J5*(1-J6),0)) | L7: =IF(K5="","",ROUND(K5*(1-K6),0)) | M7: =IF(L5="","",ROUND(L5*(1-L6),0)) | N7: =IF(M5="","",ROUND(M5*(1-M6),0)) | ... Z7: =IF(Y5="","",ROUND(Y5*(1-Y6),0))
B8: Prenhez | G8: 0.5 | H8: 0.5 | I8: 0.5 | J8: 0.5
B9: Touro | H9: =IF(G7="","",ROUND((G8*G7),0)) -> 25 | I9: =IF(H7="","",ROUND((H8*H7),0)) -> 20 | J9: =IF(I7="","",ROUND((I8*I7),0)) -> 13 | K9: =IF(J7="","",ROUND((J8*J7),0)) -> 8 | L9: =IF(K7="","",ROUND((K8*K7),0)) | M9: =IF(L7="","",ROUND((L8*L7),0)) | N9: =IF(M7="","",ROUND((M8*M7),0)) | O9: =IF(N7="","",ROUND((N8*N7),0)) | ... Z9: =IF(Y7="","",ROUND((Y8*Y7),0))
B10: Prenhez | H10: 0.3 | I10: 0.3 | J10: 0.3 | K10: 0.3
B11: 1° Nascimentos | J11: =IF(A5="","",ROUND(A5*A6,0)) | L11: =IF(C5="","",ROUND(C5*C6,0)) | M11: =IF(D5="","",ROUND(D5*D6,0)) | N11: =IF(E5="","",ROUND(E5*E6,0)) | O11: =IF(F5="","",ROUND(F5*F6,0)) -> 50 | P11: =IF(G5="","",ROUND(G5*G6,0)) -> 40 | Q11: =IF(H5="","",ROUND(H5*H6,0)) -> 25 | R11: =IF(I5="","",ROUND(I5*I6,0)) -> 15 | S11: =IF(J5="","",ROUND(J5*J6,0)) | ... Z11: =IF(Q5="","",ROUND(Q5*Q6,0))
B12: 2° Nascimentos | L12: =IF(C7="","",ROUND(C7*C8,0)) | M12: =IF(D7="","",ROUND(D7*D8,0)) | N12: =IF(E7="","",ROUND(E7*E8,0)) | O12: =IF(F7="","",ROUND(F7*F8,0)) | P12: =IF(G7="","",ROUND(G7*G8,0)) -> 25 | Q12: =IF(H7="","",ROUND(H7*H8,0)) -> 20 | R12: =IF(I7="","",ROUND(I7*I8,0)) -> 13 | S12: =IF(J7="","",ROUND(J7*J8,0)) -> 8 | ... Z12: =IF(Q7="","",ROUND(Q7*Q8,0))
B13: Nascimentos Touro | K13: =IF(C10="","",ROUND(C10*C9,0)) | L13: =IF(D10="","",ROUND(D10*D9,0)) | M13: =IF(E10="","",ROUND(E10*E9,0)) | N13: =IF(F10="","",ROUND(F10*F9,0)) | O13: =IF(G10="","",ROUND(G10*G9,0)) | P13: =IF(H10="","",ROUND(H10*H9,0)) -> 8 | Q13: =IF(I10="","",ROUND(I10*I9,0)) -> 6 | R13: =IF(J10="","",ROUND(J10*J9,0)) -> 4 | ... Z13: =IF(R10="","",ROUND(R10*R9,0))
B15: Total de bezerros de IATF | D15: =SUM(C11:Z12) -> 196
B16: Total de bezerros de Touro | D16: =SUM(C13:Z13) -> 20
B17: Vacas expostas | D17: =SUM(C4:Z4) -> 260
B18: % prenhez | D18: =(D15+D16)/D17 -> 0.83076923
B19: Inseminações | D19: =SUM(C5:Z5)+SUM(C7:Z7) -> 390

Sheet Reprodutivo LANÇAR
A1: CABEÇALHO DE RESUMO DO REPRODUTIVO
A2: n° vacas expostas | B2: n° vacas 1° IATF | C2: Prenhez 1° IATF | D2: n° vacas 2° IATF | E2: Prenhez 2° IATF | F2: n° vacas c/ Touro | G2: DG final | H2: Qnt. prenha DG final | I2: DG TOTAL | J2: Qnt. paridas | K2: % nascimento | L2: Qnt. Bez desmamados | M2: % desmame | N2: Kg desm. total | O2: Kg desm./vaca exp. | P2: Kg desmamado/ha | R2: Área de pasto em hectares:
A3: =IFERROR(COUNTA(Tabela2[Coluna1]),"") -> 0 | B3: =IFERROR(COUNTIFS(Tabela2[Coluna3],">0",Tabela2[Coluna1],">0"),"") -> 0 | C3: =IFERROR(COUNTIFS(Tabela2[Coluna5],"Cheia")/COUNTA(Tabela2[Coluna5]),"") | D3: =IFERROR(COUNTIFS(Tabela2[Coluna6],">0",Tabela2[Coluna1],">0"),"") -> 0 | E3: =IFERROR(COUNTIFS(Tabela2[Coluna8],"Cheia")/COUNTA(Tabela2[Coluna8]),"") | F3: =IFERROR(COUNTIFS(Tabela2[Coluna9],">0",Tabela2[Coluna1],">0"),"") -> 0 | G3: =IFERROR(COUNTIFS(Tabela2[Coluna11],"Cheia")/COUNTIFS(Tabela2[Coluna10],">0"),"") | H3: =COUNTIFS(Tabela2[Coluna11],"Cheia") -> 0 | I3: =IFERROR(COUNTIFS(Tabela2[Coluna 16],">0")/COUNTIFS(Tabela2[Coluna1],">0"),"") | J3: =COUNTIFS(Tabela2[Coluna12],">0") -> 0 | K3: =IFERROR(J3/H3,"") | L3: =COUNTIFS(Tabela2[Coluna14],">0") -> 0 | M3: =IFERROR(L3/A3,"") | N3: =SUM(Tabela2[Coluna15]) -> 0 | O3: =IFERROR(N3/A3,"") | P3: =IFERROR(N3/S2,"")
A5: CONTROLE DE MANEJOS REPRODUTIVOS
A6: N° vaca | B6: Categoria | C6: 1° IATF | D6: 1° DG | F6: 2° IATF | G6: 2° DG | I6: Touro | J6: DG final | L6: Nasc. | N6: Desmama. | P6: Previsão de parto
C7: Data | D7: Data | E7: Resultado | F7: Data | G7: Data | H7: Resultado | I7: Data | J7: Data | K7: Resultado | L7: Data | M7: Sexo | N7: Data | O7: Peso
A8: Coluna1 | B8: Coluna2 | C8: Coluna3 | D8: Coluna4 | E8: Coluna5 | F8: Coluna6 | G8: Coluna7 | H8: Coluna8 | I8: Coluna9 | J8: Coluna10 | K8: Coluna11 | L8: Coluna12 | M8: Coluna13 | N8: Coluna14 | O8: Coluna15 | P8: Coluna 16
P9: =IF(Tabela2[[#This Row],[Coluna11]]="Vazia","Vazia",IF(Tabela2[[#This Row],[Coluna1]]="","",IF(Tabela2[[#This Row],[Coluna5]]="Cheia",Tabela2[[#This Row],[Coluna3]]+280,IF(Tabela2[[#This Row],[Coluna8]]="Cheia",Tabela2[[#This Row],[Coluna7]]+280,IF(Tabela2[[#This Row],[Coluna11]]="Cheia",Tabela2[[#This Row],[Coluna9]]+280,"Vazia")))))
P10: =IF(Tabela2[[#This Row],[Coluna11]]="Vazia","Vazia",IF(Tabela2[[#This Row],[Coluna1]]="","",IF(Tabela2[[#This Row],[Coluna5]]="Cheia",Tabela2[[#This Row],[Coluna3]]+280,IF(Tabela2[[#This Row],[Coluna8]]="Cheia",Tabela2[[#This Row],[Coluna7]]+280,IF(Tabela2[[#This Row],[Coluna11]]="Cheia",Tabela2[[#This Row],[Coluna9]]+280,"Vazia")))))
P11: =IF(Tabela2[[#This Row],[Coluna11]]="Vazia","Vazia",IF(Tabela2[[#This Row],[Coluna1]]="","",IF(Tabela2[[#This Row],[Coluna5]]="Cheia",Tabela2[[#This Row],[Coluna3]]+280,IF(Tabela2[[#This Row],[Coluna8]]="Cheia",Tabela2[[#This Row],[Coluna7]]+280,IF(Tabela2[[#This Row],[Coluna11]]="Cheia",Tabela2[[#This Row],[Coluna9]]+280,"Vazia")))))
P12: =IF(Tabela2[[#This Row],[Coluna11]]="Vazia","Vazia",IF(Tabela2[[#This Row],[Coluna1]]="","",IF(Tabela2[[#This Row],[Coluna5]]="Cheia",Tabela2[[#This Row],[Coluna3]]+280,IF(Tabela2[[#This Row],[Coluna8]]="Cheia",Tabela2[[#This Row],[Coluna7]]+280,IF(Tabela2[[#This Row],[Coluna11]]="Cheia",Tabela2[[#This Row],[Coluna9]]+280,"Vazia")))))
P13: =IF(Tabela2[[#This Row],[Coluna11]]="Vazia","Vazia",IF(Tabela2[[#This Row],[Coluna1]]="","",IF(Tabela2[[#This Row],[Coluna5]]="Cheia",Tabela2[[#This Row],[Coluna3]]+280,IF(Tabela2[[#This Row],[Coluna8]]="Cheia",Tabela2[[#This Row],[Coluna7]]+280,IF(Tabela2[[#This Row],[Coluna11]]="Cheia",Tabela2[[#This Row],[Coluna9]]+280,"Vazia")))))
P14: =IF(Tabela2[[#This Row],[Coluna11]]="Vazia","Vazia",IF(Tabela2[[#This Row],[Coluna1]]="","",IF(Tabela2[[#This Row],[Coluna5]]="Cheia",Tabela2[[#This Row],[Coluna3]]+280,IF(Tabela2[[#This Row],[Coluna8]]="Cheia",Tabela2[[#This Row],[Coluna7]]+280,IF(Tabela2[[#This Row],[Coluna11]]="Cheia",Tabela2[[#This Row],[Coluna9]]+280,"Vazia")))))
P15: =IF(Tabela2[[#This Row],[Coluna11]]="Vazia","Vazia",IF(Tabela2[[#This Row],[Coluna1]]="","",IF(Tabela2[[#This Row],[Coluna5]]="Cheia",Tabela2[[#This Row],[Coluna3]]+280,IF(Tabela2[[#This Row],[Coluna8]]="Cheia",Tabela2[[#This Row],[Coluna7]]+280,IF(Tabela2[[#This Row],[Coluna11]]="Cheia",Tabela2[[#This Row],[Coluna9]]+280,"Vazia")))))
P16: =IF(Tabela2[[#This Row],[Coluna11]]="Vazia","Vazia",IF(Tabela2[[#This Row],[Coluna1]]="","",IF(Tabela2[[#This Row],[Coluna5]]="Cheia",Tabela2[[#This Row],[Coluna3]]+280,IF(Tabela2[[#This Row],[Coluna8]]="Cheia",Tabela2[[#This Row],[Coluna7]]+280,IF(Tabela2[[#This Row],[Coluna11]]="Cheia",Tabela2[[#This Row],[Coluna9]]+280,"Vazia")))))
P17: =IF(Tabela2[[#This Row],[Coluna11]]="Vazia","Vazia",IF(Tabela2[[#This Row],[Coluna1]]="","",IF(Tabela2[[#This Row],[Coluna5]]="Cheia",Tabela2[[#This Row],[Coluna3]]+280,IF(Tabela2[[#This Row],[Coluna8]]="Cheia",Tabela2[[#This Row],[Coluna7]]+280,IF(Tabela2[[#This Row],[Coluna11]]="Cheia",Tabela2[[#This Row],[Coluna9]]+280,"Vazia")))))
P18: =IF(Tabela2[[#This Row],[Coluna11]]="Vazia","Vazia",IF(Tabela2[[#This Row],[Coluna1]]="","",IF(Tabela2[[#This Row],[Coluna5]]="Cheia",Tabela2[[#This Row],[Coluna3]]+280,IF(Tabela2[[#This Row],[Coluna8]]="Cheia",Tabela2[[#This Row],[Coluna7]]+280,IF(Tabela2[[#This Row],[Coluna11]]="Cheia",Tabela2[[#This Row],[Coluna9]]+280,"Vazia")))))
P19: =IF(Tabela2[[#This Row],[Coluna11]]="Vazia","Vazia",IF(Tabela2[[#This Row],[Coluna1]]="","",IF(Tabela2[[#This Row],[Coluna5]]="Cheia",Tabela2[[#This Row],[Coluna3]]+280,IF(Tabela2[[#This Row],[Coluna8]]="Cheia",Tabela2[[#This Row],[Coluna7]]+280,IF(Tabela2[[#This Row],[Coluna11]]="Cheia",Tabela2[[#This Row],[Coluna9]]+280,"Vazia")))))
P20: =IF(Tabela2[[#This Row],[Coluna11]]="Vazia","Vazia",IF(Tabela2[[#This Row],[Coluna1]]="","",IF(Tabela2[[#This Row],[Coluna5]]="Cheia",Tabela2[[#This Row],[Coluna3]]+280,IF(Tabela2[[#This Row],[Coluna8]]="Cheia",Tabela2[[#This Row],[Coluna7]]+280,IF(Tabela2[[#This Row],[Coluna11]]="Cheia",Tabela2[[#This Row],[Coluna9]]+280,"Vazia")))))
... P31: =IF(Tabela2[[#This Row],[Coluna11]]="Vazia","Vazia",IF(Tabela2[[#This Row],[Coluna1]]="","",IF(Tabela2[[#This Row],[Coluna5]]="Cheia",Tabela2[[#This Row],[Coluna3]]+280,IF(Tabela2[[#This Row],[Coluna8]]="Cheia",Tabela2[[#This Row],[Coluna7]]+280,IF(Tabela2[[#This Row],[Coluna11]]="Cheia",Tabela2[[#This Row],[Coluna9]]+280,"Vazia")))))

Sheet Ficha Reprodutivo IMPRIMIR
A1: CONTROLE DE MANEJOS REPRODUTIVOS
A2: N° vaca | B2: Categoria | C2: 1° IATF | D2: 1° DG | F2: 2° IATF | G2: 2° DG | I2: Touro | J2: DG final | L2: Nasc. | N2: Desmama.
C3: Data | D3: Data | E3: Resultado | F3: Data | G3: Data | H3: Resultado | I3: Data | J3: Data | K3: Resultado | L3: Data | M3: Sexo | N3: Data | O3: Peso

Sheet Formulação suplementos
C1: PLANILHA PARA FORMULAÇÃO DE SUPLEMENTOS PARA BOVINOS A PASTO
FB3: 180 | FL3: 300 | FU3: 300
FB4: Exigência | FC4: Código | FD4: Unidade | FE4: Mínimo | FF4: Ideal | FG4: Máximo | FL4: Exigência | FM4: Código | FN4: Unidade | FO4: Mínimo | FP4: Ideal | FQ4: Máximo | FU4: Exigência | FV4: Código | FW4: Unidade | FX4: Mínimo | FY4: Ideal | FZ4: Máximo
B5: INFORMAÇÕES P/ EXIGÊNCIA | E5: FORMULAÇÃO DO SUPLEMENTO | J5: EXIGÊNCIA x DIETA | R5: RESUMO DA DIETA GERAL | AH5: Ingr | AK5: Capim | FB5: Matéria Seca | FC5: MS | FD5: kg/dia | FF5: 5.5 | FG5: 6.05 | FH5: =FG5/FF5 -> 1.1 | FL5: Matéria Seca | FM5: MS | FN5: kg/dia | FP5: 6.85 | FQ5: 7.53 | FR5: =FQ5/FP5 -> 1.0992701 | FU5: Matéria Seca | FV5: MS | FW5: kg/dia | FY5: 6.85 | FZ5: 7.53 | GA5: =FZ5/FY5 -> 1.0992701
B6: Peso médio (kg) | C6: 500 | E6: Ingrediente | F6: % | G6: R$/kg | H6: R$ | J6: Descrição | K6: Ideal | L6: Máximo | M6: Dieta | N6: Resultado | O6: % na dieta | P6: % ideal | R6: Alimentos | S6: M.O. (Kg) | T6: M.S. (Kg) | U6: % P.V | V6: % da dieta | W6: Consumo total/cab | X6: Consumo total | AF6: Ureia pelo NNP | AH6: %MS | AK6: MS | AL6: NDT | AM6: PB | FB6: Extrato Etéreo | FC6: EE | FD6: kg/dia | FG6: 0.39 | FH6: =FG6/$FB$3 -> 0.0021666667 | FI6: =FG6/$FG$5 -> 0.06446281 | FL6: Extrato Etéreo | FM6: EE | FN6: kg/dia | FQ6: 0.48 | FR6: =FQ6/FL$3 -> 0.0016 | FS6: =FQ6/FQ$5 -> 0.06374502 | FU6: Extrato Etéreo | FV6: EE | FW6: kg/dia | FZ6: 0.48 | GA6: =FZ6/FU$3 -> 0.0016 | GB6: =FZ6/FZ$5 -> 0.06374502
B7: GMD (kg/cab/dia) | C7: 0.01 | H7: =G7*F7 -> 0 | J7: Matéria seca (MS) | K7: =CA33*C6/1000 -> 8.9038128 | L7: =K7*1.05 -> 9.3490035 | M7: =IFERROR(T21,0) -> 8.9038128 | N7: =IF(K7="","",IF(M7>L7,"Reduzir",IF(M7<K7,"Aumentar",IF(M7=K7,"Ok",IF(M7=L7,"Ok",IF(OR(M7>=K7,M7<=L7),"Ok")))))) -> Ok | O7: =IF(M7=0,"", $T$21/M7) -> 1 | P7: =IF(M7=0,"",K7/ $T$21) -> 1 | R7: =IF(C18="","",C18) -> Capim Mombaça | S7: =IF(IFERROR((K7-(C6*C19*AH20))/VLOOKUP(C18,'Formulação suplementos'!$B$29:$C$40,2,0),0)=0,"",IFERROR((K7-(C6*C19*AH20))/VLOOKUP(C18,'Formulação suplementos'!$B$29:$C$40,2,0),0)) -> 32.977085 | T7: =IF(R7="","",IFERROR(S7*(VLOOKUP(R7,'Formulação suplementos'!$B$29:$W$40,2,)),0)) -> 8.9038128 | U7: =IFERROR(T7/$C$6,"") -> 0.017807626 | V7: =IFERROR(T7/$T$21,"") -> 1 | W7: =IFERROR(X7/$C$20,"") -> 4946.5627 | X7: =IFERROR(S7*$C$16*$C$20,"") -> 494656.27 | AF7: =IFERROR(VLOOKUP(R7,'Formulação suplementos'!$B$56:$W$68,22,0)*T7,"") | AH7: =IF(E7="Ureia",F7,IFERROR(VLOOKUP(E7,'Formulação suplementos'!$B$43:$C$54,2,0)*F7,"")) | AK7: =VLOOKUP(R7,B29:E40,2,0) -> 0.27 | AL7: =VLOOKUP(R7,B29:E40,3,0) -> 0.59 | AM7: =VLOOKUP(R7,B29:E40,4,0) -> 0.12 | AV7: 3 | AW7: =AV7+1 -> 4 | AX7: =AW7+1 -> 5 | AY7: =AX7+1 -> 6 | AZ7: =AY7+1 -> 7 | BA7: =AZ7+1 -> 8 | BB7: =BA7+1 -> 9 | BC7: =BB7+1 -> 10 | BD7: =BC7+1 -> 11 | ... BM7: =BL7+1 -> 20 | FB7: Carboidratos Não Fibrosos | FC7: CNF | FD7: kg/dia | FG7: 4.4 | FH7: =FG7/$FB$3 -> 0.024444444 | FI7: =FG7/$FG$5 -> 0.72727273 | FL7: Carboidratos Não Fibrosos | FM7: CNF | FN7: kg/dia | FQ7: 5.48 | FR7: =FQ7/FL$3 -> 0.018266667 | FS7: =FQ7/FQ$5 -> 0.72775564 | FU7: Carboidratos Não Fibrosos | FV7: CNF | FW7: kg/dia | FZ7: 5.48 | GA7: =FZ7/FU$3 -> 0.018266667 | GB7: =FZ7/FZ$5 -> 0.72775564
B8: Categoria | C8: Primípara | H8: =G8*F8 -> 0 | J8: Extrato etéreo (EE) | K8: =IF(C6="","","Não consta") -> Não consta | L8: =IFERROR(L7*0.063,"") -> 0.58898722 | M8: =BB24/1000 -> 0.15403596 | N8: =IF(L8="","",IF(M8>L8,"Reduzir","Ok")) -> Ok | O8: =IF(M8=0,"", M8/$M$7) -> 0.0173 | P8: =IF(C6="","","Não consta") -> Não consta | R8: =IF(F7=0,"",IF(E7="","",E7)) | S8: =IF(IF(R8="","",F7*$AB$7)=0,"",IF(R8="","",F7*$AB$7)) | T8: =IF(R8="Ureia",S8,IF(S8="","",IFERROR(S8*(VLOOKUP(R8,'Formulação suplementos'!$B$42:$W$54,2,)),0))) | U8: =IFERROR(T8/$C$6,"") | V8: =IFERROR(T8/$T$21,"") | W8: =IFERROR(X8/$C$20,"") | X8: =IFERROR(S8*$C$16*$C$20,"") | AF8: =IFERROR(VLOOKUP(R8,'Formulação suplementos'!$B$56:$W$68,22,0)*T8,"") | AH8: =IF(E8="Ureia",F8,IFERROR(VLOOKUP(E8,'Formulação suplementos'!$B$43:$C$54,2,0)*F8,"")) | AV8: NDT (Kg) | AW8: P.B (Kg) | AX8: Ca (g) | AY8: P (g) | AZ8: PDR (kg) | BA8: FDN (kg) | BB8: EE (g) | BC8: Mg (g) | BD8: Na (g) | BE8: K (g) | BF8: S (g) | BG8: Cu (mg) | BH8: Zn (mg) | BI8: Fe (mg) | BJ8: Mn (mg) | BK8: I (mg) | BL8: Co (mg) | BM8: Se (mg) | FB8: Fibra em Detergente Neutro | FC8: FDN | FD8: kg/dia | FE8: 1.38 | FG8: 2.38 | FH8: =FG8/$FB$3 -> 0.013222222 | FI8: =FG8/$FG$5 -> 0.39338843 | FJ8: =FE8/FF5 -> 0.25090909 | FL8: Fibra em Detergente Neutro | FM8: FDN | FN8: kg/dia | FO8: 1.71 | FQ8: 3.96 | FR8: =FQ8/FL$3 -> 0.0132 | FS8: =FQ8/FQ$5 -> 0.52589641 | FT8: =FO8/FP5 -> 0.24963504 | FU8: Fibra em Detergente Neutro | FV8: FDN | FW8: kg/dia | FX8: 1.71 | FZ8: 3.96 | GA8: =FZ8/FU$3 -> 0.0132 | GB8: =FZ8/FZ$5 -> 0.52589641 | GC8: =FX8/FY5 -> 0.24963504
B9: Estado fisiológico | C9: Lactante | H9: =G9*F9 -> 0 | J9: FDN | K9: =IFERROR(ROUND(K7*0.25,2),"") -> 2.23 | L9: =IF(C6="","",ROUND(C6*1.32%,2)) -> 6.6 | M9: =BA24 -> 4.4519064 | N9: =IF(K9="","",IF(M9>L9,"Reduzir",IF(M9<K9,"Aumentar",IF(M9=K9,"Ok",IF(M9=L9,"Ok",IF(OR(M9>=K9,M9<=L9),"Ok")))))) -> Ok | O9: =IF(M9=0,"", M9/$M$7) -> 0.5 | P9: =IF(M9=0,"", K9/$T$21) -> 0.2504545 | R9: =IF(F8=0,"",IF(E8="","",E8)) | S9: =IF(IF(R9="","",F8*$AB$7)=0,"",IF(R9="","",F8*$AB$7)) | T9: =IF(R9="Ureia",S9,IF(S9="","",IFERROR(S9*(VLOOKUP(R9,'Formulação suplementos'!$B$42:$W$54,2,)),0))) | U9: =IFERROR(T9/$C$6,"") | V9: =IFERROR(T9/$T$21,"") | W9: =IFERROR(X9/$C$20,"") | X9: =IFERROR(S9*$C$16*$C$20,"") | AF9: =IFERROR(VLOOKUP(R9,'Formulação suplementos'!$B$56:$W$68,22,0)*T9,"") | AH9: =IF(E9="Ureia",F9,IFERROR(VLOOKUP(E9,'Formulação suplementos'!$B$43:$C$54,2,0)*F9,"")) | AK9: %EF colheita | AV9: =IFERROR($T$7*(VLOOKUP($R$7,'Formulação suplementos'!$B$29:$W$40,AV7,0)),0) -> 5.2532496 | AW9: =IFERROR($T$7*(VLOOKUP($R$7,'Formulação suplementos'!$B$29:$W$40,AW7,0)),0) -> 1.0684575 | AX9: =IFERROR($T$7*(VLOOKUP($R$7,'Formulação suplementos'!$B$29:$W$40,AX7,0)*1000),0) -> 65.888215 | AY9: =IFERROR($T$7*(VLOOKUP($R$7,'Formulação suplementos'!$B$29:$W$40,AY7,0)*1000),0) -> 16.917244 | AZ9: =IFERROR($T$7*(VLOOKUP($R$7,'Formulação suplementos'!$B$29:$W$40,AZ7,0)),0) -> 0 | BA9: =IFERROR($T$7*(VLOOKUP($R$7,'Formulação suplementos'!$B$29:$W$40,BA7,0)),0) -> 4.4519064 | BB9: =IFERROR($T$7*(VLOOKUP($R$7,'Formulação suplementos'!$B$29:$W$40,BB7,0)*1000),0) -> 154.03596 | BC9: =IFERROR($T$7*(VLOOKUP($R$7,'Formulação suplementos'!$B$29:$W$40,BC7,0)*1000),0) -> 17.807626 | BD9: =IFERROR($T$7*(VLOOKUP($R$7,'Formulação suplementos'!$B$29:$W$40,BD7,0)*1000),0) -> 0.89038128 | BE9: =IFERROR($T$7*(VLOOKUP($R$7,'Formulação suplementos'!$B$29:$W$40,BE7,0)*1000),0) -> 243.96447 | BF9: =IFERROR($T$7*(VLOOKUP($R$7,'Formulação suplementos'!$B$29:$W$40,BF7,0)*1000),0) -> 12.465338 | BG9: =IFERROR($T$7*(VLOOKUP($R$7,'Formulação suplementos'!$B$29:$W$40,BG7,0)),0) -> 89.661395 | BH9: =IFERROR($T$7*(VLOOKUP($R$7,'Formulação suplementos'!$B$29:$W$40,BH7,0)),0) -> 238.71122 | BI9: =IFERROR($T$7*(VLOOKUP($R$7,'Formulação suplementos'!$B$29:$W$40,BI7,0)),0) -> 0 | BJ9: =IFERROR($T$7*(VLOOKUP($R$7,'Formulação suplementos'!$B$29:$W$40,BJ7,0)),0) -> 890.29224 | BK9: =IFERROR($T$7*(VLOOKUP($R$7,'Formulação suplementos'!$B$29:$W$40,BK7,0)),0) -> 0 | BL9: =IFERROR($T$7*(VLOOKUP($R$7,'Formulação suplementos'!$B$29:$W$40,BL7,0)),0) -> 3.6505633 | BM9: =IFERROR($T$7*(VLOOKUP($R$7,'Formulação suplementos'!$B$29:$W$40,BM7,0)),0) -> 0 | FB9: FDN Fisicamente Efetiva | FC9: FDNfe | FD9: kg/dia | FE9: 2.45 | FG9: 6.2 | FH9: =FG9/$FB$3 -> 0.034444444 | FI9: =FG9/$FG$5 -> 1.0247934 | FL9: FDN Fisicamente Efetiva | FM9: FDNfe | FN9: kg/dia | FO9: 2.45 | FQ9: 6.2 | FR9: =FQ9/FL$3 -> 0.020666667 | FS9: =FQ9/FQ$5 -> 0.82337317 | FU9: FDN Fisicamente Efetiva | FV9: FDNfe | FW9: kg/dia | FX9: 2.45 | FZ9: 6.2 | GA9: =FZ9/FU$3 -> 0.020666667 | GB9: =FZ9/FZ$5 -> 0.82337317
B10: Semana lactação | C10: 5 | H10: =G10*F10 -> 0 | J10: NDT | K10: =IF(C9="Gestante e lactante",(CA50/4.4)*1.087,(CA50/4.4)) -> 5.3263787 | L10: =IFERROR(K10*1.05,"") -> 5.5926976 | M10: =AV24 -> 5.2532496 | N10: =IF(K10="","",IF(M10>L10,"Reduzir",IF(M10<K10,"Aumentar",IF(M10=K10,"Ok",IF(M10=L10,"Ok",IF(OR(M10>=K10,M10<=L10),"Ok")))))) -> Aumentar | O10: =IF(M10=0,"", M10/$M$7) -> 0.59 | P10: =IF(M10=0,"", K10/$T$21) -> 0.59821324 | R10: =IF(F9=0,"",IF(E9="","",E9)) | S10: =IF(IF(R10="","",F9*$AB$7)=0,"",IF(R10="","",F9*$AB$7)) | T10: =IF(R10="Ureia",S10,IF(S10="","",IFERROR(S10*(VLOOKUP(R10,'Formulação suplementos'!$B$42:$W$54,2,)),0))) | U10: =IFERROR(T10/$C$6,"") | V10: =IFERROR(T10/$T$21,"") | W10: =IFERROR(X10/$C$20,"") | X10: =IFERROR(S10*$C$16*$C$20,"") | AF10: =IFERROR(VLOOKUP(R10,'Formulação suplementos'!$B$56:$W$68,22,0)*T10,"") | AH10: =IF(E10="Ureia",F10,IFERROR(VLOOKUP(E10,'Formulação suplementos'!$B$43:$C$54,2,0)*F10,"")) | AK10: Contínuo | AL10: 0.3 | BY10: Categoria | BZ10: Primípara | FB10: Teor de Amido | FC10: AMIDO | FD10: kg/dia | FE10: 2.45 | FG10: 6.2 | FH10: =FG10/$FB$3 -> 0.034444444 | FI10: =FG10/$FG$5 -> 1.0247934 | FL10: Teor de Amido | FM10: AMIDO | FN10: kg/dia | FO10: 2.45 | FQ10: 6.2 | FR10: =FQ10/FL$3 -> 0.020666667 | FS10: =FQ10/FQ$5 -> 0.82337317 | FU10: Teor de Amido | FV10: AMIDO | FW10: kg/dia | FX10: 2.45 | FZ10: 6.2 | GA10: =FZ10/FU$3 -> 0.020666667 | GB10: =FZ10/FZ$5 -> 0.82337317
H11: =G11*F11 -> 0 | J11: Proteína Bruta (PB) | K11: =IF(C9="Gestante e lactante",(CM40+CM38)*1.2,(CM40+CM38)) -> 1024.382 | L11: =IFERROR(K11*1.3,"") -> 1331.6967 | M11: =IFERROR(AW24*1000,0) -> 1068.4575 | N11: =IF(K11="","",IF(M11>L11,"Reduzir",IF(M11<K11,"Aumentar",IF(M11=K11,"Ok",IF(M11=L11,"Ok",IF(OR(M11>=K11,M11<=L11),"Ok")))))) -> Ok | O11: =IF(M11=0,"",(M11/1000)/$T$21) -> 0.12 | P11: =IF(M11=0,"",(K11/1000)/$T$21) -> 0.11504982 | R11: =IF(F10=0,"",IF(E10="","",E10)) | S11: =IF(IF(R11="","",F10*$AB$7)=0,"",IF(R11="","",F10*$AB$7)) | T11: =IF(R11="Ureia",S11,IF(S11="","",IFERROR(S11*(VLOOKUP(R11,'Formulação suplementos'!$B$42:$W$54,2,)),0))) | U11: =IFERROR(T11/$C$6,"") | V11: =IFERROR(T11/$T$21,"") | W11: =IFERROR(X11/$C$20,"") | X11: =IFERROR(S11*$C$16*$C$20,"") | AF11: =IFERROR(VLOOKUP(R11,'Formulação suplementos'!$B$56:$W$68,22,0)*T11,"") | AH11: =IF(E11="Ureia",F11,IFERROR(VLOOKUP(E11,'Formulação suplementos'!$B$43:$C$54,2,0)*F11,"")) | AK11: Alternado | AL11: 0.5 | AV11: =IFERROR($T8*(VLOOKUP($R8,'Formulação suplementos'!$B$42:$W$54,AV$7,0)),0) -> 0 | AW11: =IFERROR($T8*(VLOOKUP($R8,'Formulação suplementos'!$B$42:$W$54,AW$7,0)),0) -> 0 | AX11: =IFERROR($T8*(VLOOKUP($R8,'Formulação suplementos'!$B$42:$W$54,AX$7,0)*1000),0) -> 0 | AY11: =IFERROR($T8*(VLOOKUP($R8,'Formulação suplementos'!$B$42:$W$54,AY$7,0)*1000),0) -> 0 | AZ11: =IFERROR($T8*(VLOOKUP($R8,'Formulação suplementos'!$B$42:$W$54,AZ$7,0)),0) -> 0 | BA11: =IFERROR($T8*(VLOOKUP($R8,'Formulação suplementos'!$B$42:$W$54,BA$7,0)),0) -> 0 | BB11: =IFERROR($T8*(VLOOKUP($R8,'Formulação suplementos'!$B$42:$W$54,BB$7,0)*1000),0) -> 0 | BC11: =IFERROR($T8*(VLOOKUP($R8,'Formulação suplementos'!$B$42:$W$54,BC$7,0)*1000),0) -> 0 | BD11: =IFERROR($T8*(VLOOKUP($R8,'Formulação suplementos'!$B$42:$W$54,BD$7,0)*1000),0) -> 0 | BE11: =IFERROR($T8*(VLOOKUP($R8,'Formulação suplementos'!$B$42:$W$54,BE$7,0)*1000),0) -> 0 | BF11: =IFERROR($T8*(VLOOKUP($R8,'Formulação suplementos'!$B$42:$W$54,BF$7,0)*1000),0) -> 0 | BG11: =IFERROR($T8*(VLOOKUP($R8,'Formulação suplementos'!$B$42:$W$54,BG$7,0)),0) -> 0 | BH11: =IFERROR($T8*(VLOOKUP($R8,'Formulação suplementos'!$B$42:$W$54,BH$7,0)),0) -> 0 | BI11: =IFERROR($T8*(VLOOKUP($R8,'Formulação suplementos'!$B$42:$W$54,BI$7,0)),0) -> 0 | BJ11: =IFERROR($T8*(VLOOKUP($R8,'Formulação suplementos'!$B$42:$W$54,BJ$7,0)),0) -> 0 | BK11: =IFERROR($T8*(VLOOKUP($R8,'Formulação suplementos'!$B$42:$W$54,BK$7,0)),0) -> 0 | BL11: =IFERROR($T8*(VLOOKUP($R8,'Formulação suplementos'!$B$42:$W$54,BL$7,0)),0) -> 0 | BM11: =IFERROR($T8*(VLOOKUP($R8,'Formulação suplementos'!$B$42:$W$54,BM$7,0)),0) -> 0 | BZ11: Multípara | FB11: Nutrientes Digestíveis Totais | FC11: NDT | FD11: kg/dia | FE11: 3.99 | FF11: 3.99 | FG11: 4.19 | FH11: =FG11/FF11 -> 1.0501253 | FL11: Nutrientes Digestíveis Totais | FM11: NDT | FN11: kg/dia | FO11: 4.23 | FP11: 4.23 | FQ11: 4.45 | FR11: =FQ11/FP11 -> 1.0520095 | FU11: Nutrientes Digestíveis Totais | FV11: NDT | FW11: kg/dia | FX11: 4.35 | FY11: 4.35 | FZ11: 4.56 | GA11: =FZ11/FY11 -> 1.0482759
H12: =G12*F12 -> 0 | J12: Cálcio (Ca) | K12: =IFERROR(IF(C9="Gestante e lactante",ROUND(CS20*1.08,1),ROUND(CS20,1)),"") -> 22.2 | L12: =IFERROR(K12*2,"") -> 44.4 | M12: =AX24 -> 65.888215 | N12: =IF(K12="","",IF(M12>L12,"Reduzir",IF(M12<K12,"Aumentar",IF(M12=K12,"Ok",IF(M12=L12,"Ok",IF(OR(M12>=K12,M12<=L12),"Ok")))))) -> Reduzir | O12: =IF(M12=0,"",(M12/1000)/$T$21) -> 0.0074 | P12: =IF(M12=0,"",(K12/1000)/$T$21) -> 0.0024933139 | R12: =IF(F11=0,"",IF(E11="","",E11)) | S12: =IF(IF(R12="","",F11*$AB$7)=0,"",IF(R12="","",F11*$AB$7)) | T12: =IF(R12="Ureia",S12,IF(S12="","",IFERROR(S12*(VLOOKUP(R12,'Formulação suplementos'!$B$42:$W$54,2,)),0))) | U12: =IFERROR(T12/$C$6,"") | V12: =IFERROR(T12/$T$21,"") | W12: =IFERROR(X12/$C$20,"") | X12: =IFERROR(S12*$C$16*$C$20,"") | AF12: =IFERROR(VLOOKUP(R12,'Formulação suplementos'!$B$56:$W$68,22,0)*T12,"") | AH12: =IF(E13="Ureia",F13,IFERROR(VLOOKUP(E13,'Formulação suplementos'!$B$43:$C$54,2,0)*F13,"")) | AK12: Rotacionado | AL12: 0.7 | AV12: =IFERROR($T9*(VLOOKUP($R9,'Formulação suplementos'!$B$42:$W$54,AV$7,0)),0) -> 0 | AW12: =IFERROR($T9*(VLOOKUP($R9,'Formulação suplementos'!$B$42:$W$54,AW$7,0)),0) -> 0 | AX12: =IFERROR($T9*(VLOOKUP($R9,'Formulação suplementos'!$B$42:$W$54,AX$7,0)*1000),0) -> 0 | AY12: =IFERROR($T9*(VLOOKUP($R9,'Formulação suplementos'!$B$42:$W$54,AY$7,0)*1000),0) -> 0 | AZ12: =IFERROR($T9*(VLOOKUP($R9,'Formulação suplementos'!$B$42:$W$54,AZ$7,0)),0) -> 0 | BA12: =IFERROR($T9*(VLOOKUP($R9,'Formulação suplementos'!$B$42:$W$54,BA$7,0)),0) -> 0 | BB12: =IFERROR($T9*(VLOOKUP($R9,'Formulação suplementos'!$B$42:$W$54,BB$7,0)*1000),0) -> 0 | BC12: =IFERROR($T9*(VLOOKUP($R9,'Formulação suplementos'!$B$42:$W$54,BC$7,0)*1000),0) -> 0 | BD12: =IFERROR($T9*(VLOOKUP($R9,'Formulação suplementos'!$B$42:$W$54,BD$7,0)*1000),0) -> 0 | BE12: =IFERROR($T9*(VLOOKUP($R9,'Formulação suplementos'!$B$42:$W$54,BE$7,0)*1000),0) -> 0 | BF12: =IFERROR($T9*(VLOOKUP($R9,'Formulação suplementos'!$B$42:$W$54,BF$7,0)*1000),0) -> 0 | BG12: =IFERROR($T9*(VLOOKUP($R9,'Formulação suplementos'!$B$42:$W$54,BG$7,0)),0) -> 0 | BH12: =IFERROR($T9*(VLOOKUP($R9,'Formulação suplementos'!$B$42:$W$54,BH$7,0)),0) -> 0 | BI12: =IFERROR($T9*(VLOOKUP($R9,'Formulação suplementos'!$B$42:$W$54,BI$7,0)),0) -> 0 | BJ12: =IFERROR($T9*(VLOOKUP($R9,'Formulação suplementos'!$B$42:$W$54,BJ$7,0)),0) -> 0 | BK12: =IFERROR($T9*(VLOOKUP($R9,'Formulação suplementos'!$B$42:$W$54,BK$7,0)),0) -> 0 | BL12: =IFERROR($T9*(VLOOKUP($R9,'Formulação suplementos'!$B$42:$W$54,BL$7,0)),0) -> 0 | BM12: =IFERROR($T9*(VLOOKUP($R9,'Formulação suplementos'!$B$42:$W$54,BM$7,0)),0) -> 0 | FB12: Proteína Bruta | FC12: PB | FD12: g/dia | FE12: 686.93 | FF12: 686.93 | FG12: 755.63 | FH12: =FG12/FF12 -> 1.1000102 | FL12: Proteína Bruta | FM12: PB | FN12: g/dia | FO12: 777.14 | FP12: 777.14 | FQ12: 854.85 | FR12: =FQ12/FP12 -> 1.0999949 | FU12: Proteína Bruta | FV12: PB | FW12: g/dia | FX12: 754.82 | FY12: 754.82 | FZ12: 830.4 | GA12: =FZ12/FY12 -> 1.1001298
H13: =G13*F13 -> 0 | J13: Fósforo (P) | K13: =IFERROR(IF(C9="Gestante e lactante",ROUND(CS22*1.08,1),ROUND(CS22,1)),"") -> 16.9 | L13: =IFERROR(K13*2,"") -> 33.8 | M13: =AY24 -> 16.917244 | N13: =IF(K13="","",IF(M13>L13,"Reduzir",IF(M13<K13,"Aumentar",IF(M13=K13,"Ok",IF(M13=L13,"Ok",IF(OR(M13>=K13,M13<=L13),"Ok")))))) -> Ok | O13: =IF(M13=0,"",(M13/1000)/$T$21) -> 0.0019 | P13: =IF(M13=0,"",(K13/1000)/$T$21) -> 0.0018980633 | R13: =IF(F13=0,"",IF(E13="","",E13)) | S13: =IF(IF(R13="","",F13*$AB$7)=0,"",IF(R13="","",F13*$AB$7)) | T13: =IF(R13="Ureia",S13,IF(S13="","",IFERROR(S13*(VLOOKUP(R13,'Formulação suplementos'!$B$42:$W$54,2,)),0))) | U13: =IFERROR(T13/$C$6,"") | V13: =IFERROR(T13/$T$21,"") | W13: =IFERROR(X13/$C$20,"") | X13: =IFERROR(S13*$C$16*$C$20,"") | AF13: =IFERROR(VLOOKUP(R13,'Formulação suplementos'!$B$56:$W$68,22,0)*T13,"") | AH13: =IFERROR(VLOOKUP(E14,'Formulação suplementos'!$B$57:$C$68,2,0)*F14,"") | AK13: Ultra-denso | AL13: 0.95 | AV13: =IFERROR($T10*(VLOOKUP($R10,'Formulação suplementos'!$B$42:$W$54,AV$7,0)),0) -> 0 | AW13: =IFERROR($T10*(VLOOKUP($R10,'Formulação suplementos'!$B$42:$W$54,AW$7,0)),0) -> 0 | AX13: =IFERROR($T10*(VLOOKUP($R10,'Formulação suplementos'!$B$42:$W$54,AX$7,0)*1000),0) -> 0 | AY13: =IFERROR($T10*(VLOOKUP($R10,'Formulação suplementos'!$B$42:$W$54,AY$7,0)*1000),0) -> 0 | AZ13: =IFERROR($T10*(VLOOKUP($R10,'Formulação suplementos'!$B$42:$W$54,AZ$7,0)),0) -> 0 | BA13: =IFERROR($T10*(VLOOKUP($R10,'Formulação suplementos'!$B$42:$W$54,BA$7,0)),0) -> 0 | BB13: =IFERROR($T10*(VLOOKUP($R10,'Formulação suplementos'!$B$42:$W$54,BB$7,0)*1000),0) -> 0 | BC13: =IFERROR($T10*(VLOOKUP($R10,'Formulação suplementos'!$B$42:$W$54,BC$7,0)*1000),0) -> 0 | BD13: =IFERROR($T10*(VLOOKUP($R10,'Formulação suplementos'!$B$42:$W$54,BD$7,0)*1000),0) -> 0 | BE13: =IFERROR($T10*(VLOOKUP($R10,'Formulação suplementos'!$B$42:$W$54,BE$7,0)*1000),0) -> 0 | BF13: =IFERROR($T10*(VLOOKUP($R10,'Formulação suplementos'!$B$42:$W$54,BF$7,0)*1000),0) -> 0 | BG13: =IFERROR($T10*(VLOOKUP($R10,'Formulação suplementos'!$B$42:$W$54,BG$7,0)),0) -> 0 | BH13: =IFERROR($T10*(VLOOKUP($R10,'Formulação suplementos'!$B$42:$W$54,BH$7,0)),0) -> 0 | BI13: =IFERROR($T10*(VLOOKUP($R10,'Formulação suplementos'!$B$42:$W$54,BI$7,0)),0) -> 0 | BJ13: =IFERROR($T10*(VLOOKUP($R10,'Formulação suplementos'!$B$42:$W$54,BJ$7,0)),0) -> 0 | BK13: =IFERROR($T10*(VLOOKUP($R10,'Formulação suplementos'!$B$42:$W$54,BK$7,0)),0) -> 0 | BL13: =IFERROR($T10*(VLOOKUP($R10,'Formulação suplementos'!$B$42:$W$54,BL$7,0)),0) -> 0 | BM13: =IFERROR($T10*(VLOOKUP($R10,'Formulação suplementos'!$B$42:$W$54,BM$7,0)),0) -> 0 | FB13: Cálcio | FC13: Ca | FD13: g/dia | FE13: 33.1 | FF13: 33.1 | FG13: 66.21 | FH13: =FG13/FF13 -> 2.0003021 | FL13: Cálcio | FM13: Ca | FN13: g/dia | FO13: 22 | FP13: 22 | FQ13: 43.99 | FR13: =FQ13/FP13 -> 1.9995455 | FU13: Cálcio | FV13: Ca | FW13: g/dia | FX13: 21.77 | FY13: 21.77 | FZ13: 43.54 | GA13: =FZ13/FY13 -> 2
H14: =G14*F14 -> 0 | J14: Magnésio (mg) | K14: =IFERROR(IF(C9="Gestante e lactante",ROUND(CS25*1.15,1),ROUND(CS25,1)),"") -> 9.5 | L14: =IFERROR(K14*3,"") -> 28.5 | M14: =BC24 -> 0 | N14: =IF(K14="","",IF(M14>L14,"Reduzir",IF(M14<K14,"Aumentar",IF(M14=K14,"Ok",IF(M14=L14,"Ok",IF(OR(M14>=K14,M14<=L14),"Ok")))))) -> Aumentar | O14: =IF(M14=0,"",(M14/1000)/$T$21) | P14: =IF(M14=0,"",(K14/1000)/$T$21) | R14: =IF(F14=0,"",IF(E14="","",E14)) | S14: =IF(IF(R14="","",F14*$AB$7)=0,"",IF(R14="","",F14*$AB$7)) | T14: =IF(S14="","",IFERROR(S14*(VLOOKUP(R14,'Formulação suplementos'!$B$56:$W$68,2,)),0)) | U14: =IFERROR(T14/$C$6,"") | V14: =IFERROR(T14/$T$21,"") | W14: =IFERROR(X14/$C$20,"") | X14: =IFERROR(S14*$C$16*$C$20,"") | AF14: =IFERROR(VLOOKUP(R14,'Formulação suplementos'!$B$56:$W$68,22,0)*T14,"") | AH14: =IFERROR(VLOOKUP(E15,'Formulação suplementos'!$B$57:$C$68,2,0)*F15,"") | AK14: Ponta 7X | AL14: 0.8 | AV14: =IFERROR($T11*(VLOOKUP($R11,'Formulação suplementos'!$B$42:$W$54,AV$7,0)),0) -> 0 | AW14: =IFERROR($T11*(VLOOKUP($R11,'Formulação suplementos'!$B$42:$W$54,AW$7,0)),0) -> 0 | AX14: =IFERROR($T11*(VLOOKUP($R11,'Formulação suplementos'!$B$42:$W$54,AX$7,0)*1000),0) -> 0 | AY14: =IFERROR($T11*(VLOOKUP($R11,'Formulação suplementos'!$B$42:$W$54,AY$7,0)*1000),0) -> 0 | AZ14: =IFERROR($T11*(VLOOKUP($R11,'Formulação suplementos'!$B$42:$W$54,AZ$7,0)),0) -> 0 | BA14: =IFERROR($T11*(VLOOKUP($R11,'Formulação suplementos'!$B$42:$W$54,BA$7,0)),0) -> 0 | BB14: =IFERROR($T11*(VLOOKUP($R11,'Formulação suplementos'!$B$42:$W$54,BB$7,0)*1000),0) -> 0 | BC14: =IFERROR($T11*(VLOOKUP($R11,'Formulação suplementos'!$B$42:$W$54,BC$7,0)*1000),0) -> 0 | BD14: =IFERROR($T11*(VLOOKUP($R11,'Formulação suplementos'!$B$42:$W$54,BD$7,0)*1000),0) -> 0 | BE14: =IFERROR($T11*(VLOOKUP($R11,'Formulação suplementos'!$B$42:$W$54,BE$7,0)*1000),0) -> 0 | BF14: =IFERROR($T11*(VLOOKUP($R11,'Formulação suplementos'!$B$42:$W$54,BF$7,0)*1000),0) -> 0 | BG14: =IFERROR($T11*(VLOOKUP($R11,'Formulação suplementos'!$B$42:$W$54,BG$7,0)),0) -> 0 | BH14: =IFERROR($T11*(VLOOKUP($R11,'Formulação suplementos'!$B$42:$W$54,BH$7,0)),0) -> 0 | BI14: =IFERROR($T11*(VLOOKUP($R11,'Formulação suplementos'!$B$42:$W$54,BI$7,0)),0) -> 0 | BJ14: =IFERROR($T11*(VLOOKUP($R11,'Formulação suplementos'!$B$42:$W$54,BJ$7,0)),0) -> 0 | BK14: =IFERROR($T11*(VLOOKUP($R11,'Formulação suplementos'!$B$42:$W$54,BK$7,0)),0) -> 0 | BL14: =IFERROR($T11*(VLOOKUP($R11,'Formulação suplementos'!$B$42:$W$54,BL$7,0)),0) -> 0 | BM14: =IFERROR($T11*(VLOOKUP($R11,'Formulação suplementos'!$B$42:$W$54,BM$7,0)),0) -> 0 | FB14: Fósforo | FC14: P | FD14: g/dia | FE14: 17.04 | FF14: 17.04 | FG14: 34.08 | FH14: =FG14/FF14 -> 2 | FL14: Fósforo | FM14: P | FN14: g/dia | FO14: 13.5 | FP14: 13.5 | FQ14: 27.01 | FR14: =FQ14/FP14 -> 2.0007407 | FU14: Fósforo | FV14: P | FW14: g/dia | FX14: 13.43 | FY14: 13.43 | FZ14: 26.85 | GA14: =FZ14/FY14 -> 1.9992554
B15: INFORMAÇÕES DO SISTEMA | H15: =G15*F15 -> 0 | J15: Potássio (K) | K15: =IFERROR(IF(C9="Gestante e lactante",ROUND(CS29*1.15,1),ROUND(CS29,1)),"") -> 33.1 | L15: =IFERROR(K15*3,"") -> 99.3 | M15: =BE24 -> 243.96447 | N15: =IF(K15="","",IF(M15>L15,"Reduzir",IF(M15<K15,"Aumentar",IF(M15=K15,"Ok",IF(M15=L15,"Ok",IF(OR(M15>=K15,M15<=L15),"Ok")))))) -> Reduzir | O15: =IF(M15=0,"",(M15/1000)/$T$21) -> 0.0274 | P15: =IF(M15=0,"",(K15/1000)/$T$21) -> 0.0037175085 | R15: =IF(F15=0,"",IF(E15="","",E15)) | S15: =IF(IF(R15="","",F15*$AB$7)=0,"",IF(R15="","",F15*$AB$7)) | T15: =IF(S15="","",IFERROR(S15*(VLOOKUP(R15,'Formulação suplementos'!$B$56:$W$68,2,)),0)) | U15: =IFERROR(T15/$C$6,"") | V15: =IFERROR(T15/$T$21,"") | W15: =IFERROR(X15/$C$20,"") | X15: =IFERROR(S15*$C$16*$C$20,"") | AF15: =IFERROR(VLOOKUP(R15,'Formulação suplementos'!$B$56:$W$68,22,0)*T15,"") | AH15: =IFERROR(VLOOKUP(E16,'Formulação suplementos'!$B$57:$C$68,2,0)*F16,"") | AV15: =IFERROR($T12*(VLOOKUP($R12,'Formulação suplementos'!$B$42:$W$54,AV$7,0)),0) -> 0 | AW15: =IFERROR($T12*(VLOOKUP($R12,'Formulação suplementos'!$B$42:$W$54,AW$7,0)),0) -> 0 | AX15: =IFERROR($T12*(VLOOKUP($R12,'Formulação suplementos'!$B$42:$W$54,AX$7,0)*1000),0) -> 0 | AY15: =IFERROR($T12*(VLOOKUP($R12,'Formulação suplementos'!$B$42:$W$54,AY$7,0)*1000),0) -> 0 | AZ15: =IFERROR($T12*(VLOOKUP($R12,'Formulação suplementos'!$B$42:$W$54,AZ$7,0)),0) -> 0 | BA15: =IFERROR($T12*(VLOOKUP($R12,'Formulação suplementos'!$B$42:$W$54,BA$7,0)),0) -> 0 | BB15: =IFERROR($T12*(VLOOKUP($R12,'Formulação suplementos'!$B$42:$W$54,BB$7,0)*1000),0) -> 0 | BC15: =IFERROR($T12*(VLOOKUP($R12,'Formulação suplementos'!$B$42:$W$54,BC$7,0)*1000),0) -> 0 | BD15: =IFERROR($T12*(VLOOKUP($R12,'Formulação suplementos'!$B$42:$W$54,BD$7,0)*1000),0) -> 0 | BE15: =IFERROR($T12*(VLOOKUP($R12,'Formulação suplementos'!$B$42:$W$54,BE$7,0)*1000),0) -> 0 | BF15: =IFERROR($T12*(VLOOKUP($R12,'Formulação suplementos'!$B$42:$W$54,BF$7,0)*1000),0) -> 0 | BG15: =IFERROR($T12*(VLOOKUP($R12,'Formulação suplementos'!$B$42:$W$54,BG$7,0)),0) -> 0 | BH15: =IFERROR($T12*(VLOOKUP($R12,'Formulação suplementos'!$B$42:$W$54,BH$7,0)),0) -> 0 | BI15: =IFERROR($T12*(VLOOKUP($R12,'Formulação suplementos'!$B$42:$W$54,BI$7,0)),0) -> 0 | BJ15: =IFERROR($T12*(VLOOKUP($R12,'Formulação suplementos'!$B$42:$W$54,BJ$7,0)),0) -> 0 | BK15: =IFERROR($T12*(VLOOKUP($R12,'Formulação suplementos'!$B$42:$W$54,BK$7,0)),0) -> 0 | BL15: =IFERROR($T12*(VLOOKUP($R12,'Formulação suplementos'!$B$42:$W$54,BL$7,0)),0) -> 0 | BM15: =IFERROR($T12*(VLOOKUP($R12,'Formulação suplementos'!$B$42:$W$54,BM$7,0)),0) -> 0 | DN15: Sem Lac | DO15: 2 | DS15: GMD | DT15: 0.2 | FB15: Magnésio | FC15: Mg | FD15: g/dia | FE15: 4.13 | FF15: 4.13 | FG15: 12.38 | FH15: =FG15/FF15 -> 2.9975787 | FL15: Magnésio | FM15: Mg | FN15: g/dia | FO15: 5.99 | FP15: 5.99 | FQ15: 17.96 | FR15: =FQ15/FP15 -> 2.9983306 | FU15: Magnésio | FV15: Mg | FW15: g/dia | FX15: 5.99 | FY15: 5.99 | FZ15: 17.96 | GA15: =FZ15/FY15 -> 2.9983306
B16: Dias de uso | C16: 150 | H16: =G16*F16 -> 0 | J16: Sódio (Na) | K16: =IFERROR(IF(C9="Gestante e lactante",ROUND(CS27*1.15,1),ROUND(CS27,1)),"") -> 11.8 | L16: =IFERROR(K16*6,"") -> 70.8 | M16: =BD24 -> 0.89038128 | N16: =IF(K16="","",IF(M16>L16,"Reduzir",IF(M16<K16,"Aumentar",IF(M16=K16,"Ok",IF(M16=L16,"Ok",IF(OR(M16>=K16,M16<=L16),"Ok")))))) -> Aumentar | O16: =IF(M16=0,"",(M16/1000)/$T$21) -> 0.0001 | P16: =IF(M16=0,"",(K16/1000)/$T$21) -> 0.0013252749 | R16: =IF(F16=0,"",IF(E16="","",E16)) | S16: =IF(IF(R16="","",F16*$AB$7)=0,"",IF(R16="","",F16*$AB$7)) | T16: =IF(S16="","",IFERROR(S16*(VLOOKUP(R16,'Formulação suplementos'!$B$56:$W$68,2,)),0)) | U16: =IFERROR(T16/$C$6,"") | V16: =IFERROR(T16/$T$21,"") | W16: =IFERROR(X16/$C$20,"") | X16: =IFERROR(S16*$C$16*$C$20,"") | AF16: =IFERROR(VLOOKUP(R16,'Formulação suplementos'!$B$56:$W$68,22,0)*T16,"") | AH16: =IFERROR(VLOOKUP(E17,'Formulação suplementos'!$B$57:$C$68,2,0)*F17,"") | AV16: =IFERROR($T13*(VLOOKUP($R13,'Formulação suplementos'!$B$42:$W$54,AV$7,0)),0) -> 0 | AW16: =IFERROR($T13*(VLOOKUP($R13,'Formulação suplementos'!$B$42:$W$54,AW$7,0)),0) -> 0 | AX16: =IFERROR($T13*(VLOOKUP($R13,'Formulação suplementos'!$B$42:$W$54,AX$7,0)*1000),0) -> 0 | AY16: =IFERROR($T13*(VLOOKUP($R13,'Formulação suplementos'!$B$42:$W$54,AY$7,0)*1000),0) -> 0 | AZ16: =IFERROR($T13*(VLOOKUP($R13,'Formulação suplementos'!$B$42:$W$54,AZ$7,0)),0) -> 0 | BA16: =IFERROR($T13*(VLOOKUP($R13,'Formulação suplementos'!$B$42:$W$54,BA$7,0)),0) -> 0 | BB16: =IFERROR($T13*(VLOOKUP($R13,'Formulação suplementos'!$B$42:$W$54,BB$7,0)*1000),0) -> 0 | BC16: =IFERROR($T13*(VLOOKUP($R13,'Formulação suplementos'!$B$42:$W$54,BC$7,0)*1000),0) -> 0 | BD16: =IFERROR($T13*(VLOOKUP($R13,'Formulação suplementos'!$B$42:$W$54,BD$7,0)*1000),0) -> 0 | BE16: =IFERROR($T13*(VLOOKUP($R13,'Formulação suplementos'!$B$42:$W$54,BE$7,0)*1000),0) -> 0 | BF16: =IFERROR($T13*(VLOOKUP($R13,'Formulação suplementos'!$B$42:$W$54,BF$7,0)*1000),0) -> 0 | BG16: =IFERROR($T13*(VLOOKUP($R13,'Formulação suplementos'!$B$42:$W$54,BG$7,0)),0) -> 0 | BH16: =IFERROR($T13*(VLOOKUP($R13,'Formulação suplementos'!$B$42:$W$54,BH$7,0)),0) -> 0 | BI16: =IFERROR($T13*(VLOOKUP($R13,'Formulação suplementos'!$B$42:$W$54,BI$7,0)),0) -> 0 | BJ16: =IFERROR($T13*(VLOOKUP($R13,'Formulação suplementos'!$B$42:$W$54,BJ$7,0)),0) -> 0 | BK16: =IFERROR($T13*(VLOOKUP($R13,'Formulação suplementos'!$B$42:$W$54,BK$7,0)),0) -> 0 | BL16: =IFERROR($T13*(VLOOKUP($R13,'Formulação suplementos'!$B$42:$W$54,BL$7,0)),0) -> 0 | BM16: =IFERROR($T13*(VLOOKUP($R13,'Formulação suplementos'!$B$42:$W$54,BM$7,0)),0) -> 0 | DN16: GMD, kg | DO16: 0.1 | DS16: si | DT16: 1 | DU16: =-53.07 + (304.89 * (DT16-'Formulação suplementos'!$CA$214)) + (90.79 *('Formulação suplementos'!$CY$30)) - (3.13 *('Formulação suplementos'!$CY$30)^2) -> 260.45164 | FB16: Potássio | FC16: K | FD16: g/dia | FE16: 13.15 | FF16: 13.15 | FG16: 39.45 | FH16: =FG16/FF16 -> 3 | FL16: Potássio | FM16: K | FN16: g/dia | FO16: 18.25 | FP16: 18.25 | FQ16: 54.74 | FR16: =FQ16/FP16 -> 2.9994521 | FU16: Potássio | FV16: K | FW16: g/dia | FX16: 18.26 | FY16: 18.26 | FZ16: 54.78 | GA16: =FZ16/FY16 -> 3
B17: R$/@ venda | C17: 300 | H17: =G17*F17 -> 0 | J17: Enxofre (S) | K17: =IF(C6="","",ROUND(CS31,1)) -> 9.2 | L17: =IFERROR(K17*3,"") -> 27.6 | M17: =BF24 -> 12.465338 | N17: =IF(K17="","",IF(M17>L17,"Reduzir",IF(M17<K17,"Aumentar",IF(M17=K17,"Ok",IF(M17=L17,"Ok",IF(OR(M17>=K17,M17<=L17),"Ok")))))) -> Ok | O17: =IF(M17=0,"",(M17/1000)/$T$21) -> 0.0014 | P17: =IF(M17=0,"",(K17/1000)/$T$21) -> 0.0010332652 | R17: =IF(F17=0,"",IF(E17="","",E17)) | S17: =IF(IF(R17="","",F17*$AB$7)=0,"",IF(R17="","",F17*$AB$7)) | T17: =IF(S17="","",IFERROR(S17*(VLOOKUP(R17,'Formulação suplementos'!$B$56:$W$68,2,)),0)) | U17: =IFERROR(T17/$C$6,"") | V17: =IFERROR(T17/$T$21,"") | W17: =IFERROR(X17/$C$20,"") | X17: =IFERROR(S17*$C$16*$C$20,"") | AF17: =IFERROR(VLOOKUP(R17,'Formulação suplementos'!$B$56:$W$68,22,0)*T17,"") | AH17: =IFERROR(VLOOKUP(E18,'Formulação suplementos'!$B$57:$C$68,2,0)*F18,"") | DO17: =((120*'Formulação suplementos'!K10)+('Formulação suplementos'!CM37-(120*'Formulação suplementos'!K10)*0.64)/0.8)/1000 -> 1.0214078 | DP17: =-53.07 + (304.89 * (DO17)) + (90.79 *'Formulação suplementos'!$K$10) - (3.13 * 'Formulação suplementos'!$K$10*'Formulação suplementos'!$K$10) -> 653.12987 | DS17: sp | DT17: =((DU16+('Formulação suplementos'!$CY$36-(DU16*0.64))/0.8)/1000) -> 0.47407014 | DU17: =-53.07 + (304.89 * (DT17-'Formulação suplementos'!$CA$214)) + (90.79 *('Formulação suplementos'!$CY$30)) - (3.13 *('Formulação suplementos'!$CY$30)^2) -> 100.10089 | FB17: Sódio | FC17: Na | FD17: g/dia | FE17: 8.07 | FF17: 8.07 | FG17: 48.39 | FH17: =FG17/FF17 -> 5.9962825 | FL17: Sódio | FM17: Na | FN17: g/dia | FO17: 7.87 | FP17: 7.87 | FQ17: 47.24 | FR17: =FQ17/FP17 -> 6.0025413 | FU17: Sódio | FV17: Na | FW17: g/dia | FX17: 7.85 | FY17: 7.85 | FZ17: 47.1 | GA17: =FZ17/FY17 -> 6
B18: Forragem | C18: Capim Mombaça | H18: =G18*F18 -> 0 | J18: Cobalto (Co) | K18: =IFERROR(IF(C9="Gestante e lactante",ROUND(CS36*1.15,1),ROUND(CS36,1)),"") -> 9.4 | L18: =IFERROR(K18*20,"") -> 188 | M18: =BL24 -> 3.6505633 | N18: =IF(K18="","",IF(M18>L18,"Reduzir",IF(M18<K18,"Aumentar",IF(M18=K18,"Ok",IF(M18=L18,"Ok",IF(OR(M18>=K18,M18<=L18),"Ok")))))) -> Aumentar | O18: =IF(M18=0,"",(M18/1000000)/$T$21) -> 4.1e-07 | P18: =IF(M18=0,"",(K18/1000000)/T$21) -> 1.0557275e-06 | R18: =IF(F18=0,"",IF(E18="","",E18)) | S18: =IF(IF(R18="","",F18*$AB$7)=0,"",IF(R18="","",F18*$AB$7)) | T18: =IF(S18="","",IFERROR(S18*(VLOOKUP(R18,'Formulação suplementos'!$B$56:$W$68,2,)),0)) | U18: =IFERROR(T18/$C$6,"") | V18: =IFERROR(T18/$T$21,"") | W18: =IFERROR(X18/$C$20,"") | X18: =IFERROR(S18*$C$16*$C$20,"") | AF18: =IFERROR(VLOOKUP(R18,'Formulação suplementos'!$B$56:$W$68,22,0)*T18,"") | AH18: =IFERROR(VLOOKUP(E19,'Formulação suplementos'!$B$57:$C$68,2,0)*F19,"") | AV18: =IFERROR($T14*(VLOOKUP($R14,'Formulação suplementos'!$B$56:$W$68,AV$7,0))/1000,0) -> 0 | AW18: =IFERROR($T14*(VLOOKUP($R14,'Formulação suplementos'!$B$56:$W$68,AW$7,0))/1000,0) -> 0 | AX18: =IFERROR($T14*(VLOOKUP($R14,'Formulação suplementos'!$B$56:$W$68,AX$7,0)),0) -> 0 | AY18: =IFERROR($T14*(VLOOKUP($R14,'Formulação suplementos'!$B$56:$W$68,AY$7,0)),0) -> 0 | AZ18: =IFERROR($T14*(VLOOKUP($R14,'Formulação suplementos'!$B$56:$W$68,AZ$7,0)),0) -> 0 | BA18: =IFERROR($T14*(VLOOKUP($R14,'Formulação suplementos'!$B$56:$W$68,BA$7,0)),0) -> 0 | BB18: =IFERROR($T14*(VLOOKUP($R14,'Formulação suplementos'!$B$56:$W$68,BB$7,0)),0) -> 0 | BC18: =IFERROR($T14*(VLOOKUP($R14,'Formulação suplementos'!$B$56:$W$68,BC$7,0)),0) -> 0 | BD18: =IFERROR($T14*(VLOOKUP($R14,'Formulação suplementos'!$B$56:$W$68,BD$7,0)),0) -> 0 | BE18: =IFERROR($T14*(VLOOKUP($R14,'Formulação suplementos'!$B$56:$W$68,BE$7,0)),0) -> 0 | ... BM18: =IFERROR($T14*(VLOOKUP($R14,'Formulação suplementos'!$B$56:$W$68,BM$7,0)),0) -> 0 | CK18: GERAIS | CP18: MINERAIS | CW18: GERAIS | DB18: MINERAIS | DO18: =(DP17+('Formulação suplementos'!$CM$37-(DP17*0.64))/0.8)/1000 -> 1.0242007 | DP18: =-53.07 + (304.89 * (DO18)) + (90.79 *'Formulação suplementos'!$K$10) - (3.13 * 'Formulação suplementos'!$K$10*'Formulação suplementos'!$K$10) -> 653.9814 | DT18: =(DU17+('Formulação suplementos'!$CY$36-(DU17*0.64))/0.8)/1000 -> 0.44199999 | DU18: =-53.07 + (304.89 * (DT18-'Formulação suplementos'!$CA$214)) + (90.79 *('Formulação suplementos'!$CY$30)) - (3.13 *('Formulação suplementos'!$CY$30)^2) -> 90.323017 | FB18: Enxofre | FC18: S | FD18: g/dia | FE18: 6.63 | FF18: 6.63 | FG18: 19.9 | FH18: =FG18/FF18 -> 3.0015083 | FL18: Enxofre | FM18: S | FN18: g/dia | FO18: 9.09 | FP18: 9.09 | FQ18: 27.28 | FR18: =FQ18/FP18 -> 3.0011001 | FU18: Enxofre | FV18: S | FW18: g/dia | FX18: 9.23 | FY18: 9.23 | FZ18: 27.68 | GA18: =FZ18/FY18 -> 2.9989166
B19: Cons. Supl. (%P.V) | C19: 0.0005 | H19: =G19*F19 -> 0 | J19: Cobre (Cu) | K19: =IFERROR(IF(C9="Gestante e lactante",ROUND(CS34*1.15,1),ROUND(CS34,1)),"") -> 81.6 | L19: =IFERROR(K19*3,"") -> 244.8 | M19: =BG24 -> 89.661395 | N19: =IF(K19="","",IF(M19>L19,"Reduzir",IF(M19<K19,"Aumentar",IF(M19=K19,"Ok",IF(M19=L19,"Ok",IF(OR(M19>=K19,M19<=L19),"Ok")))))) -> Ok | O19: =IF(M19=0,"",(M19/1000000)/$T$21) -> 1.007e-05 | P19: =IF(M19=0,"",(K19/1000000)/T$21) -> 9.1646131e-06 | R19: =IF(F19=0,"",IF(E19="","",E19)) | S19: =IF(IF(R19="","",F19*$AB$7)=0,"",IF(R19="","",F19*$AB$7)) | T19: =IF(S19="","",IFERROR(S19*(VLOOKUP(R19,'Formulação suplementos'!$B$56:$W$68,2,)),0)) | U19: =IFERROR(T19/$C$6,"") | V19: =IFERROR(T19/$T$21,"") | W19: =IFERROR(X19/$C$20,"") | X19: =IFERROR(S19*$C$16*$C$20,"") | AF19: =IFERROR(VLOOKUP(R19,'Formulação suplementos'!$B$56:$W$68,22,0)*T19,"") | AH19: =IFERROR(VLOOKUP(E20,'Formulação suplementos'!$B$57:$C$68,2,0)*F20,"") | AV19: =IFERROR($T15*(VLOOKUP($R15,'Formulação suplementos'!$B$56:$W$68,AV$7,0))/1000,0) -> 0 | AW19: =IFERROR($T15*(VLOOKUP($R15,'Formulação suplementos'!$B$56:$W$68,AW$7,0))/1000,0) -> 0 | AX19: =IFERROR($T15*(VLOOKUP($R15,'Formulação suplementos'!$B$56:$W$68,AX$7,0)),0) -> 0 | AY19: =IFERROR($T15*(VLOOKUP($R15,'Formulação suplementos'!$B$56:$W$68,AY$7,0)),0) -> 0 | AZ19: =IFERROR($T15*(VLOOKUP($R15,'Formulação suplementos'!$B$56:$W$68,AZ$7,0)),0) -> 0 | BA19: =IFERROR($T15*(VLOOKUP($R15,'Formulação suplementos'!$B$56:$W$68,BA$7,0)),0) -> 0 | BB19: =IFERROR($T15*(VLOOKUP($R15,'Formulação suplementos'!$B$56:$W$68,BB$7,0)),0) -> 0 | BC19: =IFERROR($T15*(VLOOKUP($R15,'Formulação suplementos'!$B$56:$W$68,BC$7,0)),0) -> 0 | BD19: =IFERROR($T15*(VLOOKUP($R15,'Formulação suplementos'!$B$56:$W$68,BD$7,0)),0) -> 0 | BE19: =IFERROR($T15*(VLOOKUP($R15,'Formulação suplementos'!$B$56:$W$68,BE$7,0)),0) -> 0 | ... BM19: =IFERROR($T15*(VLOOKUP($R15,'Formulação suplementos'!$B$56:$W$68,BM$7,0)),0) -> 0 | DN19: ndt | DO19: =(DP18+('Formulação suplementos'!$CM$37-(DP18*0.64))/0.8)/1000 -> 1.024371 | DP19: =-53.07 + (304.89 * (DO19)) + (90.79 *'Formulação suplementos'!$K$10) - (3.13 * 'Formulação suplementos'!$K$10*'Formulação suplementos'!$K$10) -> 654.03332 | DT19: =(DU18+('Formulação suplementos'!$CY$36-(DU18*0.64))/0.8)/1000 -> 0.44004442 | DU19: =-53.07 + (304.89 * (DT19-'Formulação suplementos'!$CA$214)) + (90.79 *('Formulação suplementos'!$CY$30)) - (3.13 *('Formulação suplementos'!$CY$30)^2) -> 89.726782 | FB19: Cobalto | FC19: Co | FD19: mg/dia | FE19: 2.82 | FF19: 2.82 | FG19: 56.4 | FH19: =FG19/FF19 -> 20 | FL19: Cobalto | FM19: Co | FN19: mg/dia | FO19: 4.68 | FP19: 4.68 | FQ19: 93.6 | FR19: =FQ19/FP19 -> 20 | FU19: Cobalto | FV19: Co | FW19: mg/dia | FX19: 4.68 | FY19: 4.68 | FZ19: 93.6 | GA19: =FZ19/FY19 -> 20
B20: n° de animais (cab) | C20: 100 | H20: =G20*F20 -> 0 | J20: Manganês (Mn) | K20: =IFERROR(IF(C9="Gestante e lactante",ROUND(CS42*1.18,1),ROUND(CS42,1)),"") -> 230.3 | L20: =IFERROR(K20*3,"") -> 690.9 | M20: =BJ24 -> 890.29224 | N20: =IF(K20="","",IF(M20>L20,"Reduzir",IF(M20<K20,"Aumentar",IF(M20=K20,"Ok",IF(M20=L20,"Ok",IF(OR(M20>=K20,M20<=L20),"Ok")))))) -> Reduzir | O20: =IF(M20=0,"",(M20/1000000)/$T$21) -> 9.999e-05 | P20: =IF(M20=0,"",(K20/1000000)/T$21) -> 2.5865324e-05 | R20: =IF(F20=0,"",IF(E20="","",E20)) | S20: =IF(IF(R20="","",F20*$AB$7)=0,"",IF(R20="","",F20*$AB$7)) | T20: =IF(S20="","",IFERROR(S20*(VLOOKUP(R20,'Formulação suplementos'!$B$56:$W$68,2,)),0)) | U20: =IFERROR(T20/$C$6,"") | V20: =IFERROR(T20/$T$21,"") | W20: =IFERROR(X20/$C$20,"") | X20: =IFERROR(S20*$C$16*$C$20,"") | AF20: =IFERROR(VLOOKUP(R20,'Formulação suplementos'!$B$56:$W$68,22,0)*T20,"") | AH20: =SUM(AH7:AH19) -> 0 | AV20: =IFERROR($T16*(VLOOKUP($R16,'Formulação suplementos'!$B$56:$W$68,AV$7,0))/1000,0) -> 0 | AW20: =IFERROR($T16*(VLOOKUP($R16,'Formulação suplementos'!$B$56:$W$68,AW$7,0))/1000,0) -> 0 | AX20: =IFERROR($T16*(VLOOKUP($R16,'Formulação suplementos'!$B$56:$W$68,AX$7,0)),0) -> 0 | AY20: =IFERROR($T16*(VLOOKUP($R16,'Formulação suplementos'!$B$56:$W$68,AY$7,0)),0) -> 0 | AZ20: =IFERROR($T16*(VLOOKUP($R16,'Formulação suplementos'!$B$56:$W$68,AZ$7,0)),0) -> 0 | BA20: =IFERROR($T16*(VLOOKUP($R16,'Formulação suplementos'!$B$56:$W$68,BA$7,0)),0) -> 0 | BB20: =IFERROR($T16*(VLOOKUP($R16,'Formulação suplementos'!$B$56:$W$68,BB$7,0)),0) -> 0 | BC20: =IFERROR($T16*(VLOOKUP($R16,'Formulação suplementos'!$B$56:$W$68,BC$7,0)),0) -> 0 | BD20: =IFERROR($T16*(VLOOKUP($R16,'Formulação suplementos'!$B$56:$W$68,BD$7,0)),0) -> 0 | BE20: =IFERROR($T16*(VLOOKUP($R16,'Formulação suplementos'!$B$56:$W$68,BE$7,0)),0) -> 0 | ... BM20: =IFERROR($T16*(VLOOKUP($R16,'Formulação suplementos'!$B$56:$W$68,BM$7,0)),0) -> 0 | CK20: Consumo | CL20: CMS | CN20: kg | CP20: Macro | CQ20: Ca | CR20: Coef. Ret. | CS20: =CA73 -> 22.170139 | CT20: g | CW20: Consumo | CX20: Leite | CY20: =CG31*CA189 -> 0.83539 | CZ20: kg | DB20: Macro | DC20: Ca | DD20: Coef. Ret. | DE20: =CA228 -> 17.066923 | DF20: g | DN20: PM | DO20: =(DP19+('Formulação suplementos'!$CM$37-(DP19*0.64))/0.8)/1000 -> 1.0243814 | DP20: =-53.07 + (304.89 * (DO20)) + (90.79 *'Formulação suplementos'!$K$10) - (3.13 * 'Formulação suplementos'!$K$10*'Formulação suplementos'!$K$10) -> 654.03649 | DT20: =(DU19+('Formulação suplementos'!$CY$36-(DU19*0.64))/0.8)/1000 -> 0.43992517 | DU20: =-53.07 + (304.89 * (DT20-'Formulação suplementos'!$CA$214)) + (90.79 *('Formulação suplementos'!$CY$30)) - (3.13 *('Formulação suplementos'!$CY$30)^2) -> 89.690425 | FB20: Cobre | FC20: Cu | FD20: mg/dia | FE20: 34.58 | FF20: 34.58 | FG20: 103.73 | FH20: =FG20/FF20 -> 2.9997108 | FL20: Cobre | FM20: Cu | FN20: mg/dia | FO20: 49.13 | FP20: 49.13 | FQ20: 147.38 | FR20: =FQ20/FP20 -> 2.9997965 | FU20: Cobre | FV20: Cu | FW20: mg/dia | FX20: 49.22 | FY20: 49.22 | FZ20: 147.67 | GA20: =FZ20/FY20 -> 3.0002032
B21: Diária s/ supl. (R$/cab) | C21: 2 | E21: Total | F21: =SUM(F7:F20) -> 0 | H21: =SUM(H7:H20) -> 0 | J21: Selênio (Se) | K21: =IFERROR(IF(C9="Gestante e lactante",ROUND(CS48*1.2,1),ROUND(CS48,1)),"") -> 3.8 | L21: =IFERROR(K21*20,"") -> 76 | M21: =BM24 -> 0 | N21: =IF(K21="","",IF(M21>L21,"Reduzir",IF(M21<K21,"Aumentar",IF(M21=K21,"Ok",IF(M21=L21,"Ok",IF(OR(M21>=K21,M21<=L21),"Ok")))))) -> Aumentar | O21: =IF(M21=0,"",(M21/1000000)/$T$21) | P21: =IF(M21=0,"",(K21/1000000)/T$21) | R21: Total | S21: =SUM(S7:S19) -> 32.977085 | T21: =SUM(T7:T19) -> 8.9038128 | U21: =SUM(U7:U19) -> 0.017807626 | V21: =SUM(V7:V19) -> 1 | W21: =SUM(W7:W19) -> 4946.5627 | X21: =SUM(X7:X19) -> 494656.27 | AV21: =IFERROR($T17*(VLOOKUP($R17,'Formulação suplementos'!$B$56:$W$68,AV$7,0))/1000,0) -> 0 | AW21: =IFERROR($T17*(VLOOKUP($R17,'Formulação suplementos'!$B$56:$W$68,AW$7,0))/1000,0) -> 0 | AX21: =IFERROR($T17*(VLOOKUP($R17,'Formulação suplementos'!$B$56:$W$68,AX$7,0)),0) -> 0 | AY21: =IFERROR($T17*(VLOOKUP($R17,'Formulação suplementos'!$B$56:$W$68,AY$7,0)),0) -> 0 | AZ21: =IFERROR($T17*(VLOOKUP($R17,'Formulação suplementos'!$B$56:$W$68,AZ$7,0)),0) -> 0 | BA21: =IFERROR($T17*(VLOOKUP($R17,'Formulação suplementos'!$B$56:$W$68,BA$7,0)),0) -> 0 | BB21: =IFERROR($T17*(VLOOKUP($R17,'Formulação suplementos'!$B$56:$W$68,BB$7,0)),0) -> 0 | BC21: =IFERROR($T17*(VLOOKUP($R17,'Formulação suplementos'!$B$56:$W$68,BC$7,0)),0) -> 0 | BD21: =IFERROR($T17*(VLOOKUP($R17,'Formulação suplementos'!$B$56:$W$68,BD$7,0)),0) -> 0 | BE21: =IFERROR($T17*(VLOOKUP($R17,'Formulação suplementos'!$B$56:$W$68,BE$7,0)),0) -> 0 | ... BM21: =IFERROR($T17*(VLOOKUP($R17,'Formulação suplementos'!$B$56:$W$68,BM$7,0)),0) -> 0 | CR21: 0.568 | CX21: Sólidos | CY21: =0.353-0.532*CY20+0.01065*CG29+0.3497*CG33 -> 1.3232725 | CZ21: kg | DD21: 0.568 | DN21: ndt | DO21: =(DP20+('Formulação suplementos'!$CM$37-(DP20*0.64))/0.8)/1000 -> 1.024382 | DP21: =-53.07 + (304.89 * (DO21)) + (90.79 *'Formulação suplementos'!$K$10) - (3.13 * 'Formulação suplementos'!$K$10*'Formulação suplementos'!$K$10) -> 654.03668 | DT21: =(DU20+('Formulação suplementos'!$CY$36-(DU20*0.64))/0.8)/1000 -> 0.4399179 | DU21: =-53.07 + (304.89 * (DT21-'Formulação suplementos'!$CA$214)) + (90.79 *('Formulação suplementos'!$CY$30)) - (3.13 *('Formulação suplementos'!$CY$30)^2) -> 89.688208 | FB21: Iodo | FC21: I | FD21: mg/dia | FE21: 2.75 | FF21: 2.75 | FG21: 55.03 | FH21: =FG21/FF21 -> 20.010909 | FL21: Iodo | FM21: I | FN21: mg/dia | FO21: 3.42 | FP21: 3.42 | FQ21: 68.45 | FR21: =FQ21/FP21 -> 20.01462 | FU21: Iodo | FV21: I | FW21: mg/dia | FX21: 3.42 | FY21: 3.42 | FZ21: 68.45 | GA21: =FZ21/FY21 -> 20.01462
J22: Zinco (Zn) | K22: =IFERROR(IF(C9="Gestante e lactante",ROUND(CS44*1.1,1),ROUND(CS44,1)),"") -> 574.8 | L22: =IFERROR(K22*3,"") -> 1724.4 | M22: =BH24 -> 238.71122 | N22: =IF(K22="","",IF(M22>L22,"Reduzir",IF(M22<K22,"Aumentar",IF(M22=K22,"Ok",IF(M22=L22,"Ok",IF(OR(M22>=K22,M22<=L22),"Ok")))))) -> Aumentar | O22: =IF(M22=0,"",(M22/1000000)/$T$21) -> 2.681e-05 | P22: =IF(M22=0,"",(K22/1000000)/T$21) -> 6.4556613e-05 | R22: ="*% de concentrado na dieta "&ROUND(SUM(V8:V19)*100,1)&"%." -> *% de concentrado na dieta 0%. | AV22: =IFERROR($T18*(VLOOKUP($R18,'Formulação suplementos'!$B$56:$W$68,AV$7,0))/1000,0) -> 0 | AW22: =IFERROR($T18*(VLOOKUP($R18,'Formulação suplementos'!$B$56:$W$68,AW$7,0))/1000,0) -> 0 | AX22: =IFERROR($T18*(VLOOKUP($R18,'Formulação suplementos'!$B$56:$W$68,AX$7,0)),0) -> 0 | AY22: =IFERROR($T18*(VLOOKUP($R18,'Formulação suplementos'!$B$56:$W$68,AY$7,0)),0) -> 0 | AZ22: =IFERROR($T18*(VLOOKUP($R18,'Formulação suplementos'!$B$56:$W$68,AZ$7,0)),0) -> 0 | BA22: =IFERROR($T18*(VLOOKUP($R18,'Formulação suplementos'!$B$56:$W$68,BA$7,0)),0) -> 0 | BB22: =IFERROR($T18*(VLOOKUP($R18,'Formulação suplementos'!$B$56:$W$68,BB$7,0)),0) -> 0 | BC22: =IFERROR($T18*(VLOOKUP($R18,'Formulação suplementos'!$B$56:$W$68,BC$7,0)),0) -> 0 | BD22: =IFERROR($T18*(VLOOKUP($R18,'Formulação suplementos'!$B$56:$W$68,BD$7,0)),0) -> 0 | BE22: =IFERROR($T18*(VLOOKUP($R18,'Formulação suplementos'!$B$56:$W$68,BE$7,0)),0) -> 0 | ... BM22: =IFERROR($T18*(VLOOKUP($R18,'Formulação suplementos'!$B$56:$W$68,BM$7,0)),0) -> 0 | CK22: Prod. Leite | CL22: Pleite | CM22: =IF($C$8="Primípara",CA30,CA29) -> 6.0708859 | CN22: kg | CQ22: P | CR22: Coef. Ret. | CS22: =CA80 -> 16.898602 | CT22: g | CX22: CMStot | CY22: =CY21+CY20 -> 2.1586625 | CZ22: kg | DC22: P | DD22: Coef. Ret. | DE22: =CA234 -> 12.249051 | DF22: g | DO22: =(DP21+('Formulação suplementos'!$CM$37-(DP21*0.64))/0.8)/1000 -> 1.024382 | DP22: =-53.07 + (304.89 * (DO22)) + (90.79 *'Formulação suplementos'!$K$10) - (3.13 * 'Formulação suplementos'!$K$10*'Formulação suplementos'!$K$10) -> 654.03669 | DT22: =(DU21+('Formulação suplementos'!$CY$36-(DU21*0.64))/0.8)/1000 -> 0.43991746 | DU22: =-53.07 + (304.89 * (DT22-'Formulação suplementos'!$CA$214)) + (90.79 *('Formulação suplementos'!$CY$30)) - (3.13 *('Formulação suplementos'!$CY$30)^2) -> 89.688073 | FB22: Manganês | FC22: Mn | FD22: mg/dia | FE22: 86.84 | FF22: 86.84 | FG22: 260.52 | FH22: =FG22/FF22 -> 3 | FL22: Manganês | FM22: Mn | FN22: mg/dia | FO22: 139.01 | FP22: 139.01 | FQ22: 417.03 | FR22: =FQ22/FP22 -> 3 | FU22: Manganês | FV22: Mn | FW22: mg/dia | FX22: 139.31 | FY22: 139.31 | FZ22: 417.92 | GA22: =FZ22/FY22 -> 2.9999282
E23: R$/kg mão de obra | G23: R$/kg final | H23: =F23+H21 -> 0 | J23: Ureia | K23: =IF(C6="","","Não consta") -> Não consta | L23: =IF(C6="","", M7*0.01*1000) -> 89.038128 | M23: =IFERROR((SUMIFS(S7:S20,R7:R20,"Ureia")+SUM(AF14:AF20))*1000,0) -> 0 | N23: =IF(L23="","",IF(M23>L23,"Reduzir","Ok")) -> Ok | O23: =IF(M23=0,"",(M23/1000)/T21) | P23: =IF(C6="","","Não consta") -> Não consta | R23: **Para que o GMD seja alcançado, você tem que garantir que seu animal tenha acesso a essa quantidade de forragem e suplemento diariamente. | AV23: =IFERROR($T19*(VLOOKUP($R19,'Formulação suplementos'!$B$56:$W$68,AV$7,0))/1000,0) -> 0 | AW23: =IFERROR($T19*(VLOOKUP($R19,'Formulação suplementos'!$B$56:$W$68,AW$7,0))/1000,0) -> 0 | AX23: =IFERROR($T19*(VLOOKUP($R19,'Formulação suplementos'!$B$56:$W$68,AX$7,0)),0) -> 0 | AY23: =IFERROR($T19*(VLOOKUP($R19,'Formulação suplementos'!$B$56:$W$68,AY$7,0)),0) -> 0 | AZ23: =IFERROR($T19*(VLOOKUP($R19,'Formulação suplementos'!$B$56:$W$68,AZ$7,0)),0) -> 0 | BA23: =IFERROR($T19*(VLOOKUP($R19,'Formulação suplementos'!$B$56:$W$68,BA$7,0)),0) -> 0 | BB23: =IFERROR($T19*(VLOOKUP($R19,'Formulação suplementos'!$B$56:$W$68,BB$7,0)),0) -> 0 | BC23: =IFERROR($T19*(VLOOKUP($R19,'Formulação suplementos'!$B$56:$W$68,BC$7,0)),0) -> 0 | BD23: =IFERROR($T19*(VLOOKUP($R19,'Formulação suplementos'!$B$56:$W$68,BD$7,0)),0) -> 0 | BE23: =IFERROR($T19*(VLOOKUP($R19,'Formulação suplementos'!$B$56:$W$68,BE$7,0)),0) -> 0 | ... BM23: =IFERROR($T19*(VLOOKUP($R19,'Formulação suplementos'!$B$56:$W$68,BM$7,0)),0) -> 0 | CR23: 0.678 | DD23: 0.678 | DO23: =(DP22+('Formulação suplementos'!$CM$37-(DP22*0.64))/0.8)/1000 -> 1.024382 | DP23: =-53.07 + (304.89 * (DO23)) + (90.79 *'Formulação suplementos'!$K$10) - (3.13 * 'Formulação suplementos'!$K$10*'Formulação suplementos'!$K$10) -> 654.03669 | DT23: =(DU22+('Formulação suplementos'!$CY$36-(DU22*0.64))/0.8)/1000 -> 0.43991743 | DU23: =-53.07 + (304.89 * (DT23-'Formulação suplementos'!$CA$214)) + (90.79 *('Formulação suplementos'!$CY$30)) - (3.13 *('Formulação suplementos'!$CY$30)^2) -> 89.688065 | FB23: Selênio | FC23: Se | FD23: mg/dia | FE23: 3.32 | FF23: 3.32 | FG23: 66.39 | FH23: =FG23/FF23 -> 19.996988 | FL23: Selênio | FM23: Se | FN23: mg/dia | FO23: 3.73 | FP23: 3.73 | FQ23: 74.6 | FR23: =FQ23/FP23 -> 20 | FU23: Selênio | FV23: Se | FW23: mg/dia | FX23: 3.73 | FY23: 3.73 | FZ23: 74.54 | GA23: =FZ23/FY23 -> 19.983914
E24: =IF(IFERROR("*suplemento consumo de "&C19*100&"% P.V | Estimativa de "&ROUND((AX27/SUM(T8:T19))*100,1)&"% de PB e "&ROUND((AW27/SUM(T8:T19)*100),1)&"% de NDT","Tabela do suplemento formulado")="Tabela do suplemento formulado","",IFERROR("*suplemento consumo de "&C19*100&"% P.V | Estimativa de "&ROUND((AX27/SUM(T8:T19))*100,1)&"% de PB e "&ROUND((AW27/SUM(T8:T19)*100),1)&"% de NDT","Tabela do suplemento formulado")) | R24: ***As estimativas de consumo foram feitas em cima do peso médio, podendo ter variação de acordo com o desempenho. | AV24: =SUM(AV9:AV23) -> 5.2532496 | AW24: =SUM(AW9:AW23)+(((M23*280)/100)/1000) -> 1.0684575 | AX24: =SUM(AX9:AX23) -> 65.888215 | AY24: =SUM(AY9:AY23) -> 16.917244 | AZ24: =SUM(AZ9:AZ23) -> 0 | BA24: =SUM(BA9:BA23) -> 4.4519064 | BB24: =SUM(BB9:BB23) -> 154.03596 | BC24: =SUM(BC12:BD23) -> 0 | BD24: =SUM(BD9:BD23) -> 0.89038128 | BE24: =SUM(BE9:BE23) -> 243.96447 | BF24: =SUM(BF9:BF23) -> 12.465338 | BG24: =SUM(BG9:BG23) -> 89.661395 | BH24: =SUM(BH9:BH23) -> 238.71122 | BI24: =SUM(BI9:BI23) -> 0 | BJ24: =SUM(BJ9:BJ23) -> 890.29224 | BK24: =SUM(BK9:BK23) -> 0 | ... BM24: =SUM(BM9:BM23) -> 0 | BY24: GMD, kg | CA24: 0.2 | CK24: Energia | CL24: ELm | CM24: =(97.8*CA36^0.75)/1000 -> 9.0252451 | CN24: Mcal | CQ24: Ca/P | CR24: =CA82 -> 1.3119511 | CW24: Energia | CX24: ELm | CY24: =70.3*CA187^0.75/1000 -> 2.1594176 | CZ24: Mcal | DC24: Ca/P | DD24: =CA236 -> 1.3933262 | DO24: =(DP23+('Formulação suplementos'!$CM$37-(DP23*0.64))/0.8)/1000 -> 1.024382 | DP24: =-53.07 + (304.89 * (DO24)) + (90.79 *'Formulação suplementos'!$K$10) - (3.13 * 'Formulação suplementos'!$K$10*'Formulação suplementos'!$K$10) -> 654.03669 | DT24: =(DU23+('Formulação suplementos'!$CY$36-(DU23*0.64))/0.8)/1000 -> 0.43991743 | DU24: =-53.07 + (304.89 * (DT24-'Formulação suplementos'!$CA$214)) + (90.79 *('Formulação suplementos'!$CY$30)) - (3.13 *('Formulação suplementos'!$CY$30)^2) -> 89.688064 | FB24: Zinco | FC24: Zn | FD24: mg/dia | FE24: 252.29 | FF24: 252.29 | FG24: 756.87 | FH24: =FG24/FF24 -> 3 | FL24: Zinco | FM24: Zn | FN24: mg/dia | FO24: 342.02 | FP24: 342.02 | FQ24: 1026.05 | FR24: =FQ24/FP24 -> 2.9999708 | FU24: Zinco | FV24: Zn | FW24: mg/dia | FX24: 346.88 | FY24: 346.88 | FZ24: 1040.63 | GA24: =FZ24/FY24 -> 2.9999712
E25: =IFERROR("**consumo médio do suplemento de "&ROUND(C19*C6,3)&" kg/cab/dia","") -> **consumo médio do suplemento de 0,25 kg/cab/dia | J25: Acréscimo de consumo de MS | L25: 0 | CL25: ELg | CM25: =CA37*(1.0076*CA36^0.2389) -> 0.03825346 | CN25: Mcal | CQ25: Mg | CR25: Coef. Ret. | CS25: =CA89 -> 9.5119912 | CT25: g | CX25: ELg | CY25: =0.0932*CA187^0.75*CA188^0.9157 -> 2.7525398 | CZ25: Mcal | DC25: Mg | DD25: Coef. Ret. | DE25: =CA242 -> 2.5256774 | DF25: g | DO25: =(DP24+('Formulação suplementos'!$CM$37-(DP24*0.64))/0.8)/1000 -> 1.024382 | DP25: =-53.07 + (304.89 * (DO25)) + (90.79 *'Formulação suplementos'!$K$10) - (3.13 * 'Formulação suplementos'!$K$10*'Formulação suplementos'!$K$10) -> 654.03669 | DT25: =(DU24+('Formulação suplementos'!$CY$36-(DU24*0.64))/0.8)/1000 -> 0.43991743 | DU25: =-53.07 + (304.89 * (DT25-'Formulação suplementos'!$CA$214)) + (90.79 *('Formulação suplementos'!$CY$30)) - (3.13 *('Formulação suplementos'!$CY$30)^2) -> 89.688064
CD26: BEZERROS | CL26: ELlac | CM26: =(CA45*CM22) -> 4.9781265 | CN26: Mcal | CR26: 0.355 | CX26: EMm | CY26: =118.6*CA187^0.75/1000 -> 3.6430572 | CZ26: Mcal | DD26: 0.355 | DO26: =(DP25+('Formulação suplementos'!$CM$37-(DP25*0.64))/0.8)/1000 -> 1.024382 | DP26: =-53.07 + (304.89 * (DO26)) + (90.79 *'Formulação suplementos'!$K$10) - (3.13 * 'Formulação suplementos'!$K$10*'Formulação suplementos'!$K$10) -> 654.03669 | DT26: =(DU25+('Formulação suplementos'!$CY$36-(DU25*0.64))/0.8)/1000 -> 0.43991743 | DU26: =-53.07 + (304.89 * (DT26-'Formulação suplementos'!$CA$214)) + (90.79 *('Formulação suplementos'!$CY$30)) - (3.13 *('Formulação suplementos'!$CY$30)^2) -> 89.688064
B27: BIBLIOTECA DE ALIMENTOS | AW27: =AV24-AV9 -> 0 | AX27: =AW24-AW9 -> 0 | CL27: EMm | CM27: =(135*CA36^0.75)/1000 -> 12.45816 | CN27: Mcal | CQ27: Na | CR27: Coef. Ret. | CS27: =CA96 -> 11.787243 | CT27: g | CX27: EMg | CY27: =CY25/CA199 -> 4.4652244 | CZ27: Mcal | DC27: Na | DD27: Coef. Ret. | DE27: =CA248 -> 4.5124291 | DF27: g | DO27: =(DP26+('Formulação suplementos'!$CM$37-(DP26*0.64))/0.8)/1000 -> 1.024382 | DP27: =-53.07 + (304.89 * (DO27)) + (90.79 *'Formulação suplementos'!$K$10) - (3.13 * 'Formulação suplementos'!$K$10*'Formulação suplementos'!$K$10) -> 654.03669 | DT27: =(DU26+('Formulação suplementos'!$CY$36-(DU26*0.64))/0.8)/1000 -> 0.43991743 | DU27: =-53.07 + (304.89 * (DT27-'Formulação suplementos'!$CA$214)) + (90.79 *('Formulação suplementos'!$CY$30)) - (3.13 *('Formulação suplementos'!$CY$30)^2) -> 89.688064
B28: Forragem | C28: M.S (%) | D28: NDT (% M.S) | E28: PB (% M.S) | F28: Ca (% M.S) | G28: P (% M.S) | H28: PDR (%M.S) | I28: FDN (%M.S) | J28: EE (%M.S) | K28: Mg (%M.S) | L28: Na (%M.S) | M28: K (%M.S) | N28: S (%M.S) | O28: Cu (mg/kg) | P28: Zn (mg/kg) | Q28: Fe (mg/kg) | R28: Mn (mg/kg) | S28: I (mg/kg) | T28: Co (mg/kg) | U28: Se (mg/kg) | CL28: EMg | CM28: =CM25/CA43 -> 0.086939681 | CN28: Mcal | CR28: 0.371 | CX28: EMtot | CY28: =CY27+CY26 -> 8.1082816 | CZ28: Mcal | DD28: 0.371 | DO28: =(DP27+('Formulação suplementos'!$CM$37-(DP27*0.64))/0.8)/1000 -> 1.024382 | DP28: =-53.07 + (304.89 * (DO28)) + (90.79 *'Formulação suplementos'!$K$10) - (3.13 * 'Formulação suplementos'!$K$10*'Formulação suplementos'!$K$10) -> 654.03669 | DT28: =(DU27+('Formulação suplementos'!$CY$36-(DU27*0.64))/0.8)/1000 -> 0.43991743 | DU28: =-53.07 + (304.89 * (DT28-'Formulação suplementos'!$CA$214)) + (90.79 *('Formulação suplementos'!$CY$30)) - (3.13 *('Formulação suplementos'!$CY$30)^2) -> 89.688064
B29: Capim Andropogon | C29: 0.2555 | D29: 0.5356 | E29: 0.0449 | F29: 0.0004 | G29: 0 | I29: 0.7013 | J29: 0.0215 | K29: 0 | L29: 0 | M29: 0 | N29: 0 | O29: 0 | P29: 0 | R29: 0 | T29: 0 | BY29: Prod. Leite, kg | BZ29: Multip | CA29: =7.996-0.101*C10-7.996*EXP(-1.447*C10) -> 7.4852356 | CE29: Peso corporal, kg | CG29: 100 | CL29: EMlac | CM29: =CM26/CA46 -> 6.9140646 | CN29: Mcal | CQ29: K | CR29: Coef. Ret. | CS29: =CA103 -> 33.072868 | CT29: g | CX29: NDTleit | CY29: =CG31*0.18 -> 1.0818 | CZ29: kg | DC29: K | DD29: Coef. Ret. | DE29: =CA254 -> 7.0760288 | DF29: g | DO29: =(DP28+('Formulação suplementos'!$CM$37-(DP28*0.64))/0.8)/1000 -> 1.024382 | DP29: =-53.07 + (304.89 * (DO29)) + (90.79 *'Formulação suplementos'!$K$10) - (3.13 * 'Formulação suplementos'!$K$10*'Formulação suplementos'!$K$10) -> 654.03669 | DT29: =(DU28+('Formulação suplementos'!$CY$36-(DU28*0.64))/0.8)/1000 -> 0.43991743 | DU29: =-53.07 + (304.89 * (DT29-'Formulação suplementos'!$CA$214)) + (90.79 *('Formulação suplementos'!$CY$30)) - (3.13 *('Formulação suplementos'!$CY$30)^2) -> 89.688064
B30: Braquiária Brizantha | C30: 0.3409 | D30: 0.5668 | E30: 0.0691 | F30: 0.0031 | G30: 0.0011 | I30: 0.6384 | J30: 0.0196 | K30: 0.0041 | L30: 0.0002 | M30: 0.0165 | N30: 0.0009 | O30: 3.48 | P30: 26.4 | R30: 103.19 | T30: 0.07 | BZ30: Primi | CA30: =6.431-0.072*C10-6.431*EXP(-2.188*C10) -> 6.0708859 | CL30: EMtot | CM30: =CM27+CM28+CM29 -> 19.459165 | CN30: Mcal | CR30: 0.484 | CX30: NDTsól | CY30: =CY31-CY29 -> 0.83777424 | CZ30: kg | DD30: 0.484 | DO30: =(DP29+('Formulação suplementos'!$CM$37-(DP29*0.64))/0.8)/1000 -> 1.024382 | DP30: =-53.07 + (304.89 * (DO30)) + (90.79 *'Formulação suplementos'!$K$10) - (3.13 * 'Formulação suplementos'!$K$10*'Formulação suplementos'!$K$10) -> 654.03669 | DT30: =(DU29+('Formulação suplementos'!$CY$36-(DU29*0.64))/0.8)/1000 -> 0.43991743 | DU30: =-53.07 + (304.89 * (DT30-'Formulação suplementos'!$CA$214)) + (90.79 *('Formulação suplementos'!$CY$30)) - (3.13 *('Formulação suplementos'!$CY$30)^2) -> 89.688064
B31: Marandu | C31: 0.3324 | D31: 0.5552 | E31: 0.0768 | F31: 0.0028 | G31: 0.0009 | I31: 0.6415 | J31: 0.0195 | K31: 0.001 | L31: 0.0002 | M31: 0.0072 | N31: 0.0003 | O31: 15 | P31: 10 | R31: 56 | T31: 0.46 | BZ31: Final | CE31: Produção de leite da mãe, kg | CG31: 6.01 | CL31: NDT | CN31: Kg | CQ31: S | CR31: Coef. Ret. | CS31: =CA110 -> 9.1580086 | CT31: g | CX31: NDTtot | CY31: =CA202/4.4 -> 1.9195742 | CZ31: kg | DC31: S | DD31: Coef. Ret. | DE31: =CA274 -> 3.5234599 | DF31: g | DO31: =(DP30+('Formulação suplementos'!$CM$37-(DP30*0.64))/0.8)/1000 -> 1.024382 | DP31: =-53.07 + (304.89 * (DO31)) + (90.79 *'Formulação suplementos'!$K$10) - (3.13 * 'Formulação suplementos'!$K$10*'Formulação suplementos'!$K$10) -> 654.03669 | DT31: =(DU30+('Formulação suplementos'!$CY$36-(DU30*0.64))/0.8)/1000 -> 0.43991743 | DU31: =-53.07 + (304.89 * (DT31-'Formulação suplementos'!$CA$214)) + (90.79 *('Formulação suplementos'!$CY$30)) - (3.13 *('Formulação suplementos'!$CY$30)^2) -> 89.688064
B32: Decumbens | C32: 0.2849 | D32: 0.5533 | E32: 0.0674 | F32: 0.004 | G32: 0.001 | I32: 0.6638 | J32: 0.0181 | K32: 0.0009 | L32: 0.0001 | M32: 0.0094 | N32: 0.0004 | O32: 3.8 | P32: 28 | R32: 85 | T32: 0.28 | CM32: =K10/K7*100 -> 59.821324 | CN32: % | CR32: 0.773 | CX32: NDTtot | CY32: =CY31/CY22*100 -> 88.92424 | CZ32: % | DD32: 0.77 | DO32: =(DP31+('Formulação suplementos'!$CM$37-(DP31*0.64))/0.8)/1000 -> 1.024382 | DP32: =-53.07 + (304.89 * (DO32)) + (90.79 *'Formulação suplementos'!$K$10) - (3.13 * 'Formulação suplementos'!$K$10*'Formulação suplementos'!$K$10) -> 654.03669 | DT32: =(DU31+('Formulação suplementos'!$CY$36-(DU31*0.64))/0.8)/1000 -> 0.43991743 | DU32: =-53.07 + (304.89 * (DT32-'Formulação suplementos'!$CA$214)) + (90.79 *('Formulação suplementos'!$CY$30)) - (3.13 *('Formulação suplementos'!$CY$30)^2) -> 89.688064
B33: Humidícola | C33: 0.2812 | D33: 0.5661 | E33: 0.0738 | F33: 0.0038 | G33: 0.0012 | I33: 0.7186 | J33: 0.0245 | K33: 0.002 | L33: 0.0002 | M33: 0.0199 | N33: 0.0004 | O33: 13.32 | P33: 19 | R33: 93.82 | T33: 0.09 | BZ33: CMS, g/kg PC | CA33: =6.535-7.558*EXP(-0.578*C10)+0.323*C10+1.66*CM22 -> 17.807626 | CE33: Ganho médio diário, kg/dia | CG33: 1 | DO33: =(DP32+('Formulação suplementos'!$CM$37-(DP32*0.64))/0.8)/1000 -> 1.024382 | DP33: =-53.07 + (304.89 * (DO33)) + (90.79 *'Formulação suplementos'!$K$10) - (3.13 * 'Formulação suplementos'!$K$10*'Formulação suplementos'!$K$10) -> 654.03669 | DT33: =(DU32+('Formulação suplementos'!$CY$36-(DU32*0.64))/0.8)/1000 -> 0.43991743 | DU33: =-53.07 + (304.89 * (DT33-'Formulação suplementos'!$CA$214)) + (90.79 *('Formulação suplementos'!$CY$30)) - (3.13 *('Formulação suplementos'!$CY$30)^2) -> 89.688064
B34: Capim Gordura | C34: 0.2772 | D34: 0.5668 | E34: 0.0692 | F34: 0.0024 | G34: 0.0007 | I34: 0.7229 | J34: 0.013 | K34: 0.0014 | L34: 0.0002 | M34: 0.0067 | N34: 0 | O34: 0 | P34: 0 | R34: 0 | T34: 0 | BZ34: CMS, kg | CK34: Proteína | CL34: PMm | CM34: =3.9*CA35^0.75 -> 405.92795 | CN34: g | CP34: Micro | CQ34: Cu | CR34: Coef. Ret. | CS34: =CA117 -> 81.582701 | CT34: mg | CW34: Proteína | CX34: PMm | CY34: =3.9*CA186^0.75 -> 123.32883 | CZ34: g | DB34: Micro | DC34: Cu | DD34: Coef. Ret. | DE34: =CA280 -> 20.221755 | DF34: mg | DO34: =(DP33+('Formulação suplementos'!$CM$37-(DP33*0.64))/0.8)/1000 -> 1.024382 | DP34: =-53.07 + (304.89 * (DO34)) + (90.79 *'Formulação suplementos'!$K$10) - (3.13 * 'Formulação suplementos'!$K$10*'Formulação suplementos'!$K$10) -> 654.03669 | DT34: =(DU33+('Formulação suplementos'!$CY$36-(DU33*0.64))/0.8)/1000 -> 0.43991743 | DU34: =-53.07 + (304.89 * (DT34-'Formulação suplementos'!$CA$214)) + (90.79 *('Formulação suplementos'!$CY$30)) - (3.13 *('Formulação suplementos'!$CY$30)^2) -> 89.688064
B35: Capim Massai | C35: 0.2948 | D35: 0.562 | E35: 0.0799 | F35: 0 | G35: 0 | I35: 0.7002 | J35: 0.0206 | K35: 0 | L35: 0 | M35: 0 | N35: 0 | O35: 0 | P35: 0 | R35: 0 | T35: 0 | BZ35: PCJ, kg | CA35: =0.8915*C6^1.0151 -> 489.60495 | CL35: PMg | CM35: =CA56/CA57 -> 2.3520692 | CN35: g | CR35: 0.735 | CX35: PMg | CY35: =CA210/CA211*100 -> 214.25502 | CZ35: g | DD35: 0.74 | DO35: =(DP34+('Formulação suplementos'!$CM$37-(DP34*0.64))/0.8)/1000 -> 1.024382 | DP35: =-53.07 + (304.89 * (DO35)) + (90.79 *'Formulação suplementos'!$K$10) - (3.13 * 'Formulação suplementos'!$K$10*'Formulação suplementos'!$K$10) -> 654.03669 | DT35: =(DU34+('Formulação suplementos'!$CY$36-(DU34*0.64))/0.8)/1000 -> 0.43991743 | DU35: =-53.07 + (304.89 * (DT35-'Formulação suplementos'!$CA$214)) + (90.79 *('Formulação suplementos'!$CY$30)) - (3.13 *('Formulação suplementos'!$CY$30)^2) -> 89.688064
B36: Capim Mombaça | C36: 0.27 | D36: 0.59 | E36: 0.12 | F36: 0.0074 | G36: 0.0019 | I36: 0.5 | J36: 0.0173 | K36: 0.002 | L36: 0.0001 | M36: 0.0274 | N36: 0.0014 | O36: 10.07 | P36: 26.81 | R36: 99.99 | T36: 0.41 | BZ36: PCVZ, kg | CA36: =0.8507*CA35^1.0002 -> 417.02319 | CL36: PMlac | CM36: =50.5*CM22 -> 306.57974 | CN36: g | CQ36: Co | CR36: Coef. Ret. | CS36: =CA124 -> 9.385548 | CT36: mg | CX36: PMtot | CY36: =CY35+CY34 -> 337.58385 | CZ36: g | DC36: Co | DD36: Coef. Ret. | DE36: =CA286 -> 1.5963355 | DF36: mg | DO36: =(DP35+('Formulação suplementos'!$CM$37-(DP35*0.64))/0.8)/1000 -> 1.024382 | DP36: =-53.07 + (304.89 * (DO36)) + (90.79 *'Formulação suplementos'!$K$10) - (3.13 * 'Formulação suplementos'!$K$10*'Formulação suplementos'!$K$10) -> 654.03669 | DT36: =(DU35+('Formulação suplementos'!$CY$36-(DU35*0.64))/0.8)/1000 -> 0.43991743 | DU36: =-53.07 + (304.89 * (DT36-'Formulação suplementos'!$CA$214)) + (90.79 *('Formulação suplementos'!$CY$30)) - (3.13 *('Formulação suplementos'!$CY$30)^2) -> 89.688064
B37: Capim Tifton 85 | C37: 0.2696 | D37: 0.5623 | E37: 0.1291 | F37: 0.0054 | G37: 0.005 | I37: 0.4883 | J37: 0.02 | K37: 0.0017 | L37: 0 | M37: 0.0128 | N37: 0.0018 | O37: 10.35 | P37: 32.22 | R37: 305 | T37: 0 | BZ37: GPCVZ | CA37: =0.963*C7^1.0151 -> 0.0089831011 | CL37: PMtot | CM37: =CM34+CM36+CM35 -> 714.85976 | CN37: g | CR37: 0.868 | CX37: PDR | CY37: =CA216 -> 100.53291 | CZ37: g | DD37: 0.87 | DO37: =(DP36+('Formulação suplementos'!$CM$37-(DP36*0.64))/0.8)/1000 -> 1.024382 | DP37: =-53.07 + (304.89 * (DO37)) + (90.79 *'Formulação suplementos'!$K$10) - (3.13 * 'Formulação suplementos'!$K$10*'Formulação suplementos'!$K$10) -> 654.03669 | DT37: =(DU36+('Formulação suplementos'!$CY$36-(DU36*0.64))/0.8)/1000 -> 0.43991743 | DU37: =-53.07 + (304.89 * (DT37-'Formulação suplementos'!$CA$214)) + (90.79 *('Formulação suplementos'!$CY$30)) - (3.13 *('Formulação suplementos'!$CY$30)^2) -> 89.688064
B38: Milheto | C38: 0.1983 | D38: 0.5877 | E38: 0.1223 | F38: 0.0072 | G38: 0.0026 | I38: 0.6362 | J38: 0.0306 | K38: 0 | L38: 0 | M38: 0 | N38: 0 | O38: 0 | P38: 0 | R38: 0 | T38: 0 | CL38: PDR | CM38: =CA61*1000 -> 654.03669 | CN38: g | CQ38: Cr | CR38: Coef. Ret. | CS38: =CA131 -> 39.488223 | CT38: mg | CY38: =CY37/CY42*100 -> 22.740557 | CZ38: % PB | DC38: Cr | DD38: Coef. Ret. | DE38: =CA292 -> 7.5145273 | DF38: mg | DO38: =(DP37+('Formulação suplementos'!$CM$37-(DP37*0.64))/0.8)/1000 -> 1.024382 | DP38: =-53.07 + (304.89 * (DO38)) + (90.79 *'Formulação suplementos'!$K$10) - (3.13 * 'Formulação suplementos'!$K$10*'Formulação suplementos'!$K$10) -> 654.03669 | DT38: =(DU37+('Formulação suplementos'!$CY$36-(DU37*0.64))/0.8)/1000 -> 0.43991743 | DU38: =-53.07 + (304.89 * (DT38-'Formulação suplementos'!$CA$214)) + (90.79 *('Formulação suplementos'!$CY$30)) - (3.13 *('Formulação suplementos'!$CY$30)^2) -> 89.688064 | GM38: 9.94
B39: Sorgo Forrageiro | C39: 0.2411 | D39: 0.579 | E39: 0.0684 | F39: 0.0013 | G39: 0.0013 | I39: 0.6335 | J39: 0.0304 | K39: 0.0026 | L39: 0 | M39: 0 | N39: 0 | O39: 0 | P39: 0 | R39: 0 | T39: 0 | BY39: Energia | BZ39: ELm, Mcal | CM39: =CM38/K11*100 -> 63.84695 | CN39: % PB | CR39: 0.784 | CX39: PNDR | CY39: =(CY36-(CA216*0.64))/0.8 -> 341.55349 | CZ39: g | DD39: 0.78 | DO39: =(DP38+('Formulação suplementos'!$CM$37-(DP38*0.64))/0.8)/1000 -> 1.024382 | DP39: =-53.07 + (304.89 * (DO39)) + (90.79 *'Formulação suplementos'!$K$10) - (3.13 * 'Formulação suplementos'!$K$10*'Formulação suplementos'!$K$10) -> 654.03669 | DT39: =(DU38+('Formulação suplementos'!$CY$36-(DU38*0.64))/0.8)/1000 -> 0.43991743 | DU39: =-53.07 + (304.89 * (DT39-'Formulação suplementos'!$CA$214)) + (90.79 *('Formulação suplementos'!$CY$30)) - (3.13 *('Formulação suplementos'!$CY$30)^2) -> 89.688064
BZ40: EMm | CL40: PNDR | CM40: =(CM37-((CA61*1000)*0.64))/0.8 -> 370.34535 | CN40: g | CQ40: Fe | CR40: Coef. Ret. | CS40: =CA138 -> 2251.9305 | CT40: mg | CY40: =CY39/CY42*100 -> 77.259443 | CZ40: % PB | DC40: Fe | DD40: Coef. Ret. | DE40: =CA298 -> 443.84921 | DF40: mg | DO40: =(DP39+('Formulação suplementos'!$CM$37-(DP39*0.64))/0.8)/1000 -> 1.024382 | DP40: =-53.07 + (304.89 * (DO40)) + (90.79 *'Formulação suplementos'!$K$10) - (3.13 * 'Formulação suplementos'!$K$10*'Formulação suplementos'!$K$10) -> 654.03669 | DT40: =(DU39+('Formulação suplementos'!$CY$36-(DU39*0.64))/0.8)/1000 -> 0.43991743 | DU40: =-53.07 + (304.89 * (DT40-'Formulação suplementos'!$CA$214)) + (90.79 *('Formulação suplementos'!$CY$30)) - (3.13 *('Formulação suplementos'!$CY$30)^2) -> 89.688064
BZ41: km | CM41: =CM40/K11*100 -> 36.15305 | CN41: % PB | CR41: 0.734 | CX41: PBleite | CY41: =CA214*1000 -> 213.956 | CZ41: g | DD41: 0.73 | DO41: =(DP40+('Formulação suplementos'!$CM$37-(DP40*0.64))/0.8)/1000 -> 1.024382 | DP41: =-53.07 + (304.89 * (DO41)) + (90.79 *'Formulação suplementos'!$K$10) - (3.13 * 'Formulação suplementos'!$K$10*'Formulação suplementos'!$K$10) -> 654.03669 | DT41: =(DU40+('Formulação suplementos'!$CY$36-(DU40*0.64))/0.8)/1000 -> 0.43991743 | DU41: =-53.07 + (304.89 * (DT41-'Formulação suplementos'!$CA$214)) + (90.79 *('Formulação suplementos'!$CY$30)) - (3.13 *('Formulação suplementos'!$CY$30)^2) -> 89.688064
B42: Concentrados | C42: M.S (% M.S) | D42: NDT (% M.S) | E42: PB (% M.S) | F42: Ca (% M.S) | G42: P (% M.S) | H42: PDR (% M.S) | I42: FDN (% M.S) | J42: EE (% M.S) | K42: Mg (% M.S) | L42: Na (% M.S) | M42: K(% M.S) | N42: S (% M.S) | O42: Cu (mg) | P42: Zn (mg) | Q42: Fe (mg) | R42: Mn (mg) | S42: I (mg) | T42: Co (mg) | U42: Se (mg) | V42: R$/kg | W42: R$/NDT | X42: R$/PB | BZ42: ELg | CL42: PB | CN42: g | CQ42: Mn | CR42: Coef. Ret. | CS42: =CA145 -> 230.26973 | CT42: mg | CX42: PBtotal | CY42: =CY39+CY37 -> 442.0864 | CZ42: g | DC42: Mn | DD42: Coef. Ret. | DE42: =CA304 -> 47.905078 | DF42: mg | DO42: =(DP41+('Formulação suplementos'!$CM$37-(DP41*0.64))/0.8)/1000 -> 1.024382 | DP42: =-53.07 + (304.89 * (DO42)) + (90.79 *'Formulação suplementos'!$K$10) - (3.13 * 'Formulação suplementos'!$K$10*'Formulação suplementos'!$K$10) -> 654.03669 | DT42: =(DU41+('Formulação suplementos'!$CY$36-(DU41*0.64))/0.8)/1000 -> 0.43991743 | DU42: =-53.07 + (304.89 * (DT42-'Formulação suplementos'!$CA$214)) + (90.79 *('Formulação suplementos'!$CY$30)) - (3.13 *('Formulação suplementos'!$CY$30)^2) -> 89.688064
B43: Milho | C43: 0.8788 | D43: 0.8692 | E43: 0.0896 | F43: 0.0003 | G43: 0.0026 | I43: 0.1239 | J43: 0.04 | K43: 0.0011 | L43: 0.0003 | M43: 0.0035 | N43: 0.0004 | O43: 3.48 | P43: 18.85 | R43: 8.8 | T43: 0.02 | U43: 0.07 | W43: =IFERROR(IF(V43/D43=0,"",V43/D43),"") | X43: =IFERROR(IF(V43/E43=0,"",V43/E43),"") | BZ43: kg | CA43: 0.44 | CM43: =CA65 -> 11.504982 | CN43: % | CR43: 0.439 | CY43: =CY42/CY22/10 -> 20.479644 | CZ43: % | DD43: 0.44 | DO43: =(DP42+('Formulação suplementos'!$CM$37-(DP42*0.64))/0.8)/1000 -> 1.024382 | DP43: =-53.07 + (304.89 * (DO43)) + (90.79 *'Formulação suplementos'!$K$10) - (3.13 * 'Formulação suplementos'!$K$10*'Formulação suplementos'!$K$10) -> 654.03669 | DT43: =(DU42+('Formulação suplementos'!$CY$36-(DU42*0.64))/0.8)/1000 -> 0.43991743 | DU43: =-53.07 + (304.89 * (DT43-'Formulação suplementos'!$CA$214)) + (90.79 *('Formulação suplementos'!$CY$30)) - (3.13 *('Formulação suplementos'!$CY$30)^2) -> 89.688064
B44: Soja Casca | C44: 0.901 | D44: 0.7311 | E44: 0.1267 | F44: 0.0052 | G44: 0.0016 | I44: 0.6098 | J44: 0.0222 | K44: 0.0034 | L44: 0.0008 | M44: 0.0087 | N44: 0.0009 | O44: 6.46 | P44: 48.07 | R44: 17.55 | T44: 5.01 | W44: =IFERROR(IF(V44/D44=0,"",V44/D44),"") | X44: =IFERROR(IF(V44/E44=0,"",V44/E44),"") | BZ44: EMg | CQ44: Zn | CR44: Coef. Ret. | CS44: =CA152 -> 574.81541 | CT44: mg | DC44: Mo | DD44: Coef. Ret. | DE44: =CA310 -> 0.69760792 | DF44: mg | DO44: =(DP43+('Formulação suplementos'!$CM$37-(DP43*0.64))/0.8)/1000 -> 1.024382 | DP44: =-53.07 + (304.89 * (DO44)) + (90.79 *'Formulação suplementos'!$K$10) - (3.13 * 'Formulação suplementos'!$K$10*'Formulação suplementos'!$K$10) -> 654.03669 | DT44: =(DU43+('Formulação suplementos'!$CY$36-(DU43*0.64))/0.8)/1000 -> 0.43991743 | DU44: =-53.07 + (304.89 * (DT44-'Formulação suplementos'!$CA$214)) + (90.79 *('Formulação suplementos'!$CY$30)) - (3.13 *('Formulação suplementos'!$CY$30)^2) -> 89.688064
B45: Sorgo Grão | C45: 0.8801 | D45: 0.8419 | E45: 0.0933 | F45: 0.0007 | G45: 0.0029 | I45: 0.1058 | J45: 0.0291 | K45: 0.0019 | L45: 0.0003 | M45: 0.0073 | N45: 0.0003 | O45: 4.87 | P45: 15.5 | R45: 17.14 | T45: 0.04 | U45: 0.06 | W45: =IFERROR(IF(V45/D45=0,"",V45/D45),"") | X45: =IFERROR(IF(V45/E45=0,"",V45/E45),"") | BZ45: ELl,Mcal/kg Lei | CA45: 0.82 | CR45: 0.668 | DD45: 0.5 | DO45: =(DP44+('Formulação suplementos'!$CM$37-(DP44*0.64))/0.8)/1000 -> 1.024382 | DP45: =-53.07 + (304.89 * (DO45)) + (90.79 *'Formulação suplementos'!$K$10) - (3.13 * 'Formulação suplementos'!$K$10*'Formulação suplementos'!$K$10) -> 654.03669 | DT45: =(DU44+('Formulação suplementos'!$CY$36-(DU44*0.64))/0.8)/1000 -> 0.43991743 | DU45: =-53.07 + (304.89 * (DT45-'Formulação suplementos'!$CA$214)) + (90.79 *('Formulação suplementos'!$CY$30)) - (3.13 *('Formulação suplementos'!$CY$30)^2) -> 89.688064
B46: Algodão Caroço | C46: 0.9066 | D46: 0.9562 | E46: 0.2294 | F46: 0.0027 | G46: 0.0074 | I46: 0.417 | J46: 0.2006 | K46: 0.0052 | L46: 0.0012 | M46: 0.0091 | N46: 0 | W46: =IFERROR(IF(V46/D46=0,"",V46/D46),"") | X46: =IFERROR(IF(V46/E46=0,"",V46/E46),"") | BZ46: kl=km | CA46: 0.72 | CQ46: Mo | CR46: Coef. Ret. | CS46: =CA160 -> 3.2707461 | CT46: mg | DC46: Se | DD46: Coef. Ret. | DE46: =CA316 -> 2.2787895 | DF46: mg | DO46: =(DP45+('Formulação suplementos'!$CM$37-(DP45*0.64))/0.8)/1000 -> 1.024382 | DP46: =-53.07 + (304.89 * (DO46)) + (90.79 *'Formulação suplementos'!$K$10) - (3.13 * 'Formulação suplementos'!$K$10*'Formulação suplementos'!$K$10) -> 654.03669 | DT46: =(DU45+('Formulação suplementos'!$CY$36-(DU45*0.64))/0.8)/1000 -> 0.43991743 | DU46: =-53.07 + (304.89 * (DT46-'Formulação suplementos'!$CA$214)) + (90.79 *('Formulação suplementos'!$CY$30)) - (3.13 *('Formulação suplementos'!$CY$30)^2) -> 89.688064
B47: Algodão Farelo 28%PB | C47: 0.8971 | D47: 0.7708 | E47: 0.3148 | F47: 0.0026 | G47: 0.0078 | I47: 0.3326 | J47: 0.0199 | K47: 0.0054 | L47: 0.0004 | M47: 0.0127 | N47: 0.0022 | O47: 18.79 | P47: 62.42 | R47: 23.68 | T47: 0.51 | W47: =IFERROR(IF(V47/D47=0,"",V47/D47),"") | X47: =IFERROR(IF(V47/E47=0,"",V47/E47),"") | BZ47: ELl, Mcal | CR47: 0.5 | DD47: 0.49 | DO47: =(DP46+('Formulação suplementos'!$CM$37-(DP46*0.64))/0.8)/1000 -> 1.024382 | DP47: =-53.07 + (304.89 * (DO47)) + (90.79 *'Formulação suplementos'!$K$10) - (3.13 * 'Formulação suplementos'!$K$10*'Formulação suplementos'!$K$10) -> 654.03669 | DT47: =(DU46+('Formulação suplementos'!$CY$36-(DU46*0.64))/0.8)/1000 -> 0.43991743 | DU47: =-53.07 + (304.89 * (DT47-'Formulação suplementos'!$CA$214)) + (90.79 *('Formulação suplementos'!$CY$30)) - (3.13 *('Formulação suplementos'!$CY$30)^2) -> 89.688064
B48: Algodão Farelo 38%PB | C48: 0.8974 | D48: 0.7571 | E48: 0.3963 | F48: 0.0024 | G48: 0.0097 | I48: 0.2946 | J48: 0.0146 | O48: 11.19 | P48: 11.8 | R48: 33.93 | W48: =IFERROR(IF(V48/D48=0,"",V48/D48),"") | X48: =IFERROR(IF(V48/E48=0,"",V48/E48),"") | BZ48: EM1 | CQ48: Se | CR48: Coef. Ret. | CS48: =CA166 -> 3.8087772 | CT48: mg | DC48: Zn | DD48: Coef. Ret. | DE48: =CA322 -> 134.10408 | DF48: mg | DO48: =(DP47+('Formulação suplementos'!$CM$37-(DP47*0.64))/0.8)/1000 -> 1.024382 | DP48: =-53.07 + (304.89 * (DO48)) + (90.79 *'Formulação suplementos'!$K$10) - (3.13 * 'Formulação suplementos'!$K$10*'Formulação suplementos'!$K$10) -> 654.03669 | DT48: =(DU47+('Formulação suplementos'!$CY$36-(DU47*0.64))/0.8)/1000 -> 0.43991743 | DU48: =-53.07 + (304.89 * (DT48-'Formulação suplementos'!$CA$214)) + (90.79 *('Formulação suplementos'!$CY$30)) - (3.13 *('Formulação suplementos'!$CY$30)^2) -> 89.688064
B49: Algodão Torta | C49: 0.9048 | D49: 0.8188 | E49: 0.2972 | F49: 0.0028 | G49: 0.0058 | I49: 0.4521 | J49: 0.093 | W49: =IFERROR(IF(V49/D49=0,"",V49/D49),"") | X49: =IFERROR(IF(V49/E49=0,"",V49/E49),"") | BZ49: EMt | CR49: 0.49 | DD49: 0.67 | DO49: =(DP48+('Formulação suplementos'!$CM$37-(DP48*0.64))/0.8)/1000 -> 1.024382 | DP49: =-53.07 + (304.89 * (DO49)) + (90.79 *'Formulação suplementos'!$K$10) - (3.13 * 'Formulação suplementos'!$K$10*'Formulação suplementos'!$K$10) -> 654.03669 | DT49: =(DU48+('Formulação suplementos'!$CY$36-(DU48*0.64))/0.8)/1000 -> 0.43991743 | DU49: =-53.07 + (304.89 * (DT49-'Formulação suplementos'!$CA$214)) + (90.79 *('Formulação suplementos'!$CY$30)) - (3.13 *('Formulação suplementos'!$CY$30)^2) -> 89.688064
B50: DDG 18% | C50: 0.8928 | D50: 0.8109 | E50: 0.1793 | F50: 0.0004 | G50: 0.0067 | I50: 0.4267 | J50: 0.0861 | W50: =IFERROR(IF(V50/D50=0,"",V50/D50),"") | X50: =IFERROR(IF(V50/E50=0,"",V50/E50),"") | BZ50: ED | CA50: =(((CM30/K7)+0.3032)/0.9455)*K7 -> 23.436066 | DO50: =(DP49+('Formulação suplementos'!$CM$37-(DP49*0.64))/0.8)/1000 -> 1.024382 | DP50: =-53.07 + (304.89 * (DO50)) + (90.79 *'Formulação suplementos'!$K$10) - (3.13 * 'Formulação suplementos'!$K$10*'Formulação suplementos'!$K$10) -> 654.03669 | DT50: =(DU49+('Formulação suplementos'!$CY$36-(DU49*0.64))/0.8)/1000 -> 0.43991743 | DU50: =-53.07 + (304.89 * (DT50-'Formulação suplementos'!$CA$214)) + (90.79 *('Formulação suplementos'!$CY$30)) - (3.13 *('Formulação suplementos'!$CY$30)^2) -> 89.688064
B51: DDG 30% | C51: 0.8856 | D51: 0.7409 | E51: 0.3227 | F51: 0.0225 | G51: 0.0034 | I51: 0.5239 | J51: 0.0528 | W51: =IFERROR(IF(V51/D51=0,"",V51/D51),"") | X51: =IFERROR(IF(V51/E51=0,"",V51/E51),"") | BZ51: NDT, kg | DO51: =(DP50+('Formulação suplementos'!$CM$37-(DP50*0.64))/0.8)/1000 -> 1.024382 | DP51: =-53.07 + (304.89 * (DO51)) + (90.79 *'Formulação suplementos'!$K$10) - (3.13 * 'Formulação suplementos'!$K$10*'Formulação suplementos'!$K$10) -> 654.03669 | DT51: =(DU50+('Formulação suplementos'!$CY$36-(DU50*0.64))/0.8)/1000 -> 0.43991743 | DU51: =-53.07 + (304.89 * (DT51-'Formulação suplementos'!$CA$214)) + (90.79 *('Formulação suplementos'!$CY$30)) - (3.13 *('Formulação suplementos'!$CY$30)^2) -> 89.688064
B52: Soja Farelo | C52: 0.8865 | D52: 0.7945 | E52: 0.4885 | F52: 0.0034 | G52: 0.0059 | I52: 0.131 | J52: 0.0193 | K52: 0.0029 | L52: 0.0006 | M52: 0.0202 | N52: 0.0026 | O52: 18.96 | P52: 53.79 | R52: 35.38 | T52: 0.27 | U52: 0.13 | W52: =IFERROR(IF(V52/D52=0,"",V52/D52),"") | X52: =IFERROR(IF(V52/E52=0,"",V52/E52),"") | BZ52: NDT, % | DO52: =(DP51+('Formulação suplementos'!$CM$37-(DP51*0.64))/0.8)/1000 -> 1.024382 | DP52: =-53.07 + (304.89 * (DO52)) + (90.79 *'Formulação suplementos'!$K$10) - (3.13 * 'Formulação suplementos'!$K$10*'Formulação suplementos'!$K$10) -> 654.03669 | DT52: =(DU51+('Formulação suplementos'!$CY$36-(DU51*0.64))/0.8)/1000 -> 0.43991743 | DU52: =-53.07 + (304.89 * (DT52-'Formulação suplementos'!$CA$214)) + (90.79 *('Formulação suplementos'!$CY$30)) - (3.13 *('Formulação suplementos'!$CY$30)^2) -> 89.688064
B53: Sal comum | C53: 0.99 | L53: 0.39 | O53: 1.34 | P53: 9.9 | R53: 2.71 | W53: =IFERROR(IF(V53/D53=0,"",V53/D53),"") | X53: =IFERROR(IF(V53/E53=0,"",V53/E53),"") | DO53: =(DP52+('Formulação suplementos'!$CM$37-(DP52*0.64))/0.8)/1000 -> 1.024382 | DP53: =-53.07 + (304.89 * (DO53)) + (90.79 *'Formulação suplementos'!$K$10) - (3.13 * 'Formulação suplementos'!$K$10*'Formulação suplementos'!$K$10) -> 654.03669 | DT53: =(DU52+('Formulação suplementos'!$CY$36-(DU52*0.64))/0.8)/1000 -> 0.43991743 | DU53: =-53.07 + (304.89 * (DT53-'Formulação suplementos'!$CA$214)) + (90.79 *('Formulação suplementos'!$CY$30)) - (3.13 *('Formulação suplementos'!$CY$30)^2) -> 89.688064
W54: =IFERROR(IF(V54/D54=0,"",V54/D54),"") | X54: =IFERROR(IF(V54/E54=0,"",V54/E54),"") | DO54: =(DP53+('Formulação suplementos'!$CM$37-(DP53*0.64))/0.8)/1000 -> 1.024382 | DP54: =-53.07 + (304.89 * (DO54)) + (90.79 *'Formulação suplementos'!$K$10) - (3.13 * 'Formulação suplementos'!$K$10*'Formulação suplementos'!$K$10) -> 654.03669 | DT54: =(DU53+('Formulação suplementos'!$CY$36-(DU53*0.64))/0.8)/1000 -> 0.43991743 | DU54: =-53.07 + (304.89 * (DT54-'Formulação suplementos'!$CA$214)) + (90.79 *('Formulação suplementos'!$CY$30)) - (3.13 *('Formulação suplementos'!$CY$30)^2) -> 89.688064
B55: Ureia | BY55: Proteína | BZ55: PMm | DO55: =(DP54+('Formulação suplementos'!$CM$37-(DP54*0.64))/0.8)/1000 -> 1.024382 | DP55: =-53.07 + (304.89 * (DO55)) + (90.79 *'Formulação suplementos'!$K$10) - (3.13 * 'Formulação suplementos'!$K$10*'Formulação suplementos'!$K$10) -> 654.03669 | DT55: =(DU54+('Formulação suplementos'!$CY$36-(DU54*0.64))/0.8)/1000 -> 0.43991743 | DU55: =-53.07 + (304.89 * (DT55-'Formulação suplementos'!$CA$214)) + (90.79 *('Formulação suplementos'!$CY$30)) - (3.13 *('Formulação suplementos'!$CY$30)^2) -> 89.688064
B56: Mineral/núcleo | C56: M.S (g/kg) | D56: NDT (g/kg) | E56: PB (g/kg) | F56: Ca (g/kg) | G56: P (g/kg) | H56: PDR (g/kg) | I56: FDN (g/kg) | J56: EE (g/kg) | K56: Mg (g/kg) | L56: Na (g/kg) | M56: K (g/kg) | N56: S (g/kg) | O56: Cu (mg/kg) | P56: Zn (mg/kg) | Q56: Fe (g/kg) | R56: Mn (mg/kg) | S56: I (mg/kg) | T56: Co (mg/kg) | U56: Se (mg/kg) | V56: NNP (g/kg) | W56: % ureia | BZ56: PLg | CA56: =CA37*(376.4*CA36^-0.1839) -> 1.1148808 | DO56: =(DP55+('Formulação suplementos'!$CM$37-(DP55*0.64))/0.8)/1000 -> 1.024382 | DP56: =-53.07 + (304.89 * (DO56)) + (90.79 *'Formulação suplementos'!$K$10) - (3.13 * 'Formulação suplementos'!$K$10*'Formulação suplementos'!$K$10) -> 654.03669 | DT56: =(DU55+('Formulação suplementos'!$CY$36-(DU55*0.64))/0.8)/1000 -> 0.43991743 | DU56: =-53.07 + (304.89 * (DT56-'Formulação suplementos'!$CA$214)) + (90.79 *('Formulação suplementos'!$CY$30)) - (3.13 *('Formulação suplementos'!$CY$30)^2) -> 89.688064
B57: Fosbovi boi verde | C57: 1 | F57: 160 | G57: 120 | N57: 80 | O57: 1250 | P57: 5000 | R57: 2500 | S57: 0.62 | T57: 12.5 | U57: 25 | W57: =IF('Formulação suplementos'!$V57/28.125/100=0,"",'Formulação suplementos'!$V57/28.125/100) | BZ57: k | CA57: 0.474 | DO57: =(DP56+('Formulação suplementos'!$CM$37-(DP56*0.64))/0.8)/1000 -> 1.024382 | DP57: =-53.07 + (304.89 * (DO57)) + (90.79 *'Formulação suplementos'!$K$10) - (3.13 * 'Formulação suplementos'!$K$10*'Formulação suplementos'!$K$10) -> 654.03669 | DT57: =(DU56+('Formulação suplementos'!$CY$36-(DU56*0.64))/0.8)/1000 -> 0.43991743 | DU57: =-53.07 + (304.89 * (DT57-'Formulação suplementos'!$CA$214)) + (90.79 *('Formulação suplementos'!$CY$30)) - (3.13 *('Formulação suplementos'!$CY$30)^2) -> 89.688064
B58: Fortumix +engorda SP | C58: 1 | F58: 180 | G58: 29 | K58: 10 | N58: 10 | O58: 1000 | P58: 3000 | R58: 300 | S58: 50 | T58: 90 | U58: 6.6 | W58: =IF('Formulação suplementos'!$V58/28.125/100=0,"",'Formulação suplementos'!$V58/28.125/100) | BZ58: PMg | DO58: =(DP57+('Formulação suplementos'!$CM$37-(DP57*0.64))/0.8)/1000 -> 1.024382 | DP58: =-53.07 + (304.89 * (DO58)) + (90.79 *'Formulação suplementos'!$K$10) - (3.13 * 'Formulação suplementos'!$K$10*'Formulação suplementos'!$K$10) -> 654.03669 | DT58: =(DU57+('Formulação suplementos'!$CY$36-(DU57*0.64))/0.8)/1000 -> 0.43991743 | DU58: =-53.07 + (304.89 * (DT58-'Formulação suplementos'!$CA$214)) + (90.79 *('Formulação suplementos'!$CY$30)) - (3.13 *('Formulação suplementos'!$CY$30)^2) -> 89.688064
W59: =IF('Formulação suplementos'!$V59/28.125/100=0,"",'Formulação suplementos'!$V59/28.125/100) | BZ59: PMl,g | DO59: =(DP58+('Formulação suplementos'!$CM$37-(DP58*0.64))/0.8)/1000 -> 1.024382 | DP59: =-53.07 + (304.89 * (DO59)) + (90.79 *'Formulação suplementos'!$K$10) - (3.13 * 'Formulação suplementos'!$K$10*'Formulação suplementos'!$K$10) -> 654.03669 | DT59: =(DU58+('Formulação suplementos'!$CY$36-(DU58*0.64))/0.8)/1000 -> 0.43991743 | DU59: =-53.07 + (304.89 * (DT59-'Formulação suplementos'!$CA$214)) + (90.79 *('Formulação suplementos'!$CY$30)) - (3.13 *('Formulação suplementos'!$CY$30)^2) -> 89.688064
W60: =IF('Formulação suplementos'!$V60/28.125/100=0,"",'Formulação suplementos'!$V60/28.125/100) | BZ60: PMt | DO60: =(DP59+('Formulação suplementos'!$CM$37-(DP59*0.64))/0.8)/1000 -> 1.024382 | DP60: =-53.07 + (304.89 * (DO60)) + (90.79 *'Formulação suplementos'!$K$10) - (3.13 * 'Formulação suplementos'!$K$10*'Formulação suplementos'!$K$10) -> 654.03669 | DT60: =(DU59+('Formulação suplementos'!$CY$36-(DU59*0.64))/0.8)/1000 -> 0.43991743 | DU60: =-53.07 + (304.89 * (DT60-'Formulação suplementos'!$CA$214)) + (90.79 *('Formulação suplementos'!$CY$30)) - (3.13 *('Formulação suplementos'!$CY$30)^2) -> 89.688064
W61: =IF('Formulação suplementos'!$V61/28.125/100=0,"",'Formulação suplementos'!$V61/28.125/100) | BZ61: PBmic | CA61: =('Formulação suplementos'!DP116)/1000 -> 0.65403669 | DO61: =(DP60+('Formulação suplementos'!$CM$37-(DP60*0.64))/0.8)/1000 -> 1.024382 | DP61: =-53.07 + (304.89 * (DO61)) + (90.79 *'Formulação suplementos'!$K$10) - (3.13 * 'Formulação suplementos'!$K$10*'Formulação suplementos'!$K$10) -> 654.03669 | DT61: =(DU60+('Formulação suplementos'!$CY$36-(DU60*0.64))/0.8)/1000 -> 0.43991743 | DU61: =-53.07 + (304.89 * (DT61-'Formulação suplementos'!$CA$214)) + (90.79 *('Formulação suplementos'!$CY$30)) - (3.13 *('Formulação suplementos'!$CY$30)^2) -> 89.688064
W62: =IF('Formulação suplementos'!$V62/28.125/100=0,"",'Formulação suplementos'!$V62/28.125/100) | BZ62: PDR | DO62: =(DP61+('Formulação suplementos'!$CM$37-(DP61*0.64))/0.8)/1000 -> 1.024382 | DP62: =-53.07 + (304.89 * (DO62)) + (90.79 *'Formulação suplementos'!$K$10) - (3.13 * 'Formulação suplementos'!$K$10*'Formulação suplementos'!$K$10) -> 654.03669 | DT62: =(DU61+('Formulação suplementos'!$CY$36-(DU61*0.64))/0.8)/1000 -> 0.43991743 | DU62: =-53.07 + (304.89 * (DT62-'Formulação suplementos'!$CA$214)) + (90.79 *('Formulação suplementos'!$CY$30)) - (3.13 *('Formulação suplementos'!$CY$30)^2) -> 89.688064
W63: =IF('Formulação suplementos'!$V63/28.125/100=0,"",'Formulação suplementos'!$V63/28.125/100) | BZ63: PNDR | DO63: =(DP62+('Formulação suplementos'!$CM$37-(DP62*0.64))/0.8)/1000 -> 1.024382 | DP63: =-53.07 + (304.89 * (DO63)) + (90.79 *'Formulação suplementos'!$K$10) - (3.13 * 'Formulação suplementos'!$K$10*'Formulação suplementos'!$K$10) -> 654.03669 | DT63: =(DU62+('Formulação suplementos'!$CY$36-(DU62*0.64))/0.8)/1000 -> 0.43991743 | DU63: =-53.07 + (304.89 * (DT63-'Formulação suplementos'!$CA$214)) + (90.79 *('Formulação suplementos'!$CY$30)) - (3.13 *('Formulação suplementos'!$CY$30)^2) -> 89.688064
W64: =IF('Formulação suplementos'!$V64/28.125/100=0,"",'Formulação suplementos'!$V64/28.125/100) | BZ64: PB | DO64: =(DP63+('Formulação suplementos'!$CM$37-(DP63*0.64))/0.8)/1000 -> 1.024382 | DP64: =-53.07 + (304.89 * (DO64)) + (90.79 *'Formulação suplementos'!$K$10) - (3.13 * 'Formulação suplementos'!$K$10*'Formulação suplementos'!$K$10) -> 654.03669 | DT64: =(DU63+('Formulação suplementos'!$CY$36-(DU63*0.64))/0.8)/1000 -> 0.43991743 | DU64: =-53.07 + (304.89 * (DT64-'Formulação suplementos'!$CA$214)) + (90.79 *('Formulação suplementos'!$CY$30)) - (3.13 *('Formulação suplementos'!$CY$30)^2) -> 89.688064
W65: =IF('Formulação suplementos'!$V65/28.125/100=0,"",'Formulação suplementos'!$V65/28.125/100) | BZ65: PB, % | CA65: =(K11/1000)/K7*100 -> 11.504982 | DO65: =(DP64+('Formulação suplementos'!$CM$37-(DP64*0.64))/0.8)/1000 -> 1.024382 | DP65: =-53.07 + (304.89 * (DO65)) + (90.79 *'Formulação suplementos'!$K$10) - (3.13 * 'Formulação suplementos'!$K$10*'Formulação suplementos'!$K$10) -> 654.03669 | DT65: =(DU64+('Formulação suplementos'!$CY$36-(DU64*0.64))/0.8)/1000 -> 0.43991743 | DU65: =-53.07 + (304.89 * (DT65-'Formulação suplementos'!$CA$214)) + (90.79 *('Formulação suplementos'!$CY$30)) - (3.13 *('Formulação suplementos'!$CY$30)^2) -> 89.688064
W66: =IF('Formulação suplementos'!$V66/28.125/100=0,"",'Formulação suplementos'!$V66/28.125/100) | DO66: =(DP65+('Formulação suplementos'!$CM$37-(DP65*0.64))/0.8)/1000 -> 1.024382 | DP66: =-53.07 + (304.89 * (DO66)) + (90.79 *'Formulação suplementos'!$K$10) - (3.13 * 'Formulação suplementos'!$K$10*'Formulação suplementos'!$K$10) -> 654.03669 | DT66: =(DU65+('Formulação suplementos'!$CY$36-(DU65*0.64))/0.8)/1000 -> 0.43991743 | DU66: =-53.07 + (304.89 * (DT66-'Formulação suplementos'!$CA$214)) + (90.79 *('Formulação suplementos'!$CY$30)) - (3.13 *('Formulação suplementos'!$CY$30)^2) -> 89.688064
W67: =IF('Formulação suplementos'!$V67/28.125/100=0,"",'Formulação suplementos'!$V67/28.125/100) | DO67: =(DP66+('Formulação suplementos'!$CM$37-(DP66*0.64))/0.8)/1000 -> 1.024382 | DP67: =-53.07 + (304.89 * (DO67)) + (90.79 *'Formulação suplementos'!$K$10) - (3.13 * 'Formulação suplementos'!$K$10*'Formulação suplementos'!$K$10) -> 654.03669 | DT67: =(DU66+('Formulação suplementos'!$CY$36-(DU66*0.64))/0.8)/1000 -> 0.43991743 | DU67: =-53.07 + (304.89 * (DT67-'Formulação suplementos'!$CA$214)) + (90.79 *('Formulação suplementos'!$CY$30)) - (3.13 *('Formulação suplementos'!$CY$30)^2) -> 89.688064
W68: =IF('Formulação suplementos'!$V68/28.125/100=0,"",'Formulação suplementos'!$V68/28.125/100) | BZ68: Ca g | CA68: =IF(CA36<462,CA37*(147*CA36^-0.5),0) -> 0.064664142 | DO68: =(DP67+('Formulação suplementos'!$CM$37-(DP67*0.64))/0.8)/1000 -> 1.024382 | DP68: =-53.07 + (304.89 * (DO68)) + (90.79 *'Formulação suplementos'!$K$10) - (3.13 * 'Formulação suplementos'!$K$10*'Formulação suplementos'!$K$10) -> 654.03669 | DT68: =(DU67+('Formulação suplementos'!$CY$36-(DU67*0.64))/0.8)/1000 -> 0.43991743 | DU68: =-53.07 + (304.89 * (DT68-'Formulação suplementos'!$CA$214)) + (90.79 *('Formulação suplementos'!$CY$30)) - (3.13 *('Formulação suplementos'!$CY$30)^2) -> 89.688064
BY69: Cálcio | BZ69: Ca m | CA69: =11.7*C6/1000 -> 5.85 | DO69: =(DP68+('Formulação suplementos'!$CM$37-(DP68*0.64))/0.8)/1000 -> 1.024382 | DP69: =-53.07 + (304.89 * (DO69)) + (90.79 *'Formulação suplementos'!$K$10) - (3.13 * 'Formulação suplementos'!$K$10*'Formulação suplementos'!$K$10) -> 654.03669 | DT69: =(DU68+('Formulação suplementos'!$CY$36-(DU68*0.64))/0.8)/1000 -> 0.43991743 | DU69: =-53.07 + (304.89 * (DT69-'Formulação suplementos'!$CA$214)) + (90.79 *('Formulação suplementos'!$CY$30)) - (3.13 *('Formulação suplementos'!$CY$30)^2) -> 89.688064
BZ70: Ca lac | CA70: =1.1*CM22 -> 6.6779745 | DO70: =(DP69+('Formulação suplementos'!$CM$37-(DP69*0.64))/0.8)/1000 -> 1.024382 | DP70: =-53.07 + (304.89 * (DO70)) + (90.79 *'Formulação suplementos'!$K$10) - (3.13 * 'Formulação suplementos'!$K$10*'Formulação suplementos'!$K$10) -> 654.03669 | DT70: =(DU69+('Formulação suplementos'!$CY$36-(DU69*0.64))/0.8)/1000 -> 0.43991743 | DU70: =-53.07 + (304.89 * (DT70-'Formulação suplementos'!$CA$214)) + (90.79 *('Formulação suplementos'!$CY$30)) - (3.13 *('Formulação suplementos'!$CY$30)^2) -> 89.688064
B71: Atenção: | BZ71: Ca tot | CA71: =CA70+CA69+CA68 -> 12.592639 | DO71: =(DP70+('Formulação suplementos'!$CM$37-(DP70*0.64))/0.8)/1000 -> 1.024382 | DP71: =-53.07 + (304.89 * (DO71)) + (90.79 *'Formulação suplementos'!$K$10) - (3.13 * 'Formulação suplementos'!$K$10*'Formulação suplementos'!$K$10) -> 654.03669 | DT71: =(DU70+('Formulação suplementos'!$CY$36-(DU70*0.64))/0.8)/1000 -> 0.43991743 | DU71: =-53.07 + (304.89 * (DT71-'Formulação suplementos'!$CA$214)) + (90.79 *('Formulação suplementos'!$CY$30)) - (3.13 *('Formulação suplementos'!$CY$30)^2) -> 89.688064
B72: - Essa planilha é de uso exclusivo dos alunos do Programa Acelerador de Arrobas, não podendo ser compartilhada ou vendida separadamente. | BZ72: Coef retenc | DO72: =(DP71+('Formulação suplementos'!$CM$37-(DP71*0.64))/0.8)/1000 -> 1.024382 | DP72: =-53.07 + (304.89 * (DO72)) + (90.79 *'Formulação suplementos'!$K$10) - (3.13 * 'Formulação suplementos'!$K$10*'Formulação suplementos'!$K$10) -> 654.03669 | DT72: =(DU71+('Formulação suplementos'!$CY$36-(DU71*0.64))/0.8)/1000 -> 0.43991743 | DU72: =-53.07 + (304.89 * (DT72-'Formulação suplementos'!$CA$214)) + (90.79 *('Formulação suplementos'!$CY$30)) - (3.13 *('Formulação suplementos'!$CY$30)^2) -> 89.688064
B73: - Os dados gerados e coletados aqui não garantem resultado, visto que o mesmo depende de diversos outros fatores, como ensinado nas aulas. | BZ73: Ca, g | CA73: =CA71/CR21 -> 22.170139 | DO73: =(DP72+('Formulação suplementos'!$CM$37-(DP72*0.64))/0.8)/1000 -> 1.024382 | DP73: =-53.07 + (304.89 * (DO73)) + (90.79 *'Formulação suplementos'!$K$10) - (3.13 * 'Formulação suplementos'!$K$10*'Formulação suplementos'!$K$10) -> 654.03669 | DT73: =(DU72+('Formulação suplementos'!$CY$36-(DU72*0.64))/0.8)/1000 -> 0.43991743 | DU73: =-53.07 + (304.89 * (DT73-'Formulação suplementos'!$CA$214)) + (90.79 *('Formulação suplementos'!$CY$30)) - (3.13 *('Formulação suplementos'!$CY$30)^2) -> 89.688064
B74: - Essa planilha não se responsabiliza por falhas na nutrição, visto que a mesam depende de diversos outros fatores para falhar ou alcançar o sucesso, como ensinado nas aulas. | DO74: =(DP73+('Formulação suplementos'!$CM$37-(DP73*0.64))/0.8)/1000 -> 1.024382 | DP74: =-53.07 + (304.89 * (DO74)) + (90.79 *'Formulação suplementos'!$K$10) - (3.13 * 'Formulação suplementos'!$K$10*'Formulação suplementos'!$K$10) -> 654.03669 | DT74: =(DU73+('Formulação suplementos'!$CY$36-(DU73*0.64))/0.8)/1000 -> 0.43991743 | DU74: =-53.07 + (304.89 * (DT74-'Formulação suplementos'!$CA$214)) + (90.79 *('Formulação suplementos'!$CY$30)) - (3.13 *('Formulação suplementos'!$CY$30)^2) -> 89.688064
B75: - Os alimentos inseridos na biblioteca não representam a realidade de todos os locais. Sempre faça análise bromatológica e peça os níveis de garantia. | BY75: Fóforo | BZ75: P m | CA75: =13.5*C6/1000 -> 6.75 | DO75: =(DP74+('Formulação suplementos'!$CM$37-(DP74*0.64))/0.8)/1000 -> 1.024382 | DP75: =-53.07 + (304.89 * (DO75)) + (90.79 *'Formulação suplementos'!$K$10) - (3.13 * 'Formulação suplementos'!$K$10*'Formulação suplementos'!$K$10) -> 654.03669 | DT75: =(DU74+('Formulação suplementos'!$CY$36-(DU74*0.64))/0.8)/1000 -> 0.43991743 | DU75: =-53.07 + (304.89 * (DT75-'Formulação suplementos'!$CA$214)) + (90.79 *('Formulação suplementos'!$CY$30)) - (3.13 *('Formulação suplementos'!$CY$30)^2) -> 89.688064
B76: - Essa planilha é para formulações simples, que tem capim em pastejo como base da dieta. | BZ76: P g | CA76: =CA37*(54.4*CA36^-0.4484) -> 0.032669716 | DO76: =(DP75+('Formulação suplementos'!$CM$37-(DP75*0.64))/0.8)/1000 -> 1.024382 | DP76: =-53.07 + (304.89 * (DO76)) + (90.79 *'Formulação suplementos'!$K$10) - (3.13 * 'Formulação suplementos'!$K$10*'Formulação suplementos'!$K$10) -> 654.03669 | DT76: =(DU75+('Formulação suplementos'!$CY$36-(DU75*0.64))/0.8)/1000 -> 0.43991743 | DU76: =-53.07 + (304.89 * (DT76-'Formulação suplementos'!$CA$214)) + (90.79 *('Formulação suplementos'!$CY$30)) - (3.13 *('Formulação suplementos'!$CY$30)^2) -> 89.688064
BZ77: P lac | CA77: =0.77*CM22 -> 4.6745822 | DO77: =(DP76+('Formulação suplementos'!$CM$37-(DP76*0.64))/0.8)/1000 -> 1.024382 | DP77: =-53.07 + (304.89 * (DO77)) + (90.79 *'Formulação suplementos'!$K$10) - (3.13 * 'Formulação suplementos'!$K$10*'Formulação suplementos'!$K$10) -> 654.03669 | DT77: =(DU76+('Formulação suplementos'!$CY$36-(DU76*0.64))/0.8)/1000 -> 0.43991743 | DU77: =-53.07 + (304.89 * (DT77-'Formulação suplementos'!$CA$214)) + (90.79 *('Formulação suplementos'!$CY$30)) - (3.13 *('Formulação suplementos'!$CY$30)^2) -> 89.688064
BZ78: P tot | CA78: =CA77+CA76+CA75 -> 11.457252 | DO78: =(DP77+('Formulação suplementos'!$CM$37-(DP77*0.64))/0.8)/1000 -> 1.024382 | DP78: =-53.07 + (304.89 * (DO78)) + (90.79 *'Formulação suplementos'!$K$10) - (3.13 * 'Formulação suplementos'!$K$10*'Formulação suplementos'!$K$10) -> 654.03669 | DT78: =(DU77+('Formulação suplementos'!$CY$36-(DU77*0.64))/0.8)/1000 -> 0.43991743 | DU78: =-53.07 + (304.89 * (DT78-'Formulação suplementos'!$CA$214)) + (90.79 *('Formulação suplementos'!$CY$30)) - (3.13 *('Formulação suplementos'!$CY$30)^2) -> 89.688064
BZ79: Coef. Ret. | DO79: =(DP78+('Formulação suplementos'!$CM$37-(DP78*0.64))/0.8)/1000 -> 1.024382 | DP79: =-53.07 + (304.89 * (DO79)) + (90.79 *'Formulação suplementos'!$K$10) - (3.13 * 'Formulação suplementos'!$K$10*'Formulação suplementos'!$K$10) -> 654.03669 | DT79: =(DU78+('Formulação suplementos'!$CY$36-(DU78*0.64))/0.8)/1000 -> 0.43991743 | DU79: =-53.07 + (304.89 * (DT79-'Formulação suplementos'!$CA$214)) + (90.79 *('Formulação suplementos'!$CY$30)) - (3.13 *('Formulação suplementos'!$CY$30)^2) -> 89.688064
BZ80: P, g | CA80: =CA78/CR23 -> 16.898602 | DO80: =(DP79+('Formulação suplementos'!$CM$37-(DP79*0.64))/0.8)/1000 -> 1.024382 | DP80: =-53.07 + (304.89 * (DO80)) + (90.79 *'Formulação suplementos'!$K$10) - (3.13 * 'Formulação suplementos'!$K$10*'Formulação suplementos'!$K$10) -> 654.03669 | DT80: =(DU79+('Formulação suplementos'!$CY$36-(DU79*0.64))/0.8)/1000 -> 0.43991743 | DU80: =-53.07 + (304.89 * (DT80-'Formulação suplementos'!$CA$214)) + (90.79 *('Formulação suplementos'!$CY$30)) - (3.13 *('Formulação suplementos'!$CY$30)^2) -> 89.688064
DO81: =(DP80+('Formulação suplementos'!$CM$37-(DP80*0.64))/0.8)/1000 -> 1.024382 | DP81: =-53.07 + (304.89 * (DO81)) + (90.79 *'Formulação suplementos'!$K$10) - (3.13 * 'Formulação suplementos'!$K$10*'Formulação suplementos'!$K$10) -> 654.03669 | DT81: =(DU80+('Formulação suplementos'!$CY$36-(DU80*0.64))/0.8)/1000 -> 0.43991743 | DU81: =-53.07 + (304.89 * (DT81-'Formulação suplementos'!$CA$214)) + (90.79 *('Formulação suplementos'!$CY$30)) - (3.13 *('Formulação suplementos'!$CY$30)^2) -> 89.688064
BY82: Relação Ca/P | CA82: =CA73/CA80 -> 1.3119511 | DO82: =(DP81+('Formulação suplementos'!$CM$37-(DP81*0.64))/0.8)/1000 -> 1.024382 | DP82: =-53.07 + (304.89 * (DO82)) + (90.79 *'Formulação suplementos'!$K$10) - (3.13 * 'Formulação suplementos'!$K$10*'Formulação suplementos'!$K$10) -> 654.03669 | DT82: =(DU81+('Formulação suplementos'!$CY$36-(DU81*0.64))/0.8)/1000 -> 0.43991743 | DU82: =-53.07 + (304.89 * (DT82-'Formulação suplementos'!$CA$214)) + (90.79 *('Formulação suplementos'!$CY$30)) - (3.13 *('Formulação suplementos'!$CY$30)^2) -> 89.688064
DO83: =(DP82+('Formulação suplementos'!$CM$37-(DP82*0.64))/0.8)/1000 -> 1.024382 | DP83: =-53.07 + (304.89 * (DO83)) + (90.79 *'Formulação suplementos'!$K$10) - (3.13 * 'Formulação suplementos'!$K$10*'Formulação suplementos'!$K$10) -> 654.03669 | DT83: =(DU82+('Formulação suplementos'!$CY$36-(DU82*0.64))/0.8)/1000 -> 0.43991743 | DU83: =-53.07 + (304.89 * (DT83-'Formulação suplementos'!$CA$214)) + (90.79 *('Formulação suplementos'!$CY$30)) - (3.13 *('Formulação suplementos'!$CY$30)^2) -> 89.688064
BY84: Magnésio | BZ84: Mg m | CA84: =C6*5.9/1000 -> 2.95 | DO84: =(DP83+('Formulação suplementos'!$CM$37-(DP83*0.64))/0.8)/1000 -> 1.024382 | DP84: =-53.07 + (304.89 * (DO84)) + (90.79 *'Formulação suplementos'!$K$10) - (3.13 * 'Formulação suplementos'!$K$10*'Formulação suplementos'!$K$10) -> 654.03669 | DT84: =(DU83+('Formulação suplementos'!$CY$36-(DU83*0.64))/0.8)/1000 -> 0.43991743 | DU84: =-53.07 + (304.89 * (DT84-'Formulação suplementos'!$CA$214)) + (90.79 *('Formulação suplementos'!$CY$30)) - (3.13 *('Formulação suplementos'!$CY$30)^2) -> 89.688064
BZ85: Mg g | CA85: =CA37*(1.4*CA36^-0.3227) -> 0.0017948519 | DO85: =(DP84+('Formulação suplementos'!$CM$37-(DP84*0.64))/0.8)/1000 -> 1.024382 | DP85: =-53.07 + (304.89 * (DO85)) + (90.79 *'Formulação suplementos'!$K$10) - (3.13 * 'Formulação suplementos'!$K$10*'Formulação suplementos'!$K$10) -> 654.03669 | DT85: =(DU84+('Formulação suplementos'!$CY$36-(DU84*0.64))/0.8)/1000 -> 0.43991743 | DU85: =-53.07 + (304.89 * (DT85-'Formulação suplementos'!$CA$214)) + (90.79 *('Formulação suplementos'!$CY$30)) - (3.13 *('Formulação suplementos'!$CY$30)^2) -> 89.688064
BZ86: Mg lac | CA86: =0.07*CM22 -> 0.42496202 | DO86: =(DP85+('Formulação suplementos'!$CM$37-(DP85*0.64))/0.8)/1000 -> 1.024382 | DP86: =-53.07 + (304.89 * (DO86)) + (90.79 *'Formulação suplementos'!$K$10) - (3.13 * 'Formulação suplementos'!$K$10*'Formulação suplementos'!$K$10) -> 654.03669 | DT86: =(DU85+('Formulação suplementos'!$CY$36-(DU85*0.64))/0.8)/1000 -> 0.43991743 | DU86: =-53.07 + (304.89 * (DT86-'Formulação suplementos'!$CA$214)) + (90.79 *('Formulação suplementos'!$CY$30)) - (3.13 *('Formulação suplementos'!$CY$30)^2) -> 89.688064
BZ87: Mg tot | CA87: =CA86+CA85+CA84 -> 3.3767569 | DO87: =(DP86+('Formulação suplementos'!$CM$37-(DP86*0.64))/0.8)/1000 -> 1.024382 | DP87: =-53.07 + (304.89 * (DO87)) + (90.79 *'Formulação suplementos'!$K$10) - (3.13 * 'Formulação suplementos'!$K$10*'Formulação suplementos'!$K$10) -> 654.03669 | DT87: =(DU86+('Formulação suplementos'!$CY$36-(DU86*0.64))/0.8)/1000 -> 0.43991743 | DU87: =-53.07 + (304.89 * (DT87-'Formulação suplementos'!$CA$214)) + (90.79 *('Formulação suplementos'!$CY$30)) - (3.13 *('Formulação suplementos'!$CY$30)^2) -> 89.688064
BZ88: Coef. Ret. | DO88: =(DP87+('Formulação suplementos'!$CM$37-(DP87*0.64))/0.8)/1000 -> 1.024382 | DP88: =-53.07 + (304.89 * (DO88)) + (90.79 *'Formulação suplementos'!$K$10) - (3.13 * 'Formulação suplementos'!$K$10*'Formulação suplementos'!$K$10) -> 654.03669 | DT88: =(DU87+('Formulação suplementos'!$CY$36-(DU87*0.64))/0.8)/1000 -> 0.43991743 | DU88: =-53.07 + (304.89 * (DT88-'Formulação suplementos'!$CA$214)) + (90.79 *('Formulação suplementos'!$CY$30)) - (3.13 *('Formulação suplementos'!$CY$30)^2) -> 89.688064
BZ89: Mg, g | CA89: =CA87/CR26 -> 9.5119912 | DO89: =(DP88+('Formulação suplementos'!$CM$37-(DP88*0.64))/0.8)/1000 -> 1.024382 | DP89: =-53.07 + (304.89 * (DO89)) + (90.79 *'Formulação suplementos'!$K$10) - (3.13 * 'Formulação suplementos'!$K$10*'Formulação suplementos'!$K$10) -> 654.03669 | DT89: =(DU88+('Formulação suplementos'!$CY$36-(DU88*0.64))/0.8)/1000 -> 0.43991743 | DU89: =-53.07 + (304.89 * (DT89-'Formulação suplementos'!$CA$214)) + (90.79 *('Formulação suplementos'!$CY$30)) - (3.13 *('Formulação suplementos'!$CY$30)^2) -> 89.688064
DO90: =(DP89+('Formulação suplementos'!$CM$37-(DP89*0.64))/0.8)/1000 -> 1.024382 | DP90: =-53.07 + (304.89 * (DO90)) + (90.79 *'Formulação suplementos'!$K$10) - (3.13 * 'Formulação suplementos'!$K$10*'Formulação suplementos'!$K$10) -> 654.03669 | DT90: =(DU89+('Formulação suplementos'!$CY$36-(DU89*0.64))/0.8)/1000 -> 0.43991743 | DU90: =-53.07 + (304.89 * (DT90-'Formulação suplementos'!$CA$214)) + (90.79 *('Formulação suplementos'!$CY$30)) - (3.13 *('Formulação suplementos'!$CY$30)^2) -> 89.688064
BY91: Sódio | BZ91: Na m | CA91: =C6*6.3/1000 -> 3.15 | DO91: =(DP90+('Formulação suplementos'!$CM$37-(DP90*0.64))/0.8)/1000 -> 1.024382 | DP91: =-53.07 + (304.89 * (DO91)) + (90.79 *'Formulação suplementos'!$K$10) - (3.13 * 'Formulação suplementos'!$K$10*'Formulação suplementos'!$K$10) -> 654.03669 | DT91: =(DU90+('Formulação suplementos'!$CY$36-(DU90*0.64))/0.8)/1000 -> 0.43991743 | DU91: =-53.07 + (304.89 * (DT91-'Formulação suplementos'!$CA$214)) + (90.79 *('Formulação suplementos'!$CY$30)) - (3.13 *('Formulação suplementos'!$CY$30)^2) -> 89.688064
BZ92: Na g | CA92: =CA37*(1.4*CA36^-0.0575) -> 0.0088898639 | DO92: =(DP91+('Formulação suplementos'!$CM$37-(DP91*0.64))/0.8)/1000 -> 1.024382 | DP92: =-53.07 + (304.89 * (DO92)) + (90.79 *'Formulação suplementos'!$K$10) - (3.13 * 'Formulação suplementos'!$K$10*'Formulação suplementos'!$K$10) -> 654.03669 | DT92: =(DU91+('Formulação suplementos'!$CY$36-(DU91*0.64))/0.8)/1000 -> 0.43991743 | DU92: =-53.07 + (304.89 * (DT92-'Formulação suplementos'!$CA$214)) + (90.79 *('Formulação suplementos'!$CY$30)) - (3.13 *('Formulação suplementos'!$CY$30)^2) -> 89.688064
BZ93: Na lac | CA93: =0.2*CM22 -> 1.2141772 | DO93: =(DP92+('Formulação suplementos'!$CM$37-(DP92*0.64))/0.8)/1000 -> 1.024382 | DP93: =-53.07 + (304.89 * (DO93)) + (90.79 *'Formulação suplementos'!$K$10) - (3.13 * 'Formulação suplementos'!$K$10*'Formulação suplementos'!$K$10) -> 654.03669 | DT93: =(DU92+('Formulação suplementos'!$CY$36-(DU92*0.64))/0.8)/1000 -> 0.43991743 | DU93: =-53.07 + (304.89 * (DT93-'Formulação suplementos'!$CA$214)) + (90.79 *('Formulação suplementos'!$CY$30)) - (3.13 *('Formulação suplementos'!$CY$30)^2) -> 89.688064
BZ94: Na tot | CA94: =CA93+CA92+CA91 -> 4.3730671 | DO94: =(DP93+('Formulação suplementos'!$CM$37-(DP93*0.64))/0.8)/1000 -> 1.024382 | DP94: =-53.07 + (304.89 * (DO94)) + (90.79 *'Formulação suplementos'!$K$10) - (3.13 * 'Formulação suplementos'!$K$10*'Formulação suplementos'!$K$10) -> 654.03669 | DT94: =(DU93+('Formulação suplementos'!$CY$36-(DU93*0.64))/0.8)/1000 -> 0.43991743 | DU94: =-53.07 + (304.89 * (DT94-'Formulação suplementos'!$CA$214)) + (90.79 *('Formulação suplementos'!$CY$30)) - (3.13 *('Formulação suplementos'!$CY$30)^2) -> 89.688064
BZ95: Coef. Ret. | DO95: =(DP94+('Formulação suplementos'!$CM$37-(DP94*0.64))/0.8)/1000 -> 1.024382 | DP95: =-53.07 + (304.89 * (DO95)) + (90.79 *'Formulação suplementos'!$K$10) - (3.13 * 'Formulação suplementos'!$K$10*'Formulação suplementos'!$K$10) -> 654.03669 | DT95: =(DU94+('Formulação suplementos'!$CY$36-(DU94*0.64))/0.8)/1000 -> 0.43991743 | DU95: =-53.07 + (304.89 * (DT95-'Formulação suplementos'!$CA$214)) + (90.79 *('Formulação suplementos'!$CY$30)) - (3.13 *('Formulação suplementos'!$CY$30)^2) -> 89.688064
BZ96: Na, g | CA96: =CA94/CR28 -> 11.787243 | DO96: =(DP95+('Formulação suplementos'!$CM$37-(DP95*0.64))/0.8)/1000 -> 1.024382 | DP96: =-53.07 + (304.89 * (DO96)) + (90.79 *'Formulação suplementos'!$K$10) - (3.13 * 'Formulação suplementos'!$K$10*'Formulação suplementos'!$K$10) -> 654.03669 | DT96: =(DU95+('Formulação suplementos'!$CY$36-(DU95*0.64))/0.8)/1000 -> 0.43991743 | DU96: =-53.07 + (304.89 * (DT96-'Formulação suplementos'!$CA$214)) + (90.79 *('Formulação suplementos'!$CY$30)) - (3.13 *('Formulação suplementos'!$CY$30)^2) -> 89.688064
DO97: =(DP96+('Formulação suplementos'!$CM$37-(DP96*0.64))/0.8)/1000 -> 1.024382 | DP97: =-53.07 + (304.89 * (DO97)) + (90.79 *'Formulação suplementos'!$K$10) - (3.13 * 'Formulação suplementos'!$K$10*'Formulação suplementos'!$K$10) -> 654.03669 | DT97: =(DU96+('Formulação suplementos'!$CY$36-(DU96*0.64))/0.8)/1000 -> 0.43991743 | DU97: =-53.07 + (304.89 * (DT97-'Formulação suplementos'!$CA$214)) + (90.79 *('Formulação suplementos'!$CY$30)) - (3.13 *('Formulação suplementos'!$CY$30)^2) -> 89.688064
BY98: Potássio | BZ98: K m | CA98: =C6*23.5/1000 -> 11.75 | DO98: =(DP97+('Formulação suplementos'!$CM$37-(DP97*0.64))/0.8)/1000 -> 1.024382 | DP98: =-53.07 + (304.89 * (DO98)) + (90.79 *'Formulação suplementos'!$K$10) - (3.13 * 'Formulação suplementos'!$K$10*'Formulação suplementos'!$K$10) -> 654.03669 | DT98: =(DU97+('Formulação suplementos'!$CY$36-(DU97*0.64))/0.8)/1000 -> 0.43991743 | DU98: =-53.07 + (304.89 * (DT98-'Formulação suplementos'!$CA$214)) + (90.79 *('Formulação suplementos'!$CY$30)) - (3.13 *('Formulação suplementos'!$CY$30)^2) -> 89.688064
BZ99: K g | CA99: =CA37*(3.1*CA36^-0.2142) -> 0.0076480315 | DO99: =(DP98+('Formulação suplementos'!$CM$37-(DP98*0.64))/0.8)/1000 -> 1.024382 | DP99: =-53.07 + (304.89 * (DO99)) + (90.79 *'Formulação suplementos'!$K$10) - (3.13 * 'Formulação suplementos'!$K$10*'Formulação suplementos'!$K$10) -> 654.03669 | DT99: =(DU98+('Formulação suplementos'!$CY$36-(DU98*0.64))/0.8)/1000 -> 0.43991743 | DU99: =-53.07 + (304.89 * (DT99-'Formulação suplementos'!$CA$214)) + (90.79 *('Formulação suplementos'!$CY$30)) - (3.13 *('Formulação suplementos'!$CY$30)^2) -> 89.688064
BZ100: K lac | CA100: =0.7*CM22 -> 4.2496202 | DO100: =(DP99+('Formulação suplementos'!$CM$37-(DP99*0.64))/0.8)/1000 -> 1.024382 | DP100: =-53.07 + (304.89 * (DO100)) + (90.79 *'Formulação suplementos'!$K$10) - (3.13 * 'Formulação suplementos'!$K$10*'Formulação suplementos'!$K$10) -> 654.03669 | DT100: =(DU99+('Formulação suplementos'!$CY$36-(DU99*0.64))/0.8)/1000 -> 0.43991743 | DU100: =-53.07 + (304.89 * (DT100-'Formulação suplementos'!$CA$214)) + (90.79 *('Formulação suplementos'!$CY$30)) - (3.13 *('Formulação suplementos'!$CY$30)^2) -> 89.688064
BZ101: K tot | CA101: =CA100+CA99+CA98 -> 16.007268 | DO101: =(DP100+('Formulação suplementos'!$CM$37-(DP100*0.64))/0.8)/1000 -> 1.024382 | DP101: =-53.07 + (304.89 * (DO101)) + (90.79 *'Formulação suplementos'!$K$10) - (3.13 * 'Formulação suplementos'!$K$10*'Formulação suplementos'!$K$10) -> 654.03669 | DT101: =(DU100+('Formulação suplementos'!$CY$36-(DU100*0.64))/0.8)/1000 -> 0.43991743 | DU101: =-53.07 + (304.89 * (DT101-'Formulação suplementos'!$CA$214)) + (90.79 *('Formulação suplementos'!$CY$30)) - (3.13 *('Formulação suplementos'!$CY$30)^2) -> 89.688064
...

Sheet CHUVAS
A1: ENTENDENDO O CLIMA
A2: Analisar o clima é fundamental para entender por quanto tempo seu sistema poderá ser utilizado de forma
A3: intensiva. Como a proposta desse treinamento é para que você aproveite o máximo possível o período
A4: do verão/chuvas, essa etapa vai direcionar todo o potencial do seu projeto. Quanto menos tempo disponível
A5: para intensificar, mais vocêterá que produzir, para garantir alta produção em curto espaço de tempo.
A7: Mês | B7: C° min | C7: C° Máx | D7: mm | F7: Resultado
A8: Jan | E8: > | F8: =IF(D8="","",IF(Q8=30,"Chuva",IF(Q8=0,"Seca",IF(Q8=20,"Chuva -1",IF(Q8=10,"Transição",0))))) | G8: =IF(OR(B8="",C8=""),"",IF(S8=1,"Verão",IF(S8=0,"Inverno",IF(S8=0.5,"Transição",IF(S8=0.75,"Transição",0))))) | H8: =IF(OR(F8="",G8=""),"",IF(AND(G8="Verão",F8="Chuva"),"Ok","Cuidado")) | Q8: =IF(D8="","",IF(D8>=150,30,IF(AND(D8>=120,D8<150),20,IF(AND(D8>=60,D8<120),10,0)))) | R8: =IF(OR(B8="",C8=""),"",AVERAGE(B8:C8)) | S8: =IF(R8="","",IF(AND(R8<=19,R8>=17),0.5,IF(R8<16,0,IF(AND(R8>19,R8<20),0.75,IF(R8>19,1,0))))) | T8: =IF(S8="","", S8*Q8)
A9: Fev | E9: > | F9: =IF(D9="","",IF(Q9=30,"Chuva",IF(Q9=0,"Seca",IF(Q9=20,"Chuva -1",IF(Q9=10,"Transição",0))))) | G9: =IF(OR(B9="",C9=""),"",IF(S9=1,"Verão",IF(S9=0,"Inverno",IF(S9=0.5,"Transição",IF(S9=0.75,"Transição",0))))) | H9: =IF(OR(F9="",G9=""),"",IF(AND(G9="Verão",F9="Chuva"),"Ok","Cuidado")) | Q9: =IF(D9="","",IF(D9>=150,30,IF(AND(D9>=120,D9<150),20,IF(AND(D9>=60,D9<120),10,0)))) | R9: =IF(OR(B9="",C9=""),"",AVERAGE(B9:C9)) | S9: =IF(R9="","",IF(AND(R9<=19,R9>=17),0.5,IF(R9<16,0,IF(AND(R9>19,R9<20),0.75,IF(R9>19,1,0))))) | T9: =IF(S9="","", S9*Q9)
A10: Mar | E10: > | F10: =IF(D10="","",IF(Q10=30,"Chuva",IF(Q10=0,"Seca",IF(Q10=20,"Chuva -1",IF(Q10=10,"Transição",0))))) | G10: =IF(OR(B10="",C10=""),"",IF(S10=1,"Verão",IF(S10=0,"Inverno",IF(S10=0.5,"Transição",IF(S10=0.75,"Transição",0))))) | H10: =IF(OR(F10="",G10=""),"",IF(AND(G10="Verão",F10="Chuva"),"Ok","Cuidado")) | Q10: =IF(D10="","",IF(D10>=150,30,IF(AND(D10>=120,D10<150),20,IF(AND(D10>=60,D10<120),10,0)))) | R10: =IF(OR(B10="",C10=""),"",AVERAGE(B10:C10)) | S10: =IF(R10="","",IF(AND(R10<=19,R10>=17),0.5,IF(R10<16,0,IF(AND(R10>19,R10<20),0.75,IF(R10>19,1,0))))) | T10: =IF(S10="","", S10*Q10)
A11: Abr | E11: > | F11: =IF(D11="","",IF(Q11=30,"Chuva",IF(Q11=0,"Seca",IF(Q11=20,"Chuva -1",IF(Q11=10,"Transição",0))))) | G11: =IF(OR(B11="",C11=""),"",IF(S11=1,"Verão",IF(S11=0,"Inverno",IF(S11=0.5,"Transição",IF(S11=0.75,"Transição",0))))) | H11: =IF(OR(F11="",G11=""),"",IF(AND(G11="Verão",F11="Chuva"),"Ok","Cuidado")) | Q11: =IF(D11="","",IF(D11>=150,30,IF(AND(D11>=120,D11<150),20,IF(AND(D11>=60,D11<120),10,0)))) | R11: =IF(OR(B11="",C11=""),"",AVERAGE(B11:C11)) | S11: =IF(R11="","",IF(AND(R11<=19,R11>=17),0.5,IF(R11<16,0,IF(AND(R11>19,R11<20),0.75,IF(R11>19,1,0))))) | T11: =IF(S11="","", S11*Q11)
A12: Mai | E12: > | F12: =IF(D12="","",IF(Q12=30,"Chuva",IF(Q12=0,"Seca",IF(Q12=20,"Chuva -1",IF(Q12=10,"Transição",0))))) | G12: =IF(OR(B12="",C12=""),"",IF(S12=1,"Verão",IF(S12=0,"Inverno",IF(S12=0.5,"Transição",IF(S12=0.75,"Transição",0))))) | H12: =IF(OR(F12="",G12=""),"",IF(AND(G12="Verão",F12="Chuva"),"Ok","Cuidado")) | Q12: =IF(D12="","",IF(D12>=150,30,IF(AND(D12>=120,D12<150),20,IF(AND(D12>=60,D12<120),10,0)))) | R12: =IF(OR(B12="",C12=""),"",AVERAGE(B12:C12)) | S12: =IF(R12="","",IF(AND(R12<=19,R12>=17),0.5,IF(R12<16,0,IF(AND(R12>19,R12<20),0.75,IF(R12>19,1,0))))) | T12: =IF(S12="","", S12*Q12)
A13: Jun | E13: > | F13: =IF(D13="","",IF(Q13=30,"Chuva",IF(Q13=0,"Seca",IF(Q13=20,"Chuva -1",IF(Q13=10,"Transição",0))))) | G13: =IF(OR(B13="",C13=""),"",IF(S13=1,"Verão",IF(S13=0,"Inverno",IF(S13=0.5,"Transição",IF(S13=0.75,"Transição",0))))) | H13: =IF(OR(F13="",G13=""),"",IF(AND(G13="Verão",F13="Chuva"),"Ok","Cuidado")) | Q13: =IF(D13="","",IF(D13>=150,30,IF(AND(D13>=120,D13<150),20,IF(AND(D13>=60,D13<120),10,0)))) | R13: =IF(OR(B13="",C13=""),"",AVERAGE(B13:C13)) | S13: =IF(R13="","",IF(AND(R13<=19,R13>=17),0.5,IF(R13<16,0,IF(AND(R13>19,R13<20),0.75,IF(R13>19,1,0))))) | T13: =IF(S13="","", S13*Q13)
A14: Jul | E14: > | F14: =IF(D14="","",IF(Q14=30,"Chuva",IF(Q14=0,"Seca",IF(Q14=20,"Chuva -1",IF(Q14=10,"Transição",0))))) | G14: =IF(OR(B14="",C14=""),"",IF(S14=1,"Verão",IF(S14=0,"Inverno",IF(S14=0.5,"Transição",IF(S14=0.75,"Transição",0))))) | H14: =IF(OR(F14="",G14=""),"",IF(AND(G14="Verão",F14="Chuva"),"Ok","Cuidado")) | Q14: =IF(D14="","",IF(D14>=150,30,IF(AND(D14>=120,D14<150),20,IF(AND(D14>=60,D14<120),10,0)))) | R14: =IF(OR(B14="",C14=""),"",AVERAGE(B14:C14)) | S14: =IF(R14="","",IF(AND(R14<=19,R14>=17),0.5,IF(R14<16,0,IF(AND(R14>19,R14<20),0.75,IF(R14>19,1,0))))) | T14: =IF(S14="","", S14*Q14)
A15: Ago | E15: > | F15: =IF(D15="","",IF(Q15=30,"Chuva",IF(Q15=0,"Seca",IF(Q15=20,"Chuva -1",IF(Q15=10,"Transição",0))))) | G15: =IF(OR(B15="",C15=""),"",IF(S15=1,"Verão",IF(S15=0,"Inverno",IF(S15=0.5,"Transição",IF(S15=0.75,"Transição",0))))) | H15: =IF(OR(F15="",G15=""),"",IF(AND(G15="Verão",F15="Chuva"),"Ok","Cuidado")) | Q15: =IF(D15="","",IF(D15>=150,30,IF(AND(D15>=120,D15<150),20,IF(AND(D15>=60,D15<120),10,0)))) | R15: =IF(OR(B15="",C15=""),"",AVERAGE(B15:C15)) | S15: =IF(R15="","",IF(AND(R15<=19,R15>=17),0.5,IF(R15<16,0,IF(AND(R15>19,R15<20),0.75,IF(R15>19,1,0))))) | T15: =IF(S15="","", S15*Q15)
A16: Set | E16: > | F16: =IF(D16="","",IF(Q16=30,"Chuva",IF(Q16=0,"Seca",IF(Q16=20,"Chuva -1",IF(Q16=10,"Transição",0))))) | G16: =IF(OR(B16="",C16=""),"",IF(S16=1,"Verão",IF(S16=0,"Inverno",IF(S16=0.5,"Transição",IF(S16=0.75,"Transição",0))))) | H16: =IF(OR(F16="",G16=""),"",IF(AND(G16="Verão",F16="Chuva"),"Ok","Cuidado")) | Q16: =IF(D16="","",IF(D16>=150,30,IF(AND(D16>=120,D16<150),20,IF(AND(D16>=60,D16<120),10,0)))) | R16: =IF(OR(B16="",C16=""),"",AVERAGE(B16:C16)) | S16: =IF(R16="","",IF(AND(R16<=19,R16>=17),0.5,IF(R16<16,0,IF(AND(R16>19,R16<20),0.75,IF(R16>19,1,0))))) | T16: =IF(S16="","", S16*Q16)
A17: Out | E17: > | F17: =IF(D17="","",IF(Q17=30,"Chuva",IF(Q17=0,"Seca",IF(Q17=20,"Chuva -1",IF(Q17=10,"Transição",0))))) | G17: =IF(OR(B17="",C17=""),"",IF(S17=1,"Verão",IF(S17=0,"Inverno",IF(S17=0.5,"Transição",IF(S17=0.75,"Transição",0))))) | H17: =IF(OR(F17="",G17=""),"",IF(AND(G17="Verão",F17="Chuva"),"Ok","Cuidado")) | Q17: =IF(D17="","",IF(D17>=150,30,IF(AND(D17>=120,D17<150),20,IF(AND(D17>=60,D17<120),10,0)))) | R17: =IF(OR(B17="",C17=""),"",AVERAGE(B17:C17)) | S17: =IF(R17="","",IF(AND(R17<=19,R17>=17),0.5,IF(R17<16,0,IF(AND(R17>19,R17<20),0.75,IF(R17>19,1,0))))) | T17: =IF(S17="","", S17*Q17)
A18: Nov | E18: > | F18: =IF(D18="","",IF(Q18=30,"Chuva",IF(Q18=0,"Seca",IF(Q18=20,"Chuva -1",IF(Q18=10,"Transição",0))))) | G18: =IF(OR(B18="",C18=""),"",IF(S18=1,"Verão",IF(S18=0,"Inverno",IF(S18=0.5,"Transição",IF(S18=0.75,"Transição",0))))) | H18: =IF(OR(F18="",G18=""),"",IF(AND(G18="Verão",F18="Chuva"),"Ok","Cuidado")) | Q18: =IF(D18="","",IF(D18>=150,30,IF(AND(D18>=120,D18<150),20,IF(AND(D18>=60,D18<120),10,0)))) | R18: =IF(OR(B18="",C18=""),"",AVERAGE(B18:C18)) | S18: =IF(R18="","",IF(AND(R18<=19,R18>=17),0.5,IF(R18<16,0,IF(AND(R18>19,R18<20),0.75,IF(R18>19,1,0))))) | T18: =IF(S18="","", S18*Q18)
A19: Dez | E19: > | F19: =IF(D19="","",IF(Q19=30,"Chuva",IF(Q19=0,"Seca",IF(Q19=20,"Chuva -1",IF(Q19=10,"Transição",0))))) | G19: =IF(OR(B19="",C19=""),"",IF(S19=1,"Verão",IF(S19=0,"Inverno",IF(S19=0.5,"Transição",IF(S19=0.75,"Transição",0))))) | H19: =IF(OR(F19="",G19=""),"",IF(AND(G19="Verão",F19="Chuva"),"Ok","Cuidado")) | Q19: =IF(D19="","",IF(D19>=150,30,IF(AND(D19>=120,D19<150),20,IF(AND(D19>=60,D19<120),10,0)))) | R19: =IF(OR(B19="",C19=""),"",AVERAGE(B19:C19)) | S19: =IF(R19="","",IF(AND(R19<=19,R19>=17),0.5,IF(R19<16,0,IF(AND(R19>19,R19<20),0.75,IF(R19>19,1,0))))) | T19: =IF(S19="","", S19*Q19)
A20: Total | B20: =IFERROR(AVERAGE(B8:B19),"") | C20: =IFERROR(AVERAGE(C8:C19),"") | D20: =SUM(D8:D19) -> 0
A22: Para propriedades que possuem inverno mais rigoroso, a planilha não está considerando o período
A23: de inverno como um período disponível para acúmulo de forragem. Caso você faça sobresemeadura
A24: de plantas de inverno, seu período de uso poderá ser maior. No entanto, o foco ainda é no verão.
A39: Dias disponíveis para intensificação: | E39: ="de "&COUNTIFS(H8:H19,"Ok")*30&" a "&SUM(T8:T19)&" dias disponíveis." -> de 0 a 0 dias disponíveis.
A40: Lotação aproximada LIMITE: | E40: ="de "&COUNTIFS(H8:H19,"Ok")&" a "&ROUND(SUM(T8:T19)/30,0)&" U.A/ha na época das chuvas." -> de 0 a 0 U.A/ha na época das chuvas.

Sheet Cadastro pastos
A1: Cadastro de áreas | F1: Resumo das áreas | J1: Informações mensais
A2: Id. | B2: Área (ha) | C2: Nota | D2: Aproveita | F2: Id | G2: Área | H2: % do total | J2: Ordem | K2: 1° Mês | L2: 2° Mês | M2: 3° Mês | N2: 4° Mês | O2: 5° Mês | P2: 6° Mês | Q2: 7° Mês | R2: 8° Mês | S2: 9° Mês | T2: 10° Mês | U2: 11° Mês | V2: 12° Mês
A3: 1 | B3: 10 | C3: 1 | D3: =IF(C3="","",IF(C3=1,B3,IF(C3=2,B3*0.8,IF(C3=3,B3*0.5,B3*0.2)))) -> 10 | F3: 1 | G3: =SUMIFS($B$3:$B$60,$C$3:$C$60,F3) -> 60 | H3: =IFERROR(G3/SUM($G$3:$G$6),"") -> 0.5 | J3: Mês | K3: Julho | L3: Agosto | M3: Setembro | N3: Outubro | O3: Novembro | P3: Dezembro | Q3: Janeiro | R3: Fevereiro | S3: Março | T3: Abril | U3: Maio | V3: Junho
A4: 2 | B4: 20 | C4: 1 | D4: =IF(C4="","",IF(C4=1,B4,IF(C4=2,B4*0.8,IF(C4=3,B4*0.5,B4*0.2)))) -> 20 | F4: 2 | G4: =SUMIFS($B$3:$B$60,$C$3:$C$60,F4) -> 35 | H4: =IFERROR(G4/SUM($G$3:$G$6),"") -> 0.29166667 | J4: Clima | K4: Seca | L4: Seca | M4: Seca | N4: Chuva | O4: Chuva | P4: Chuva | Q4: Chuva | R4: Chuva | S4: Chuva | T4: Seca | U4: Seca | V4: Seca
A5: 3 | B5: 30 | C5: 1 | D5: =IF(C5="","",IF(C5=1,B5,IF(C5=2,B5*0.8,IF(C5=3,B5*0.5,B5*0.2)))) -> 30 | F5: 3 | G5: =SUMIFS($B$3:$B$60,$C$3:$C$60,F5) -> 25 | H5: =IFERROR(G5/SUM($G$3:$G$6),"") -> 0.20833333
A6: 4 | B6: 15 | C6: 2 | D6: =IF(C6="","",IF(C6=1,B6,IF(C6=2,B6*0.8,IF(C6=3,B6*0.5,B6*0.2)))) -> 12 | F6: 4 | G6: =SUMIFS($B$3:$B$60,$C$3:$C$60,F6) -> 0 | H6: =IFERROR(G6/SUM($G$3:$G$6),"") -> 0
A7: 5 | B7: 20 | C7: 2 | D7: =IF(C7="","",IF(C7=1,B7,IF(C7=2,B7*0.8,IF(C7=3,B7*0.5,B7*0.2)))) -> 16
A8: 6 | B8: 25 | C8: 3 | D8: =IF(C8="","",IF(C8=1,B8,IF(C8=2,B8*0.8,IF(C8=3,B8*0.5,B8*0.2)))) -> 12.5
D9: =IF(C9="","",IF(C9=1,B9,IF(C9=2,B9*0.8,IF(C9=3,B9*0.5,B9*0.2))))
D10: =IF(C10="","",IF(C10=1,B10,IF(C10=2,B10*0.8,IF(C10=3,B10*0.5,B10*0.2))))
D11: =IF(C11="","",IF(C11=1,B11,IF(C11=2,B11*0.8,IF(C11=3,B11*0.5,B11*0.2))))
D12: =IF(C12="","",IF(C12=1,B12,IF(C12=2,B12*0.8,IF(C12=3,B12*0.5,B12*0.2))))
D13: =IF(C13="","",IF(C13=1,B13,IF(C13=2,B13*0.8,IF(C13=3,B13*0.5,B13*0.2))))
D14: =IF(C14="","",IF(C14=1,B14,IF(C14=2,B14*0.8,IF(C14=3,B14*0.5,B14*0.2))))
D15: =IF(C15="","",IF(C15=1,B15,IF(C15=2,B15*0.8,IF(C15=3,B15*0.5,B15*0.2))))
D16: =IF(C16="","",IF(C16=1,B16,IF(C16=2,B16*0.8,IF(C16=3,B16*0.5,B16*0.2))))
D17: =IF(C17="","",IF(C17=1,B17,IF(C17=2,B17*0.8,IF(C17=3,B17*0.5,B17*0.2))))
D18: =IF(C18="","",IF(C18=1,B18,IF(C18=2,B18*0.8,IF(C18=3,B18*0.5,B18*0.2))))
D19: =IF(C19="","",IF(C19=1,B19,IF(C19=2,B19*0.8,IF(C19=3,B19*0.5,B19*0.2))))
D20: =IF(C20="","",IF(C20=1,B20,IF(C20=2,B20*0.8,IF(C20=3,B20*0.5,B20*0.2))))
... D60: =IF(C60="","",IF(C60=1,B60,IF(C60=2,B60*0.8,IF(C60=3,B60*0.5,B60*0.2))))
A61: Área total | B61: =SUM(B3:B60) -> 120 | C61: Área aprov. | D61: =SUM(D3:D60) -> 100.5

Sheet Planejamento de lotação
B1: PLANEJAMENTO DE LOTAÇÃO MENSAL
A3: Descrição | B3: ='Cadastro pastos'!K3 -> Julho | H3: ='Cadastro pastos'!L3 -> Agosto | N3: ='Cadastro pastos'!M3 -> Setembro | T3: ='Cadastro pastos'!N3 -> Outubro | Z3: ='Cadastro pastos'!O3 -> Novembro | AF3: ='Cadastro pastos'!P3 -> Dezembro | AL3: ='Cadastro pastos'!Q3 -> Janeiro | AR3: ='Cadastro pastos'!R3 -> Fevereiro | AX3: ='Cadastro pastos'!S3 -> Março | BD3: ='Cadastro pastos'!T3 -> Abril | BJ3: ='Cadastro pastos'!U3 -> Maio | BP3: ='Cadastro pastos'!V3 -> Junho
A4: Categoria | B4: Qnt. | C4: Peso | D4: GMD | E4: Peso final | F4: U.A inicial | G4: U.A Final | H4: Qnt. | I4: Peso | J4: GMD | K4: Peso final | L4: U.A inicial | M4: U.A Final | N4: Qnt. | O4: Peso | P4: GMD | Q4: Peso final | R4: U.A inicial | S4: U.A Final | T4: Qnt. | U4: Peso | V4: GMD | W4: Peso final | X4: U.A inicial | Y4: U.A Final | Z4: Qnt. | AA4: Peso | AB4: GMD | AC4: Peso final | AD4: U.A inicial | AE4: U.A Final | AF4: Qnt. | AG4: Peso | AH4: GMD | AI4: Peso final | AJ4: U.A inicial | AK4: U.A Final | AL4: Qnt. | AM4: Peso | AN4: GMD | AO4: Peso final | AP4: U.A inicial | AQ4: U.A Final | AR4: Qnt. | AS4: Peso | AT4: GMD | AU4: Peso final | AV4: U.A inicial | AW4: U.A Final | AX4: Qnt. | AY4: Peso | AZ4: GMD | BA4: Peso final | BB4: U.A inicial | BC4: U.A Final | BD4: Qnt. | BE4: Peso | BF4: GMD | BG4: Peso final | BH4: U.A inicial | BI4: U.A Final | BJ4: Qnt. | BK4: Peso | BL4: GMD | BM4: Peso final | BN4: U.A inicial | BO4: U.A Final | BP4: Qnt. | BQ4: Peso | BR4: GMD | BS4: Peso final | BT4: U.A inicial | BU4: U.A Final
A5: Vaca | B5: 40 | C5: 450 | D5: 0.4 | E5: =(D5*30)+C5 -> 462 | F5: =C5*B5/450 -> 40 | G5: =E5*B5/450 -> 41.066667 | H5: =IF($A5="","",B5) -> 40 | I5: =IF(H5=0,"",IF($A5="","",E5)) -> 462 | J5: =IF($A5="","",D5) -> 0.4 | K5: =IF($A5="","",(J5*30)+I5) -> 474 | L5: =IF($A5="","",I5*H5/450) -> 41.066667 | M5: =IF($A5="","",K5*H5/450) -> 42.133333 | N5: =IF($A5="","",H5) -> 40 | O5: =IF(N5=0,"",IF($A5="","",K5)) -> 474 | P5: =IF($A5="","",J5) -> 0.4 | Q5: =IF($A5="","",(P5*30)+O5) -> 486 | R5: =IF($A5="","",O5*N5/450) -> 42.133333 | S5: =IF($A5="","",Q5*N5/450) -> 43.2 | T5: =IF($A5="","",N5) -> 40 | U5: =IF(T5=0,"",IF($A5="","",Q5)) -> 486 | V5: =IF($A5="","",P5) -> 0.4 | W5: =IF($A5="","",(V5*30)+U5) -> 498 | X5: =IF($A5="","",U5*T5/450) -> 43.2 | Y5: =IF($A5="","",W5*T5/450) -> 44.266667 | Z5: =IF($A5="","",T5) -> 40 | AA5: =IF(Z5=0,"",IF($A5="","",W5)) -> 498 | AB5: =IF($A5="","",V5) -> 0.4 | AC5: =IF($A5="","",(AB5*30)+AA5) -> 510 | AD5: =IF($A5="","",AA5*Z5/450) -> 44.266667 | AE5: =IF($A5="","",AC5*Z5/450) -> 45.333333 | AF5: =IF($A5="","",Z5) -> 40 | AG5: =IF(AF5=0,"",IF($A5="","",AC5)) -> 510 | AH5: =IF($A5="","",AB5) -> 0.4 | AI5: =IF($A5="","",(AH5*30)+AG5) -> 522 | AJ5: =IF($A5="","",AG5*AF5/450) -> 45.333333 | AK5: =IF($A5="","",AI5*AF5/450) -> 46.4 | AL5: =IF($A5="","",AF5) -> 40 | AM5: =IF(AL5=0,"",IF($A5="","",AI5)) -> 522 | AN5: =IF($A5="","",AH5) -> 0.4 | AO5: =IF($A5="","",(AN5*30)+AM5) -> 534 | AP5: =IF($A5="","",AM5*AL5/450) -> 46.4 | AQ5: =IF($A5="","",AO5*AL5/450) -> 47.466667 | AR5: =IF($A5="","",AL5) -> 40 | AS5: =IF(AR5=0,"",IF($A5="","",AO5)) -> 534 | AT5: =IF($A5="","",AN5) -> 0.4 | AU5: =IF($A5="","",(AT5*30)+AS5) -> 546 | AV5: =IF($A5="","",AS5*AR5/450) -> 47.466667 | AW5: =IF($A5="","",AU5*AR5/450) -> 48.533333 | AX5: =IF($A5="","",AR5) -> 40 | AY5: =IF(AX5=0,"",IF($A5="","",AU5)) -> 546 | AZ5: =IF($A5="","",AT5) -> 0.4 | BA5: =IF($A5="","",(AZ5*30)+AY5) -> 558 | BB5: =IF($A5="","",AY5*AX5/450) -> 48.533333 | BC5: =IF($A5="","",BA5*AX5/450) -> 49.6 | BD5: =IF($A5="","",AX5) -> 40 | BE5: =IF(BD5=0,"",IF($A5="","",BA5)) -> 558 | BF5: =IF($A5="","",AZ5) -> 0.4 | BG5: =IF($A5="","",(BF5*30)+BE5) -> 570 | BH5: =IF($A5="","",BE5*BD5/450) -> 49.6 | BI5: =IF($A5="","",BG5*BD5/450) -> 50.666667 | BJ5: =IF($A5="","",BD5) -> 40 | BK5: =IF(BJ5=0,"",IF($A5="","",BG5)) -> 570 | BL5: =IF($A5="","",BF5) -> 0.4 | BM5: =IF($A5="","",(BL5*30)+BK5) -> 582 | BN5: =IF($A5="","",BK5*BJ5/450) -> 50.666667 | BO5: =IF($A5="","",BM5*BJ5/450) -> 51.733333 | BP5: =IF($A5="","",BJ5) -> 40 | BQ5: =IF(BP5=0,"",IF($A5="","",BM5)) -> 582 | BR5: =IF($A5="","",BL5) -> 0.4 | BS5: =IF($A5="","",(BR5*30)+BQ5) -> 594 | BT5: =IF($A5="","",BQ5*BP5/450) -> 51.733333 | BU5: =IF($A5="","",BS5*BP5/450) -> 52.8
E6: =(D6*30)+C6 -> 0 | F6: =C6*B6/450 -> 0 | G6: =E6*B6/450 -> 0 | H6: =IF($A6="","",B6) | I6: =IF(H6=0,"",IF($A6="","",E6)) | J6: =IF($A6="","",D6) | K6: =IF($A6="","",(J6*30)+I6) | L6: =IF($A6="","",I6*H6/450) | M6: =IF($A6="","",K6*H6/450) | N6: =IF($A6="","",H6) | O6: =IF(N6=0,"",IF($A6="","",K6)) | P6: =IF($A6="","",J6) | Q6: =IF($A6="","",(P6*30)+O6) | R6: =IF($A6="","",O6*N6/450) | S6: =IF($A6="","",Q6*N6/450) | T6: =IF($A6="","",N6) | U6: =IF(T6=0,"",IF($A6="","",Q6)) | V6: =IF($A6="","",P6) | W6: =IF($A6="","",(V6*30)+U6) | X6: =IF($A6="","",U6*T6/450) | Y6: =IF($A6="","",W6*T6/450) | Z6: =IF($A6="","",T6) | AA6: =IF(Z6=0,"",IF($A6="","",W6)) | AB6: =IF($A6="","",V6) | AC6: =IF($A6="","",(AB6*30)+AA6) | AD6: =IF($A6="","",AA6*Z6/450) | AE6: =IF($A6="","",AC6*Z6/450) | AF6: =IF($A6="","",Z6) | AG6: =IF(AF6=0,"",IF($A6="","",AC6)) | AH6: =IF($A6="","",AB6) | AI6: =IF($A6="","",(AH6*30)+AG6) | AJ6: =IF($A6="","",AG6*AF6/450) | AK6: =IF($A6="","",AI6*AF6/450) | AL6: =IF($A6="","",AF6) | AM6: =IF(AL6=0,"",IF($A6="","",AI6)) | AN6: =IF($A6="","",AH6) | AO6: =IF($A6="","",(AN6*30)+AM6) | AP6: =IF($A6="","",AM6*AL6/450) | AQ6: =IF($A6="","",AO6*AL6/450) | AR6: =IF($A6="","",AL6) | AS6: =IF(AR6=0,"",IF($A6="","",AO6)) | AT6: =IF($A6="","",AN6) | AU6: =IF($A6="","",(AT6*30)+AS6) | AV6: =IF($A6="","",AS6*AR6/450) | AW6: =IF($A6="","",AU6*AR6/450) | AX6: =IF($A6="","",AR6) | AY6: =IF(AX6=0,"",IF($A6="","",AU6)) | AZ6: =IF($A6="","",AT6) | BA6: =IF($A6="","",(AZ6*30)+AY6) | BB6: =IF($A6="","",AY6*AX6/450) | BC6: =IF($A6="","",BA6*AX6/450) | BD6: =IF($A6="","",AX6) | BE6: =IF(BD6=0,"",IF($A6="","",BA6)) | BF6: =IF($A6="","",AZ6) | BG6: =IF($A6="","",(BF6*30)+BE6) | BH6: =IF($A6="","",BE6*BD6/450) | BI6: =IF($A6="","",BG6*BD6/450) | BJ6: =IF($A6="","",BD6) | BK6: =IF(BJ6=0,"",IF($A6="","",BG6)) | BL6: =IF($A6="","",BF6) | BM6: =IF($A6="","",(BL6*30)+BK6) | BN6: =IF($A6="","",BK6*BJ6/450) | BO6: =IF($A6="","",BM6*BJ6/450) | BP6: =IF($A6="","",BJ6) | BQ6: =IF(BP6=0,"",IF($A6="","",BM6)) | BR6: =IF($A6="","",BL6) | BS6: =IF($A6="","",(BR6*30)+BQ6) | BT6: =IF($A6="","",BQ6*BP6/450) | BU6: =IF($A6="","",BS6*BP6/450)
E7: =(D7*30)+C7 -> 0 | F7: =C7*B7/450 -> 0 | G7: =E7*B7/450 -> 0 | H7: =IF($A7="","",B7) | I7: =IF(H7=0,"",IF($A7="","",E7)) | J7: =IF($A7="","",D7) | K7: =IF($A7="","",(J7*30)+I7) | L7: =IF($A7="","",I7*H7/450) | M7: =IF($A7="","",K7*H7/450) | N7: =IF($A7="","",H7) | O7: =IF(N7=0,"",IF($A7="","",K7)) | P7: =IF($A7="","",J7) | Q7: =IF($A7="","",(P7*30)+O7) | R7: =IF($A7="","",O7*N7/450) | S7: =IF($A7="","",Q7*N7/450) | T7: =IF($A7="","",N7) | U7: =IF(T7=0,"",IF($A7="","",Q7)) | V7: =IF($A7="","",P7) | W7: =IF($A7="","",(V7*30)+U7) | X7: =IF($A7="","",U7*T7/450) | Y7: =IF($A7="","",W7*T7/450) | Z7: =IF($A7="","",T7) | AA7: =IF(Z7=0,"",IF($A7="","",W7)) | AB7: =IF($A7="","",V7) | AC7: =IF($A7="","",(AB7*30)+AA7) | AD7: =IF($A7="","",AA7*Z7/450) | AE7: =IF($A7="","",AC7*Z7/450) | AF7: =IF($A7="","",Z7) | AG7: =IF(AF7=0,"",IF($A7="","",AC7)) | AH7: =IF($A7="","",AB7) | AI7: =IF($A7="","",(AH7*30)+AG7) | AJ7: =IF($A7="","",AG7*AF7/450) | AK7: =IF($A7="","",AI7*AF7/450) | AL7: =IF($A7="","",AF7) | AM7: =IF(AL7=0,"",IF($A7="","",AI7)) | AN7: =IF($A7="","",AH7) | AO7: =IF($A7="","",(AN7*30)+AM7) | AP7: =IF($A7="","",AM7*AL7/450) | AQ7: =IF($A7="","",AO7*AL7/450) | AR7: =IF($A7="","",AL7) | AS7: =IF(AR7=0,"",IF($A7="","",AO7)) | AT7: =IF($A7="","",AN7) | AU7: =IF($A7="","",(AT7*30)+AS7) | AV7: =IF($A7="","",AS7*AR7/450) | AW7: =IF($A7="","",AU7*AR7/450) | AX7: =IF($A7="","",AR7) | AY7: =IF(AX7=0,"",IF($A7="","",AU7)) | AZ7: =IF($A7="","",AT7) | BA7: =IF($A7="","",(AZ7*30)+AY7) | BB7: =IF($A7="","",AY7*AX7/450) | BC7: =IF($A7="","",BA7*AX7/450) | BD7: =IF($A7="","",AX7) | BE7: =IF(BD7=0,"",IF($A7="","",BA7)) | BF7: =IF($A7="","",AZ7) | BG7: =IF($A7="","",(BF7*30)+BE7) | BH7: =IF($A7="","",BE7*BD7/450) | BI7: =IF($A7="","",BG7*BD7/450) | BJ7: =IF($A7="","",BD7) | BK7: =IF(BJ7=0,"",IF($A7="","",BG7)) | BL7: =IF($A7="","",BF7) | BM7: =IF($A7="","",(BL7*30)+BK7) | BN7: =IF($A7="","",BK7*BJ7/450) | BO7: =IF($A7="","",BM7*BJ7/450) | BP7: =IF($A7="","",BJ7) | BQ7: =IF(BP7=0,"",IF($A7="","",BM7)) | BR7: =IF($A7="","",BL7) | BS7: =IF($A7="","",(BR7*30)+BQ7) | BT7: =IF($A7="","",BQ7*BP7/450) | BU7: =IF($A7="","",BS7*BP7/450)
E8: =(D8*30)+C8 -> 0 | F8: =C8*B8/450 -> 0 | G8: =E8*B8/450 -> 0 | H8: =IF($A8="","",B8) | I8: =IF(H8=0,"",IF($A8="","",E8)) | J8: =IF($A8="","",D8) | K8: =IF($A8="","",(J8*30)+I8) | L8: =IF($A8="","",I8*H8/450) | M8: =IF($A8="","",K8*H8/450) | N8: =IF($A8="","",H8) | O8: =IF(N8=0,"",IF($A8="","",K8)) | P8: =IF($A8="","",J8) | Q8: =IF($A8="","",(P8*30)+O8) | R8: =IF($A8="","",O8*N8/450) | S8: =IF($A8="","",Q8*N8/450) | T8: =IF($A8="","",N8) | U8: =IF(T8=0,"",IF($A8="","",Q8)) | V8: =IF($A8="","",P8) | W8: =IF($A8="","",(V8*30)+U8) | X8: =IF($A8="","",U8*T8/450) | Y8: =IF($A8="","",W8*T8/450) | Z8: =IF($A8="","",T8) | AA8: =IF(Z8=0,"",IF($A8="","",W8)) | AB8: =IF($A8="","",V8) | AC8: =IF($A8="","",(AB8*30)+AA8) | AD8: =IF($A8="","",AA8*Z8/450) | AE8: =IF($A8="","",AC8*Z8/450) | AF8: =IF($A8="","",Z8) | AG8: =IF(AF8=0,"",IF($A8="","",AC8)) | AH8: =IF($A8="","",AB8) | AI8: =IF($A8="","",(AH8*30)+AG8) | AJ8: =IF($A8="","",AG8*AF8/450) | AK8: =IF($A8="","",AI8*AF8/450) | AL8: =IF($A8="","",AF8) | AM8: =IF(AL8=0,"",IF($A8="","",AI8)) | AN8: =IF($A8="","",AH8) | AO8: =IF($A8="","",(AN8*30)+AM8) | AP8: =IF($A8="","",AM8*AL8/450) | AQ8: =IF($A8="","",AO8*AL8/450) | AR8: =IF($A8="","",AL8) | AS8: =IF(AR8=0,"",IF($A8="","",AO8)) | AT8: =IF($A8="","",AN8) | AU8: =IF($A8="","",(AT8*30)+AS8) | AV8: =IF($A8="","",AS8*AR8/450) | AW8: =IF($A8="","",AU8*AR8/450) | AX8: =IF($A8="","",AR8) | AY8: =IF(AX8=0,"",IF($A8="","",AU8)) | AZ8: =IF($A8="","",AT8) | BA8: =IF($A8="","",(AZ8*30)+AY8) | BB8: =IF($A8="","",AY8*AX8/450) | BC8: =IF($A8="","",BA8*AX8/450) | BD8: =IF($A8="","",AX8) | BE8: =IF(BD8=0,"",IF($A8="","",BA8)) | BF8: =IF($A8="","",AZ8) | BG8: =IF($A8="","",(BF8*30)+BE8) | BH8: =IF($A8="","",BE8*BD8/450) | BI8: =IF($A8="","",BG8*BD8/450) | BJ8: =IF($A8="","",BD8) | BK8: =IF(BJ8=0,"",IF($A8="","",BG8)) | BL8: =IF($A8="","",BF8) | BM8: =IF($A8="","",(BL8*30)+BK8) | BN8: =IF($A8="","",BK8*BJ8/450) | BO8: =IF($A8="","",BM8*BJ8/450) | BP8: =IF($A8="","",BJ8) | BQ8: =IF(BP8=0,"",IF($A8="","",BM8)) | BR8: =IF($A8="","",BL8) | BS8: =IF($A8="","",(BR8*30)+BQ8) | BT8: =IF($A8="","",BQ8*BP8/450) | BU8: =IF($A8="","",BS8*BP8/450)
E9: =(D9*30)+C9 -> 0 | F9: =C9*B9/450 -> 0 | G9: =E9*B9/450 -> 0 | H9: =IF($A9="","",B9) | I9: =IF(H9=0,"",IF($A9="","",E9)) | J9: =IF($A9="","",D9) | K9: =IF($A9="","",(J9*30)+I9) | L9: =IF($A9="","",I9*H9/450) | M9: =IF($A9="","",K9*H9/450) | N9: =IF($A9="","",H9) | O9: =IF(N9=0,"",IF($A9="","",K9)) | P9: =IF($A9="","",J9) | Q9: =IF($A9="","",(P9*30)+O9) | R9: =IF($A9="","",O9*N9/450) | S9: =IF($A9="","",Q9*N9/450) | T9: =IF($A9="","",N9) | U9: =IF(T9=0,"",IF($A9="","",Q9)) | V9: =IF($A9="","",P9) | W9: =IF($A9="","",(V9*30)+U9) | X9: =IF($A9="","",U9*T9/450) | Y9: =IF($A9="","",W9*T9/450) | Z9: =IF($A9="","",T9) | AA9: =IF(Z9=0,"",IF($A9="","",W9)) | AB9: =IF($A9="","",V9) | AC9: =IF($A9="","",(AB9*30)+AA9) | AD9: =IF($A9="","",AA9*Z9/450) | AE9: =IF($A9="","",AC9*Z9/450) | AF9: =IF($A9="","",Z9) | AG9: =IF(AF9=0,"",IF($A9="","",AC9)) | AH9: =IF($A9="","",AB9) | AI9: =IF($A9="","",(AH9*30)+AG9) | AJ9: =IF($A9="","",AG9*AF9/450) | AK9: =IF($A9="","",AI9*AF9/450) | AL9: =IF($A9="","",AF9) | AM9: =IF(AL9=0,"",IF($A9="","",AI9)) | AN9: =IF($A9="","",AH9) | AO9: =IF($A9="","",(AN9*30)+AM9) | AP9: =IF($A9="","",AM9*AL9/450) | AQ9: =IF($A9="","",AO9*AL9/450) | AR9: =IF($A9="","",AL9) | AS9: =IF(AR9=0,"",IF($A9="","",AO9)) | AT9: =IF($A9="","",AN9) | AU9: =IF($A9="","",(AT9*30)+AS9) | AV9: =IF($A9="","",AS9*AR9/450) | AW9: =IF($A9="","",AU9*AR9/450) | AX9: =IF($A9="","",AR9) | AY9: =IF(AX9=0,"",IF($A9="","",AU9)) | AZ9: =IF($A9="","",AT9) | BA9: =IF($A9="","",(AZ9*30)+AY9) | BB9: =IF($A9="","",AY9*AX9/450) | BC9: =IF($A9="","",BA9*AX9/450) | BD9: =IF($A9="","",AX9) | BE9: =IF(BD9=0,"",IF($A9="","",BA9)) | BF9: =IF($A9="","",AZ9) | BG9: =IF($A9="","",(BF9*30)+BE9) | BH9: =IF($A9="","",BE9*BD9/450) | BI9: =IF($A9="","",BG9*BD9/450) | BJ9: =IF($A9="","",BD9) | BK9: =IF(BJ9=0,"",IF($A9="","",BG9)) | BL9: =IF($A9="","",BF9) | BM9: =IF($A9="","",(BL9*30)+BK9) | BN9: =IF($A9="","",BK9*BJ9/450) | BO9: =IF($A9="","",BM9*BJ9/450) | BP9: =IF($A9="","",BJ9) | BQ9: =IF(BP9=0,"",IF($A9="","",BM9)) | BR9: =IF($A9="","",BL9) | BS9: =IF($A9="","",(BR9*30)+BQ9) | BT9: =IF($A9="","",BQ9*BP9/450) | BU9: =IF($A9="","",BS9*BP9/450)
E10: =(D10*30)+C10 -> 0 | F10: =C10*B10/450 -> 0 | G10: =E10*B10/450 -> 0 | H10: =IF($A10="","",B10) | I10: =IF(H10=0,"",IF($A10="","",E10)) | J10: =IF($A10="","",D10) | K10: =IF($A10="","",(J10*30)+I10) | L10: =IF($A10="","",I10*H10/450) | M10: =IF($A10="","",K10*H10/450) | N10: =IF($A10="","",H10) | O10: =IF(N10=0,"",IF($A10="","",K10)) | P10: =IF($A10="","",J10) | Q10: =IF($A10="","",(P10*30)+O10) | R10: =IF($A10="","",O10*N10/450) | S10: =IF($A10="","",Q10*N10/450) | T10: =IF($A10="","",N10) | U10: =IF(T10=0,"",IF($A10="","",Q10)) | V10: =IF($A10="","",P10) | W10: =IF($A10="","",(V10*30)+U10) | X10: =IF($A10="","",U10*T10/450) | Y10: =IF($A10="","",W10*T10/450) | Z10: =IF($A10="","",T10) | AA10: =IF(Z10=0,"",IF($A10="","",W10)) | AB10: =IF($A10="","",V10) | AC10: =IF($A10="","",(AB10*30)+AA10) | AD10: =IF($A10="","",AA10*Z10/450) | AE10: =IF($A10="","",AC10*Z10/450) | AF10: =IF($A10="","",Z10) | AG10: =IF(AF10=0,"",IF($A10="","",AC10)) | AH10: =IF($A10="","",AB10) | AI10: =IF($A10="","",(AH10*30)+AG10) | AJ10: =IF($A10="","",AG10*AF10/450) | AK10: =IF($A10="","",AI10*AF10/450) | AL10: =IF($A10="","",AF10) | AM10: =IF(AL10=0,"",IF($A10="","",AI10)) | AN10: =IF($A10="","",AH10) | AO10: =IF($A10="","",(AN10*30)+AM10) | AP10: =IF($A10="","",AM10*AL10/450) | AQ10: =IF($A10="","",AO10*AL10/450) | AR10: =IF($A10="","",AL10) | AS10: =IF(AR10=0,"",IF($A10="","",AO10)) | AT10: =IF($A10="","",AN10) | AU10: =IF($A10="","",(AT10*30)+AS10) | AV10: =IF($A10="","",AS10*AR10/450) | AW10: =IF($A10="","",AU10*AR10/450) | AX10: =IF($A10="","",AR10) | AY10: =IF(AX10=0,"",IF($A10="","",AU10)) | AZ10: =IF($A10="","",AT10) | BA10: =IF($A10="","",(AZ10*30)+AY10) | BB10: =IF($A10="","",AY10*AX10/450) | BC10: =IF($A10="","",BA10*AX10/450) | BD10: =IF($A10="","",AX10) | BE10: =IF(BD10=0,"",IF($A10="","",BA10)) | BF10: =IF($A10="","",AZ10) | BG10: =IF($A10="","",(BF10*30)+BE10) | BH10: =IF($A10="","",BE10*BD10/450) | BI10: =IF($A10="","",BG10*BD10/450) | BJ10: =IF($A10="","",BD10) | BK10: =IF(BJ10=0,"",IF($A10="","",BG10)) | BL10: =IF($A10="","",BF10) | BM10: =IF($A10="","",(BL10*30)+BK10) | BN10: =IF($A10="","",BK10*BJ10/450) | BO10: =IF($A10="","",BM10*BJ10/450) | BP10: =IF($A10="","",BJ10) | BQ10: =IF(BP10=0,"",IF($A10="","",BM10)) | BR10: =IF($A10="","",BL10) | BS10: =IF($A10="","",(BR10*30)+BQ10) | BT10: =IF($A10="","",BQ10*BP10/450) | BU10: =IF($A10="","",BS10*BP10/450)
E11: =(D11*30)+C11 -> 0 | F11: =C11*B11/450 -> 0 | G11: =E11*B11/450 -> 0 | H11: =IF($A11="","",B11) | I11: =IF(H11=0,"",IF($A11="","",E11)) | J11: =IF($A11="","",D11) | K11: =IF($A11="","",(J11*30)+I11) | L11: =IF($A11="","",I11*H11/450) | M11: =IF($A11="","",K11*H11/450) | N11: =IF($A11="","",H11) | O11: =IF(N11=0,"",IF($A11="","",K11)) | P11: =IF($A11="","",J11) | Q11: =IF($A11="","",(P11*30)+O11) | R11: =IF($A11="","",O11*N11/450) | S11: =IF($A11="","",Q11*N11/450) | T11: =IF($A11="","",N11) | U11: =IF(T11=0,"",IF($A11="","",Q11)) | V11: =IF($A11="","",P11) | W11: =IF($A11="","",(V11*30)+U11) | X11: =IF($A11="","",U11*T11/450) | Y11: =IF($A11="","",W11*T11/450) | Z11: =IF($A11="","",T11) | AA11: =IF(Z11=0,"",IF($A11="","",W11)) | AB11: =IF($A11="","",V11) | AC11: =IF($A11="","",(AB11*30)+AA11) | AD11: =IF($A11="","",AA11*Z11/450) | AE11: =IF($A11="","",AC11*Z11/450) | AF11: =IF($A11="","",Z11) | AG11: =IF(AF11=0,"",IF($A11="","",AC11)) | AH11: =IF($A11="","",AB11) | AI11: =IF($A11="","",(AH11*30)+AG11) | AJ11: =IF($A11="","",AG11*AF11/450) | AK11: =IF($A11="","",AI11*AF11/450) | AL11: =IF($A11="","",AF11) | AM11: =IF(AL11=0,"",IF($A11="","",AI11)) | AN11: =IF($A11="","",AH11) | AO11: =IF($A11="","",(AN11*30)+AM11) | AP11: =IF($A11="","",AM11*AL11/450) | AQ11: =IF($A11="","",AO11*AL11/450) | AR11: =IF($A11="","",AL11) | AS11: =IF(AR11=0,"",IF($A11="","",AO11)) | AT11: =IF($A11="","",AN11) | AU11: =IF($A11="","",(AT11*30)+AS11) | AV11: =IF($A11="","",AS11*AR11/450) | AW11: =IF($A11="","",AU11*AR11/450) | AX11: =IF($A11="","",AR11) | AY11: =IF(AX11=0,"",IF($A11="","",AU11)) | AZ11: =IF($A11="","",AT11) | BA11: =IF($A11="","",(AZ11*30)+AY11) | BB11: =IF($A11="","",AY11*AX11/450) | BC11: =IF($A11="","",BA11*AX11/450) | BD11: =IF($A11="","",AX11) | BE11: =IF(BD11=0,"",IF($A11="","",BA11)) | BF11: =IF($A11="","",AZ11) | BG11: =IF($A11="","",(BF11*30)+BE11) | BH11: =IF($A11="","",BE11*BD11/450) | BI11: =IF($A11="","",BG11*BD11/450) | BJ11: =IF($A11="","",BD11) | BK11: =IF(BJ11=0,"",IF($A11="","",BG11)) | BL11: =IF($A11="","",BF11) | BM11: =IF($A11="","",(BL11*30)+BK11) | BN11: =IF($A11="","",BK11*BJ11/450) | BO11: =IF($A11="","",BM11*BJ11/450) | BP11: =IF($A11="","",BJ11) | BQ11: =IF(BP11=0,"",IF($A11="","",BM11)) | BR11: =IF($A11="","",BL11) | BS11: =IF($A11="","",(BR11*30)+BQ11) | BT11: =IF($A11="","",BQ11*BP11/450) | BU11: =IF($A11="","",BS11*BP11/450)
E12: =(D12*30)+C12 -> 0 | F12: =C12*B12/450 -> 0 | G12: =E12*B12/450 -> 0 | H12: =IF($A12="","",B12) | I12: =IF(H12=0,"",IF($A12="","",E12)) | J12: =IF($A12="","",D12) | K12: =IF($A12="","",(J12*30)+I12) | L12: =IF($A12="","",I12*H12/450) | M12: =IF($A12="","",K12*H12/450) | N12: =IF($A12="","",H12) | O12: =IF(N12=0,"",IF($A12="","",K12)) | P12: =IF($A12="","",J12) | Q12: =IF($A12="","",(P12*30)+O12) | R12: =IF($A12="","",O12*N12/450) | S12: =IF($A12="","",Q12*N12/450) | T12: =IF($A12="","",N12) | U12: =IF(T12=0,"",IF($A12="","",Q12)) | V12: =IF($A12="","",P12) | W12: =IF($A12="","",(V12*30)+U12) | X12: =IF($A12="","",U12*T12/450) | Y12: =IF($A12="","",W12*T12/450) | Z12: =IF($A12="","",T12) | AA12: =IF(Z12=0,"",IF($A12="","",W12)) | AB12: =IF($A12="","",V12) | AC12: =IF($A12="","",(AB12*30)+AA12) | AD12: =IF($A12="","",AA12*Z12/450) | AE12: =IF($A12="","",AC12*Z12/450) | AF12: =IF($A12="","",Z12) | AG12: =IF(AF12=0,"",IF($A12="","",AC12)) | AH12: =IF($A12="","",AB12) | AI12: =IF($A12="","",(AH12*30)+AG12) | AJ12: =IF($A12="","",AG12*AF12/450) | AK12: =IF($A12="","",AI12*AF12/450) | AL12: =IF($A12="","",AF12) | AM12: =IF(AL12=0,"",IF($A12="","",AI12)) | AN12: =IF($A12="","",AH12) | AO12: =IF($A12="","",(AN12*30)+AM12) | AP12: =IF($A12="","",AM12*AL12/450) | AQ12: =IF($A12="","",AO12*AL12/450) | AR12: =IF($A12="","",AL12) | AS12: =IF(AR12=0,"",IF($A12="","",AO12)) | AT12: =IF($A12="","",AN12) | AU12: =IF($A12="","",(AT12*30)+AS12) | AV12: =IF($A12="","",AS12*AR12/450) | AW12: =IF($A12="","",AU12*AR12/450) | AX12: =IF($A12="","",AR12) | AY12: =IF(AX12=0,"",IF($A12="","",AU12)) | AZ12: =IF($A12="","",AT12) | BA12: =IF($A12="","",(AZ12*30)+AY12) | BB12: =IF($A12="","",AY12*AX12/450) | BC12: =IF($A12="","",BA12*AX12/450) | BD12: =IF($A12="","",AX12) | BE12: =IF(BD12=0,"",IF($A12="","",BA12)) | BF12: =IF($A12="","",AZ12) | BG12: =IF($A12="","",(BF12*30)+BE12) | BH12: =IF($A12="","",BE12*BD12/450) | BI12: =IF($A12="","",BG12*BD12/450) | BJ12: =IF($A12="","",BD12) | BK12: =IF(BJ12=0,"",IF($A12="","",BG12)) | BL12: =IF($A12="","",BF12) | BM12: =IF($A12="","",(BL12*30)+BK12) | BN12: =IF($A12="","",BK12*BJ12/450) | BO12: =IF($A12="","",BM12*BJ12/450) | BP12: =IF($A12="","",BJ12) | BQ12: =IF(BP12=0,"",IF($A12="","",BM12)) | BR12: =IF($A12="","",BL12) | BS12: =IF($A12="","",(BR12*30)+BQ12) | BT12: =IF($A12="","",BQ12*BP12/450) | BU12: =IF($A12="","",BS12*BP12/450)
E13: =(D13*30)+C13 -> 0 | F13: =C13*B13/450 -> 0 | G13: =E13*B13/450 -> 0 | H13: =IF($A13="","",B13) | I13: =IF(H13=0,"",IF($A13="","",E13)) | J13: =IF($A13="","",D13) | K13: =IF($A13="","",(J13*30)+I13) | L13: =IF($A13="","",I13*H13/450) | M13: =IF($A13="","",K13*H13/450) | N13: =IF($A13="","",H13) | O13: =IF(N13=0,"",IF($A13="","",K13)) | P13: =IF($A13="","",J13) | Q13: =IF($A13="","",(P13*30)+O13) | R13: =IF($A13="","",O13*N13/450) | S13: =IF($A13="","",Q13*N13/450) | T13: =IF($A13="","",N13) | U13: =IF(T13=0,"",IF($A13="","",Q13)) | V13: =IF($A13="","",P13) | W13: =IF($A13="","",(V13*30)+U13) | X13: =IF($A13="","",U13*T13/450) | Y13: =IF($A13="","",W13*T13/450) | Z13: =IF($A13="","",T13) | AA13: =IF(Z13=0,"",IF($A13="","",W13)) | AB13: =IF($A13="","",V13) | AC13: =IF($A13="","",(AB13*30)+AA13) | AD13: =IF($A13="","",AA13*Z13/450) | AE13: =IF($A13="","",AC13*Z13/450) | AF13: =IF($A13="","",Z13) | AG13: =IF(AF13=0,"",IF($A13="","",AC13)) | AH13: =IF($A13="","",AB13) | AI13: =IF($A13="","",(AH13*30)+AG13) | AJ13: =IF($A13="","",AG13*AF13/450) | AK13: =IF($A13="","",AI13*AF13/450) | AL13: =IF($A13="","",AF13) | AM13: =IF(AL13=0,"",IF($A13="","",AI13)) | AN13: =IF($A13="","",AH13) | AO13: =IF($A13="","",(AN13*30)+AM13) | AP13: =IF($A13="","",AM13*AL13/450) | AQ13: =IF($A13="","",AO13*AL13/450) | AR13: =IF($A13="","",AL13) | AS13: =IF(AR13=0,"",IF($A13="","",AO13)) | AT13: =IF($A13="","",AN13) | AU13: =IF($A13="","",(AT13*30)+AS13) | AV13: =IF($A13="","",AS13*AR13/450) | AW13: =IF($A13="","",AU13*AR13/450) | AX13: =IF($A13="","",AR13) | AY13: =IF(AX13=0,"",IF($A13="","",AU13)) | AZ13: =IF($A13="","",AT13) | BA13: =IF($A13="","",(AZ13*30)+AY13) | BB13: =IF($A13="","",AY13*AX13/450) | BC13: =IF($A13="","",BA13*AX13/450) | BD13: =IF($A13="","",AX13) | BE13: =IF(BD13=0,"",IF($A13="","",BA13)) | BF13: =IF($A13="","",AZ13) | BG13: =IF($A13="","",(BF13*30)+BE13) | BH13: =IF($A13="","",BE13*BD13/450) | BI13: =IF($A13="","",BG13*BD13/450) | BJ13: =IF($A13="","",BD13) | BK13: =IF(BJ13=0,"",IF($A13="","",BG13)) | BL13: =IF($A13="","",BF13) | BM13: =IF($A13="","",(BL13*30)+BK13) | BN13: =IF($A13="","",BK13*BJ13/450) | BO13: =IF($A13="","",BM13*BJ13/450) | BP13: =IF($A13="","",BJ13) | BQ13: =IF(BP13=0,"",IF($A13="","",BM13)) | BR13: =IF($A13="","",BL13) | BS13: =IF($A13="","",(BR13*30)+BQ13) | BT13: =IF($A13="","",BQ13*BP13/450) | BU13: =IF($A13="","",BS13*BP13/450)
E14: =(D14*30)+C14 -> 0 | F14: =C14*B14/450 -> 0 | G14: =E14*B14/450 -> 0 | H14: =IF($A14="","",B14) | I14: =IF(H14=0,"",IF($A14="","",E14)) | J14: =IF($A14="","",D14) | K14: =IF($A14="","",(J14*30)+I14) | L14: =IF($A14="","",I14*H14/450) | M14: =IF($A14="","",K14*H14/450) | N14: =IF($A14="","",H14) | O14: =IF(N14=0,"",IF($A14="","",K14)) | P14: =IF($A14="","",J14) | Q14: =IF($A14="","",(P14*30)+O14) | R14: =IF($A14="","",O14*N14/450) | S14: =IF($A14="","",Q14*N14/450) | T14: =IF($A14="","",N14) | U14: =IF(T14=0,"",IF($A14="","",Q14)) | V14: =IF($A14="","",P14) | W14: =IF($A14="","",(V14*30)+U14) | X14: =IF($A14="","",U14*T14/450) | Y14: =IF($A14="","",W14*T14/450) | Z14: =IF($A14="","",T14) | AA14: =IF(Z14=0,"",IF($A14="","",W14)) | AB14: =IF($A14="","",V14) | AC14: =IF($A14="","",(AB14*30)+AA14) | AD14: =IF($A14="","",AA14*Z14/450) | AE14: =IF($A14="","",AC14*Z14/450) | AF14: =IF($A14="","",Z14) | AG14: =IF(AF14=0,"",IF($A14="","",AC14)) | AH14: =IF($A14="","",AB14) | AI14: =IF($A14="","",(AH14*30)+AG14) | AJ14: =IF($A14="","",AG14*AF14/450) | AK14: =IF($A14="","",AI14*AF14/450) | AL14: =IF($A14="","",AF14) | AM14: =IF(AL14=0,"",IF($A14="","",AI14)) | AN14: =IF($A14="","",AH14) | AO14: =IF($A14="","",(AN14*30)+AM14) | AP14: =IF($A14="","",AM14*AL14/450) | AQ14: =IF($A14="","",AO14*AL14/450) | AR14: =IF($A14="","",AL14) | AS14: =IF(AR14=0,"",IF($A14="","",AO14)) | AT14: =IF($A14="","",AN14) | AU14: =IF($A14="","",(AT14*30)+AS14) | AV14: =IF($A14="","",AS14*AR14/450) | AW14: =IF($A14="","",AU14*AR14/450) | AX14: =IF($A14="","",AR14) | AY14: =IF(AX14=0,"",IF($A14="","",AU14)) | AZ14: =IF($A14="","",AT14) | BA14: =IF($A14="","",(AZ14*30)+AY14) | BB14: =IF($A14="","",AY14*AX14/450) | BC14: =IF($A14="","",BA14*AX14/450) | BD14: =IF($A14="","",AX14) | BE14: =IF(BD14=0,"",IF($A14="","",BA14)) | BF14: =IF($A14="","",AZ14) | BG14: =IF($A14="","",(BF14*30)+BE14) | BH14: =IF($A14="","",BE14*BD14/450) | BI14: =IF($A14="","",BG14*BD14/450) | BJ14: =IF($A14="","",BD14) | BK14: =IF(BJ14=0,"",IF($A14="","",BG14)) | BL14: =IF($A14="","",BF14) | BM14: =IF($A14="","",(BL14*30)+BK14) | BN14: =IF($A14="","",BK14*BJ14/450) | BO14: =IF($A14="","",BM14*BJ14/450) | BP14: =IF($A14="","",BJ14) | BQ14: =IF(BP14=0,"",IF($A14="","",BM14)) | BR14: =IF($A14="","",BL14) | BS14: =IF($A14="","",(BR14*30)+BQ14) | BT14: =IF($A14="","",BQ14*BP14/450) | BU14: =IF($A14="","",BS14*BP14/450)
E15: =(D15*30)+C15 -> 0 | F15: =C15*B15/450 -> 0 | G15: =E15*B15/450 -> 0 | H15: =IF($A15="","",B15) | I15: =IF(H15=0,"",IF($A15="","",E15)) | J15: =IF($A15="","",D15) | K15: =IF($A15="","",(J15*30)+I15) | L15: =IF($A15="","",I15*H15/450) | M15: =IF($A15="","",K15*H15/450) | N15: =IF($A15="","",H15) | O15: =IF(N15=0,"",IF($A15="","",K15)) | P15: =IF($A15="","",J15) | Q15: =IF($A15="","",(P15*30)+O15) | R15: =IF($A15="","",O15*N15/450) | S15: =IF($A15="","",Q15*N15/450) | T15: =IF($A15="","",N15) | U15: =IF(T15=0,"",IF($A15="","",Q15)) | V15: =IF($A15="","",P15) | W15: =IF($A15="","",(V15*30)+U15) | X15: =IF($A15="","",U15*T15/450) | Y15: =IF($A15="","",W15*T15/450) | Z15: =IF($A15="","",T15) | AA15: =IF(Z15=0,"",IF($A15="","",W15)) | AB15: =IF($A15="","",V15) | AC15: =IF($A15="","",(AB15*30)+AA15) | AD15: =IF($A15="","",AA15*Z15/450) | AE15: =IF($A15="","",AC15*Z15/450) | AF15: =IF($A15="","",Z15) | AG15: =IF(AF15=0,"",IF($A15="","",AC15)) | AH15: =IF($A15="","",AB15) | AI15: =IF($A15="","",(AH15*30)+AG15) | AJ15: =IF($A15="","",AG15*AF15/450) | AK15: =IF($A15="","",AI15*AF15/450) | AL15: =IF($A15="","",AF15) | AM15: =IF(AL15=0,"",IF($A15="","",AI15)) | AN15: =IF($A15="","",AH15) | AO15: =IF($A15="","",(AN15*30)+AM15) | AP15: =IF($A15="","",AM15*AL15/450) | AQ15: =IF($A15="","",AO15*AL15/450) | AR15: =IF($A15="","",AL15) | AS15: =IF(AR15=0,"",IF($A15="","",AO15)) | AT15: =IF($A15="","",AN15) | AU15: =IF($A15="","",(AT15*30)+AS15) | AV15: =IF($A15="","",AS15*AR15/450) | AW15: =IF($A15="","",AU15*AR15/450) | AX15: =IF($A15="","",AR15) | AY15: =IF(AX15=0,"",IF($A15="","",AU15)) | AZ15: =IF($A15="","",AT15) | BA15: =IF($A15="","",(AZ15*30)+AY15) | BB15: =IF($A15="","",AY15*AX15/450) | BC15: =IF($A15="","",BA15*AX15/450) | BD15: =IF($A15="","",AX15) | BE15: =IF(BD15=0,"",IF($A15="","",BA15)) | BF15: =IF($A15="","",AZ15) | BG15: =IF($A15="","",(BF15*30)+BE15) | BH15: =IF($A15="","",BE15*BD15/450) | BI15: =IF($A15="","",BG15*BD15/450) | BJ15: =IF($A15="","",BD15) | BK15: =IF(BJ15=0,"",IF($A15="","",BG15)) | BL15: =IF($A15="","",BF15) | BM15: =IF($A15="","",(BL15*30)+BK15) | BN15: =IF($A15="","",BK15*BJ15/450) | BO15: =IF($A15="","",BM15*BJ15/450) | BP15: =IF($A15="","",BJ15) | BQ15: =IF(BP15=0,"",IF($A15="","",BM15)) | BR15: =IF($A15="","",BL15) | BS15: =IF($A15="","",(BR15*30)+BQ15) | BT15: =IF($A15="","",BQ15*BP15/450) | BU15: =IF($A15="","",BS15*BP15/450)
E16: =(D16*30)+C16 -> 0 | F16: =C16*B16/450 -> 0 | G16: =E16*B16/450 -> 0 | H16: =IF($A16="","",B16) | I16: =IF(H16=0,"",IF($A16="","",E16)) | J16: =IF($A16="","",D16) | K16: =IF($A16="","",(J16*30)+I16) | L16: =IF($A16="","",I16*H16/450) | M16: =IF($A16="","",K16*H16/450) | N16: =IF($A16="","",H16) | O16: =IF(N16=0,"",IF($A16="","",K16)) | P16: =IF($A16="","",J16) | Q16: =IF($A16="","",(P16*30)+O16) | R16: =IF($A16="","",O16*N16/450) | S16: =IF($A16="","",Q16*N16/450) | T16: =IF($A16="","",N16) | U16: =IF(T16=0,"",IF($A16="","",Q16)) | V16: =IF($A16="","",P16) | W16: =IF($A16="","",(V16*30)+U16) | X16: =IF($A16="","",U16*T16/450) | Y16: =IF($A16="","",W16*T16/450) | Z16: =IF($A16="","",T16) | AA16: =IF(Z16=0,"",IF($A16="","",W16)) | AB16: =IF($A16="","",V16) | AC16: =IF($A16="","",(AB16*30)+AA16) | AD16: =IF($A16="","",AA16*Z16/450) | AE16: =IF($A16="","",AC16*Z16/450) | AF16: =IF($A16="","",Z16) | AG16: =IF(AF16=0,"",IF($A16="","",AC16)) | AH16: =IF($A16="","",AB16) | AI16: =IF($A16="","",(AH16*30)+AG16) | AJ16: =IF($A16="","",AG16*AF16/450) | AK16: =IF($A16="","",AI16*AF16/450) | AL16: =IF($A16="","",AF16) | AM16: =IF(AL16=0,"",IF($A16="","",AI16)) | AN16: =IF($A16="","",AH16) | AO16: =IF($A16="","",(AN16*30)+AM16) | AP16: =IF($A16="","",AM16*AL16/450) | AQ16: =IF($A16="","",AO16*AL16/450) | AR16: =IF($A16="","",AL16) | AS16: =IF(AR16=0,"",IF($A16="","",AO16)) | AT16: =IF($A16="","",AN16) | AU16: =IF($A16="","",(AT16*30)+AS16) | AV16: =IF($A16="","",AS16*AR16/450) | AW16: =IF($A16="","",AU16*AR16/450) | AX16: =IF($A16="","",AR16) | AY16: =IF(AX16=0,"",IF($A16="","",AU16)) | AZ16: =IF($A16="","",AT16) | BA16: =IF($A16="","",(AZ16*30)+AY16) | BB16: =IF($A16="","",AY16*AX16/450) | BC16: =IF($A16="","",BA16*AX16/450) | BD16: =IF($A16="","",AX16) | BE16: =IF(BD16=0,"",IF($A16="","",BA16)) | BF16: =IF($A16="","",AZ16) | BG16: =IF($A16="","",(BF16*30)+BE16) | BH16: =IF($A16="","",BE16*BD16/450) | BI16: =IF($A16="","",BG16*BD16/450) | BJ16: =IF($A16="","",BD16) | BK16: =IF(BJ16=0,"",IF($A16="","",BG16)) | BL16: =IF($A16="","",BF16) | BM16: =IF($A16="","",(BL16*30)+BK16) | BN16: =IF($A16="","",BK16*BJ16/450) | BO16: =IF($A16="","",BM16*BJ16/450) | BP16: =IF($A16="","",BJ16) | BQ16: =IF(BP16=0,"",IF($A16="","",BM16)) | BR16: =IF($A16="","",BL16) | BS16: =IF($A16="","",(BR16*30)+BQ16) | BT16: =IF($A16="","",BQ16*BP16/450) | BU16: =IF($A16="","",BS16*BP16/450)
E17: =(D17*30)+C17 -> 0 | F17: =C17*B17/450 -> 0 | G17: =E17*B17/450 -> 0 | H17: =IF($A17="","",B17) | I17: =IF(H17=0,"",IF($A17="","",E17)) | J17: =IF($A17="","",D17) | K17: =IF($A17="","",(J17*30)+I17) | L17: =IF($A17="","",I17*H17/450) | M17: =IF($A17="","",K17*H17/450) | N17: =IF($A17="","",H17) | O17: =IF(N17=0,"",IF($A17="","",K17)) | P17: =IF($A17="","",J17) | Q17: =IF($A17="","",(P17*30)+O17) | R17: =IF($A17="","",O17*N17/450) | S17: =IF($A17="","",Q17*N17/450) | T17: =IF($A17="","",N17) | U17: =IF(T17=0,"",IF($A17="","",Q17)) | V17: =IF($A17="","",P17) | W17: =IF($A17="","",(V17*30)+U17) | X17: =IF($A17="","",U17*T17/450) | Y17: =IF($A17="","",W17*T17/450) | Z17: =IF($A17="","",T17) | AA17: =IF(Z17=0,"",IF($A17="","",W17)) | AB17: =IF($A17="","",V17) | AC17: =IF($A17="","",(AB17*30)+AA17) | AD17: =IF($A17="","",AA17*Z17/450) | AE17: =IF($A17="","",AC17*Z17/450) | AF17: =IF($A17="","",Z17) | AG17: =IF(AF17=0,"",IF($A17="","",AC17)) | AH17: =IF($A17="","",AB17) | AI17: =IF($A17="","",(AH17*30)+AG17) | AJ17: =IF($A17="","",AG17*AF17/450) | AK17: =IF($A17="","",AI17*AF17/450) | AL17: =IF($A17="","",AF17) | AM17: =IF(AL17=0,"",IF($A17="","",AI17)) | AN17: =IF($A17="","",AH17) | AO17: =IF($A17="","",(AN17*30)+AM17) | AP17: =IF($A17="","",AM17*AL17/450) | AQ17: =IF($A17="","",AO17*AL17/450) | AR17: =IF($A17="","",AL17) | AS17: =IF(AR17=0,"",IF($A17="","",AO17)) | AT17: =IF($A17="","",AN17) | AU17: =IF($A17="","",(AT17*30)+AS17) | AV17: =IF($A17="","",AS17*AR17/450) | AW17: =IF($A17="","",AU17*AR17/450) | AX17: =IF($A17="","",AR17) | AY17: =IF(AX17=0,"",IF($A17="","",AU17)) | AZ17: =IF($A17="","",AT17) | BA17: =IF($A17="","",(AZ17*30)+AY17) | BB17: =IF($A17="","",AY17*AX17/450) | BC17: =IF($A17="","",BA17*AX17/450) | BD17: =IF($A17="","",AX17) | BE17: =IF(BD17=0,"",IF($A17="","",BA17)) | BF17: =IF($A17="","",AZ17) | BG17: =IF($A17="","",(BF17*30)+BE17) | BH17: =IF($A17="","",BE17*BD17/450) | BI17: =IF($A17="","",BG17*BD17/450) | BJ17: =IF($A17="","",BD17) | BK17: =IF(BJ17=0,"",IF($A17="","",BG17)) | BL17: =IF($A17="","",BF17) | BM17: =IF($A17="","",(BL17*30)+BK17) | BN17: =IF($A17="","",BK17*BJ17/450) | BO17: =IF($A17="","",BM17*BJ17/450) | BP17: =IF($A17="","",BJ17) | BQ17: =IF(BP17=0,"",IF($A17="","",BM17)) | BR17: =IF($A17="","",BL17) | BS17: =IF($A17="","",(BR17*30)+BQ17) | BT17: =IF($A17="","",BQ17*BP17/450) | BU17: =IF($A17="","",BS17*BP17/450)
... E22: =(D22*30)+C22 -> 0 | F22: =C22*B22/450 -> 0 | G22: =E22*B22/450 -> 0 | H22: =IF($A22="","",B22) | I22: =IF(H22=0,"",IF($A22="","",E22)) | J22: =IF($A22="","",D22) | K22: =IF($A22="","",(J22*30)+I22) | L22: =IF($A22="","",I22*H22/450) | M22: =IF($A22="","",K22*H22/450) | N22: =IF($A22="","",H22) | O22: =IF(N22=0,"",IF($A22="","",K22)) | P22: =IF($A22="","",J22) | Q22: =IF($A22="","",(P22*30)+O22) | R22: =IF($A22="","",O22*N22/450) | S22: =IF($A22="","",Q22*N22/450) | T22: =IF($A22="","",N22) | U22: =IF(T22=0,"",IF($A22="","",Q22)) | V22: =IF($A22="","",P22) | W22: =IF($A22="","",(V22*30)+U22) | X22: =IF($A22="","",U22*T22/450) | Y22: =IF($A22="","",W22*T22/450) | Z22: =IF($A22="","",T22) | AA22: =IF(Z22=0,"",IF($A22="","",W22)) | AB22: =IF($A22="","",V22) | AC22: =IF($A22="","",(AB22*30)+AA22) | AD22: =IF($A22="","",AA22*Z22/450) | AE22: =IF($A22="","",AC22*Z22/450) | AF22: =IF($A22="","",Z22) | AG22: =IF(AF22=0,"",IF($A22="","",AC22)) | AH22: =IF($A22="","",AB22) | AI22: =IF($A22="","",(AH22*30)+AG22) | AJ22: =IF($A22="","",AG22*AF22/450) | AK22: =IF($A22="","",AI22*AF22/450) | AL22: =IF($A22="","",AF22) | AM22: =IF(AL22=0,"",IF($A22="","",AI22)) | AN22: =IF($A22="","",AH22) | AO22: =IF($A22="","",(AN22*30)+AM22) | AP22: =IF($A22="","",AM22*AL22/450) | AQ22: =IF($A22="","",AO22*AL22/450) | AR22: =IF($A22="","",AL22) | AS22: =IF(AR22=0,"",IF($A22="","",AO22)) | AT22: =IF($A22="","",AN22) | AU22: =IF($A22="","",(AT22*30)+AS22) | AV22: =IF($A22="","",AS22*AR22/450) | AW22: =IF($A22="","",AU22*AR22/450) | AX22: =IF($A22="","",AR22) | AY22: =IF(AX22=0,"",IF($A22="","",AU22)) | AZ22: =IF($A22="","",AT22) | BA22: =IF($A22="","",(AZ22*30)+AY22) | BB22: =IF($A22="","",AY22*AX22/450) | BC22: =IF($A22="","",BA22*AX22/450) | BD22: =IF($A22="","",AX22) | BE22: =IF(BD22=0,"",IF($A22="","",BA22)) | BF22: =IF($A22="","",AZ22) | BG22: =IF($A22="","",(BF22*30)+BE22) | BH22: =IF($A22="","",BE22*BD22/450) | BI22: =IF($A22="","",BG22*BD22/450) | BJ22: =IF($A22="","",BD22) | BK22: =IF(BJ22=0,"",IF($A22="","",BG22)) | BL22: =IF($A22="","",BF22) | BM22: =IF($A22="","",(BL22*30)+BK22) | BN22: =IF($A22="","",BK22*BJ22/450) | BO22: =IF($A22="","",BM22*BJ22/450) | BP22: =IF($A22="","",BJ22) | BQ22: =IF(BP22=0,"",IF($A22="","",BM22)) | BR22: =IF($A22="","",BL22) | BS22: =IF($A22="","",(BR22*30)+BQ22) | BT22: =IF($A22="","",BQ22*BP22/450) | BU22: =IF($A22="","",BS22*BP22/450)
A24: Total cabeças | B24: =SUM(B5:B22) -> 40 | H24: =SUM(H5:H22) -> 40 | N24: =SUM(N5:N22) -> 40 | T24: =SUM(T5:T22) -> 40 | Z24: =SUM(Z5:Z22) -> 40 | AF24: =SUM(AF5:AF22) -> 40 | AL24: =SUM(AL5:AL22) -> 40 | AR24: =SUM(AR5:AR22) -> 40 | AX24: =SUM(AX5:AX22) -> 40 | BD24: =SUM(BD5:BD22) -> 40 | BJ24: =SUM(BJ5:BJ22) -> 40 | BP24: =SUM(BP5:BP22) -> 40
A25: Lotação total (U.A/ha) | B25: =ROUND(AVERAGE(SUM(F5:F22),SUM(G5:G22))/'Cadastro pastos'!$B$61,2) -> 0.34 | H25: =ROUND(AVERAGE(SUM(L5:L22),SUM(M5:M22))/'Cadastro pastos'!$B$61,2) -> 0.35 | N25: =ROUND(AVERAGE(SUM(R5:R22),SUM(S5:S22))/'Cadastro pastos'!$B$61,2) -> 0.36 | T25: =ROUND(AVERAGE(SUM(X5:X22),SUM(Y5:Y22))/'Cadastro pastos'!$B$61,2) -> 0.36 | Z25: =ROUND(AVERAGE(SUM(AD5:AD22),SUM(AE5:AE22))/'Cadastro pastos'!$B$61,2) -> 0.37 | AF25: =ROUND(AVERAGE(SUM(AJ5:AJ22),SUM(AK5:AK22))/'Cadastro pastos'!$B$61,2) -> 0.38 | AL25: =ROUND(AVERAGE(SUM(AP5:AP22),SUM(AQ5:AQ22))/'Cadastro pastos'!$B$61,2) -> 0.39 | AR25: =ROUND(AVERAGE(SUM(AV5:AV22),SUM(AW5:AW22))/'Cadastro pastos'!$B$61,2) -> 0.4 | AX25: =ROUND(AVERAGE(SUM(BB5:BB22),SUM(BC5:BC22))/'Cadastro pastos'!$B$61,2) -> 0.41 | BD25: =ROUND(AVERAGE(SUM(BH5:BH22),SUM(BI5:BI22))/'Cadastro pastos'!$B$61,2) -> 0.42 | BJ25: =ROUND(AVERAGE(SUM(BN5:BN22),SUM(BO5:BO22))/'Cadastro pastos'!$B$61,2) -> 0.43 | BP25: =ROUND(AVERAGE(SUM(BT5:BT22),SUM(BU5:BU22))/'Cadastro pastos'!$B$61,2) -> 0.44
A26: Lotação corrigida (U.A/ha) | B26: =ROUND(AVERAGE(SUM(F5:F22),SUM(G5:G22))/'Cadastro pastos'!$D$61,2) -> 0.4 | H26: =ROUND(AVERAGE(SUM(L5:L22),SUM(M5:M22))/'Cadastro pastos'!$D$61,2) -> 0.41 | N26: =ROUND(AVERAGE(SUM(R5:R22),SUM(S5:S22))/'Cadastro pastos'!$D$61,2) -> 0.42 | T26: =ROUND(AVERAGE(SUM(X5:X22),SUM(Y5:Y22))/'Cadastro pastos'!$D$61,2) -> 0.44 | Z26: =ROUND(AVERAGE(SUM(AD5:AD22),SUM(AE5:AE22))/'Cadastro pastos'!$D$61,2) -> 0.45 | AF26: =ROUND(AVERAGE(SUM(AJ5:AJ22),SUM(AK5:AK22))/'Cadastro pastos'!$D$61,2) -> 0.46 | AL26: =ROUND(AVERAGE(SUM(AP5:AP22),SUM(AQ5:AQ22))/'Cadastro pastos'!$D$61,2) -> 0.47 | AR26: =ROUND(AVERAGE(SUM(AV5:AV22),SUM(AW5:AW22))/'Cadastro pastos'!$D$61,2) -> 0.48 | AX26: =ROUND(AVERAGE(SUM(BB5:BB22),SUM(BC5:BC22))/'Cadastro pastos'!$D$61,2) -> 0.49 | BD26: =ROUND(AVERAGE(SUM(BH5:BH22),SUM(BI5:BI22))/'Cadastro pastos'!$D$61,2) -> 0.5 | BJ26: =ROUND(AVERAGE(SUM(BN5:BN22),SUM(BO5:BO22))/'Cadastro pastos'!$D$61,2) -> 0.51 | BP26: =ROUND(AVERAGE(SUM(BT5:BT22),SUM(BU5:BU22))/'Cadastro pastos'!$D$61,2) -> 0.52

Sheet Resultado lotação
B11: ='Cadastro pastos'!K4 -> Seca | C11: ='Cadastro pastos'!L4 -> Seca | D11: ='Cadastro pastos'!M4 -> Seca | E11: ='Cadastro pastos'!N4 -> Chuva | F11: ='Cadastro pastos'!O4 -> Chuva | G11: ='Cadastro pastos'!P4 -> Chuva | H11: ='Cadastro pastos'!Q4 -> Chuva | I11: ='Cadastro pastos'!R4 -> Chuva | ... M11: ='Cadastro pastos'!V4 -> Seca
A12: Descrição | B12: ='Cadastro pastos'!K3 -> Julho | C12: ='Cadastro pastos'!L3 -> Agosto | D12: ='Cadastro pastos'!M3 -> Setembro | E12: ='Cadastro pastos'!N3 -> Outubro | F12: ='Cadastro pastos'!O3 -> Novembro | G12: ='Cadastro pastos'!P3 -> Dezembro | H12: ='Cadastro pastos'!Q3 -> Janeiro | I12: ='Cadastro pastos'!R3 -> Fevereiro | ... M12: ='Cadastro pastos'!V3 -> Junho | N12: Média
A13: ='Planejamento de lotação'!A25 -> Lotação total (U.A/ha) | B13: ='Planejamento de lotação'!B25 -> 0.34 | C13: ='Planejamento de lotação'!H25 -> 0.35 | D13: ='Planejamento de lotação'!N25 -> 0.36 | E13: ='Planejamento de lotação'!T25 -> 0.36 | F13: ='Planejamento de lotação'!Z25 -> 0.37 | G13: ='Planejamento de lotação'!AF25 -> 0.38 | H13: ='Planejamento de lotação'!AL25 -> 0.39 | I13: ='Planejamento de lotação'!AR25 -> 0.4 | J13: ='Planejamento de lotação'!AX25 -> 0.41 | K13: ='Planejamento de lotação'!BD25 -> 0.42 | L13: ='Planejamento de lotação'!BJ25 -> 0.43 | M13: ='Planejamento de lotação'!BP25 -> 0.44 | N13: =AVERAGE(B13:M13) -> 0.3875
A14: ='Planejamento de lotação'!A26 -> Lotação corrigida (U.A/ha) | B14: ='Planejamento de lotação'!B26 -> 0.4 | C14: ='Planejamento de lotação'!H26 -> 0.41 | D14: ='Planejamento de lotação'!N26 -> 0.42 | E14: ='Planejamento de lotação'!T26 -> 0.44 | F14: ='Planejamento de lotação'!Z26 -> 0.45 | G14: ='Planejamento de lotação'!AF26 -> 0.46 | H14: ='Planejamento de lotação'!AL26 -> 0.47 | I14: ='Planejamento de lotação'!AR26 -> 0.48 | J14: ='Planejamento de lotação'!AX26 -> 0.49 | K14: ='Planejamento de lotação'!BD26 -> 0.5 | L14: ='Planejamento de lotação'!BJ26 -> 0.51 | M14: ='Planejamento de lotação'!BP26 -> 0.52 | N14: =AVERAGE(B14:M14) -> 0.4625
A17: Lotação área intensiva | B17: 1 | C17: 1 | D17: 1 | E17: 3 | F17: 3 | G17: 3 | H17: 3 | I17: 3 | J17: 3 | K17: 1 | L17: 1 | M17: 1 | N17: =AVERAGE(B17:M17) -> 2 | O17: > | P17: Nas células em amarelo, você poderá preencher a lotação e a área que quer intensificar
A18: Tamanho área intensiva | B18: 10 | C18: 10 | D18: 10 | E18: 10 | F18: 10 | G18: 10 | H18: 10 | I18: 10 | J18: 10 | K18: 10 | L18: 10 | M18: 10 | N18: =AVERAGE(B18:M18) -> 10 | P18: Cada coluna é referente a um mês. Planeje de acordo com os meses de chuva da sua região.
A19: U.A área intensiva | B19: =B18*B17 -> 10 | C19: =C18*C17 -> 10 | D19: =D18*D17 -> 10 | E19: =E18*E17 -> 30 | F19: =F18*F17 -> 30 | G19: =G18*G17 -> 30 | H19: =H18*H17 -> 30 | I19: =I18*I17 -> 30 | ... M19: =M18*M17 -> 10
L20: Lotação chuva: | N20: =AVERAGEIFS(B17:M17,B11:M11,"Chuva") -> 3 | O20: > | P20: Essa lotação de chuva que vai ser seu norteador para a adubação.
A22: U.A área extensiva | B22: =B14*'Cadastro pastos'!$D$61 -> 40.2 | C22: =C14*'Cadastro pastos'!$D$61 -> 41.205 | D22: =D14*'Cadastro pastos'!$D$61 -> 42.21 | E22: =E14*'Cadastro pastos'!$D$61 -> 44.22 | F22: =F14*'Cadastro pastos'!$D$61 -> 45.225 | G22: =G14*'Cadastro pastos'!$D$61 -> 46.23 | H22: =H14*'Cadastro pastos'!$D$61 -> 47.235 | I22: =I14*'Cadastro pastos'!$D$61 -> 48.24 | ... M22: =M14*'Cadastro pastos'!$D$61 -> 52.26
A23: Diferença | B23: =B22-B19 -> 30.2 | C23: =C22-C19 -> 31.205 | D23: =D22-D19 -> 32.21 | E23: =E22-E19 -> 14.22 | F23: =F22-F19 -> 15.225 | G23: =G22-G19 -> 16.23 | H23: =H22-H19 -> 17.235 | I23: =I22-I19 -> 18.24 | ... M23: =M22-M19 -> 42.26
A24: Área ext. restante | B24: ='Cadastro pastos'!$D$61-'Resultado lotação'!B18 -> 90.5 | C24: ='Cadastro pastos'!$D$61-'Resultado lotação'!C18 -> 90.5 | D24: ='Cadastro pastos'!$D$61-'Resultado lotação'!D18 -> 90.5 | E24: ='Cadastro pastos'!$D$61-'Resultado lotação'!E18 -> 90.5 | F24: ='Cadastro pastos'!$D$61-'Resultado lotação'!F18 -> 90.5 | G24: ='Cadastro pastos'!$D$61-'Resultado lotação'!G18 -> 90.5 | H24: ='Cadastro pastos'!$D$61-'Resultado lotação'!H18 -> 90.5 | I24: ='Cadastro pastos'!$D$61-'Resultado lotação'!I18 -> 90.5 | ... M24: ='Cadastro pastos'!$D$61-'Resultado lotação'!M18 -> 90.5
A25: Lotação área extensiva | B25: =B23/B24 -> 0.33370166 | C25: =C23/C24 -> 0.34480663 | D25: =D23/D24 -> 0.3559116 | E25: =E23/E24 -> 0.15712707 | F25: =F23/F24 -> 0.16823204 | G25: =G23/G24 -> 0.17933702 | H25: =H23/H24 -> 0.19044199 | I25: =I23/I24 -> 0.20154696 | ... M25: =M23/M24 -> 0.46696133 | N25: =AVERAGE(B25:M25) -> 0.2926105 | O25: > | P25: A área intensiva acioma, resultara em uma redução de lotação na área extensiva, representada por essa linha.
P26: Essa lotação permitirá uma sobra de pasto ou aumento do número de animais na área.
P27: Por isso, use a intensificação com essa estratégia.

Sheet Resumo materiais
A1: ESTIMATIVA MATERIAIS
B3: CERCA ELÉTRICA | J3: CERCA CONVENCIONAL | R3: ÁGUA ENCANADA
C5: Estimativa de materiais | F5: Resultados | K5: Estimativa de materiais | N5: Resultados
C6: Comprimento total da cerca (m) | F6: Total de lascas (un.) | G6: =D6/D7 -> #DIV/0! | K6: Comprimento total da cerca (m) | N6: Total de lascas (un.) | O6: =L6/L7 -> #DIV/0!
C7: Espaçamento entre lasca | F7: Total de arame (m) | G7: =D6*D8 -> 0 | K7: Espaçamento entre lasca | N7: Total de arame (m) | O7: =L6*L8 -> 0
C8: Quantidade de fios | F8: Estimativa de palanques | G8: =(D9*2)+IF(D10="Sim",4*D11,0) -> 0 | K8: Quantidade de fios | N8: Estimativa de palanques | O8: =(L9*2)+(O9*2)+IF(L10="Sim",4*L11,0) -> 0
C9: Número de piquetes | F9: Estimativa de porteiras de choque | G9: =D9 -> 0 | K9: Número de piquetes | N9: Estimativa de porteiras | O9: =L9+IF(L10="Sim",2*L11,0) -> 0
C10: Tem praça de alimentação? | F10: Estimativa de porteiras convencional | G10: =IF(D10="Sim",2*D11,0) -> 0 | K10: Tem praça de alimentação?
C11: Quantas praças de alimentação | F11: Potência eletrificador (J) | G11: =ROUNDUP(D6/3000,0) -> 0 | K11: Quantas praças de alimentação
F12: Isolador W (un.) | G12: =G6 -> #DIV/0!
F13: Hastes de aterramento | G13: =IF(G11<=3,3,G11) -> 3
C15: LISTA DE MATERIAIS | K15: LISTA DE MATERIAIS | S15: LISTA DE MATERIAIS
C16: Foto | D16: Item | E16: Preço un. | F16: Qnt. Necessária | G16: R$ Total | K16: Foto | L16: Item | M16: Preço un. | N16: Qnt. Necessária | O16: R$ Total | S16: Foto | T16: Item | U16: Preço un. | V16: Qnt. Necessária | W16: R$ Total
D17: Lasca | F17: =G6 -> #DIV/0! | G17: =F17*E17 -> #DIV/0! | L17: Lasca | N17: =O6 -> #DIV/0! | O17: =N17*M17 -> #DIV/0! | T17: Cano 50mm PN60 | W17: =V17*U17 -> 0
D18: Arame liso | F18: =G7 -> 0 | G18: =F18*E18 -> 0 | L18: Arame liso | N18: =O7 -> 0 | O18: =N18*M18 -> 0 | T18: Bebedouros | W18: =V18*U18 -> 0
D19: Porteira convencional | F19: =G10 -> 0 | G19: =F19*E19 -> 0 | L19: Porteira convencional | N19: =O9 -> 0 | O19: =N19*M19 -> 0 | T19: Boia p/ bebedouros (vazão total) | W19: =V19*U19 -> 0
D20: Palanque | F20: =G8 -> 0 | G20: =F20*E20 -> 0 | L20: Palanque | N20: =O8 -> 0 | O20: =N20*M20 -> 0 | T20: Tê 50mm | W20: =V20*U20 -> 0
D21: Porteira de choque | F21: =G9 -> 0 | G21: =F21*E21 -> 0 | L21: Mão de obra (km) | N21: =L6/1000 -> 0 | O21: =N21*M21 -> 0 | T21: Cotovelo | W21: =V21*U21 -> 0
D22: Castanha | F22: =F20*2.5 -> 0 | G22: =F22*E22 -> 0 | O22: =N22*M22 -> 0 | T22: Registros | W22: =V22*U22 -> 0
D23: Isolador W | F23: =F17 -> #DIV/0! | G23: =F23*E23 -> #DIV/0! | O23: =N23*M23 -> 0 | T23: Cola para canos | W23: =V23*U23 -> 0
D24: ="Eletrificador "&G11&"J" -> Eletrificador 0J | F24: 1 | G24: =F24*E24 -> 0 | O24: =N24*M24 -> 0 | T24: Abertura de valetas | W24: =V24*U24 -> 0
D25: Hastes aterramento | F25: =$G$13 -> 3 | G25: =F25*E25 -> 0 | O25: =N25*M25 -> 0 | T25: Mão de obra | W25: =V25*U25 -> 0
D26: Fio encapado | F26: =(($G$9+$G$10)*5)+($G$8*1) -> 0 | G26: =F26*E26 -> 0 | O26: =N26*M26 -> 0 | T26: Reservatório | W26: =V26*U26 -> 0
D27: Mão de obra (km) | F27: =$D$6/1000 -> 0 | G27: =F27*E27 -> 0 | O27: =N27*M27 -> 0 | W27: =V27*U27 -> 0
G28: =F28*E28 -> 0 | O28: =N28*M28 -> 0 | W28: =V28*U28 -> 0
G29: =F29*E29 -> 0 | O29: =N29*M29 -> 0 | W29: =V29*U29 -> 0
C30: Total | G30: =SUM(G17:G29) -> #DIV/0! | K30: Total | O30: =SUM(O17:O29) -> #DIV/0! | S30: Total | W30: =SUM(W17:W29) -> 0

Sheet Dimensionamento de água
B1: PLANILHA PARA DIMENSIONAMENTO DO SISTEMA DE ÁGUA
B3: INFORMAÇÕES DO SISTEMA | L3: L/H | M3: 25 | N3: 32 | O3: 40 | P3: 50 | Q3: 75 | R3: 100 | S3: 125 | T3: 150 | U3: 200 | V3: 250 | W3: 300 | AB3: DADOS GEOMÉTRICOS DA INSTALAÇÃO | AD3: L (m)
B4: Qnt. Cabeças | K4: 1 | L4: 498 | M4: 0.7 | N4: 0.2 | O4: 0 | X4: 1 | AB4: A | AD4: 0
B5: Tempo de bombeamento (horas) | K5: 2 | L5: 1002 | M5: 2.7 | N5: 0.75 | O5: 0.22 | P5: 0.08 | X5: 2 | AB5: B | AD5: 0
B6: Dias p/ manutenção | K6: 3 | L6: 1500 | M6: 6 | N6: 1.6 | O6: 0.5 | P6: 0.17 | X6: 3 | AB6: C | AD6: ='Dimensionamento de água'!C13 -> 0
B7: Potência bomba (cv) | C7: =ROUNDUP(AC39/735,0) -> #DIV/0! | K7: 4 | L7: 1998 | M7: 10 | N7: 2.7 | O7: 0.8 | P7: 0.28 | X7: 4 | AB7: D | AD7: ='Dimensionamento de água'!C14 -> 0
B8: Tamanho reservatório (L) | C8: =C6*C4*60 -> 0 | K8: 5 | L8: 3000 | M8: 21.5 | N8: 6 | O8: 1.8 | P8: 0.6 | Q8: 0.05 | X8: 5 | AB8: E | AD8: 3
K9: 6 | L9: 4002 | M9: 27 | N9: 10 | O9: 3 | P9: 1.05 | Q9: 0.1 | X9: 6 | AB9: F | AD9: 2
B10: LINHA DE CAPTAÇÃO | K10: 7 | L10: 4998 | M10: 55 | N10: 15.5 | O10: 4.7 | P10: 1.6 | Q10: 0.15 | R10: 0.05 | X10: 7 | AB10: H | AD10: =AD6+AD8+AD4 -> 3
B11: Altitude Inicial (m) | D11: =IFERROR(IF(C16=0,"Diminuir o diâmetro",IF(C17<=1.5,"Aumentar diâmetro ou altitude","Ok")),"Pode diminuir o diâmetro") -> Pode diminuir o diâmetro | K11: 8 | L11: 6000 | M11: 60 | N11: 22 | O11: 6.6 | P11: 2.2 | Q11: 0.2 | R11: 0.07 | X11: 8 | AB11: ACESSÓRIOS | AC11: QUANT. | AD11: L EQ (m)
B12: Altitude reservatório (m) | K12: 9 | L12: 7998 | N12: 37 | O12: 11.5 | P12: 3.9 | Q12: 0.35 | R12: 0.13 | X12: 9 | AB12: CURVA DE 90 graus | AC12: 4 | AD12: =AC12*((0.786*LN(AC21))-1.845) -> #NUM!
B13: Dif. Nível (m) | C13: =(C11-C12)*-1 -> 0 | K13: 10 | L13: 10002 | N13: 56 | O13: 17 | P13: 5.7 | Q13: 0.5 | R13: 0.2 | S13: 0.06 | X13: 10 | AB13: VÁLVULA DE RETENÇÃO | AC13: 1 | AD13: =AC13*(0.12449*AC21-0.01819) -> -0.01819
B14: Comprimento (m) | K14: 11 | L14: 12498 | N14: 85 | O14: 26 | P14: 8.5 | Q14: 0.8 | R14: 0.28 | S14: 0.09 | X14: 11 | AB14: VÁLVULA DE PÉ OU CRIVO | AC14: 1 | AD14: =AC14*(15.3311*LN(AC21)-36.98) -> #NUM!
B15: Diâmetro (mm) | K15: 12 | L15: 15000 | O15: 37 | P15: 12.5 | Q15: 1.1 | R15: 0.4 | S15: 0.13 | T15: 0.05 | X15: 12 | AB15: SAÍDA DA TUBULAÇÃO | AC15: 3 | AD15: =2.21*LN(AC21)-5.559 -> #NUM!
B16: Perda (m) | C16: =HLOOKUP(C15,'Dimensionamento de água'!$L$3:$W$45,VLOOKUP(VLOOKUP((C4*50)/C5,'Dimensionamento de água'!$L$4:$L$45,1,1),'Dimensionamento de água'!$L$4:$X$45,13,0)+2,0)*(C14/100) -> #DIV/0! | K16: 13 | L16: 17502 | O16: 47 | P16: 16 | Q16: 1.4 | R16: 0.5 | S16: 0.17 | T16: 0.06 | X16: 13 | AB16: REGISTRO DE GLOBO | AC16: 0 | AD16: =AC16*(0.3269*AC21+0.6384) -> 0
B17: Pressão final (MCA) | C17: =C13-C16 -> #DIV/0! | K17: 14 | L17: 19998 | O17: 63 | P17: 21.5 | Q17: 2 | R17: 0.7 | S17: 0.23 | T17: 0.09 | X17: 14 | AB17: REGISTRO DE GAVETA | AC17: 0 | AD17: =AC17*(0.5269*LN(AC21)-1.3735) -> #NUM!
B18: PN (mínimo) | C18: =(C17+C16)*1.3 -> #DIV/0! | K18: 15 | L18: 25002 | O18: 95 | P18: 33 | Q18: 3 | R18: 1.1 | S18: 0.35 | T18: 0.13 | X18: 15 | AB18: DADOS DO ESCOAMENTO
K19: 16 | L19: 30000 | P19: 45 | Q19: 4.2 | R19: 1.5 | S19: 0.5 | T19: 0.2 | U19: 0.05 | X19: 16 | AB19: VAZÃO DA BOMBA | AC19: =('Dimensionamento de água'!C4*50)/'Dimensionamento de água'!C5/60/60 -> #DIV/0! | AD19: LITROS/SEG
B20: LINHA DE DISTRIBUIÇÃO | K20: 17 | L20: 34998 | P20: 61 | Q20: 5.7 | R20: 2 | S20: 0.65 | T20: 0.24 | U20: 0.06 | X20: 17 | AB20: VAZÃO DA BOMBA | AC20: =AC19/1000 -> #DIV/0! | AD20: m³/s
B21: Altitude Inicial (m) | C21: =C12 -> 0 | D21: =IFERROR(IF(C26=0,"Corrigir o diâmetro",IF(C27<=1.5,"Aumentar diâmetro","Ok")),"Pode diminuir o diâmetro") -> Pode diminuir o diâmetro | K21: 18 | L21: 40002 | P21: 78 | Q21: 7 | R21: 2.5 | S21: 0.8 | T21: 0.3 | U21: 0.08 | X21: 18 | AB21: DIÂMETRO DA CANALIZAÇÃO | AC21: ='Dimensionamento de água'!C15 -> 0 | AD21: mm
B22: Altitude Final (m) | K22: 19 | L22: 45000 | P22: 100 | Q22: 9 | R22: 3.1 | S22: 1 | T22: 0.4 | U22: 0.1 | X22: 19 | AB22: DIÂMETRO DA CANALIZAÇÃO EM METROS | AC22: =AC21/1000 -> 0 | AD22: m
B23: Dif. Nível (m) | C23: =C21-C22 -> 0 | K23: 20 | L23: 49998 | Q23: 11 | R23: 3.8 | S23: 1.25 | T23: 0.5 | U23: 0.12 | X23: 20 | AB23: PROPRIEDADES DA ÁGUA
B24: Comprimento (m) | K24: 21 | L24: 60000 | Q24: 16 | R24: 5.5 | S24: 1.8 | T24: 0.7 | U24: 0.16 | V24: 0.05 | X24: 21 | AB24: VISCOSIDADE | AC24: 1.127e-06 | AD24: m²/s
B25: Diâmetro (mm) | K25: 22 | L25: 70002 | Q25: 21 | R25: 7.2 | S25: 2.4 | T25: 0.9 | U25: 0.21 | V25: 0.07 | X25: 22 | AB25: DENSIDADE | AC25: 1000 | AD25: kg/m³
B26: Perda (m) | C26: =HLOOKUP(C25,'Dimensionamento de água'!$L$3:$W$45,VLOOKUP(VLOOKUP((C4*50)/12,'Dimensionamento de água'!$L$4:$L$45,1,1),'Dimensionamento de água'!$L$4:$X$45,13,0)+2,0)*(C24/100) -> #N/A | K26: 23 | L26: 79998 | Q26: 26.5 | R26: 9.2 | S26: 3.1 | T26: 1.2 | U26: 0.27 | V26: 0.09 | X26: 23 | AB26: TEMPERATURA | AC26: 25 | AD26: oC
B27: Pressão final (MCA) | C27: =C23-C26 -> #N/A | K27: 24 | L27: 90000 | Q27: 34 | R27: 12 | S27: 3.8 | T27: 1.4 | U27: 0.35 | V27: 0.12 | X27: 24 | AB27: CÁLCULOS GERAIS
B28: PN (mínimo) | C28: =(C27+C26)*1.3 -> #N/A | K28: 25 | L28: 100002 | Q28: 40 | R28: 14 | S28: 4.7 | T28: 1.8 | U28: 0.42 | V28: 0.14 | X28: 25 | AB28: VELOCIDADE DO ESCOAMENTO | AC28: =AC20/AC29 -> #DIV/0! | AD28: m/s
K29: 26 | L29: 120000 | Q29: 58 | R29: 20 | S29: 6.6 | T29: 2.5 | U29: 0.6 | V29: 0.2 | W29: 0.08 | X29: 26 | AB29: ÁREA INTERNA DA TUBULAÇÃO | AC29: =(3.14*AC22^2)/4 -> 0 | AD29: m²
K30: 27 | L30: 139998 | Q30: 80 | R30: 27 | S30: 9 | T30: 3.3 | U30: 0.8 | V30: 0.26 | W30: 0.1 | X30: 27 | AB30: NÚMERO DE REYNOLDS | AC30: =AC28*AC22/0.000001127 -> #DIV/0!
B31: Tamanho bebedouro (m) | C31: =C4*0.05 -> 0 | K31: 28 | L31: 160002 | R31: 35 | S31: 11.5 | T31: 4.25 | U31: 1 | V31: 0.34 | W31: 0.13 | X31: 28 | AB31: FATOR DE ATRITO (D.MOODY) | AC31: =0.222554*AC30^-0.216968 -> #DIV/0!
B32: Se beber dos dois lados | C32: =C31/2 -> 0 | K32: 29 | L32: 180000 | R32: 43 | S32: 14 | T32: 5.3 | U32: 1.25 | V32: 0.42 | W32: 0.17 | X32: 29 | AB32: COMPRIMENTO DE TRECHO RETO DE TUBO | AC32: =AD4+AD5+AD6+AD7+AD8+AD9 -> 5 | AD32: m
K33: 30 | L33: 199998 | R33: 50 | S33: 17.5 | T33: 6.5 | U33: 1.5 | V33: 0.5 | W33: 0.2 | X33: 30 | AB33: COMPRIMENTO EQUIVALENTE DE TUBO | AC33: =AD12+AD13+AD14+AD15+AD16+AD17 -> #NUM! | AD33: m
K34: 31 | L34: 250002 | R34: 80 | S34: 26.5 | T34: 10 | U34: 2.3 | V34: 0.8 | W34: 0.32 | X34: 31 | AB34: COMPRIMENTO TOTAL DE TUBULAÇÃO | AC34: =AC32+AC33 -> #NUM! | AD34: m
K35: 32 | L35: 300000 | S35: 36 | T35: 14 | U35: 3.3 | V35: 1.1 | W35: 0.45 | X35: 32 | AB35: VARIAÇÃO DE ENERGIA (DELTA E) | AC35: =AC31*AC34*AC28*AC28/(2*AC22) -> #DIV/0! | AD35: m²/s²
K36: 33 | L36: 349998 | T36: 19 | U36: 4.5 | V36: 1.5 | W36: 0.6 | X36: 33 | AB36: ALTURA MANOMÉTRICA (m) | AC36: =(AC35/9.81)+AD10 -> #DIV/0! | AD36: m
K37: 34 | L37: 400002 | T37: 24 | U37: 5.8 | V37: 1.9 | W37: 0.8 | X37: 34 | AB37: EFICIÊNCIA DA BOMBA | AC37: 0.7
K38: 35 | L38: 450000 | U38: 7 | V38: 2.4 | W38: 1 | X38: 35 | AB38: POTÊNCIA TEÓRICA DA BOMBA (W) | AC38: =AC19*(((AC28^2)/2)+(9.81*AD10)+(AC35)) -> #DIV/0! | AD38: w
K39: 36 | L39: 499998 | U39: 8.5 | V39: 2.9 | W39: 1.2 | X39: 36 | AB39: POTÊNCIA DE ACIONAMENTO (W) | AC39: =AC38/AC37 -> #DIV/0! | AD39: w
K40: 37 | L40: 550002 | U40: 10.2 | V40: 3.5 | W40: 1.5 | X40: 37
K41: 38 | L41: 600000 | U41: 12 | V41: 4.1 | W41: 1.75 | X41: 38
K42: 39 | L42: 649998 | U42: 14.5 | V42: 4.8 | W42: 2 | X42: 39
K43: 40 | L43: 700002 | U43: 16 | V43: 5.7 | W43: 2.3 | X43: 40
K44: 41 | L44: 750000 | V44: 8.4 | W44: 2.6 | X44: 41
K45: 42 | L45: 799998 | V45: 7.1 | W45: 3 | X45: 42

Sheet Adubação
C1: CORREÇÃO E ADUBAÇÃO
B3: Cadastro de áreas para utilizar
B5: Identificação | C5: Área (ha) | D5: Lotação (U.A/ha) | E5: V% | F5: M% | G5: CTC (cmol/dm³) | H5: % K/CTC (K/T) | I5: Ca (cmol/dm³) | J5: Mg (cmol/dm³) | K5: P (mg/dm³) | L5: Argila (g/kg) | M5: Dias capim verde
B12: Calagem | F12: =SUM(F15:F19) -> 0 | H12: =SUM(H15:H19) -> 0
B14: V% desejado | C14: PRNT Calcário (%) | D14: N.C. (ton/ha) | E14: Calcário | F14: Total (ton) | G14: R$/ton | H14: R$ Total | I14: R$/ha | J14: Recomendação
D15: =IF(OR(B6=0,B6=""),"",IF(ROUND(IFERROR(IF(((Adubação!$B15-E6)*G6)/Adubação!$C15<0,0,((Adubação!$B15-E6)*G6)/Adubação!$C15),"S/ infos"),1)<1,0,ROUND(IFERROR(IF(((Adubação!$B15-E6)*G6)/Adubação!$C15<0,0,((Adubação!$B15-E6)*G6)/Adubação!$C15),"S/ infos"),1))) | E15: =IFERROR(IF((I6/J6)>=3,"Dolomítico",IF((I6/J6)<=3,"Magnesiano","")),"") | F15: =IF(OR(B6=0,B6=""),"",ROUND(IFERROR((D15*C6),""),1)) | H15: =IFERROR(G15*F15,0) -> 0 | I15: =IFERROR(Adubação!$H15/C6,0) -> 0 | J15: =IF(Adubação!$D15="","",IF(Adubação!$F15=0,"Não precisa de calcário.",IF(Adubação!$D15>2,"Se o pasto já estiver formado, distribuir apenas 2 Ton/hectare de Calcário "&Adubação!$E15&". Se for incorporar, distribuir "&Adubação!$D15&" ton/ha. Pelo menos 60 dias antes do plantio ou das chuvas.","Distribuir "&Adubação!$D15&" Ton/hectare de Calcário "&Adubação!$E15&" pelo menos 60 dias antes do plantio ou início das chuvas.")))
