Workbook

Sheet CHUVAS
A1: ENTENDENDO O CLIMA
A2: Analisar o clima é fundamental para entender por quanto tempo seu sistema poderá ser utilizado de forma
A3: intensiva. Como a proposta desse treinamento é para que você aproveite o máximo possível o período
A4: do verão/chuvas, essa etapa vai direcionar todo o potencial do seu projeto. Quanto menos tempo disponível
A5: para intensificar, mais vocêterá que produzir, para garantir alta produção em curto espaço de tempo.
A7: Mês | B7: C° min | C7: C° Máx | D7: mm | F7: Resultado
A8: Jan | E8: > | F8: =IF(D8="","",IF(Q8=30,"Chuva",IF(Q8=0,"Seca",IF(Q8=20,"Chuva -1",IF(Q8=10,"Transição",0))))) | G8: =IF(OR(B8="",C8=""),"",IF(S8=1,"Verão",IF(S8=0,"Inverno",IF(S8=0.5,"Transição",IF(S8=0.75,"Transição",0))))) | H8: =IF(OR(F8="",G8=""),"",IF(AND(G8="Verão",F8="Chuva"),"Ok","Cuidado")) | Q8: =IF(D8="","",IF(D8>=150,30,IF(AND(D8>=120,D8<150),20,IF(AND(D8>=60,D8<120),10,0)))) | R8: =IF(OR(B8="",C8=""),"",AVERAGE(B8:C8)) | S8: =IF(R8="","",IF(AND(R8<=19,R8>=17),0.5,IF(R8<16,0,IF(AND(R8>19,R8<20),0.75,IF(R8>19,1,0))))) | T8: =IF(S8="","", S8*Q8)
A9: Fev | E9: > | F9: =IF(D9="","",IF(Q9=30,"Chuva",IF(Q9=0,"Seca",IF(Q9=20,"Chuva -1",IF(Q9=10,"Transição",0))))) | G9: =IF(OR(B9="",C9=""),"",IF(S9=1,"Verão",IF(S9=0,"Inverno",IF(S9=0.5,"Transição",IF(S9=0.75,"Transição",0))))) | H9: =IF(OR(F9="",G9=""),"",IF(AND(G9="Verão",F9="Chuva"),"Ok","Cuidado")) | Q9: =IF(D9="","",IF(D9>=150,30,IF(AND(D9>=120,D9<150),20,IF(AND(D9>=60,D9<120),10,0)))) | R9: =IF(OR(B9="",C9=""),"",AVERAGE(B9:C9)) | S9: =IF(R9="","",IF(AND(R9<=19,R9>=17),0.5,IF(R9<16,0,IF(AND(R9>19,R9<20),0.75,IF(R9>19,1,0))))) | T9: =IF(S9="","", S9*Q9)
A10: Mar | E10: > | F10: =IF(D10="","",IF(Q10=30,"Chuva",IF(Q10=0,"Seca",IF(Q10=20,"Chuva -1",IF(Q10=10,"Transição",0))))) | G10: =IF(OR(B10="",C10=""),"",IF(S10=1,"Verão",IF(S10=0,"Inverno",IF(S10=0.5,"Transição",IF(S10=0.75,"Transição",0))))) | H10: =IF(OR(F10="",G10=""),"",IF(AND(G10="Verão",F10="Chuva"),"Ok","Cuidado")) | Q10: =IF(D10="","",IF(D10>=150,30,IF(AND(D10>=120,D10<150),20,IF(AND(D10>=60,D10<120),10,0)))) | R10: =IF(OR(B10="",C10=""),"",AVERAGE(B10:C10)) | S10: =IF(R10="","",IF(AND(R10<=19,R10>=17),0.5,IF(R10<16,0,IF(AND(R10>19,R10<20),0.75,IF(R10>19,1,0))))) | T10: =IF(S10="","", S10*Q10)
A11: Abr | E11: > | F11: =IF(D11="","",IF(Q11=30,"Chuva",IF(Q11=0,"Seca",IF(Q11=20,"Chuva -1",IF(Q11=10,"Transição",0))))) | G11: =IF(OR(B11="",C11=""),"",IF(S11=1,"Verão",IF(S11=0,"Inverno",IF(S11=0.5,"Transição",IF(S11=0.75,"Transição",0))))) | H11: =IF(OR(F11="",G11=""),"",IF(AND(G11="Verão",F11="Chuva"),"Ok","Cuidado")) | Q11: =IF(D11="","",IF(D11>=150,30,IF(AND(D11>=120,D11<150),20,IF(AND(D11>=60,D11<120),10,0)))) | R11: =IF(OR(B11="",C11=""),"",AVERAGE(B11:C11)) | S11: =IF(R11="","",IF(AND(R11<=19,R11>=17),0.5,IF(R11<16,0,IF(AND(R11>19,R11<20),0.75,IF(R11>19,1,0))))) | T11: =IF(S11="","", S11*Q11)
A12: Mai | E12: > | F12: =IF(D12="","",IF(Q12=30,"Chuva",IF(Q12=0,"Seca",IF(Q12=20,"Chuva -1",IF(Q12=10,"Transição",0))))) | G12: =IF(OR(B12="",C12=""),"",IF(S12=1,"Verão",IF(S12=0,"Inverno",IF(S12=0.5,"Transição",IF(S12=0.75,"Transição",0))))) | H12: =IF(OR(F12="",G12=""),"",IF(AND(G12="Verão",F12="Chuva"),"Ok","Cuidado")) | Q12: =IF(D12="","",IF(D12>=150,30,IF(AND(D12>=120,D12<150),20,IF(AND(D12>=60,D12<120),10,0)))) | R12: =IF(OR(B12="",C12=""),"",AVERAGE(B12:C12)) | S12: =IF(R12="","",IF(AND(R12<=19,R12>=17),0.5,IF(R12<16,0,IF(AND(R12>19,R12<20),0.75,IF(R12>19,1,0))))) | T12: =IF(S12="","", S12*Q12)
A13: Jun | E13: > | F13: =IF(D13="","",IF(Q13=30,"Chuva",IF(Q13=0,"Seca",IF(Q13=20,"Chuva -1",IF(Q13=10,"Transição",0))))) | G13: =IF(OR(B13="",C13=""),"",IF(S13=1,"Verão",IF(S13=0,"Inverno",IF(S13=0.5,"Transição",IF(S13=0.75,"Transição",0))))) | H13: =IF(OR(F13="",G13=""),"",IF(AND(G13="Verão",F13="Chuva"),"Ok","Cuidado")) | Q13: =IF(D13="","",IF(D13>=150,30,IF(AND(D13>=120,D13<150),20,IF(AND(D13>=60,D13<120),10,0)))) | R13: =IF(OR(B13="",C13=""),"",AVERAGE(B13:C13)) | S13: =IF(R13="","",IF(AND(R13<=19,R13>=17),0.5,IF(R13<16,0,IF(AND(R13>19,R13<20),0.75,IF(R13>19,1,0))))) | T13: =IF(S13="","", S13*Q13)
A14: Jul | E14: > | F14: =IF(D14="","",IF(Q14=30,"Chuva",IF(Q14=0,"Seca",IF(Q14=20,"Chuva -1",IF(Q14=10,"Transição",0))))) | G14: =IF(OR(B14="",C14=""),"",IF(S14=1,"Verão",IF(S14=0,"Inverno",IF(S14=0.5,"Transição",IF(S14=0.75,"Transição",0))))) | H14: =IF(OR(F14="",G14=""),"",IF(AND(G14="Verão",F14="Chuva"),"Ok","Cuidado")) | Q14: =IF(D14="","",IF(D14>=150,30,IF(AND(D14>=120,D14<150),20,IF(AND(D14>=60,D14<120),10,0)))) | R14: =IF(OR(B14="",C14=""),"",AVERAGE(B14:C14)) | S14: =IF(R14="","",IF(AND(R14<=19,R14>=17),0.5,IF(R14<16,0,IF(AND(R14>19,R14<20),0.75,IF(R14>19,1,0))))) | T14: =IF(S14="","", S14*Q14)
A15: Ago | E15: > | F15: =IF(D15="","",IF(Q15=30,"Chuva",IF(Q15=0,"Seca",IF(Q15=20,"Chuva -1",IF(Q15=10,"Transição",0))))) | G15: =IF(OR(B15="",C15=""),"",IF(S15=1,"Verão",IF(S15=0,"Inverno",IF(S15=0.5,"Transição",IF(S15=0.75,"Transição",0))))) | H15: =IF(OR(F15="",G15=""),"",IF(AND(G15="Verão",F15="Chuva"),"Ok","Cuidado")) | Q15: =IF(D15="","",IF(D15>=150,30,IF(AND(D15>=120,D15<150),20,IF(AND(D15>=60,D15<120),10,0)))) | R15: =IF(OR(B15="",C15=""),"",AVERAGE(B15:C15)) | S15: =IF(R15="","",IF(AND(R15<=19,R15>=17),0.5,IF(R15<16,0,IF(AND(R15>19,R15<20),0.75,IF(R15>19,1,0))))) | T15: =IF(S15="","", S15*Q15)
A16: Set | E16: > | F16: =IF(D16="","",IF(Q16=30,"Chuva",IF(Q16=0,"Seca",IF(Q16=20,"Chuva -1",IF(Q16=10,"Transição",0))))) | G16: =IF(OR(B16="",C16=""),"",IF(S16=1,"Verão",IF(S16=0,"Inverno",IF(S16=0.5,"Transição",IF(S16=0.75,"Transição",0))))) | H16: =IF(OR(F16="",G16=""),"",IF(AND(G16="Verão",F16="Chuva"),"Ok","Cuidado")) | Q16: =IF(D16="","",IF(D16>=150,30,IF(AND(D16>=120,D16<150),20,IF(AND(D16>=60,D16<120),10,0)))) | R16: =IF(OR(B16="",C16=""),"",AVERAGE(B16:C16)) | S16: =IF(R16="","",IF(AND(R16<=19,R16>=17),0.5,IF(R16<16,0,IF(AND(R16>19,R16<20),0.75,IF(R16>19,1,0))))) | T16: =IF(S16="","", S16*Q16)
A17: Out | E17: > | F17: =IF(D17="","",IF(Q17=30,"Chuva",IF(Q17=0,"Seca",IF(Q17=20,"Chuva -1",IF(Q17=10,"Transição",0))))) | G17: =IF(OR(B17="",C17=""),"",IF(S17=1,"Verão",IF(S17=0,"Inverno",IF(S17=0.5,"Transição",IF(S17=0.75,"Transição",0))))) | H17: =IF(OR(F17="",G17=""),"",IF(AND(G17="Verão",F17="Chuva"),"Ok","Cuidado")) | Q17: =IF(D17="","",IF(D17>=150,30,IF(AND(D17>=120,D17<150),20,IF(AND(D17>=60,D17<120),10,0)))) | R17: =IF(OR(B17="",C17=""),"",AVERAGE(B17:C17)) | S17: =IF(R17="","",IF(AND(R17<=19,R17>=17),0.5,IF(R17<16,0,IF(AND(R17>19,R17<20),0.75,IF(R17>19,1,0))))) | T17: =IF(S17="","", S17*Q17)
A18: Nov | E18: > | F18: =IF(D18="","",IF(Q18=30,"Chuva",IF(Q18=0,"Seca",IF(Q18=20,"Chuva -1",IF(Q18=10,"Transição",0))))) | G18: =IF(OR(B18="",C18=""),"",IF(S18=1,"Verão",IF(S18=0,"Inverno",IF(S18=0.5,"Transição",IF(S18=0.75,"Transição",0))))) | H18: =IF(OR(F18="",G18=""),"",IF(AND(G18="Verão",F18="Chuva"),"Ok","Cuidado")) | Q18: =IF(D18="","",IF(D18>=150,30,IF(AND(D18>=120,D18<150),20,IF(AND(D18>=60,D18<120),10,0)))) | R18: =IF(OR(B18="",C18=""),"",AVERAGE(B18:C18)) | S18: =IF(R18="","",IF(AND(R18<=19,R18>=17),0.5,IF(R18<16,0,IF(AND(R18>19,R18<20),0.75,IF(R18>19,1,0))))) | T18: =IF(S18="","", S18*Q18)
A19: Dez | E19: > | F19: =IF(D19="","",IF(Q19=30,"Chuva",IF(Q19=0,"Seca",IF(Q19=20,"Chuva -1",IF(Q19=10,"Transição",0))))) | G19: =IF(OR(B19="",C19=""),"",IF(S19=1,"Verão",IF(S19=0,"Inverno",IF(S19=0.5,"Transição",IF(S19=0.75,"Transição",0))))) | H19: =IF(OR(F19="",G19=""),"",IF(AND(G19="Verão",F19="Chuva"),"Ok","Cuidado")) | Q19: =IF(D19="","",IF(D19>=150,30,IF(AND(D19>=120,D19<150),20,IF(AND(D19>=60,D19<120),10,0)))) | R19: =IF(OR(B19="",C19=""),"",AVERAGE(B19:C19)) | S19: =IF(R19="","",IF(AND(R19<=19,R19>=17),0.5,IF(R19<16,0,IF(AND(R19>19,R19<20),0.75,IF(R19>19,1,0))))) | T19: =IF(S19="","", S19*Q19)
A20: Total | B20: =IFERROR(AVERAGE(B8:B19),"") | C20: =IFERROR(AVERAGE(C8:C19),"") | D20: =SUM(D8:D19) -> 0
A22: Para propriedades que possuem inverno mais rigoroso, a planilha não está considerando o período
A23: de inverno como um período disponível para acúmulo de forragem. Caso você faça sobresemeadura
A24: de plantas de inverno, seu período de uso poderá ser maior. No entanto, o foco ainda é no verão.
A39: Dias disponíveis para intensificação: | E39: ="de "&COUNTIFS(H8:H19,"Ok")*30&" a "&SUM(T8:T19)&" dias disponíveis." -> de 0 a 0 dias disponíveis.
A40: Lotação aproximada LIMITE: | E40: ="de "&COUNTIFS(H8:H19,"Ok")&" a "&ROUND(SUM(T8:T19)/30,0)&" U.A/ha na época das chuvas." -> de 0 a 0 U.A/ha na época das chuvas.

Sheet Metas
B1: PLANILHA PARA PLANEJAMENTO DE METAS
E3: AVISOS
B4: SISTEMA
B5: Qnt. Cabeças | E5: =IF(C5<=250,"Quantas cabeças quer rodar nesse sistema? (no máximo 250 por lote).","REDUZIR TAMANHO DO LOTE, SEJA POR REDUÇÃO NA ÁREA OU DIMINUINDO A META DE LOTAÇÃO!") -> Quantas cabeças quer rodar nesse sistema? (no máximo 250 por lote).
B6: Peso de entrada (kg) | E6: Quanto maior esse peso, maior vai ser a lotação média e mais vai gastar com adubação. Porém, um animal que entra leve pode não ter peso de saída adequado no final do período.
B7: Dias de capim verde | D7: =C7/30 -> 0 | E7: Essa informação foi levantada no diagnóstico. Se não se lembra, volte as aulas.
B8: Peso de saída (kg) | E8: Garanta que com esse peso seu animal tenha mercado para venda, entrada no confinamento ou qualquer outra ação para aliviar pasto.
B9: GMD (kg/dia) | C9: =IF(C8="","",IFERROR((C8-C6)/C7,"")) | E9: O GMD tem que ser suficiente para que o animal tenha peso de saída no final do periodo. Não recomendo ultrapassar demais 1 kg/dia.
B10: Data de entrada | E10: Tente aproveitar o máximo possível do período de chuva. Para isso, tenha certeza que essa data está próximo ao início da estação de capim verde. Pode iniciar no final da seca se tiver massa.
B11: Data de saída | C11: =IFERROR(((C8-C6)/C9)+C10,"") | E11: A sua região tem que ter chuva suficiente para ter capim verde (ou em transição para a seca) ainda nessa data. Caso não tenha, diminua o período ou aumente o GMD para garantir que o animal saia antes.
B12: Área disponível (ha) | E12: Quantos hectares quer disponibilizar para esse sistema? Caso não saiba, vá ajustando o tamanho da área e o tamanho do lote de acordo com a lotação.
B13: Cabeças/ha | C13: =IFERROR(C5/C12,"")
B14: Lotação entrada (U.A/ha) | C14: =IFERROR((C13*C6)/450,"") | E14: =IF(C14="","",IF(C14>4,"Cuidado, essa lotação de entrada está alta. Para que ela aconteça, o capim já deve estar alto no início do período, ou com uma boa fertilidade inicial.","Ok"))
B15: Lotação média (U.A/ha) | C15: =IFERROR(AVERAGE(C14,C16),"") | E15: =IF(C15="","",IF(C15>ROUND(C7/30.3,0),"Pelo período de chuva disponível em sua região, você não conseguirá intensificar nesse nível. Diminua a meta de produção ou aumente os dias de capim verde (se for possível). Seu limite é de "&ROUND(C7/30.3,0)&" U.A/ha",IF(C15>5,"Cuidado, essa lotação média está alta. Recomendo que seu rotacionado tenha pelo menos 8 piquetes para aproveitar melhor o capim. Você aprenderá isso na aula sobre rotacionado.","Ok")))
B16: Lotação saída (U.A/ha) | C16: =IFERROR((C13*C8)/450,"") | E16: =IF(C16="","",IF(C16>6,"Cuidado, essa lotação de saída está alta. Garanta que seus animais tenham o GMD necessário para sair até final de chuva, já que provavelmente não será possível usar esse pasto na seca","Ok"))
B18: FINANCEIRO
B19: R$/@ compra | E19: Quanto está pagando na @ dos animais que rodarão no sistema (coloque mesmo que você já tenha os animais).
B20: R$/@ venda | E20: Quanto receberá pela @ desse animal na hora da venda? Caso não saiba, use o preço de hoje. Você também pode usar esse campo para simular uma possível queda.
B21: Desembolso (R$/cab/mês) | E21: Quanto você PODE gastar por cabeça/mês durante esse período? Vá simulando até chegar no máximo possível, analisando o custo operacional e total logo abaixo.
B22: R$ compra do lote | C22: =(C6/30)*C5*C19 -> 0
B23: R$ compra por cabeça | C23: =IFERROR(C22/C5,0) -> 0
B24: Custo operacional total | C24: =(C7/30)*C5*C21 -> 0 | E24: Esse valor engloba o custo operacional, exceto compra de animais. Ele varia de acordo com o "Desembolso R$/cab/mês"
B25: Custo operacional/cab | C25: =IFERROR(C24/C5,0) -> 0 | E25: Esse valor significa quanto você gastará por cabeça para desenvolver ela nesse sistema. Esse valor varia de acordo com o "Desembolso R$/cab/mês"
B26: Custo operacional/ha | C26: =IFERROR(C24/C12,0) -> 0 | E26: Esse valor significa quanto você gastará por hectare para desenvolver ela nesse sistema. Esse valor varia de acordo com o "Desembolso R$/cab/mês".
B27: Custo total total | C27: =(C22+C24) -> 0 | E27: Esse é o valor gasto total, considerando compra de animais + operacional. Varia de acordo com o "Desembolso R$/cab/mês", e a compra de animais, que depende de: quantidade de cabeças, peso e R$/@.
B28: Custo total/cab | C28: =IFERROR(C27/C5,0) -> 0 | E28: Esse valor significa quanto custará seu animal no final do sistema (compra de animais + operacional)
B29: Custo total/ha | C29: =IFERROR(C27/C12,0) -> 0 | E29: Esse valor significa quanto você irá investir por hectare (compra de animais + operacional)
B30: Faturamento total | C30: =(C8/30)*C5*C20 -> 0 | E30: Esse é o valor que irá receber depois que vender os animais no final do sistema.
B31: Faturamento/cab | C31: =IFERROR(C30/C5,0) -> 0 | E31: Valor que irá receber por cada animal.
B32: Faturamento/ha | C32: =IFERROR(C30/C12,0) -> 0 | E32: Valor que irá receber por hectare.
B33: Margem total | C33: =C30-C27 -> 0 | E33: Esse valor sobrará no seu bolso no final do período, após a venda dos animais, caso tudo ocorra como planejado.
B34: Margem/cab | C34: =IFERROR(C33/C5,0) -> 0 | E34: Esse valor significa quanto cada cabeça deu de lucro no período.
B35: Margem/ha | C35: =IFERROR(C33/C12,0) -> 0 | E35: Esse valor significa quanto você terá de lucro por hectare. O pecuarista médio brasileiro tem em torno de R$650/ha/ano
B36: Rentabilidade a.m | C36: =IFERROR((C33/C27)/D7,0) -> 0 | E36: Essa é a rentabilidade AO MÊS do seu sistema. Sempre compare com a taxa de juros atual do Brasil. Se estiver acima da taxa de juros, é porque está sendo um bom negócio.
B38: ZOOTÉCNICO
B39: @ produzidas | C39: =((C8-C6)/30)*C5 -> 0
B40: @ produzidas/hectare | C40: =IFERROR(C39/C12,0) -> 0 | E40: A média brasileira é de 6 @/ha por ano.
B41: Custo da @ produzida | C41: =IFERROR(C24/C39,0) -> 0
B43: Ao lado você tem uma simulação de como seu rotacionado irá se comportar. Isso não é garantia de resultado, mas sim o objetivo que você precisa alcançar. | E43: Data | F43: =C10 -> 0 | G43: =IF(F43="","",IF(F43=$C$11,"",IF(F43+30>$C$11,$C$11,F43+30))) -> 30 | H43: =IF(G43="","",IF(G43=$C$11,"",IF(G43+30>$C$11,$C$11,G43+30))) -> 60 | I43: =IF(H43="","",IF(H43=$C$11,"",IF(H43+30>$C$11,$C$11,H43+30))) -> 90 | J43: =IF(I43="","",IF(I43=$C$11,"",IF(I43+30>$C$11,$C$11,I43+30))) -> 120 | K43: =IF(J43="","",IF(J43=$C$11,"",IF(J43+30>$C$11,$C$11,J43+30))) -> 150 | L43: =IF(K43="","",IF(K43=$C$11,"",IF(K43+30>$C$11,$C$11,K43+30))) -> 180 | M43: =IF(L43="","",IF(L43=$C$11,"",IF(L43+30>$C$11,$C$11,L43+30))) -> 210 | N43: =IF(M43="","",IF(M43=$C$11,"",IF(M43+30>$C$11,$C$11,M43+30))) -> 240 | ... Q43: =IF(P43="","",IF(P43=$C$11,"",IF(P43+30>$C$11,$C$11,P43+30))) -> 330
E44: Peso médio | F44: =C6 -> 0 | G44: =IFERROR(F44+((G43-F43)*$C$9),"") | H44: =IFERROR(G44+((H43-G43)*$C$9),"") | I44: =IFERROR(H44+((I43-H43)*$C$9),"") | J44: =IFERROR(I44+((J43-I43)*$C$9),"") | K44: =IFERROR(J44+((K43-J43)*$C$9),"") | L44: =IFERROR(K44+((L43-K43)*$C$9),"") | M44: =IFERROR(L44+((M43-L43)*$C$9),"") | N44: =IFERROR(M44+((N43-M43)*$C$9),"") | ... Q44: =IFERROR(P44+((Q43-P43)*$C$9),"")
E45: Lotação (U.A/ha) | F45: =IFERROR((F44/450)*$C$13,"") | G45: =IFERROR((G44/450)*$C$13,"") | H45: =IFERROR((H44/450)*$C$13,"") | I45: =IFERROR((I44/450)*$C$13,"") | J45: =IFERROR((J44/450)*$C$13,"") | K45: =IFERROR((K44/450)*$C$13,"") | L45: =IFERROR((L44/450)*$C$13,"") | M45: =IFERROR((M44/450)*$C$13,"") | ... Q45: =IFERROR((Q44/450)*$C$13,"")
E46: @ produzidas | G46: =IFERROR(((G44-F44)/30)*$C$13,"") | H46: =IFERROR(((H44-G44)/30)*$C$13,"") | I46: =IFERROR(((I44-H44)/30)*$C$13,"") | J46: =IFERROR(((J44-I44)/30)*$C$13,"") | K46: =IFERROR(((K44-J44)/30)*$C$13,"") | L46: =IFERROR(((L44-K44)/30)*$C$13,"") | M46: =IFERROR(((M44-L44)/30)*$C$13,"") | N46: =IFERROR(((N44-M44)/30)*$C$13,"") | ... Q46: =IFERROR(((Q44-P44)/30)*$C$13,"")
E47: Saldo de @ produzidas | G47: =IFERROR(IF(G46="","",F47+G46),"") | H47: =IFERROR(IF(H46="","",G47+H46),"") | I47: =IFERROR(IF(I46="","",H47+I46),"") | J47: =IFERROR(IF(J46="","",I47+J46),"") | K47: =IFERROR(IF(K46="","",J47+K46),"") | L47: =IFERROR(IF(L46="","",K47+L46),"") | M47: =IFERROR(IF(M46="","",L47+M46),"") | N47: =IFERROR(IF(N46="","",M47+N46),"") | ... Q47: =IFERROR(IF(Q46="","",P47+Q46),"")

Sheet Adubação
C1: CORREÇÃO E ADUBAÇÃO
B3: Cadastro de áreas para utilizar
B5: Identificação | C5: Área (ha) | D5: Lotação (U.A/ha) | E5: V% | F5: M% | G5: CTC (cmol/dm³) | H5: % K/CTC (K/T) | I5: Ca (cmol/dm³) | J5: Mg (cmol/dm³) | K5: P (mg/dm³) | L5: Argila (g/kg) | M5: Dias capim verde
B12: Calagem | F12: =SUM(F15:F19) -> 0 | H12: =SUM(H15:H19) -> 0
B14: V% desejado | C14: PRNT Calcário (%) | D14: N.C. (ton/ha) | E14: Calcário | F14: Total (ton) | G14: R$/ton | H14: R$ Total | I14: R$/ha | J14: Recomendação
D15: =IF(OR(B6=0,B6=""),"",IF(ROUND(IFERROR(IF(((Adubação!$B15-E6)*G6)/Adubação!$C15<0,0,((Adubação!$B15-E6)*G6)/Adubação!$C15),"S/ infos"),1)<1,0,ROUND(IFERROR(IF(((Adubação!$B15-E6)*G6)/Adubação!$C15<0,0,((Adubação!$B15-E6)*G6)/Adubação!$C15),"S/ infos"),1))) | E15: =IFERROR(IF((I6/J6)>=3,"Dolomítico",IF((I6/J6)<=3,"Magnesiano","")),"") | F15: =IF(OR(B6=0,B6=""),"",ROUND(IFERROR((D15*C6),""),1)) | H15: =IFERROR(G15*F15,0) -> 0 | I15: =IFERROR(Adubação!$H15/C6,0) -> 0 | J15: =IF(Adubação!$D15="","",IF(Adubação!$F15=0,"Não precisa de calcário.",IF(Adubação!$D15>2,"Se o pasto já estiver formado, distribuir apenas 2 Ton/hectare de Calcário "&Adubação!$E15&". Se for incorporar, distribuir "&Adubação!$D15&" ton/ha. Pelo menos 60 dias antes do plantio ou das chuvas.","Distribuir "&Adubação!$D15&" Ton/hectare de Calcário "&Adubação!$E15&" pelo menos 60 dias antes do plantio ou início das chuvas.")))
D16: =IF(OR(B7=0,B7=""),"",IF(ROUND(IFERROR(IF(((Adubação!$B16-E7)*G7)/Adubação!$C16<0,0,((Adubação!$B16-E7)*G7)/Adubação!$C16),"S/ infos"),1)<1,0,ROUND(IFERROR(IF(((Adubação!$B16-E7)*G7)/Adubação!$C16<0,0,((Adubação!$B16-E7)*G7)/Adubação!$C16),"S/ infos"),1))) | E16: =IFERROR(IF((I7/J7)>=3,"Dolomítico",IF((I7/J7)<=3,"Magnesiano","")),"") | F16: =IF(OR(B7=0,B7=""),"",ROUND(IFERROR((D16*C7),""),1)) | H16: =IFERROR(G16*F16,0) -> 0 | I16: =IFERROR(Adubação!$H16/C7,0) -> 0 | J16: =IF(Adubação!$D16="","",IF(Adubação!$F16=0,"Não precisa de calcário.",IF(Adubação!$D16>2,"Se o pasto já estiver formado, distribuir apenas 2 Ton/hectare de Calcário "&Adubação!$E16&". Se for incorporar, distribuir "&Adubação!$D16&" ton/ha. Pelo menos 60 dias antes do plantio ou das chuvas.","Distribuir "&Adubação!$D16&" Ton/hectare de Calcário "&Adubação!$E16&" pelo menos 60 dias antes do plantio ou início das chuvas.")))
D17: =IF(OR(B8=0,B8=""),"",IF(ROUND(IFERROR(IF(((Adubação!$B17-E8)*G8)/Adubação!$C17<0,0,((Adubação!$B17-E8)*G8)/Adubação!$C17),"S/ infos"),1)<1,0,ROUND(IFERROR(IF(((Adubação!$B17-E8)*G8)/Adubação!$C17<0,0,((Adubação!$B17-E8)*G8)/Adubação!$C17),"S/ infos"),1))) | E17: =IFERROR(IF((I8/J8)>=3,"Dolomítico",IF((I8/J8)<=3,"Magnesiano","")),"") | F17: =IF(OR(B8=0,B8=""),"",ROUND(IFERROR((D17*C8),""),1)) | H17: =IFERROR(G17*F17,0) -> 0 | I17: =IFERROR(Adubação!$H17/C8,0) -> 0 | J17: =IF(Adubação!$D17="","",IF(Adubação!$F17=0,"Não precisa de calcário.",IF(Adubação!$D17>2,"Se o pasto já estiver formado, distribuir apenas 2 Ton/hectare de Calcário "&Adubação!$E17&". Se for incorporar, distribuir "&Adubação!$D17&" ton/ha. Pelo menos 60 dias antes do plantio ou das chuvas.","Distribuir "&Adubação!$D17&" Ton/hectare de Calcário "&Adubação!$E17&" pelo menos 60 dias antes do plantio ou início das chuvas.")))
D18: =IF(OR(B9=0,B9=""),"",IF(ROUND(IFERROR(IF(((Adubação!$B18-E9)*G9)/Adubação!$C18<0,0,((Adubação!$B18-E9)*G9)/Adubação!$C18),"S/ infos"),1)<1,0,ROUND(IFERROR(IF(((Adubação!$B18-E9)*G9)/Adubação!$C18<0,0,((Adubação!$B18-E9)*G9)/Adubação!$C18),"S/ infos"),1))) | E18: =IFERROR(IF((I9/J9)>=3,"Dolomítico",IF((I9/J9)<=3,"Magnesiano","")),"") | F18: =IF(OR(B9=0,B9=""),"",ROUND(IFERROR((D18*C9),""),1)) | H18: =IFERROR(G18*F18,0) -> 0 | I18: =IFERROR(Adubação!$H18/C9,0) -> 0 | J18: =IF(Adubação!$D18="","",IF(Adubação!$F18=0,"Não precisa de calcário.",IF(Adubação!$D18>2,"Se o pasto já estiver formado, distribuir apenas 2 Ton/hectare de Calcário "&Adubação!$E18&". Se for incorporar, distribuir "&Adubação!$D18&" ton/ha. Pelo menos 60 dias antes do plantio ou das chuvas.","Distribuir "&Adubação!$D18&" Ton/hectare de Calcário "&Adubação!$E18&" pelo menos 60 dias antes do plantio ou início das chuvas.")))
D19: =IF(OR(B10=0,B10=""),"",IF(ROUND(IFERROR(IF(((Adubação!$B19-E10)*G10)/Adubação!$C19<0,0,((Adubação!$B19-E10)*G10)/Adubação!$C19),"S/ infos"),1)<1,0,ROUND(IFERROR(IF(((Adubação!$B19-E10)*G10)/Adubação!$C19<0,0,((Adubação!$B19-E10)*G10)/Adubação!$C19),"S/ infos"),1))) | E19: =IFERROR(IF((I10/J10)>=3,"Dolomítico",IF((I10/J10)<=3,"Magnesiano","")),"") | F19: =IF(OR(B10=0,B10=""),"",ROUND(IFERROR((D19*C10),""),1)) | H19: =IFERROR(G19*F19,0) -> 0 | I19: =IFERROR(Adubação!$H19/C10,0) -> 0 | J19: =IF(Adubação!$D19="","",IF(Adubação!$F19=0,"Não precisa de calcário.",IF(Adubação!$D19>2,"Se o pasto já estiver formado, distribuir apenas 2 Ton/hectare de Calcário "&Adubação!$E19&". Se for incorporar, distribuir "&Adubação!$D19&" ton/ha. Pelo menos 60 dias antes do plantio ou das chuvas.","Distribuir "&Adubação!$D19&" Ton/hectare de Calcário "&Adubação!$E19&" pelo menos 60 dias antes do plantio ou início das chuvas.")))
B20: *se não encontrar o calcário correto que foi recomendado pela planilha, a segunda opção é calcário dolomítico, terceira magnesiano e quarta calcítico.
B22: Nitrogênio | F22: =SUM(F25:F29) -> 0 | H22: =SUM(H25:H29) -> 0
B24: % N na fonte | C24: Nome da fonte | D24: Rec. Kg/ha | E24: Ajustado (kg/ha) | F24: Total (ton) | G24: R$/kg | H24: R$ Total | I24: R$/ha | J24: Recomendação
D25: =IFERROR((IF(D6<=5,40,50))*D6/B25,"Falta %N") -> Falta %N | F25: =IFERROR(IF(OR(B$6=0,B$6=""),"",ROUND(IFERROR(((E25*C$6)/1000),""),1)),"") | H25: =IF(G25="","0",IFERROR(G25*E25*C6,"Falta R$/kg")) -> 0 | I25: =IFERROR(Adubação!$H25/C6,0) -> 0 | J25: =IF(Adubação!$D25=0,"",IF(Adubação!$E25>0,IFERROR("Parcelar a adubação em "&I30&" vezes, durante o período da chuva, sendo uma aplicação a cada "&ROUND(Adubação!M6/I30,0)&" dias, aplicando "&J30&" kg/ha de "&C25&" por aplicação.","Informações incompletas para gerar o relatório."),IFERROR("Parcelar a adubação em "&IF(#REF!>180,4,3)&" vezes, durante o período da chuva, aplicando "&ROUND(IF(#REF!>180,D25/4,D25/3),0)&" kg/ha de "&C25&" por aplicação.","Informações incompletas para gerar o relatório."))) -> Informações incompletas para gerar o relatório.
D26: =IFERROR((IF(D7<=5,40,50))*D7/B26,"Falta %N") -> Falta %N | F26: =IFERROR(IF(OR(B$6=0,B$6=""),"",ROUND(IFERROR(((E26*C$6)/1000),""),1)),"") | H26: =IF(G26="","0",IFERROR(G26*E26*C7,"Falta R$/kg")) -> 0 | I26: =IFERROR(Adubação!$H26/C7,0) -> 0 | J26: =IF(Adubação!$D26=0,"",IF(Adubação!$E26>0,IFERROR("Parcelar a adubação em "&I31&" vezes, durante o período da chuva, sendo uma aplicação a cada "&ROUND(Adubação!M7/I31,0)&" dias, aplicando "&J31&" kg/ha de "&C26&" por aplicação.","Informações incompletas para gerar o relatório."),IFERROR("Parcelar a adubação em "&IF(#REF!>180,4,3)&" vezes, durante o período da chuva, aplicando "&ROUND(IF(#REF!>180,D26/4,D26/3),0)&" kg/ha de "&C26&" por aplicação.","Informações incompletas para gerar o relatório."))) -> Informações incompletas para gerar o relatório.
D27: =IFERROR((IF(D8<=5,40,50))*D8/B27,"Falta %N") -> Falta %N | F27: =IFERROR(IF(OR(B$6=0,B$6=""),"",ROUND(IFERROR(((E27*C$6)/1000),""),1)),"") | H27: =IF(G27="","0",IFERROR(G27*E27*C8,"Falta R$/kg")) -> 0 | I27: =IFERROR(Adubação!$H27/C8,0) -> 0 | J27: =IF(Adubação!$D27=0,"",IF(Adubação!$E27>0,IFERROR("Parcelar a adubação em "&I32&" vezes, durante o período da chuva, sendo uma aplicação a cada "&ROUND(Adubação!M8/I32,0)&" dias, aplicando "&J32&" kg/ha de "&C27&" por aplicação.","Informações incompletas para gerar o relatório."),IFERROR("Parcelar a adubação em "&IF(#REF!>180,4,3)&" vezes, durante o período da chuva, aplicando "&ROUND(IF(#REF!>180,D27/4,D27/3),0)&" kg/ha de "&C27&" por aplicação.","Informações incompletas para gerar o relatório."))) -> Informações incompletas para gerar o relatório.
D28: =IFERROR((IF(D9<=5,40,50))*D9/B28,"Falta %N") -> Falta %N | F28: =IFERROR(IF(OR(B$6=0,B$6=""),"",ROUND(IFERROR(((E28*C$6)/1000),""),1)),"") | H28: =IF(G28="","0",IFERROR(G28*E28*C9,"Falta R$/kg")) -> 0 | I28: =IFERROR(Adubação!$H28/C9,0) -> 0 | J28: =IF(Adubação!$D28=0,"",IF(Adubação!$E28>0,IFERROR("Parcelar a adubação em "&I33&" vezes, durante o período da chuva, sendo uma aplicação a cada "&ROUND(Adubação!M9/I33,0)&" dias, aplicando "&J33&" kg/ha de "&C28&" por aplicação.","Informações incompletas para gerar o relatório."),IFERROR("Parcelar a adubação em "&IF(#REF!>180,4,3)&" vezes, durante o período da chuva, aplicando "&ROUND(IF(#REF!>180,D28/4,D28/3),0)&" kg/ha de "&C28&" por aplicação.","Informações incompletas para gerar o relatório."))) -> Informações incompletas para gerar o relatório.
D29: =IFERROR((IF(D10<=5,40,50))*D10/B29,"Falta %N") -> Falta %N | F29: =IFERROR(IF(OR(B$6=0,B$6=""),"",ROUND(IFERROR(((E29*C$6)/1000),""),1)),"") | H29: =IF(G29="","0",IFERROR(G29*E29*C10,"Falta R$/kg")) -> 0 | I29: =IFERROR(Adubação!$H29/C10,0) -> 0 | J29: =IF(Adubação!$D29=0,"",IF(Adubação!$E29>0,IFERROR("Parcelar a adubação em "&I34&" vezes, durante o período da chuva, sendo uma aplicação a cada "&ROUND(Adubação!M10/I34,0)&" dias, aplicando "&J34&" kg/ha de "&C29&" por aplicação.","Informações incompletas para gerar o relatório."),IFERROR("Parcelar a adubação em "&IF(#REF!>180,4,3)&" vezes, durante o período da chuva, aplicando "&ROUND(IF(#REF!>180,D29/4,D29/3),0)&" kg/ha de "&C29&" por aplicação.","Informações incompletas para gerar o relatório."))) -> Informações incompletas para gerar o relatório.
B30: *se você usar um formulado que tem potássio na sua composição, precisa ser descontado na hora da adubação de potássio. | I30: =ROUND((B25*D25)/50,0) -> #VALUE! | J30: =ROUNDUP((E25/I30),0) -> #VALUE!
B31: *para lotações acima de 5 U.A/ha, para cada 10 Kg de nitrogênio aplicado, distribuir 1 kg de Enxofre. | I31: =ROUND((B26*D26)/50,0) -> #VALUE! | J31: =ROUNDUP((E26/I31),0) -> #VALUE!
I32: =ROUND((B27*D27)/50,0) -> #VALUE! | J32: =ROUNDUP((E27/I32),0) -> #VALUE!
I33: =ROUND((B28*D28)/50,0) -> #VALUE! | J33: =ROUNDUP((E28/I33),0) -> #VALUE!
I34: =ROUND((B29*D29)/50,0) -> #VALUE! | J34: =ROUNDUP((E29/I34),0) -> #VALUE!
B37: Fósforo | F37: =SUM(F40:F44) -> 0 | H37: =SUM(H40:H44) -> 0
B39: %P fonte | C39: Nome da fonte | D39: Rec. Kg/ha | E39: Ajustado (kg/ha) | F39: Total (ton) | G39: R$/kg | H39: R$ Total | I39: R$/ha | J39: Recomendação
D40: =IF(B40="","Falta %P",IF(L6>300,(((MAX(0,(5+(2*D6)-K6)*10))/B40)*1.3),(MAX(0,(5+(2*D6)-K6)*10))/B40)) -> Falta %P | F40: =IFERROR(IF(OR(B$6=0,B$6=""),"",ROUND(IFERROR(((E40*C$6)/1000),""),1)),"") | H40: =IF(Adubação!$G40="",0,G40*E40*C6) -> 0 | I40: =IFERROR(IF(Adubação!$G40="",0,H40/C6),0) -> 0 | J40: =IF(OR(Adubação!$C40="",Adubação!$B40="",Adubação!$E40=""),"Informações incompletas para gerar o relatório.",IF(F6>=0.1,"Como o M% (Sat/Al) está alto, é preciso realizar a calagem obrigatoriamente antes da fosfatagem! De 60 a 90 dias (c/ chuva) após a calagem, distribuir "&E40&" kg/ha de "&C40&". Pode ser distribuído antes, junto ou logo depois da semente, no caso de reforma, ou por cobertura no pasto já formado.","Em reformas, distribuir antes, junto ou logo depois da semente. Em pasto formado, distribua em cobertura, no início do período das águas "&E40&" kg/ha de "&C40&".")) -> Informações incompletas para gerar o relatório.
D41: =IF(B41="","Falta %P",IF(L7>300,(((MAX(0,(5+(2*D7)-K7)*10))/B41)*1.3),(MAX(0,(5+(2*D7)-K7)*10))/B41)) -> Falta %P | F41: =IFERROR(IF(OR(B$6=0,B$6=""),"",ROUND(IFERROR(((E41*C$6)/1000),""),1)),"") | H41: =IF(Adubação!$G41="",0,G41*E41*C7) -> 0 | I41: =IFERROR(IF(Adubação!$G41="",0,H41/C7),0) -> 0 | J41: =IF(OR(Adubação!$C41="",Adubação!$B41="",Adubação!$E41=""),"Informações incompletas para gerar o relatório.",IF(F7>=0.1,"Como o M% (Sat/Al) está alto, é preciso realizar a calagem obrigatoriamente antes da fosfatagem! De 60 a 90 dias (c/ chuva) após a calagem, distribuir "&E41&" kg/ha de "&C41&". Pode ser distribuído antes, junto ou logo depois da semente, no caso de reforma, ou por cobertura no pasto já formado.","Em reformas, distribuir antes, junto ou logo depois da semente. Em pasto formado, distribua em cobertura, no início do período das águas "&E41&" kg/ha de "&C41&".")) -> Informações incompletas para gerar o relatório.
D42: =IF(B42="","Falta %P",IF(L8>300,(((MAX(0,(5+(2*D8)-K8)*10))/B42)*1.3),(MAX(0,(5+(2*D8)-K8)*10))/B42)) -> Falta %P | F42: =IFERROR(IF(OR(B$6=0,B$6=""),"",ROUND(IFERROR(((E42*C$6)/1000),""),1)),"") | H42: =IF(Adubação!$G42="",0,G42*E42*C8) -> 0 | I42: =IFERROR(IF(Adubação!$G42="",0,H42/C8),0) -> 0 | J42: =IF(OR(Adubação!$C42="",Adubação!$B42="",Adubação!$E42=""),"Informações incompletas para gerar o relatório.",IF(F8>=0.1,"Como o M% (Sat/Al) está alto, é preciso realizar a calagem obrigatoriamente antes da fosfatagem! De 60 a 90 dias (c/ chuva) após a calagem, distribuir "&E42&" kg/ha de "&C42&". Pode ser distribuído antes, junto ou logo depois da semente, no caso de reforma, ou por cobertura no pasto já formado.","Em reformas, distribuir antes, junto ou logo depois da semente. Em pasto formado, distribua em cobertura, no início do período das águas "&E42&" kg/ha de "&C42&".")) -> Informações incompletas para gerar o relatório.
D43: =IF(B43="","Falta %P",IF(L9>300,(((MAX(0,(5+(2*D9)-K9)*10))/B43)*1.3),(MAX(0,(5+(2*D9)-K9)*10))/B43)) -> Falta %P | F43: =IFERROR(IF(OR(B$6=0,B$6=""),"",ROUND(IFERROR(((E43*C$6)/1000),""),1)),"") | H43: =IF(Adubação!$G43="",0,G43*E43*C9) -> 0 | I43: =IFERROR(IF(Adubação!$G43="",0,H43/C9),0) -> 0 | J43: =IF(OR(Adubação!$C43="",Adubação!$B43="",Adubação!$E43=""),"Informações incompletas para gerar o relatório.",IF(F9>=0.1,"Como o M% (Sat/Al) está alto, é preciso realizar a calagem obrigatoriamente antes da fosfatagem! De 60 a 90 dias (c/ chuva) após a calagem, distribuir "&E43&" kg/ha de "&C43&". Pode ser distribuído antes, junto ou logo depois da semente, no caso de reforma, ou por cobertura no pasto já formado.","Em reformas, distribuir antes, junto ou logo depois da semente. Em pasto formado, distribua em cobertura, no início do período das águas "&E43&" kg/ha de "&C43&".")) -> Informações incompletas para gerar o relatório.
D44: =IF(B44="","Falta %P",IF(L10>300,(((MAX(0,(5+(2*D10)-K10)*10))/B44)*1.3),(MAX(0,(5+(2*D10)-K10)*10))/B44)) -> Falta %P | F44: =IFERROR(IF(OR(B$6=0,B$6=""),"",ROUND(IFERROR(((E44*C$6)/1000),""),1)),"") | H44: =IF(Adubação!$G44="",0,G44*E44*C10) -> 0 | I44: =IFERROR(IF(Adubação!$G44="",0,H44/C10),0) -> 0 | J44: =IF(OR(Adubação!$C44="",Adubação!$B44="",Adubação!$E44=""),"Informações incompletas para gerar o relatório.",IF(F10>=0.1,"Como o M% (Sat/Al) está alto, é preciso realizar a calagem obrigatoriamente antes da fosfatagem! De 60 a 90 dias (c/ chuva) após a calagem, distribuir "&E44&" kg/ha de "&C44&". Pode ser distribuído antes, junto ou logo depois da semente, no caso de reforma, ou por cobertura no pasto já formado.","Em reformas, distribuir antes, junto ou logo depois da semente. Em pasto formado, distribua em cobertura, no início do período das águas "&E44&" kg/ha de "&C44&".")) -> Informações incompletas para gerar o relatório.
B45: *se for usar um adubo de rápida liberação, como por exemplo o MAP, é recomendável parcelar quando a recomendação for acima de 300kg/ha. Em 2x é suficiente, sendo uma no início e outra no meio da chuva.
B47: Potássio | F47: =SUM(F50:F54) -> 0 | H47: =SUM(H50:H54) -> 0
B49: %K fonte | C49: Nome da fonte | D49: Kg/ha | E49: Ajustado (kg/ha) | F49: Total (ton) | G49: R$/kg | H49: R$ Total | I49: R$/ha | J49: Recomendação
D50: =IF(B50="","Falta %K", IFERROR((IF((3+(D6-1)*0.6-H6)*(G6/10)*100<0,0,(3+(D6-1)*0.6-H6)*(G6/10)*100))/B50,0)) -> Falta %K | F50: =IFERROR(IF(OR(B$6=0,B$6=""),"",ROUND(IFERROR(((E50*C$6)/1000),""),1)),"") | H50: =IF(Adubação!$G50="",0,IFERROR((G50*E50*C6),"Falta Kg/ha")) -> 0 | I50: =IF(Adubação!$G50="",0,IFERROR(G50*D50,0)) -> 0 | J50: =IF(AND(Adubação!$E50="",Adubação!$C50=""),"Informações incompletas para gerar o relatório.",IF(Adubação!$E50="Falta %K","Informações incompletas para gerar o relatório.",IF(Adubação!$E50=0,"Não precisa realizar adubação de potássio",IF(Adubação!$E50<=120,"Parcelar a adubação em 2x de "&ROUND(Adubação!$E50/2,0)&"kg/ha de "&Adubação!$C50&" em períodos equidistantes na época da chuva. Se possível, adubar próximo a adubação de N.",IF(AND(Adubação!$E50>120,Adubação!$E50<=240),"Parcelar a adubação em 3x de "&ROUND(Adubação!$E50/3,0)&"kg/ha de "&Adubação!$C50&" em períodos equidistantes na época da chuva. Se possível, adubar próximo a adubação de N.","Parcelar a adubação em 4x de "&ROUND(Adubação!$E50/4,0)&"kg/ha de "&Adubação!$C50&" em períodos equidistantes na época da chuva. Se possível, adubar próximo a adubação de N."))))) -> Informações incompletas para gerar o relatório.
D51: =IF(B51="","Falta %K", IFERROR((IF((3+(D7-1)*0.6-H7)*(G7/10)*100<0,0,(3+(D7-1)*0.6-H7)*(G7/10)*100))/B51,0)) -> Falta %K | F51: =IFERROR(IF(OR(B$6=0,B$6=""),"",ROUND(IFERROR(((E51*C$6)/1000),""),1)),"") | H51: =IF(Adubação!$G51="",0,IFERROR((G51*E51*C7),"Falta Kg/ha")) -> 0 | I51: =IF(Adubação!$G51="",0,IFERROR(G51*D51,0)) -> 0 | J51: =IF(AND(Adubação!$E51="",Adubação!$C51=""),"Informações incompletas para gerar o relatório.",IF(Adubação!$E51="Falta %K","Informações incompletas para gerar o relatório.",IF(Adubação!$E51=0,"Não precisa realizar adubação de potássio",IF(Adubação!$E51<=120,"Parcelar a adubação em 2x de "&ROUND(Adubação!$E51/2,0)&"kg/ha de "&Adubação!$C51&" em períodos equidistantes na época da chuva. Se possível, adubar próximo a adubação de N.",IF(AND(Adubação!$E51>120,Adubação!$E51<=240),"Parcelar a adubação em 3x de "&ROUND(Adubação!$E51/3,0)&"kg/ha de "&Adubação!$C51&" em períodos equidistantes na época da chuva. Se possível, adubar próximo a adubação de N.","Parcelar a adubação em 4x de "&ROUND(Adubação!$E51/4,0)&"kg/ha de "&Adubação!$C51&" em períodos equidistantes na época da chuva. Se possível, adubar próximo a adubação de N."))))) -> Informações incompletas para gerar o relatório.
D52: =IF(B52="","Falta %K", IFERROR((IF((3+(D8-1)*0.6-H8)*(G8/10)*100<0,0,(3+(D8-1)*0.6-H8)*(G8/10)*100))/B52,0)) -> Falta %K | F52: =IFERROR(IF(OR(B$6=0,B$6=""),"",ROUND(IFERROR(((E52*C$6)/1000),""),1)),"") | H52: =IF(Adubação!$G52="",0,IFERROR((G52*E52*C8),"Falta Kg/ha")) -> 0 | I52: =IF(Adubação!$G52="",0,IFERROR(G52*D52,0)) -> 0 | J52: =IF(AND(Adubação!$E52="",Adubação!$C52=""),"Informações incompletas para gerar o relatório.",IF(Adubação!$E52="Falta %K","Informações incompletas para gerar o relatório.",IF(Adubação!$E52=0,"Não precisa realizar adubação de potássio",IF(Adubação!$E52<=120,"Parcelar a adubação em 2x de "&ROUND(Adubação!$E52/2,0)&"kg/ha de "&Adubação!$C52&" em períodos equidistantes na época da chuva. Se possível, adubar próximo a adubação de N.",IF(AND(Adubação!$E52>120,Adubação!$E52<=240),"Parcelar a adubação em 3x de "&ROUND(Adubação!$E52/3,0)&"kg/ha de "&Adubação!$C52&" em períodos equidistantes na época da chuva. Se possível, adubar próximo a adubação de N.","Parcelar a adubação em 4x de "&ROUND(Adubação!$E52/4,0)&"kg/ha de "&Adubação!$C52&" em períodos equidistantes na época da chuva. Se possível, adubar próximo a adubação de N."))))) -> Informações incompletas para gerar o relatório.
D53: =IF(B53="","Falta %K", IFERROR((IF((3+(D9-1)*0.6-H9)*(G9/10)*100<0,0,(3+(D9-1)*0.6-H9)*(G9/10)*100))/B53,0)) -> Falta %K | F53: =IFERROR(IF(OR(B$6=0,B$6=""),"",ROUND(IFERROR(((E53*C$6)/1000),""),1)),"") | H53: =IF(Adubação!$G53="",0,IFERROR((G53*E53*C9),"Falta Kg/ha")) -> 0 | I53: =IF(Adubação!$G53="",0,IFERROR(G53*D53,0)) -> 0 | J53: =IF(AND(Adubação!$E53="",Adubação!$C53=""),"Informações incompletas para gerar o relatório.",IF(Adubação!$E53="Falta %K","Informações incompletas para gerar o relatório.",IF(Adubação!$E53=0,"Não precisa realizar adubação de potássio",IF(Adubação!$E53<=120,"Parcelar a adubação em 2x de "&ROUND(Adubação!$E53/2,0)&"kg/ha de "&Adubação!$C53&" em períodos equidistantes na época da chuva. Se possível, adubar próximo a adubação de N.",IF(AND(Adubação!$E53>120,Adubação!$E53<=240),"Parcelar a adubação em 3x de "&ROUND(Adubação!$E53/3,0)&"kg/ha de "&Adubação!$C53&" em períodos equidistantes na época da chuva. Se possível, adubar próximo a adubação de N.","Parcelar a adubação em 4x de "&ROUND(Adubação!$E53/4,0)&"kg/ha de "&Adubação!$C53&" em períodos equidistantes na época da chuva. Se possível, adubar próximo a adubação de N."))))) -> Informações incompletas para gerar o relatório.
D54: =IF(B54="","Falta %K", IFERROR((IF((3+(D10-1)*0.6-H10)*(G10/10)*100<0,0,(3+(D10-1)*0.6-H10)*(G10/10)*100))/B54,0)) -> Falta %K | F54: =IFERROR(IF(OR(B$6=0,B$6=""),"",ROUND(IFERROR(((E54*C$6)/1000),""),1)),"") | H54: =IF(Adubação!$G54="",0,IFERROR((G54*E54*C10),"Falta Kg/ha")) -> 0 | I54: =IF(Adubação!$G54="",0,IFERROR(G54*D54,0)) -> 0 | J54: =IF(AND(Adubação!$E54="",Adubação!$C54=""),"Informações incompletas para gerar o relatório.",IF(Adubação!$E54="Falta %K","Informações incompletas para gerar o relatório.",IF(Adubação!$E54=0,"Não precisa realizar adubação de potássio",IF(Adubação!$E54<=120,"Parcelar a adubação em 2x de "&ROUND(Adubação!$E54/2,0)&"kg/ha de "&Adubação!$C54&" em períodos equidistantes na época da chuva. Se possível, adubar próximo a adubação de N.",IF(AND(Adubação!$E54>120,Adubação!$E54<=240),"Parcelar a adubação em 3x de "&ROUND(Adubação!$E54/3,0)&"kg/ha de "&Adubação!$C54&" em períodos equidistantes na época da chuva. Se possível, adubar próximo a adubação de N.","Parcelar a adubação em 4x de "&ROUND(Adubação!$E54/4,0)&"kg/ha de "&Adubação!$C54&" em períodos equidistantes na época da chuva. Se possível, adubar próximo a adubação de N."))))) -> Informações incompletas para gerar o relatório.
B55: *pode acontecer de pedir muito potássio, caso a CTC do seu solo seja alta. Não precisa necessariamente corrigir todo o potássio em um ano só, pode trabalhar com um "limite" de 200 kg de K por ano.
B57: Micro nutrientes
B59: Recomendação
B60: Caso trabalhe com lotação acima de 5 U.A/ha, utilizar 50 kg/ha de FTE-BR12 a cada 2 anos.
B62: Gesso
B64: Recomendação
B65: =IF(L6="","Falta preencher informações da área",(50*(L6/10))/1000) -> Falta preencher informações da área
B66: =IF(L7="","Falta preencher informações da área",(50*(L7/10))/1000) -> Falta preencher informações da área
B67: =IF(L8="","Falta preencher informações da área",(50*(L8/10))/1000) -> Falta preencher informações da área
B68: =IF(L9="","Falta preencher informações da área",(50*(L9/10))/1000) -> Falta preencher informações da área
B69: =IF(L10="","Falta preencher informações da área",(50*(L10/10))/1000) -> Falta preencher informações da área
B71: Total | C71: =IFERROR(H50++H16+H17+H18+H19+H26+H27+H28+H29+H40+H25+H15+H41+H42+H43+H44+H51+H52+H53+H54,0) -> 0

Sheet Dimensionamento de água
B1: PLANILHA PARA DIMENSIONAMENTO DO SISTEMA DE ÁGUA
B3: INFORMAÇÕES DO SISTEMA | L3: L/H | M3: 25 | N3: 32 | O3: 40 | P3: 50 | Q3: 75 | R3: 100 | S3: 125 | T3: 150 | U3: 200 | V3: 250 | W3: 300 | AB3: DADOS GEOMÉTRICOS DA INSTALAÇÃO | AD3: L (m)
B4: Qnt. Cabeças | K4: 1 | L4: 498 | M4: 0.7 | N4: 0.2 | O4: 0 | X4: 1 | AB4: A | AD4: 0
B5: Tempo de bombeamento (horas) | K5: 2 | L5: 1002 | M5: 2.7 | N5: 0.75 | O5: 0.22 | P5: 0.08 | X5: 2 | AB5: B | AD5: 0
B6: Dias p/ manutenção | K6: 3 | L6: 1500 | M6: 6 | N6: 1.6 | O6: 0.5 | P6: 0.17 | X6: 3 | AB6: C | AD6: ='Dimensionamento de água'!C13 -> 0
B7: Potência bomba (cv) | C7: =ROUNDUP(AC39/735,0) -> #DIV/0! | K7: 4 | L7: 1998 | M7: 10 | N7: 2.7 | O7: 0.8 | P7: 0.28 | X7: 4 | AB7: D | AD7: ='Dimensionamento de água'!C14 -> 0
B8: Tamanho reservatório (L) | C8: =C6*C4*60 -> 0 | K8: 5 | L8: 3000 | M8: 21.5 | N8: 6 | O8: 1.8 | P8: 0.6 | Q8: 0.05 | X8: 5 | AB8: E | AD8: 3
K9: 6 | L9: 4002 | M9: 27 | N9: 10 | O9: 3 | P9: 1.05 | Q9: 0.1 | X9: 6 | AB9: F | AD9: 2
B10: LINHA DE CAPTAÇÃO | K10: 7 | L10: 4998 | M10: 55 | N10: 15.5 | O10: 4.7 | P10: 1.6 | Q10: 0.15 | R10: 0.05 | X10: 7 | AB10: H | AD10: =AD6+AD8+AD4 -> 3
B11: Altitude Inicial (m) | D11: =IFERROR(IF(C16=0,"Diminuir o diâmetro",IF(C17<=1.5,"Aumentar diâmetro ou altitude","Ok")),"Pode diminuir o diâmetro") -> Pode diminuir o diâmetro | K11: 8 | L11: 6000 | M11: 60 | N11: 22 | O11: 6.6 | P11: 2.2 | Q11: 0.2 | R11: 0.07 | X11: 8 | AB11: ACESSÓRIOS | AC11: QUANT. | AD11: L EQ (m)
B12: Altitude reservatório (m) | K12: 9 | L12: 7998 | N12: 37 | O12: 11.5 | P12: 3.9 | Q12: 0.35 | R12: 0.13 | X12: 9 | AB12: CURVA DE 90 graus | AC12: 4 | AD12: =AC12*((0.786*LN(AC21))-1.845) -> #NUM!
B13: Dif. Nível (m) | C13: =(C11-C12)*-1 -> 0 | K13: 10 | L13: 10002 | N13: 56 | O13: 17 | P13: 5.7 | Q13: 0.5 | R13: 0.2 | S13: 0.06 | X13: 10 | AB13: VÁLVULA DE RETENÇÃO | AC13: 1 | AD13: =AC13*(0.12449*AC21-0.01819) -> -0.01819
B14: Comprimento (m) | K14: 11 | L14: 12498 | N14: 85 | O14: 26 | P14: 8.5 | Q14: 0.8 | R14: 0.28 | S14: 0.09 | X14: 11 | AB14: VÁLVULA DE PÉ OU CRIVO | AC14: 1 | AD14: =AC14*(15.3311*LN(AC21)-36.98) -> #NUM!
B15: Diâmetro (mm) | K15: 12 | L15: 15000 | O15: 37 | P15: 12.5 | Q15: 1.1 | R15: 0.4 | S15: 0.13 | T15: 0.05 | X15: 12 | AB15: SAÍDA DA TUBULAÇÃO | AC15: 3 | AD15: =2.21*LN(AC21)-5.559 -> #NUM!
B16: Perda (m) | C16: =HLOOKUP(C15,'Dimensionamento de água'!$L$3:$W$45,VLOOKUP(VLOOKUP((C4*50)/C5,'Dimensionamento de água'!$L$4:$L$45,1,1),'Dimensionamento de água'!$L$4:$X$45,13,0)+2,0)*(C14/100) -> #DIV/0! | K16: 13 | L16: 17502 | O16: 47 | P16: 16 | Q16: 1.4 | R16: 0.5 | S16: 0.17 | T16: 0.06 | X16: 13 | AB16: REGISTRO DE GLOBO | AC16: 0 | AD16: =AC16*(0.3269*AC21+0.6384) -> 0
B17: Pressão final (MCA) | C17: =C13-C16 -> #DIV/0! | K17: 14 | L17: 19998 | O17: 63 | P17: 21.5 | Q17: 2 | R17: 0.7 | S17: 0.23 | T17: 0.09 | X17: 14 | AB17: REGISTRO DE GAVETA | AC17: 0 | AD17: =AC17*(0.5269*LN(AC21)-1.3735) -> #NUM!
B18: PN (mínimo) | C18: =(C17+C16)*1.3 -> #DIV/0! | K18: 15 | L18: 25002 | O18: 95 | P18: 33 | Q18: 3 | R18: 1.1 | S18: 0.35 | T18: 0.13 | X18: 15 | AB18: DADOS DO ESCOAMENTO
K19: 16 | L19: 30000 | P19: 45 | Q19: 4.2 | R19: 1.5 | S19: 0.5 | T19: 0.2 | U19: 0.05 | X19: 16 | AB19: VAZÃO DA BOMBA | AC19: =('Dimensionamento de água'!C4*50)/'Dimensionamento de água'!C5/60/60 -> #DIV/0! | AD19: LITROS/SEG
B20: LINHA DE DISTRIBUIÇÃO | K20: 17 | L20: 34998 | P20: 61 | Q20: 5.7 | R20: 2 | S20: 0.65 | T20: 0.24 | U20: 0.06 | X20: 17 | AB20: VAZÃO DA BOMBA | AC20: =AC19/1000 -> #DIV/0! | AD20: m³/s
B21: Altitude Inicial (m) | C21: =C12 -> 0 | D21: =IFERROR(IF(C26=0,"Corrigir o diâmetro",IF(C27<=1.5,"Aumentar diâmetro","Ok")),"Pode diminuir o diâmetro") -> Pode diminuir o diâmetro | K21: 18 | L21: 40002 | P21: 78 | Q21: 7 | R21: 2.5 | S21: 0.8 | T21: 0.3 | U21: 0.08 | X21: 18 | AB21: DIÂMETRO DA CANALIZAÇÃO | AC21: ='Dimensionamento de água'!C15 -> 0 | AD21: mm
B22: Altitude Final (m) | K22: 19 | L22: 45000 | P22: 100 | Q22: 9 | R22: 3.1 | S22: 1 | T22: 0.4 | U22: 0.1 | X22: 19 | AB22: DIÂMETRO DA CANALIZAÇÃO EM METROS | AC22: =AC21/1000 -> 0 | AD22: m
B23: Dif. Nível (m) | C23: =C21-C22 -> 0 | K23: 20 | L23: 49998 | Q23: 11 | R23: 3.8 | S23: 1.25 | T23: 0.5 | U23: 0.12 | X23: 20 | AB23: PROPRIEDADES DA ÁGUA
B24: Comprimento (m) | K24: 21 | L24: 60000 | Q24: 16 | R24: 5.5 | S24: 1.8 | T24: 0.7 | U24: 0.16 | V24: 0.05 | X24: 21 | AB24: VISCOSIDADE | AC24: 1.127e-06 | AD24: m²/s
B25: Diâmetro (mm) | K25: 22 | L25: 70002 | Q25: 21 | R25: 7.2 | S25: 2.4 | T25: 0.9 | U25: 0.21 | V25: 0.07 | X25: 22 | AB25: DENSIDADE | AC25: 1000 | AD25: kg/m³
B26: Perda (m) | C26: =HLOOKUP(C25,'Dimensionamento de água'!$L$3:$W$45,VLOOKUP(VLOOKUP((C4*50)/12,'Dimensionamento de água'!$L$4:$L$45,1,1),'Dimensionamento de água'!$L$4:$X$45,13,0)+2,0)*(C24/100) -> #N/A | K26: 23 | L26: 79998 | Q26: 26.5 | R26: 9.2 | S26: 3.1 | T26: 1.2 | U26: 0.27 | V26: 0.09 | X26: 23 | AB26: TEMPERATURA | AC26: 25 | AD26: oC
B27: Pressão final (MCA) | C27: =C23-C26 -> #N/A | K27: 24 | L27: 90000 | Q27: 34 | R27: 12 | S27: 3.8 | T27: 1.4 | U27: 0.35 | V27: 0.12 | X27: 24 | AB27: CÁLCULOS GERAIS
B28: PN (mínimo) | C28: =(C27+C26)*1.3 -> #N/A | K28: 25 | L28: 100002 | Q28: 40 | R28: 14 | S28: 4.7 | T28: 1.8 | U28: 0.42 | V28: 0.14 | X28: 25 | AB28: VELOCIDADE DO ESCOAMENTO | AC28: =AC20/AC29 -> #DIV/0! | AD28: m/s
K29: 26 | L29: 120000 | Q29: 58 | R29: 20 | S29: 6.6 | T29: 2.5 | U29: 0.6 | V29: 0.2 | W29: 0.08 | X29: 26 | AB29: ÁREA INTERNA DA TUBULAÇÃO | AC29: =(3.14*AC22^2)/4 -> 0 | AD29: m²
K30: 27 | L30: 139998 | Q30: 80 | R30: 27 | S30: 9 | T30: 3.3 | U30: 0.8 | V30: 0.26 | W30: 0.1 | X30: 27 | AB30: NÚMERO DE REYNOLDS | AC30: =AC28*AC22/0.000001127 -> #DIV/0!
B31: Tamanho bebedouro (m) | C31: =C4*0.05 -> 0 | K31: 28 | L31: 160002 | R31: 35 | S31: 11.5 | T31: 4.25 | U31: 1 | V31: 0.34 | W31: 0.13 | X31: 28 | AB31: FATOR DE ATRITO (D.MOODY) | AC31: =0.222554*AC30^-0.216968 -> #DIV/0!
B32: Se beber dos dois lados | C32: =C31/2 -> 0 | K32: 29 | L32: 180000 | R32: 43 | S32: 14 | T32: 5.3 | U32: 1.25 | V32: 0.42 | W32: 0.17 | X32: 29 | AB32: COMPRIMENTO DE TRECHO RETO DE TUBO | AC32: =AD4+AD5+AD6+AD7+AD8+AD9 -> 5 | AD32: m
K33: 30 | L33: 199998 | R33: 50 | S33: 17.5 | T33: 6.5 | U33: 1.5 | V33: 0.5 | W33: 0.2 | X33: 30 | AB33: COMPRIMENTO EQUIVALENTE DE TUBO | AC33: =AD12+AD13+AD14+AD15+AD16+AD17 -> #NUM! | AD33: m
K34: 31 | L34: 250002 | R34: 80 | S34: 26.5 | T34: 10 | U34: 2.3 | V34: 0.8 | W34: 0.32 | X34: 31 | AB34: COMPRIMENTO TOTAL DE TUBULAÇÃO | AC34: =AC32+AC33 -> #NUM! | AD34: m
K35: 32 | L35: 300000 | S35: 36 | T35: 14 | U35: 3.3 | V35: 1.1 | W35: 0.45 | X35: 32 | AB35: VARIAÇÃO DE ENERGIA (DELTA E) | AC35: =AC31*AC34*AC28*AC28/(2*AC22) -> #DIV/0! | AD35: m²/s²
K36: 33 | L36: 349998 | T36: 19 | U36: 4.5 | V36: 1.5 | W36: 0.6 | X36: 33 | AB36: ALTURA MANOMÉTRICA (m) | AC36: =(AC35/9.81)+AD10 -> #DIV/0! | AD36: m
K37: 34 | L37: 400002 | T37: 24 | U37: 5.8 | V37: 1.9 | W37: 0.8 | X37: 34 | AB37: EFICIÊNCIA DA BOMBA | AC37: 0.7
K38: 35 | L38: 450000 | U38: 7 | V38: 2.4 | W38: 1 | X38: 35 | AB38: POTÊNCIA TEÓRICA DA BOMBA (W) | AC38: =AC19*(((AC28^2)/2)+(9.81*AD10)+(AC35)) -> #DIV/0! | AD38: w
K39: 36 | L39: 499998 | U39: 8.5 | V39: 2.9 | W39: 1.2 | X39: 36 | AB39: POTÊNCIA DE ACIONAMENTO (W) | AC39: =AC38/AC37 -> #DIV/0! | AD39: w
K40: 37 | L40: 550002 | U40: 10.2 | V40: 3.5 | W40: 1.5 | X40: 37
K41: 38 | L41: 600000 | U41: 12 | V41: 4.1 | W41: 1.75 | X41: 38
K42: 39 | L42: 649998 | U42: 14.5 | V42: 4.8 | W42: 2 | X42: 39
K43: 40 | L43: 700002 | U43: 16 | V43: 5.7 | W43: 2.3 | X43: 40
K44: 41 | L44: 750000 | V44: 8.4 | W44: 2.6 | X44: 41
K45: 42 | L45: 799998 | V45: 7.1 | W45: 3 | X45: 42

Sheet Formulação de suplemento
C1: PLANILHA PARA FORMULAÇÃO DE SUPLEMENTOS PARA BOVINOS A PASTO
FD3: 180 | FN3: 300 | FW3: 300 | GO3: Categoria | GP3: Ingrediente | GQ3: MS (%) | GR3: EE (%MS) | GS3: PB (%MS) | GT3: NDT (%MS) | GU3: FDN (%MS) | GV3: Ca (%MS) | GW3: P (%MS) | GX3: Mg (%MS) | GY3: K (%MS) | GZ3: Na (%MS) | HA3: S (%MS) | HB3: Co (mg/kg) | HC3: Cu (mg/kg) | HD3: Mn (mg/kg) | HE3: Se (mg/kg) | HF3: Zn (mg/kg)
FD4: Exigência | FE4: Código | FF4: Unidade | FG4: Mínimo | FH4: Ideal | FI4: Máximo | FN4: Exigência | FO4: Código | FP4: Unidade | FQ4: Mínimo | FR4: Ideal | FS4: Máximo | FW4: Exigência | FX4: Código | FY4: Unidade | FZ4: Mínimo | GA4: Ideal | GB4: Máximo | GO4: Forragens Verdes | GP4: Cana-de-açúcar | GQ4: 27.53 | GR4: 1.46 | GS4: 2.86 | GT4: 63.48 | GU4: 49.49 | GV4: 0.24 | GW4: 0.08 | GX4: 0.18 | GY4: 0.68 | GZ4: 0.03 | HA4: 0.06 | HB4: 0.54 | HC4: 5.85 | HD4: 49.57 | HF4: 21.18
B5: INFORMAÇÕES P/ EXIGÊNCIA | E5: FORMULAÇÃO DO SUPLEMENTO | J5: EXIGÊNCIA x DIETA | R5: RESUMO DA DIETA GERAL | Z5: OUTRAS INFORMAÇÕES | AH5: Ingr | AK5: Capim | FD5: Matéria Seca | FE5: MS | FF5: kg/dia | FH5: 5.5 | FI5: 6.05 | FJ5: =FI5/FH5 -> 1.1 | FN5: Matéria Seca | FO5: MS | FP5: kg/dia | FR5: 6.85 | FS5: 7.53 | FT5: =FS5/FR5 -> 1.0992701 | FW5: Matéria Seca | FX5: MS | FY5: kg/dia | GA5: 6.85 | GB5: 7.53 | GC5: =GB5/GA5 -> 1.0992701 | GO5: Forragens Verdes | GP5: Capim Andropogon | GQ5: 25.55 | GR5: 2.15 | GS5: 4.49 | GT5: 53.56 | GU5: 70.13 | GV5: 0.04
B6: Peso inicial (kg) | E6: Ingrediente | F6: % | G6: R$/kg | H6: R$ | J6: Descrição | K6: Ideal | L6: Máximo | M6: Dieta | N6: Resultado | O6: % na dieta | P6: % ideal | R6: Alimentos | S6: M.O. (Kg) | T6: M.S. (Kg) | U6: % P.V | V6: % da dieta | W6: Consumo total/cab | X6: Consumo total | Z6: Descrição | AB6: Resultado | AF6: Ureia pelo NNP | AH6: %MS | AK6: MS | AL6: NDT | AM6: PB | FD6: Extrato Etéreo | FE6: EE | FF6: kg/dia | FI6: 0.39 | FJ6: =FI6/$FD$3 -> 0.0021666667 | FK6: =FI6/$FI$5 -> 0.06446281 | FN6: Extrato Etéreo | FO6: EE | FP6: kg/dia | FS6: 0.48 | FT6: =FS6/FN$3 -> 0.0016 | FU6: =FS6/FS$5 -> 0.06374502 | FW6: Extrato Etéreo | FX6: EE | FY6: kg/dia | GB6: 0.48 | GC6: =GB6/FW$3 -> 0.0016 | GD6: =GB6/GB$5 -> 0.06374502 | GO6: Forragens Verdes | GP6: Capim Braquiária Brizantha | GQ6: 34.09 | GR6: 1.96 | GS6: 6.91 | GT6: 56.68 | GU6: 63.84 | GV6: 0.31 | GW6: 0.11 | GX6: 0.41 | GY6: 1.65 | GZ6: 0.02 | HA6: 0.09 | HB6: 0.07 | HC6: 3.48 | HD6: 103.19 | HF6: 26.4
B7: Peso final (kg) | H7: =G7*F7 -> 0 | J7: Matéria seca (MS) | K7: =IF(C8="","",((ROUND(IF(C10="Zebuíno",-2.1948+0.08338*C8^0.75+3.9328*C9-0.903*C9^2,IF(C11="Corte",-0.6273+0.06453*C8^0.75+3.871*C9-0.614*C9^2,-2.8836+0.08435*C8^0.75+4.5145*C9-0.9631*C9^2)),2))*L25)+(ROUND(IF(C10="Zebuíno",-2.1948+0.08338*C8^0.75+3.9328*C9-0.903*C9^2,IF(C11="Corte",-0.6273+0.06453*C8^0.75+3.871*C9-0.614*C9^2,-2.8836+0.08435*C8^0.75+4.5145*C9-0.9631*C9^2)),2))) | L7: =IF(K7="","",(ROUND(IF(C10="Zebuíno",-2.1948+0.08338*C8^0.75+3.9328*C9-0.903*C9^2,IF(C11="Corte",-0.6273+0.06453*C8^0.75+3.871*C9-0.614*C9^2,-2.8836+0.08435*C8^0.75+4.5145*C9-0.9631*C9^2)),2))*1.1) | M7: =IFERROR(T21,0) -> 0 | N7: =IF(K7="","",IF(M7>L7,"Reduzir",IF(M7<K7,"Aumentar",IF(M7=K7,"Ok",IF(M7=L7,"Ok",IF(OR(M7>=K7,M7<=L7),"Ok")))))) | O7: =IF(M7=0,"", $T$21/M7) | P7: =IF(M7=0,"",K7/ $T$21) | R7: =IF(C18="","",C18) | S7: =IF(IFERROR((K7-(C8*C19*AH20))/VLOOKUP(C18,'Formulação de suplemento'!$B$29:$C$40,2,0),0)=0,"",IFERROR((K7-(C8*C19*AH20))/VLOOKUP(C18,'Formulação de suplemento'!$B$29:$C$40,2,0),0)) | T7: =IF(R7="","",IFERROR(S7*(VLOOKUP(R7,'Formulação de suplemento'!$B$29:$W$40,2,)),0)) | U7: =IFERROR(T7/$C$8,"") | V7: =IFERROR(T7/$T$21,"") | W7: =IFERROR(X7/$C$20,"") | X7: =IFERROR(S7*$C$16*$C$20,"") | Z7: Consumo de supl. diário/cab | AB7: =IFERROR(C19*C8,"") | AF7: =IFERROR(VLOOKUP(R7,'Formulação de suplemento'!$B$56:$W$68,22,0)*T7,"") | AH7: =IF(E7="Ureia",F7,IFERROR(VLOOKUP(E7,'Formulação de suplemento'!$B$43:$C$54,2,0)*F7,"")) | AK7: =VLOOKUP(R7,B29:E40,2,0) -> #N/A | AL7: =VLOOKUP(R7,B29:E40,3,0) -> #N/A | AM7: =VLOOKUP(R7,B29:E40,4,0) -> #N/A | AV7: 3 | AW7: =AV7+1 -> 4 | AX7: =AW7+1 -> 5 | AY7: =AX7+1 -> 6 | AZ7: =AY7+1 -> 7 | BA7: =AZ7+1 -> 8 | BB7: =BA7+1 -> 9 | BC7: =BB7+1 -> 10 | BD7: =BC7+1 -> 11 | ... BM7: =BL7+1 -> 20 | FD7: Carboidratos Não Fibrosos | FE7: CNF | FF7: kg/dia | FI7: 4.4 | FJ7: =FI7/$FD$3 -> 0.024444444 | FK7: =FI7/$FI$5 -> 0.72727273 | FN7: Carboidratos Não Fibrosos | FO7: CNF | FP7: kg/dia | FS7: 5.48 | FT7: =FS7/FN$3 -> 0.018266667 | FU7: =FS7/FS$5 -> 0.72775564 | FW7: Carboidratos Não Fibrosos | FX7: CNF | FY7: kg/dia | GB7: 5.48 | GC7: =GB7/FW$3 -> 0.018266667 | GD7: =GB7/GB$5 -> 0.72775564 | GO7: Forragens Verdes | GP7: Capim Braquiária Brizantha Marandu | GQ7: 33.24 | GR7: 1.95 | GS7: 7.68 | GT7: 55.52 | GU7: 64.15 | GV7: 0.28 | GW7: 0.09 | GX7: 0.1 | GY7: 0.72 | GZ7: 0.02 | HA7: 0.03 | HB7: 0.46 | HC7: 15 | HD7: 56 | HF7: 10
B8: Peso médio (kg) | C8: =IFERROR(AVERAGE(C6:C7),"") | H8: =G8*F8 -> 0 | J8: Extrato etéreo (EE) | K8: =IF(C8="","","Não consta") | L8: =IFERROR(L7*0.063,"") | M8: =BB24/1000 -> 0 | N8: =IF(L8="","",IF(M8>L8,"Reduzir","Ok")) | O8: =IF(M8=0,"", M8/$M$7) | P8: =IF(C8="","","Não consta") | R8: =IF(F7=0,"",IF(E7="","",E7)) | S8: =IF(IF(R8="","",F7*$AB$7)=0,"",IF(R8="","",F7*$AB$7)) | T8: =IF(R8="Ureia",S8,IF(S8="","",IFERROR(S8*(VLOOKUP(R8,'Formulação de suplemento'!$B$42:$W$54,2,)),0))) | U8: =IFERROR(T8/$C$8,"") | V8: =IFERROR(T8/$T$21,"") | W8: =IFERROR(X8/$C$20,"") | X8: =IFERROR(S8*$C$16*$C$20,"") | Z8: Consumo de supl. diário no lote | AB8: =IFERROR(AB7*C20,"") | AF8: =IFERROR(VLOOKUP(R8,'Formulação de suplemento'!$B$56:$W$68,22,0)*T8,"") | AH8: =IF(E8="Ureia",F8,IFERROR(VLOOKUP(E8,'Formulação de suplemento'!$B$43:$C$54,2,0)*F8,"")) | AV8: NDT (Kg) | AW8: P.B (Kg) | AX8: Ca (g) | AY8: P (g) | AZ8: PDR (kg) | BA8: FDN (kg) | BB8: EE (g) | BC8: Mg (g) | BD8: Na (g) | BE8: K (g) | BF8: S (g) | BG8: Cu (mg) | BH8: Zn (mg) | BI8: Fe (mg) | BJ8: Mn (mg) | BK8: I (mg) | BL8: Co (mg) | BM8: Se (mg) | FD8: Fibra em Detergente Neutro | FE8: FDN | FF8: kg/dia | FG8: 1.38 | FI8: 2.38 | FJ8: =FI8/$FD$3 -> 0.013222222 | FK8: =FI8/$FI$5 -> 0.39338843 | FL8: =FG8/FH5 -> 0.25090909 | FN8: Fibra em Detergente Neutro | FO8: FDN | FP8: kg/dia | FQ8: 1.71 | FS8: 3.96 | FT8: =FS8/FN$3 -> 0.0132 | FU8: =FS8/FS$5 -> 0.52589641 | FV8: =FQ8/FR5 -> 0.24963504 | FW8: Fibra em Detergente Neutro | FX8: FDN | FY8: kg/dia | FZ8: 1.71 | GB8: 3.96 | GC8: =GB8/FW$3 -> 0.0132 | GD8: =GB8/GB$5 -> 0.52589641 | GE8: =FZ8/GA5 -> 0.24963504 | GO8: Forragens Verdes | GP8: Capim Braquiária Decumbens | GQ8: 28.49 | GR8: 1.81 | GS8: 6.74 | GT8: 55.33 | GU8: 66.38 | GV8: 0.4 | GW8: 0.1 | GX8: 0.09 | GY8: 0.94 | GZ8: 0.01 | HA8: 0.04 | HB8: 0.28 | HC8: 3.8 | HD8: 85 | HF8: 28
B9: GMD (kg/cab/dia) | H9: =G9*F9 -> 0 | J9: FDN | K9: =IFERROR(ROUND(K7*0.25,2),"") | L9: =IF(C8="","",ROUND(C8*1.32%,2)) | M9: =BA24 -> 0 | N9: =IF(K9="","",IF(M9>L9,"Reduzir",IF(M9<K9,"Aumentar",IF(M9=K9,"Ok",IF(M9=L9,"Ok",IF(OR(M9>=K9,M9<=L9),"Ok")))))) | O9: =IF(M9=0,"", M9/$M$7) | P9: =IF(M9=0,"", K9/$T$21) | R9: =IF(F8=0,"",IF(E8="","",E8)) | S9: =IF(IF(R9="","",F8*$AB$7)=0,"",IF(R9="","",F8*$AB$7)) | T9: =IF(R9="Ureia",S9,IF(S9="","",IFERROR(S9*(VLOOKUP(R9,'Formulação de suplemento'!$B$42:$W$54,2,)),0))) | U9: =IFERROR(T9/$C$8,"") | V9: =IFERROR(T9/$T$21,"") | W9: =IFERROR(X9/$C$20,"") | X9: =IFERROR(S9*$C$16*$C$20,"") | Z9: Consumo de supl. total no período | AB9: =IFERROR(AB8*C16,"") | AF9: =IFERROR(VLOOKUP(R9,'Formulação de suplemento'!$B$56:$W$68,22,0)*T9,"") | AH9: =IF(E9="Ureia",F9,IFERROR(VLOOKUP(E9,'Formulação de suplemento'!$B$43:$C$54,2,0)*F9,"")) | AK9: %EF colheita | AV9: =IFERROR($T$7*(VLOOKUP($R$7,'Formulação de suplemento'!$B$29:$W$40,AV7,0)),0) -> 0 | AW9: =IFERROR($T$7*(VLOOKUP($R$7,'Formulação de suplemento'!$B$29:$W$40,AW7,0)),0) -> 0 | AX9: =IFERROR($T$7*(VLOOKUP($R$7,'Formulação de suplemento'!$B$29:$W$40,AX7,0)*1000),0) -> 0 | AY9: =IFERROR($T$7*(VLOOKUP($R$7,'Formulação de suplemento'!$B$29:$W$40,AY7,0)*1000),0) -> 0 | AZ9: =IFERROR($T$7*(VLOOKUP($R$7,'Formulação de suplemento'!$B$29:$W$40,AZ7,0)),0) -> 0 | BA9: =IFERROR($T$7*(VLOOKUP($R$7,'Formulação de suplemento'!$B$29:$W$40,BA7,0)),0) -> 0 | BB9: =IFERROR($T$7*(VLOOKUP($R$7,'Formulação de suplemento'!$B$29:$W$40,BB7,0)*1000),0) -> 0 | BC9: =IFERROR($T$7*(VLOOKUP($R$7,'Formulação de suplemento'!$B$29:$W$40,BC7,0)*1000),0) -> 0 | BD9: =IFERROR($T$7*(VLOOKUP($R$7,'Formulação de suplemento'!$B$29:$W$40,BD7,0)*1000),0) -> 0 | BE9: =IFERROR($T$7*(VLOOKUP($R$7,'Formulação de suplemento'!$B$29:$W$40,BE7,0)*1000),0) -> 0 | BF9: =IFERROR($T$7*(VLOOKUP($R$7,'Formulação de suplemento'!$B$29:$W$40,BF7,0)*1000),0) -> 0 | BG9: =IFERROR($T$7*(VLOOKUP($R$7,'Formulação de suplemento'!$B$29:$W$40,BG7,0)),0) -> 0 | BH9: =IFERROR($T$7*(VLOOKUP($R$7,'Formulação de suplemento'!$B$29:$W$40,BH7,0)),0) -> 0 | BI9: =IFERROR($T$7*(VLOOKUP($R$7,'Formulação de suplemento'!$B$29:$W$40,BI7,0)),0) -> 0 | BJ9: =IFERROR($T$7*(VLOOKUP($R$7,'Formulação de suplemento'!$B$29:$W$40,BJ7,0)),0) -> 0 | BK9: =IFERROR($T$7*(VLOOKUP($R$7,'Formulação de suplemento'!$B$29:$W$40,BK7,0)),0) -> 0 | BL9: =IFERROR($T$7*(VLOOKUP($R$7,'Formulação de suplemento'!$B$29:$W$40,BL7,0)),0) -> 0 | BM9: =IFERROR($T$7*(VLOOKUP($R$7,'Formulação de suplemento'!$B$29:$W$40,BM7,0)),0) -> 0 | FD9: FDN Fisicamente Efetiva | FE9: FDNfe | FF9: kg/dia | FG9: 2.45 | FI9: 6.2 | FJ9: =FI9/$FD$3 -> 0.034444444 | FK9: =FI9/$FI$5 -> 1.0247934 | FN9: FDN Fisicamente Efetiva | FO9: FDNfe | FP9: kg/dia | FQ9: 2.45 | FS9: 6.2 | FT9: =FS9/FN$3 -> 0.020666667 | FU9: =FS9/FS$5 -> 0.82337317 | FW9: FDN Fisicamente Efetiva | FX9: FDNfe | FY9: kg/dia | FZ9: 2.45 | GB9: 6.2 | GC9: =GB9/FW$3 -> 0.020666667 | GD9: =GB9/GB$5 -> 0.82337317 | GO9: Forragens Verdes | GP9: Capim Braquiária Humidícola | GQ9: 28.12 | GR9: 2.45 | GS9: 7.38 | GT9: 56.61 | GU9: 71.86 | GV9: 0.38 | GW9: 0.12 | GX9: 0.2 | GY9: 1.99 | GZ9: 0.02 | HA9: 0.04 | HB9: 0.09 | HC9: 13.32 | HD9: 93.82 | HF9: 19
B10: Raça | H10: =G10*F10 -> 0 | J10: NDT | K10: =IFERROR(IF(C8="","",ROUND(BJ90/4.4,2)),"") | L10: =IFERROR(K10*1.05,"") | M10: =AV24 -> 0 | N10: =IF(K10="","",IF(M10>L10,"Reduzir",IF(M10<K10,"Aumentar",IF(M10=K10,"Ok",IF(M10=L10,"Ok",IF(OR(M10>=K10,M10<=L10),"Ok")))))) | O10: =IF(M10=0,"", M10/$M$7) | P10: =IF(M10=0,"", K10/$T$21) | R10: =IF(F9=0,"",IF(E9="","",E9)) | S10: =IF(IF(R10="","",F9*$AB$7)=0,"",IF(R10="","",F9*$AB$7)) | T10: =IF(R10="Ureia",S10,IF(S10="","",IFERROR(S10*(VLOOKUP(R10,'Formulação de suplemento'!$B$42:$W$54,2,)),0))) | U10: =IFERROR(T10/$C$8,"") | V10: =IFERROR(T10/$T$21,"") | W10: =IFERROR(X10/$C$20,"") | X10: =IFERROR(S10*$C$16*$C$20,"") | Z10: Diária do suplemento (R$/cab) | AB10: =IFERROR(AB7*H23,"") | AF10: =IFERROR(VLOOKUP(R10,'Formulação de suplemento'!$B$56:$W$68,22,0)*T10,"") | AH10: =IF(E10="Ureia",F10,IFERROR(VLOOKUP(E10,'Formulação de suplemento'!$B$43:$C$54,2,0)*F10,"")) | AK10: Contínuo | AL10: 0.3 | FD10: Teor de Amido | FE10: AMIDO | FF10: kg/dia | FG10: 2.45 | FI10: 6.2 | FJ10: =FI10/$FD$3 -> 0.034444444 | FK10: =FI10/$FI$5 -> 1.0247934 | FN10: Teor de Amido | FO10: AMIDO | FP10: kg/dia | FQ10: 2.45 | FS10: 6.2 | FT10: =FS10/FN$3 -> 0.020666667 | FU10: =FS10/FS$5 -> 0.82337317 | FW10: Teor de Amido | FX10: AMIDO | FY10: kg/dia | FZ10: 2.45 | GB10: 6.2 | GC10: =GB10/FW$3 -> 0.020666667 | GD10: =GB10/GB$5 -> 0.82337317 | GO10: Forragens Verdes | GP10: Capim Gordura | GQ10: 27.72 | GR10: 1.3 | GS10: 6.92 | GT10: 56.68 | GU10: 72.29 | GV10: 0.24 | GW10: 0.07 | GX10: 0.14 | GY10: 0.67 | GZ10: 0.02
H11: =G11*F11 -> 0 | J11: Proteína Bruta (PB) | K11: =IFERROR(ROUND(((BN58-(BN59*0.64))/0.8)+BN60,1),"") | L11: =IFERROR(K11*1.1,"") | M11: =IFERROR(AW24*1000,0) -> 0 | N11: =IF(K11="","",IF(M11>L11,"Reduzir",IF(M11<K11,"Aumentar",IF(M11=K11,"Ok",IF(M11=L11,"Ok",IF(OR(M11>=K11,M11<=L11),"Ok")))))) | O11: =IF(M11=0,"",(M11/1000)/$T$21) | P11: =IF(M11=0,"",(K11/1000)/$T$21) | R11: =IF(F10=0,"",IF(E10="","",E10)) | S11: =IF(IF(R11="","",F10*$AB$7)=0,"",IF(R11="","",F10*$AB$7)) | T11: =IF(R11="Ureia",S11,IF(S11="","",IFERROR(S11*(VLOOKUP(R11,'Formulação de suplemento'!$B$42:$W$54,2,)),0))) | U11: =IFERROR(T11/$C$8,"") | V11: =IFERROR(T11/$T$21,"") | W11: =IFERROR(X11/$C$20,"") | X11: =IFERROR(S11*$C$16*$C$20,"") | Z11: Diária total (R$/cab) | AB11: =IFERROR((AB10+C21),"") | AF11: =IFERROR(VLOOKUP(R11,'Formulação de suplemento'!$B$56:$W$68,22,0)*T11,"") | AH11: =IF(E11="Ureia",F11,IFERROR(VLOOKUP(E11,'Formulação de suplemento'!$B$43:$C$54,2,0)*F11,"")) | AK11: Alternado | AL11: 0.5 | AV11: =IFERROR($T8*(VLOOKUP($R8,'Formulação de suplemento'!$B$42:$W$54,AV$7,0)),0) -> 0 | AW11: =IFERROR($T8*(VLOOKUP($R8,'Formulação de suplemento'!$B$42:$W$54,AW$7,0)),0) -> 0 | AX11: =IFERROR($T8*(VLOOKUP($R8,'Formulação de suplemento'!$B$42:$W$54,AX$7,0)*1000),0) -> 0 | AY11: =IFERROR($T8*(VLOOKUP($R8,'Formulação de suplemento'!$B$42:$W$54,AY$7,0)*1000),0) -> 0 | AZ11: =IFERROR($T8*(VLOOKUP($R8,'Formulação de suplemento'!$B$42:$W$54,AZ$7,0)),0) -> 0 | BA11: =IFERROR($T8*(VLOOKUP($R8,'Formulação de suplemento'!$B$42:$W$54,BA$7,0)),0) -> 0 | BB11: =IFERROR($T8*(VLOOKUP($R8,'Formulação de suplemento'!$B$42:$W$54,BB$7,0)*1000),0) -> 0 | BC11: =IFERROR($T8*(VLOOKUP($R8,'Formulação de suplemento'!$B$42:$W$54,BC$7,0)*1000),0) -> 0 | BD11: =IFERROR($T8*(VLOOKUP($R8,'Formulação de suplemento'!$B$42:$W$54,BD$7,0)*1000),0) -> 0 | BE11: =IFERROR($T8*(VLOOKUP($R8,'Formulação de suplemento'!$B$42:$W$54,BE$7,0)*1000),0) -> 0 | BF11: =IFERROR($T8*(VLOOKUP($R8,'Formulação de suplemento'!$B$42:$W$54,BF$7,0)*1000),0) -> 0 | BG11: =IFERROR($T8*(VLOOKUP($R8,'Formulação de suplemento'!$B$42:$W$54,BG$7,0)),0) -> 0 | BH11: =IFERROR($T8*(VLOOKUP($R8,'Formulação de suplemento'!$B$42:$W$54,BH$7,0)),0) -> 0 | BI11: =IFERROR($T8*(VLOOKUP($R8,'Formulação de suplemento'!$B$42:$W$54,BI$7,0)),0) -> 0 | BJ11: =IFERROR($T8*(VLOOKUP($R8,'Formulação de suplemento'!$B$42:$W$54,BJ$7,0)),0) -> 0 | BK11: =IFERROR($T8*(VLOOKUP($R8,'Formulação de suplemento'!$B$42:$W$54,BK$7,0)),0) -> 0 | BL11: =IFERROR($T8*(VLOOKUP($R8,'Formulação de suplemento'!$B$42:$W$54,BL$7,0)),0) -> 0 | BM11: =IFERROR($T8*(VLOOKUP($R8,'Formulação de suplemento'!$B$42:$W$54,BM$7,0)),0) -> 0 | FD11: Nutrientes Digestíveis Totais | FE11: NDT | FF11: kg/dia | FG11: 3.99 | FH11: 3.99 | FI11: 4.19 | FJ11: =FI11/FH11 -> 1.0501253 | FN11: Nutrientes Digestíveis Totais | FO11: NDT | FP11: kg/dia | FQ11: 4.23 | FR11: 4.23 | FS11: 4.45 | FT11: =FS11/FR11 -> 1.0520095 | FW11: Nutrientes Digestíveis Totais | FX11: NDT | FY11: kg/dia | FZ11: 4.35 | GA11: 4.35 | GB11: 4.56 | GC11: =GB11/GA11 -> 1.0482759 | GO11: Forragens Verdes | GP11: Capim Massai | GQ11: 29.48 | GR11: 2.06 | GS11: 7.99 | GT11: 56.2 | GU11: 70.02
B12: Sexo | H12: =G12*F12 -> 0 | J12: Cálcio (Ca) | K12: =IFERROR(ROUND(BJ116,1),"") | L12: =IFERROR(K12*2,"") | M12: =AX24 -> 0 | N12: =IF(K12="","",IF(M12>L12,"Reduzir",IF(M12<K12,"Aumentar",IF(M12=K12,"Ok",IF(M12=L12,"Ok",IF(OR(M12>=K12,M12<=L12),"Ok")))))) | O12: =IF(M12=0,"",(M12/1000)/$T$21) | P12: =IF(M12=0,"",(K12/1000)/$T$21) | R12: =IF(F11=0,"",IF(E11="","",E11)) | S12: =IF(IF(R12="","",F11*$AB$7)=0,"",IF(R12="","",F11*$AB$7)) | T12: =IF(R12="Ureia",S12,IF(S12="","",IFERROR(S12*(VLOOKUP(R12,'Formulação de suplemento'!$B$42:$W$54,2,)),0))) | U12: =IFERROR(T12/$C$8,"") | V12: =IFERROR(T12/$T$21,"") | W12: =IFERROR(X12/$C$20,"") | X12: =IFERROR(S12*$C$16*$C$20,"") | Z12: Desembolso (R$/cab/mês) | AB12: =IFERROR(AB11*30.4,"") | AF12: =IFERROR(VLOOKUP(R12,'Formulação de suplemento'!$B$56:$W$68,22,0)*T12,"") | AH12: =IF(E13="Ureia",F13,IFERROR(VLOOKUP(E13,'Formulação de suplemento'!$B$43:$C$54,2,0)*F13,"")) | AK12: Rotacionado | AL12: 0.7 | AV12: =IFERROR($T9*(VLOOKUP($R9,'Formulação de suplemento'!$B$42:$W$54,AV$7,0)),0) -> 0 | AW12: =IFERROR($T9*(VLOOKUP($R9,'Formulação de suplemento'!$B$42:$W$54,AW$7,0)),0) -> 0 | AX12: =IFERROR($T9*(VLOOKUP($R9,'Formulação de suplemento'!$B$42:$W$54,AX$7,0)*1000),0) -> 0 | AY12: =IFERROR($T9*(VLOOKUP($R9,'Formulação de suplemento'!$B$42:$W$54,AY$7,0)*1000),0) -> 0 | AZ12: =IFERROR($T9*(VLOOKUP($R9,'Formulação de suplemento'!$B$42:$W$54,AZ$7,0)),0) -> 0 | BA12: =IFERROR($T9*(VLOOKUP($R9,'Formulação de suplemento'!$B$42:$W$54,BA$7,0)),0) -> 0 | BB12: =IFERROR($T9*(VLOOKUP($R9,'Formulação de suplemento'!$B$42:$W$54,BB$7,0)*1000),0) -> 0 | BC12: =IFERROR($T9*(VLOOKUP($R9,'Formulação de suplemento'!$B$42:$W$54,BC$7,0)*1000),0) -> 0 | BD12: =IFERROR($T9*(VLOOKUP($R9,'Formulação de suplemento'!$B$42:$W$54,BD$7,0)*1000),0) -> 0 | BE12: =IFERROR($T9*(VLOOKUP($R9,'Formulação de suplemento'!$B$42:$W$54,BE$7,0)*1000),0) -> 0 | BF12: =IFERROR($T9*(VLOOKUP($R9,'Formulação de suplemento'!$B$42:$W$54,BF$7,0)*1000),0) -> 0 | BG12: =IFERROR($T9*(VLOOKUP($R9,'Formulação de suplemento'!$B$42:$W$54,BG$7,0)),0) -> 0 | BH12: =IFERROR($T9*(VLOOKUP($R9,'Formulação de suplemento'!$B$42:$W$54,BH$7,0)),0) -> 0 | BI12: =IFERROR($T9*(VLOOKUP($R9,'Formulação de suplemento'!$B$42:$W$54,BI$7,0)),0) -> 0 | BJ12: =IFERROR($T9*(VLOOKUP($R9,'Formulação de suplemento'!$B$42:$W$54,BJ$7,0)),0) -> 0 | BK12: =IFERROR($T9*(VLOOKUP($R9,'Formulação de suplemento'!$B$42:$W$54,BK$7,0)),0) -> 0 | BL12: =IFERROR($T9*(VLOOKUP($R9,'Formulação de suplemento'!$B$42:$W$54,BL$7,0)),0) -> 0 | BM12: =IFERROR($T9*(VLOOKUP($R9,'Formulação de suplemento'!$B$42:$W$54,BM$7,0)),0) -> 0 | FD12: Proteína Bruta | FE12: PB | FF12: g/dia | FG12: 686.93 | FH12: 686.93 | FI12: 755.63 | FJ12: =FI12/FH12 -> 1.1000102 | FN12: Proteína Bruta | FO12: PB | FP12: g/dia | FQ12: 777.14 | FR12: 777.14 | FS12: 854.85 | FT12: =FS12/FR12 -> 1.0999949 | FW12: Proteína Bruta | FX12: PB | FY12: g/dia | FZ12: 754.82 | GA12: 754.82 | GB12: 830.4 | GC12: =GB12/GA12 -> 1.1001298 | GO12: Forragens Verdes | GP12: Capim Mombaça | GQ12: 27 | GR12: 1.73 | GS12: 11.05 | GT12: 54.74 | GU12: 66.2 | GV12: 0.74 | GW12: 0.19 | GX12: 0.2 | GY12: 2.74 | GZ12: 0.01 | HA12: 0.14 | HB12: 0.41 | HC12: 10.07 | HD12: 99.99 | HF12: 26.81
B13: Sistema | H13: =G13*F13 -> 0 | J13: Fósforo (P) | K13: =IFERROR(ROUND(BJ123,1),"") | L13: =IFERROR(K13*2,"") | M13: =AY24 -> 0 | N13: =IF(K13="","",IF(M13>L13,"Reduzir",IF(M13<K13,"Aumentar",IF(M13=K13,"Ok",IF(M13=L13,"Ok",IF(OR(M13>=K13,M13<=L13),"Ok")))))) | O13: =IF(M13=0,"",(M13/1000)/$T$21) | P13: =IF(M13=0,"",(K13/1000)/$T$21) | R13: =IF(F13=0,"",IF(E13="","",E13)) | S13: =IF(IF(R13="","",F13*$AB$7)=0,"",IF(R13="","",F13*$AB$7)) | T13: =IF(R13="Ureia",S13,IF(S13="","",IFERROR(S13*(VLOOKUP(R13,'Formulação de suplemento'!$B$42:$W$54,2,)),0))) | U13: =IFERROR(T13/$C$8,"") | V13: =IFERROR(T13/$T$21,"") | W13: =IFERROR(X13/$C$20,"") | X13: =IFERROR(S13*$C$16*$C$20,"") | Z13: GMD de equilíbrio | AB13: =IFERROR(AB11/(C17/30),"") | AF13: =IFERROR(VLOOKUP(R13,'Formulação de suplemento'!$B$56:$W$68,22,0)*T13,"") | AH13: =IFERROR(VLOOKUP(E14,'Formulação de suplemento'!$B$57:$C$68,2,0)*F14,"") | AK13: Ultra-denso | AL13: 0.95 | AV13: =IFERROR($T10*(VLOOKUP($R10,'Formulação de suplemento'!$B$42:$W$54,AV$7,0)),0) -> 0 | AW13: =IFERROR($T10*(VLOOKUP($R10,'Formulação de suplemento'!$B$42:$W$54,AW$7,0)),0) -> 0 | AX13: =IFERROR($T10*(VLOOKUP($R10,'Formulação de suplemento'!$B$42:$W$54,AX$7,0)*1000),0) -> 0 | AY13: =IFERROR($T10*(VLOOKUP($R10,'Formulação de suplemento'!$B$42:$W$54,AY$7,0)*1000),0) -> 0 | AZ13: =IFERROR($T10*(VLOOKUP($R10,'Formulação de suplemento'!$B$42:$W$54,AZ$7,0)),0) -> 0 | BA13: =IFERROR($T10*(VLOOKUP($R10,'Formulação de suplemento'!$B$42:$W$54,BA$7,0)),0) -> 0 | BB13: =IFERROR($T10*(VLOOKUP($R10,'Formulação de suplemento'!$B$42:$W$54,BB$7,0)*1000),0) -> 0 | BC13: =IFERROR($T10*(VLOOKUP($R10,'Formulação de suplemento'!$B$42:$W$54,BC$7,0)*1000),0) -> 0 | BD13: =IFERROR($T10*(VLOOKUP($R10,'Formulação de suplemento'!$B$42:$W$54,BD$7,0)*1000),0) -> 0 | BE13: =IFERROR($T10*(VLOOKUP($R10,'Formulação de suplemento'!$B$42:$W$54,BE$7,0)*1000),0) -> 0 | BF13: =IFERROR($T10*(VLOOKUP($R10,'Formulação de suplemento'!$B$42:$W$54,BF$7,0)*1000),0) -> 0 | BG13: =IFERROR($T10*(VLOOKUP($R10,'Formulação de suplemento'!$B$42:$W$54,BG$7,0)),0) -> 0 | BH13: =IFERROR($T10*(VLOOKUP($R10,'Formulação de suplemento'!$B$42:$W$54,BH$7,0)),0) -> 0 | BI13: =IFERROR($T10*(VLOOKUP($R10,'Formulação de suplemento'!$B$42:$W$54,BI$7,0)),0) -> 0 | BJ13: =IFERROR($T10*(VLOOKUP($R10,'Formulação de suplemento'!$B$42:$W$54,BJ$7,0)),0) -> 0 | BK13: =IFERROR($T10*(VLOOKUP($R10,'Formulação de suplemento'!$B$42:$W$54,BK$7,0)),0) -> 0 | BL13: =IFERROR($T10*(VLOOKUP($R10,'Formulação de suplemento'!$B$42:$W$54,BL$7,0)),0) -> 0 | BM13: =IFERROR($T10*(VLOOKUP($R10,'Formulação de suplemento'!$B$42:$W$54,BM$7,0)),0) -> 0 | FD13: Cálcio | FE13: Ca | FF13: g/dia | FG13: 33.1 | FH13: 33.1 | FI13: 66.21 | FJ13: =FI13/FH13 -> 2.0003021 | FN13: Cálcio | FO13: Ca | FP13: g/dia | FQ13: 22 | FR13: 22 | FS13: 43.99 | FT13: =FS13/FR13 -> 1.9995455 | FW13: Cálcio | FX13: Ca | FY13: g/dia | FZ13: 21.77 | GA13: 21.77 | GB13: 43.54 | GC13: =GB13/GA13 -> 2 | GO13: Forragens Verdes | GP13: Capim Tifton 85 | GQ13: 26.96 | GR13: 2 | GS13: 12.91 | GT13: 56.23 | GU13: 48.83 | GV13: 0.54 | GW13: 0.5 | GX13: 0.17 | GY13: 1.28 | HA13: 0.18 | HC13: 10.35 | HD13: 305 | HF13: 32.22
H14: =G14*F14 -> 0 | J14: Magnésio (mg) | K14: =IF(C8="","",IFERROR(ROUND(BJ132,1),"")) | L14: =IFERROR(K14*3,"") | M14: =BC24 -> 0 | N14: =IF(K14="","",IF(M14>L14,"Reduzir",IF(M14<K14,"Aumentar",IF(M14=K14,"Ok",IF(M14=L14,"Ok",IF(OR(M14>=K14,M14<=L14),"Ok")))))) | O14: =IF(M14=0,"",(M14/1000)/$T$21) | P14: =IF(M14=0,"",(K14/1000)/$T$21) | R14: =IF(F14=0,"",IF(E14="","",E14)) | S14: =IF(IF(R14="","",F14*$AB$7)=0,"",IF(R14="","",F14*$AB$7)) | T14: =IF(S14="","",IFERROR(S14*(VLOOKUP(R14,'Formulação de suplemento'!$B$56:$W$68,2,)),0)) | U14: =IFERROR(T14/$C$8,"") | V14: =IFERROR(T14/$T$21,"") | W14: =IFERROR(X14/$C$20,"") | X14: =IFERROR(S14*$C$16*$C$20,"") | Z14: GMC de equilíbrio | AB14: =IFERROR(ROUND((AB12/30.4)/(C17/15),3),"") | AF14: =IFERROR(VLOOKUP(R14,'Formulação de suplemento'!$B$56:$W$68,22,0)*T14,"") | AH14: =IFERROR(VLOOKUP(E15,'Formulação de suplemento'!$B$57:$C$68,2,0)*F15,"") | AK14: Ponta 7X | AL14: 0.8 | AV14: =IFERROR($T11*(VLOOKUP($R11,'Formulação de suplemento'!$B$42:$W$54,AV$7,0)),0) -> 0 | AW14: =IFERROR($T11*(VLOOKUP($R11,'Formulação de suplemento'!$B$42:$W$54,AW$7,0)),0) -> 0 | AX14: =IFERROR($T11*(VLOOKUP($R11,'Formulação de suplemento'!$B$42:$W$54,AX$7,0)*1000),0) -> 0 | AY14: =IFERROR($T11*(VLOOKUP($R11,'Formulação de suplemento'!$B$42:$W$54,AY$7,0)*1000),0) -> 0 | AZ14: =IFERROR($T11*(VLOOKUP($R11,'Formulação de suplemento'!$B$42:$W$54,AZ$7,0)),0) -> 0 | BA14: =IFERROR($T11*(VLOOKUP($R11,'Formulação de suplemento'!$B$42:$W$54,BA$7,0)),0) -> 0 | BB14: =IFERROR($T11*(VLOOKUP($R11,'Formulação de suplemento'!$B$42:$W$54,BB$7,0)*1000),0) -> 0 | BC14: =IFERROR($T11*(VLOOKUP($R11,'Formulação de suplemento'!$B$42:$W$54,BC$7,0)*1000),0) -> 0 | BD14: =IFERROR($T11*(VLOOKUP($R11,'Formulação de suplemento'!$B$42:$W$54,BD$7,0)*1000),0) -> 0 | BE14: =IFERROR($T11*(VLOOKUP($R11,'Formulação de suplemento'!$B$42:$W$54,BE$7,0)*1000),0) -> 0 | BF14: =IFERROR($T11*(VLOOKUP($R11,'Formulação de suplemento'!$B$42:$W$54,BF$7,0)*1000),0) -> 0 | BG14: =IFERROR($T11*(VLOOKUP($R11,'Formulação de suplemento'!$B$42:$W$54,BG$7,0)),0) -> 0 | BH14: =IFERROR($T11*(VLOOKUP($R11,'Formulação de suplemento'!$B$42:$W$54,BH$7,0)),0) -> 0 | BI14: =IFERROR($T11*(VLOOKUP($R11,'Formulação de suplemento'!$B$42:$W$54,BI$7,0)),0) -> 0 | BJ14: =IFERROR($T11*(VLOOKUP($R11,'Formulação de suplemento'!$B$42:$W$54,BJ$7,0)),0) -> 0 | BK14: =IFERROR($T11*(VLOOKUP($R11,'Formulação de suplemento'!$B$42:$W$54,BK$7,0)),0) -> 0 | BL14: =IFERROR($T11*(VLOOKUP($R11,'Formulação de suplemento'!$B$42:$W$54,BL$7,0)),0) -> 0 | BM14: =IFERROR($T11*(VLOOKUP($R11,'Formulação de suplemento'!$B$42:$W$54,BM$7,0)),0) -> 0 | FD14: Fósforo | FE14: P | FF14: g/dia | FG14: 17.04 | FH14: 17.04 | FI14: 34.08 | FJ14: =FI14/FH14 -> 2 | FN14: Fósforo | FO14: P | FP14: g/dia | FQ14: 13.5 | FR14: 13.5 | FS14: 27.01 | FT14: =FS14/FR14 -> 2.0007407 | FW14: Fósforo | FX14: P | FY14: g/dia | FZ14: 13.43 | GA14: 13.43 | GB14: 26.85 | GC14: =GB14/GA14 -> 1.9992554 | GO14: Forragens Verdes | GP14: Milheto | GQ14: 19.83 | GR14: 3.06 | GS14: 12.23 | GT14: 58.77 | GU14: 63.62 | GV14: 0.72 | GW14: 0.26
B15: INFORMAÇÕES DO SISTEMA | H15: =G15*F15 -> 0 | J15: Potássio (K) | K15: =IF(C8="","",ROUND(BJ146,1)) | L15: =IFERROR(K15*3,"") | M15: =BE24 -> 0 | N15: =IF(K15="","",IF(M15>L15,"Reduzir",IF(M15<K15,"Aumentar",IF(M15=K15,"Ok",IF(M15=L15,"Ok",IF(OR(M15>=K15,M15<=L15),"Ok")))))) | O15: =IF(M15=0,"",(M15/1000)/$T$21) | P15: =IF(M15=0,"",(K15/1000)/$T$21) | R15: =IF(F15=0,"",IF(E15="","",E15)) | S15: =IF(IF(R15="","",F15*$AB$7)=0,"",IF(R15="","",F15*$AB$7)) | T15: =IF(S15="","",IFERROR(S15*(VLOOKUP(R15,'Formulação de suplemento'!$B$56:$W$68,2,)),0)) | U15: =IFERROR(T15/$C$8,"") | V15: =IFERROR(T15/$T$21,"") | W15: =IFERROR(X15/$C$20,"") | X15: =IFERROR(S15*$C$16*$C$20,"") | Z15: Custo da @ produzia (R$) | AB15: =IFERROR(((30/C9)/30.4)*AB12,"") | AF15: =IFERROR(VLOOKUP(R15,'Formulação de suplemento'!$B$56:$W$68,22,0)*T15,"") | AH15: =IFERROR(VLOOKUP(E16,'Formulação de suplemento'!$B$57:$C$68,2,0)*F16,"") | AV15: =IFERROR($T12*(VLOOKUP($R12,'Formulação de suplemento'!$B$42:$W$54,AV$7,0)),0) -> 0 | AW15: =IFERROR($T12*(VLOOKUP($R12,'Formulação de suplemento'!$B$42:$W$54,AW$7,0)),0) -> 0 | AX15: =IFERROR($T12*(VLOOKUP($R12,'Formulação de suplemento'!$B$42:$W$54,AX$7,0)*1000),0) -> 0 | AY15: =IFERROR($T12*(VLOOKUP($R12,'Formulação de suplemento'!$B$42:$W$54,AY$7,0)*1000),0) -> 0 | AZ15: =IFERROR($T12*(VLOOKUP($R12,'Formulação de suplemento'!$B$42:$W$54,AZ$7,0)),0) -> 0 | BA15: =IFERROR($T12*(VLOOKUP($R12,'Formulação de suplemento'!$B$42:$W$54,BA$7,0)),0) -> 0 | BB15: =IFERROR($T12*(VLOOKUP($R12,'Formulação de suplemento'!$B$42:$W$54,BB$7,0)*1000),0) -> 0 | BC15: =IFERROR($T12*(VLOOKUP($R12,'Formulação de suplemento'!$B$42:$W$54,BC$7,0)*1000),0) -> 0 | BD15: =IFERROR($T12*(VLOOKUP($R12,'Formulação de suplemento'!$B$42:$W$54,BD$7,0)*1000),0) -> 0 | BE15: =IFERROR($T12*(VLOOKUP($R12,'Formulação de suplemento'!$B$42:$W$54,BE$7,0)*1000),0) -> 0 | BF15: =IFERROR($T12*(VLOOKUP($R12,'Formulação de suplemento'!$B$42:$W$54,BF$7,0)*1000),0) -> 0 | BG15: =IFERROR($T12*(VLOOKUP($R12,'Formulação de suplemento'!$B$42:$W$54,BG$7,0)),0) -> 0 | BH15: =IFERROR($T12*(VLOOKUP($R12,'Formulação de suplemento'!$B$42:$W$54,BH$7,0)),0) -> 0 | BI15: =IFERROR($T12*(VLOOKUP($R12,'Formulação de suplemento'!$B$42:$W$54,BI$7,0)),0) -> 0 | BJ15: =IFERROR($T12*(VLOOKUP($R12,'Formulação de suplemento'!$B$42:$W$54,BJ$7,0)),0) -> 0 | BK15: =IFERROR($T12*(VLOOKUP($R12,'Formulação de suplemento'!$B$42:$W$54,BK$7,0)),0) -> 0 | BL15: =IFERROR($T12*(VLOOKUP($R12,'Formulação de suplemento'!$B$42:$W$54,BL$7,0)),0) -> 0 | BM15: =IFERROR($T12*(VLOOKUP($R12,'Formulação de suplemento'!$B$42:$W$54,BM$7,0)),0) -> 0 | FD15: Magnésio | FE15: Mg | FF15: g/dia | FG15: 4.13 | FH15: 4.13 | FI15: 12.38 | FJ15: =FI15/FH15 -> 2.9975787 | FN15: Magnésio | FO15: Mg | FP15: g/dia | FQ15: 5.99 | FR15: 5.99 | FS15: 17.96 | FT15: =FS15/FR15 -> 2.9983306 | FW15: Magnésio | FX15: Mg | FY15: g/dia | FZ15: 5.99 | GA15: 5.99 | GB15: 17.96 | GC15: =GB15/GA15 -> 2.9983306 | GO15: Forragens Verdes | GP15: Sorgo Forrageiro | GQ15: 24.11 | GR15: 3.04 | GS15: 6.84 | GT15: 57.9 | GU15: 63.35 | GV15: 0.13 | GW15: 0.13 | GX15: 0.26
B16: Dias de uso | C16: =IFERROR((C7-C6)/C9,"") | H16: =G16*F16 -> 0 | J16: Sódio (Na) | K16: =IF(C8="","",ROUND(BJ139,1)) | L16: =IFERROR(K16*6,"") | M16: =BD24 -> 0 | N16: =IF(K16="","",IF(M16>L16,"Reduzir",IF(M16<K16,"Aumentar",IF(M16=K16,"Ok",IF(M16=L16,"Ok",IF(OR(M16>=K16,M16<=L16),"Ok")))))) | O16: =IF(M16=0,"",(M16/1000)/$T$21) | P16: =IF(M16=0,"",(K16/1000)/$T$21) | R16: =IF(F16=0,"",IF(E16="","",E16)) | S16: =IF(IF(R16="","",F16*$AB$7)=0,"",IF(R16="","",F16*$AB$7)) | T16: =IF(S16="","",IFERROR(S16*(VLOOKUP(R16,'Formulação de suplemento'!$B$56:$W$68,2,)),0)) | U16: =IFERROR(T16/$C$8,"") | V16: =IFERROR(T16/$T$21,"") | W16: =IFERROR(X16/$C$20,"") | X16: =IFERROR(S16*$C$16*$C$20,"") | Z16: Dias para produzir 1@ | AB16: =IFERROR(30/C9,"") | AF16: =IFERROR(VLOOKUP(R16,'Formulação de suplemento'!$B$56:$W$68,22,0)*T16,"") | AH16: =IFERROR(VLOOKUP(E17,'Formulação de suplemento'!$B$57:$C$68,2,0)*F17,"") | AV16: =IFERROR($T13*(VLOOKUP($R13,'Formulação de suplemento'!$B$42:$W$54,AV$7,0)),0) -> 0 | AW16: =IFERROR($T13*(VLOOKUP($R13,'Formulação de suplemento'!$B$42:$W$54,AW$7,0)),0) -> 0 | AX16: =IFERROR($T13*(VLOOKUP($R13,'Formulação de suplemento'!$B$42:$W$54,AX$7,0)*1000),0) -> 0 | AY16: =IFERROR($T13*(VLOOKUP($R13,'Formulação de suplemento'!$B$42:$W$54,AY$7,0)*1000),0) -> 0 | AZ16: =IFERROR($T13*(VLOOKUP($R13,'Formulação de suplemento'!$B$42:$W$54,AZ$7,0)),0) -> 0 | BA16: =IFERROR($T13*(VLOOKUP($R13,'Formulação de suplemento'!$B$42:$W$54,BA$7,0)),0) -> 0 | BB16: =IFERROR($T13*(VLOOKUP($R13,'Formulação de suplemento'!$B$42:$W$54,BB$7,0)*1000),0) -> 0 | BC16: =IFERROR($T13*(VLOOKUP($R13,'Formulação de suplemento'!$B$42:$W$54,BC$7,0)*1000),0) -> 0 | BD16: =IFERROR($T13*(VLOOKUP($R13,'Formulação de suplemento'!$B$42:$W$54,BD$7,0)*1000),0) -> 0 | BE16: =IFERROR($T13*(VLOOKUP($R13,'Formulação de suplemento'!$B$42:$W$54,BE$7,0)*1000),0) -> 0 | BF16: =IFERROR($T13*(VLOOKUP($R13,'Formulação de suplemento'!$B$42:$W$54,BF$7,0)*1000),0) -> 0 | BG16: =IFERROR($T13*(VLOOKUP($R13,'Formulação de suplemento'!$B$42:$W$54,BG$7,0)),0) -> 0 | BH16: =IFERROR($T13*(VLOOKUP($R13,'Formulação de suplemento'!$B$42:$W$54,BH$7,0)),0) -> 0 | BI16: =IFERROR($T13*(VLOOKUP($R13,'Formulação de suplemento'!$B$42:$W$54,BI$7,0)),0) -> 0 | BJ16: =IFERROR($T13*(VLOOKUP($R13,'Formulação de suplemento'!$B$42:$W$54,BJ$7,0)),0) -> 0 | BK16: =IFERROR($T13*(VLOOKUP($R13,'Formulação de suplemento'!$B$42:$W$54,BK$7,0)),0) -> 0 | BL16: =IFERROR($T13*(VLOOKUP($R13,'Formulação de suplemento'!$B$42:$W$54,BL$7,0)),0) -> 0 | BM16: =IFERROR($T13*(VLOOKUP($R13,'Formulação de suplemento'!$B$42:$W$54,BM$7,0)),0) -> 0 | FD16: Potássio | FE16: K | FF16: g/dia | FG16: 13.15 | FH16: 13.15 | FI16: 39.45 | FJ16: =FI16/FH16 -> 3 | FN16: Potássio | FO16: K | FP16: g/dia | FQ16: 18.25 | FR16: 18.25 | FS16: 54.74 | FT16: =FS16/FR16 -> 2.9994521 | FW16: Potássio | FX16: K | FY16: g/dia | FZ16: 18.26 | GA16: 18.26 | GB16: 54.78 | GC16: =GB16/GA16 -> 3 | GO16: Forragens Secas | GP16: Capim Braquiária Brizantha Feno | GQ16: 87.99 | GR16: 1.22 | GS16: 4.19 | GT16: 54.11 | GU16: 77.52 | GV16: 0.33 | GW16: 0.11 | GX16: 0.21 | GY16: 0.88 | GZ16: 0.03
B17: R$/@ venda | H17: =G17*F17 -> 0 | J17: Enxofre (S) | K17: =IF(C8="","",ROUND(BJ152,1)) | L17: =IFERROR(K17*3,"") | M17: =BF24 -> 0 | N17: =IF(K17="","",IF(M17>L17,"Reduzir",IF(M17<K17,"Aumentar",IF(M17=K17,"Ok",IF(M17=L17,"Ok",IF(OR(M17>=K17,M17<=L17),"Ok")))))) | O17: =IF(M17=0,"",(M17/1000)/$T$21) | P17: =IF(M17=0,"",(K17/1000)/$T$21) | R17: =IF(F17=0,"",IF(E17="","",E17)) | S17: =IF(IF(R17="","",F17*$AB$7)=0,"",IF(R17="","",F17*$AB$7)) | T17: =IF(S17="","",IFERROR(S17*(VLOOKUP(R17,'Formulação de suplemento'!$B$56:$W$68,2,)),0)) | U17: =IFERROR(T17/$C$8,"") | V17: =IFERROR(T17/$T$21,"") | W17: =IFERROR(X17/$C$20,"") | X17: =IFERROR(S17*$C$16*$C$20,"") | Z17: R$ produzidos/cab/dia | AB17: =(C9/30)*C17 -> 0 | AF17: =IFERROR(VLOOKUP(R17,'Formulação de suplemento'!$B$56:$W$68,22,0)*T17,"") | AH17: =IFERROR(VLOOKUP(E18,'Formulação de suplemento'!$B$57:$C$68,2,0)*F18,"") | FD17: Sódio | FE17: Na | FF17: g/dia | FG17: 8.07 | FH17: 8.07 | FI17: 48.39 | FJ17: =FI17/FH17 -> 5.9962825 | FN17: Sódio | FO17: Na | FP17: g/dia | FQ17: 7.87 | FR17: 7.87 | FS17: 47.24 | FT17: =FS17/FR17 -> 6.0025413 | FW17: Sódio | FX17: Na | FY17: g/dia | FZ17: 7.85 | GA17: 7.85 | GB17: 47.1 | GC17: =GB17/GA17 -> 6 | GO17: Silagens | GP17: Cana-de-açúcar Silagem | GQ17: 25.68 | GR17: 1.7 | GS17: 3.47 | GT17: 58.75 | GU17: 62.02 | GV17: 0.3 | GW17: 0.05
B18: Forragem | H18: =G18*F18 -> 0 | J18: Cobalto (Co) | K18: =IF(C8="","",ROUND(BJ164,0)) | L18: =IFERROR(K18*20,"") | M18: =BL24 -> 0 | N18: =IF(K18="","",IF(M18>L18,"Reduzir",IF(M18<K18,"Aumentar",IF(M18=K18,"Ok",IF(M18=L18,"Ok",IF(OR(M18>=K18,M18<=L18),"Ok")))))) | O18: =IF(M18=0,"",(M18/1000000)/$T$21) | P18: =IF(M18=0,"",(K18/1000000)/T$21) | R18: =IF(F18=0,"",IF(E18="","",E18)) | S18: =IF(IF(R18="","",F18*$AB$7)=0,"",IF(R18="","",F18*$AB$7)) | T18: =IF(S18="","",IFERROR(S18*(VLOOKUP(R18,'Formulação de suplemento'!$B$56:$W$68,2,)),0)) | U18: =IFERROR(T18/$C$8,"") | V18: =IFERROR(T18/$T$21,"") | W18: =IFERROR(X18/$C$20,"") | X18: =IFERROR(S18*$C$16*$C$20,"") | Z18: Margem de produção/cab/dia | AB18: =IFERROR(AB17-AB11,"") | AF18: =IFERROR(VLOOKUP(R18,'Formulação de suplemento'!$B$56:$W$68,22,0)*T18,"") | AH18: =IFERROR(VLOOKUP(E19,'Formulação de suplemento'!$B$57:$C$68,2,0)*F19,"") | AV18: =IFERROR($T14*(VLOOKUP($R14,'Formulação de suplemento'!$B$56:$W$68,AV$7,0))/1000,0) -> 0 | AW18: =IFERROR($T14*(VLOOKUP($R14,'Formulação de suplemento'!$B$56:$W$68,AW$7,0))/1000,0) -> 0 | AX18: =IFERROR($T14*(VLOOKUP($R14,'Formulação de suplemento'!$B$56:$W$68,AX$7,0)),0) -> 0 | AY18: =IFERROR($T14*(VLOOKUP($R14,'Formulação de suplemento'!$B$56:$W$68,AY$7,0)),0) -> 0 | AZ18: =IFERROR($T14*(VLOOKUP($R14,'Formulação de suplemento'!$B$56:$W$68,AZ$7,0)),0) -> 0 | BA18: =IFERROR($T14*(VLOOKUP($R14,'Formulação de suplemento'!$B$56:$W$68,BA$7,0)),0) -> 0 | BB18: =IFERROR($T14*(VLOOKUP($R14,'Formulação de suplemento'!$B$56:$W$68,BB$7,0)),0) -> 0 | BC18: =IFERROR($T14*(VLOOKUP($R14,'Formulação de suplemento'!$B$56:$W$68,BC$7,0)),0) -> 0 | BD18: =IFERROR($T14*(VLOOKUP($R14,'Formulação de suplemento'!$B$56:$W$68,BD$7,0)),0) -> 0 | BE18: =IFERROR($T14*(VLOOKUP($R14,'Formulação de suplemento'!$B$56:$W$68,BE$7,0)),0) -> 0 | ... BM18: =IFERROR($T14*(VLOOKUP($R14,'Formulação de suplemento'!$B$56:$W$68,BM$7,0)),0) -> 0 | FD18: Enxofre | FE18: S | FF18: g/dia | FG18: 6.63 | FH18: 6.63 | FI18: 19.9 | FJ18: =FI18/FH18 -> 3.0015083 | FN18: Enxofre | FO18: S | FP18: g/dia | FQ18: 9.09 | FR18: 9.09 | FS18: 27.28 | FT18: =FS18/FR18 -> 3.0011001 | FW18: Enxofre | FX18: S | FY18: g/dia | FZ18: 9.23 | GA18: 9.23 | GB18: 27.68 | GC18: =GB18/GA18 -> 2.9989166 | GO18: Silagens | GP18: Capim Elefante Silagem | GQ18: 27.53 | GR18: 2.22 | GS18: 5.52 | GT18: 52.28 | GU18: 68.3 | GV18: 0.31 | GW18: 0.2 | GX18: 0.2 | GY18: 3 | GZ18: 0.02
B19: Cons. Supl. (%P.V) | H19: =G19*F19 -> 0 | J19: Cobre (Cu) | K19: =IF(C8="","",ROUND(BJ158,0)) | L19: =IFERROR(K19*3,"") | M19: =BG24 -> 0 | N19: =IF(K19="","",IF(M19>L19,"Reduzir",IF(M19<K19,"Aumentar",IF(M19=K19,"Ok",IF(M19=L19,"Ok",IF(OR(M19>=K19,M19<=L19),"Ok")))))) | O19: =IF(M19=0,"",(M19/1000000)/$T$21) | P19: =IF(M19=0,"",(K19/1000000)/T$21) | R19: =IF(F19=0,"",IF(E19="","",E19)) | S19: =IF(IF(R19="","",F19*$AB$7)=0,"",IF(R19="","",F19*$AB$7)) | T19: =IF(S19="","",IFERROR(S19*(VLOOKUP(R19,'Formulação de suplemento'!$B$56:$W$68,2,)),0)) | U19: =IFERROR(T19/$C$8,"") | V19: =IFERROR(T19/$T$21,"") | W19: =IFERROR(X19/$C$20,"") | X19: =IFERROR(S19*$C$16*$C$20,"") | Z19: Margem R$/cab/mês | AB19: =IFERROR(AB18*30.4,"") | AF19: =IFERROR(VLOOKUP(R19,'Formulação de suplemento'!$B$56:$W$68,22,0)*T19,"") | AH19: =IFERROR(VLOOKUP(E20,'Formulação de suplemento'!$B$57:$C$68,2,0)*F20,"") | AV19: =IFERROR($T15*(VLOOKUP($R15,'Formulação de suplemento'!$B$56:$W$68,AV$7,0))/1000,0) -> 0 | AW19: =IFERROR($T15*(VLOOKUP($R15,'Formulação de suplemento'!$B$56:$W$68,AW$7,0))/1000,0) -> 0 | AX19: =IFERROR($T15*(VLOOKUP($R15,'Formulação de suplemento'!$B$56:$W$68,AX$7,0)),0) -> 0 | AY19: =IFERROR($T15*(VLOOKUP($R15,'Formulação de suplemento'!$B$56:$W$68,AY$7,0)),0) -> 0 | AZ19: =IFERROR($T15*(VLOOKUP($R15,'Formulação de suplemento'!$B$56:$W$68,AZ$7,0)),0) -> 0 | BA19: =IFERROR($T15*(VLOOKUP($R15,'Formulação de suplemento'!$B$56:$W$68,BA$7,0)),0) -> 0 | BB19: =IFERROR($T15*(VLOOKUP($R15,'Formulação de suplemento'!$B$56:$W$68,BB$7,0)),0) -> 0 | BC19: =IFERROR($T15*(VLOOKUP($R15,'Formulação de suplemento'!$B$56:$W$68,BC$7,0)),0) -> 0 | BD19: =IFERROR($T15*(VLOOKUP($R15,'Formulação de suplemento'!$B$56:$W$68,BD$7,0)),0) -> 0 | BE19: =IFERROR($T15*(VLOOKUP($R15,'Formulação de suplemento'!$B$56:$W$68,BE$7,0)),0) -> 0 | ... BM19: =IFERROR($T15*(VLOOKUP($R15,'Formulação de suplemento'!$B$56:$W$68,BM$7,0)),0) -> 0 | FD19: Cobalto | FE19: Co | FF19: mg/dia | FG19: 2.82 | FH19: 2.82 | FI19: 56.4 | FJ19: =FI19/FH19 -> 20 | FN19: Cobalto | FO19: Co | FP19: mg/dia | FQ19: 4.68 | FR19: 4.68 | FS19: 93.6 | FT19: =FS19/FR19 -> 20 | FW19: Cobalto | FX19: Co | FY19: mg/dia | FZ19: 4.68 | GA19: 4.68 | GB19: 93.6 | GC19: =GB19/GA19 -> 20 | GO19: Silagens | GP19: Capim Mombaça Silagem | GQ19: 24.41 | GR19: 1.71 | GS19: 7.36 | GT19: 50.38 | GU19: 71.49 | GV19: 0.44 | GW19: 0.12
B20: n° de animais (cab) | H20: =G20*F20 -> 0 | J20: Manganês (Mn) | K20: =IF(C8="","",ROUND(BJ182,0)) | L20: =IFERROR(K20*3,"") | M20: =BJ24 -> 0 | N20: =IF(K20="","",IF(M20>L20,"Reduzir",IF(M20<K20,"Aumentar",IF(M20=K20,"Ok",IF(M20=L20,"Ok",IF(OR(M20>=K20,M20<=L20),"Ok")))))) | O20: =IF(M20=0,"",(M20/1000000)/$T$21) | P20: =IF(M20=0,"",(K20/1000000)/T$21) | R20: =IF(F20=0,"",IF(E20="","",E20)) | S20: =IF(IF(R20="","",F20*$AB$7)=0,"",IF(R20="","",F20*$AB$7)) | T20: =IF(S20="","",IFERROR(S20*(VLOOKUP(R20,'Formulação de suplemento'!$B$56:$W$68,2,)),0)) | U20: =IFERROR(T20/$C$8,"") | V20: =IFERROR(T20/$T$21,"") | W20: =IFERROR(X20/$C$20,"") | X20: =IFERROR(S20*$C$16*$C$20,"") | Z20: *Esses resultados serão alcançados somente se todos os números preenchidos na planilha acontecerem na vida real. | AF20: =IFERROR(VLOOKUP(R20,'Formulação de suplemento'!$B$56:$W$68,22,0)*T20,"") | AH20: =SUM(AH7:AH19) -> 0 | AV20: =IFERROR($T16*(VLOOKUP($R16,'Formulação de suplemento'!$B$56:$W$68,AV$7,0))/1000,0) -> 0 | AW20: =IFERROR($T16*(VLOOKUP($R16,'Formulação de suplemento'!$B$56:$W$68,AW$7,0))/1000,0) -> 0 | AX20: =IFERROR($T16*(VLOOKUP($R16,'Formulação de suplemento'!$B$56:$W$68,AX$7,0)),0) -> 0 | AY20: =IFERROR($T16*(VLOOKUP($R16,'Formulação de suplemento'!$B$56:$W$68,AY$7,0)),0) -> 0 | AZ20: =IFERROR($T16*(VLOOKUP($R16,'Formulação de suplemento'!$B$56:$W$68,AZ$7,0)),0) -> 0 | BA20: =IFERROR($T16*(VLOOKUP($R16,'Formulação de suplemento'!$B$56:$W$68,BA$7,0)),0) -> 0 | BB20: =IFERROR($T16*(VLOOKUP($R16,'Formulação de suplemento'!$B$56:$W$68,BB$7,0)),0) -> 0 | BC20: =IFERROR($T16*(VLOOKUP($R16,'Formulação de suplemento'!$B$56:$W$68,BC$7,0)),0) -> 0 | BD20: =IFERROR($T16*(VLOOKUP($R16,'Formulação de suplemento'!$B$56:$W$68,BD$7,0)),0) -> 0 | BE20: =IFERROR($T16*(VLOOKUP($R16,'Formulação de suplemento'!$B$56:$W$68,BE$7,0)),0) -> 0 | ... BM20: =IFERROR($T16*(VLOOKUP($R16,'Formulação de suplemento'!$B$56:$W$68,BM$7,0)),0) -> 0 | FD20: Cobre | FE20: Cu | FF20: mg/dia | FG20: 34.58 | FH20: 34.58 | FI20: 103.73 | FJ20: =FI20/FH20 -> 2.9997108 | FN20: Cobre | FO20: Cu | FP20: mg/dia | FQ20: 49.13 | FR20: 49.13 | FS20: 147.38 | FT20: =FS20/FR20 -> 2.9997965 | FW20: Cobre | FX20: Cu | FY20: mg/dia | FZ20: 49.22 | GA20: 49.22 | GB20: 147.67 | GC20: =GB20/GA20 -> 3.0002032 | GO20: Silagens | GP20: Milho Silagem | GQ20: 31.02 | GR20: 2.77 | GS20: 7.12 | GT20: 64.86 | GU20: 47.51 | GV20: 0.28 | GW20: 0.19 | GX20: 0.14 | GY20: 0.96 | GZ20: 0.04 | HA20: 0.08 | HB20: 0.2 | HC20: 5.6 | HD20: 26.07 | HE20: 0.03 | HF20: 19.41
B21: Diária s/ supl. (R$/cab) | E21: Total | F21: =SUM(F7:F20) -> 0 | H21: =SUM(H7:H20) -> 0 | J21: Selênio (Se) | K21: =IF(C8="","",ROUND(BJ194,0)) | L21: =IFERROR(K21*20,"") | M21: =BM24 -> 0 | N21: =IF(K21="","",IF(M21>L21,"Reduzir",IF(M21<K21,"Aumentar",IF(M21=K21,"Ok",IF(M21=L21,"Ok",IF(OR(M21>=K21,M21<=L21),"Ok")))))) | O21: =IF(M21=0,"",(M21/1000000)/$T$21) | P21: =IF(M21=0,"",(K21/1000000)/T$21) | R21: Total | S21: =SUM(S7:S19) -> 0 | T21: =SUM(T7:T19) -> 0 | U21: =SUM(U7:U19) -> 0 | V21: =SUM(V7:V19) -> 0 | W21: =SUM(W7:W19) -> 0 | X21: =SUM(X7:X19) -> 0 | AV21: =IFERROR($T17*(VLOOKUP($R17,'Formulação de suplemento'!$B$56:$W$68,AV$7,0))/1000,0) -> 0 | AW21: =IFERROR($T17*(VLOOKUP($R17,'Formulação de suplemento'!$B$56:$W$68,AW$7,0))/1000,0) -> 0 | AX21: =IFERROR($T17*(VLOOKUP($R17,'Formulação de suplemento'!$B$56:$W$68,AX$7,0)),0) -> 0 | AY21: =IFERROR($T17*(VLOOKUP($R17,'Formulação de suplemento'!$B$56:$W$68,AY$7,0)),0) -> 0 | AZ21: =IFERROR($T17*(VLOOKUP($R17,'Formulação de suplemento'!$B$56:$W$68,AZ$7,0)),0) -> 0 | BA21: =IFERROR($T17*(VLOOKUP($R17,'Formulação de suplemento'!$B$56:$W$68,BA$7,0)),0) -> 0 | BB21: =IFERROR($T17*(VLOOKUP($R17,'Formulação de suplemento'!$B$56:$W$68,BB$7,0)),0) -> 0 | BC21: =IFERROR($T17*(VLOOKUP($R17,'Formulação de suplemento'!$B$56:$W$68,BC$7,0)),0) -> 0 | BD21: =IFERROR($T17*(VLOOKUP($R17,'Formulação de suplemento'!$B$56:$W$68,BD$7,0)),0) -> 0 | BE21: =IFERROR($T17*(VLOOKUP($R17,'Formulação de suplemento'!$B$56:$W$68,BE$7,0)),0) -> 0 | ... BM21: =IFERROR($T17*(VLOOKUP($R17,'Formulação de suplemento'!$B$56:$W$68,BM$7,0)),0) -> 0 | FD21: Iodo | FE21: I | FF21: mg/dia | FG21: 2.75 | FH21: 2.75 | FI21: 55.03 | FJ21: =FI21/FH21 -> 20.010909 | FN21: Iodo | FO21: I | FP21: mg/dia | FQ21: 3.42 | FR21: 3.42 | FS21: 68.45 | FT21: =FS21/FR21 -> 20.01462 | FW21: Iodo | FX21: I | FY21: mg/dia | FZ21: 3.42 | GA21: 3.42 | GB21: 68.45 | GC21: =GB21/GA21 -> 20.01462 | GO21: Silagens | GP21: Milho Silagem Sem Espiga | GQ21: 21.3 | GR21: 1.36 | GS21: 6.39 | GT21: 53.43 | GU21: 65.9
J22: Zinco (Zn) | K22: =IF(C8="","",ROUND(BJ200,0)) | L22: =IFERROR(K22*3,"") | M22: =BH24 -> 0 | N22: =IF(K22="","",IF(M22>L22,"Reduzir",IF(M22<K22,"Aumentar",IF(M22=K22,"Ok",IF(M22=L22,"Ok",IF(OR(M22>=K22,M22<=L22),"Ok")))))) | O22: =IF(M22=0,"",(M22/1000000)/$T$21) | P22: =IF(M22=0,"",(K22/1000000)/T$21) | R22: ="*% de concentrado na dieta "&ROUND(SUM(V8:V19)*100,1)&"%." -> *% de concentrado na dieta 0%. | AV22: =IFERROR($T18*(VLOOKUP($R18,'Formulação de suplemento'!$B$56:$W$68,AV$7,0))/1000,0) -> 0 | AW22: =IFERROR($T18*(VLOOKUP($R18,'Formulação de suplemento'!$B$56:$W$68,AW$7,0))/1000,0) -> 0 | AX22: =IFERROR($T18*(VLOOKUP($R18,'Formulação de suplemento'!$B$56:$W$68,AX$7,0)),0) -> 0 | AY22: =IFERROR($T18*(VLOOKUP($R18,'Formulação de suplemento'!$B$56:$W$68,AY$7,0)),0) -> 0 | AZ22: =IFERROR($T18*(VLOOKUP($R18,'Formulação de suplemento'!$B$56:$W$68,AZ$7,0)),0) -> 0 | BA22: =IFERROR($T18*(VLOOKUP($R18,'Formulação de suplemento'!$B$56:$W$68,BA$7,0)),0) -> 0 | BB22: =IFERROR($T18*(VLOOKUP($R18,'Formulação de suplemento'!$B$56:$W$68,BB$7,0)),0) -> 0 | BC22: =IFERROR($T18*(VLOOKUP($R18,'Formulação de suplemento'!$B$56:$W$68,BC$7,0)),0) -> 0 | BD22: =IFERROR($T18*(VLOOKUP($R18,'Formulação de suplemento'!$B$56:$W$68,BD$7,0)),0) -> 0 | BE22: =IFERROR($T18*(VLOOKUP($R18,'Formulação de suplemento'!$B$56:$W$68,BE$7,0)),0) -> 0 | ... BM22: =IFERROR($T18*(VLOOKUP($R18,'Formulação de suplemento'!$B$56:$W$68,BM$7,0)),0) -> 0 | FD22: Manganês | FE22: Mn | FF22: mg/dia | FG22: 86.84 | FH22: 86.84 | FI22: 260.52 | FJ22: =FI22/FH22 -> 3 | FN22: Manganês | FO22: Mn | FP22: mg/dia | FQ22: 139.01 | FR22: 139.01 | FS22: 417.03 | FT22: =FS22/FR22 -> 3 | FW22: Manganês | FX22: Mn | FY22: mg/dia | FZ22: 139.31 | GA22: 139.31 | GB22: 417.92 | GC22: =GB22/GA22 -> 2.9999282 | GO22: Silagens | GP22: Sorgo Silagem | GQ22: 29.65 | GR22: 2.58 | GS22: 6.45 | GT22: 61.44 | GU22: 57.6 | GV22: 0.32 | GW22: 0.18 | GX22: 0.29 | GY22: 1.2 | GZ22: 0.03
E23: R$/kg mão de obra | G23: R$/kg final | H23: =F23+H21 -> 0 | J23: Ureia | K23: =IF(C8="","","Não consta") | L23: =IF(C8="","", M7*0.01*1000) | M23: =IFERROR((SUMIFS(S7:S20,R7:R20,"Ureia")+SUM(AF14:AF20))*1000,0) -> 0 | N23: =IF(L23="","",IF(M23>L23,"Reduzir","Ok")) | O23: =IF(M23=0,"",(M23/1000)/T21) | P23: =IF(C8="","","Não consta") | R23: **Para que o GMD seja alcançado, você tem que garantir que seu animal tenha acesso a essa quantidade de forragem e suplemento diariamente. | AV23: =IFERROR($T19*(VLOOKUP($R19,'Formulação de suplemento'!$B$56:$W$68,AV$7,0))/1000,0) -> 0 | AW23: =IFERROR($T19*(VLOOKUP($R19,'Formulação de suplemento'!$B$56:$W$68,AW$7,0))/1000,0) -> 0 | AX23: =IFERROR($T19*(VLOOKUP($R19,'Formulação de suplemento'!$B$56:$W$68,AX$7,0)),0) -> 0 | AY23: =IFERROR($T19*(VLOOKUP($R19,'Formulação de suplemento'!$B$56:$W$68,AY$7,0)),0) -> 0 | AZ23: =IFERROR($T19*(VLOOKUP($R19,'Formulação de suplemento'!$B$56:$W$68,AZ$7,0)),0) -> 0 | BA23: =IFERROR($T19*(VLOOKUP($R19,'Formulação de suplemento'!$B$56:$W$68,BA$7,0)),0) -> 0 | BB23: =IFERROR($T19*(VLOOKUP($R19,'Formulação de suplemento'!$B$56:$W$68,BB$7,0)),0) -> 0 | BC23: =IFERROR($T19*(VLOOKUP($R19,'Formulação de suplemento'!$B$56:$W$68,BC$7,0)),0) -> 0 | BD23: =IFERROR($T19*(VLOOKUP($R19,'Formulação de suplemento'!$B$56:$W$68,BD$7,0)),0) -> 0 | BE23: =IFERROR($T19*(VLOOKUP($R19,'Formulação de suplemento'!$B$56:$W$68,BE$7,0)),0) -> 0 | ... BM23: =IFERROR($T19*(VLOOKUP($R19,'Formulação de suplemento'!$B$56:$W$68,BM$7,0)),0) -> 0 | FD23: Selênio | FE23: Se | FF23: mg/dia | FG23: 3.32 | FH23: 3.32 | FI23: 66.39 | FJ23: =FI23/FH23 -> 19.996988 | FN23: Selênio | FO23: Se | FP23: mg/dia | FQ23: 3.73 | FR23: 3.73 | FS23: 74.6 | FT23: =FS23/FR23 -> 20 | FW23: Selênio | FX23: Se | FY23: mg/dia | FZ23: 3.73 | GA23: 3.73 | GB23: 74.54 | GC23: =GB23/GA23 -> 19.983914 | GO23: Concentrados Energéticos | GP23: Milho Fubá | GQ23: 87.88 | GR23: 4 | GS23: 8.96 | GT23: 86.92 | GU23: 12.39 | GV23: 0.03 | GW23: 0.26 | GX23: 0.11 | GY23: 0.35 | GZ23: 0.03 | HA23: 0.04 | HB23: 0.02 | HC23: 3.48 | HD23: 8.8 | HE23: 0.07 | HF23: 18.85
E24: =IF(IFERROR("*suplemento consumo de "&C19*100&"% P.V | Estimativa de "&ROUND((AX27/SUM(T8:T19))*100,1)&"% de PB e "&ROUND((AW27/SUM(T8:T19)*100),1)&"% de NDT","Tabela do suplemento formulado")="Tabela do suplemento formulado","",IFERROR("*suplemento consumo de "&C19*100&"% P.V | Estimativa de "&ROUND((AX27/SUM(T8:T19))*100,1)&"% de PB e "&ROUND((AW27/SUM(T8:T19)*100),1)&"% de NDT","Tabela do suplemento formulado")) | R24: ***As estimativas de consumo foram feitas em cima do peso médio, podendo ter variação de acordo com o desempenho. | AV24: =SUM(AV9:AV23) -> 0 | AW24: =SUM(AW9:AW23)+(((M23*280)/100)/1000) -> 0 | AX24: =SUM(AX9:AX23) -> 0 | AY24: =SUM(AY9:AY23) -> 0 | AZ24: =SUM(AZ9:AZ23) -> 0 | BA24: =SUM(BA9:BA23) -> 0 | BB24: =SUM(BB9:BB23) -> 0 | BC24: =SUM(BC9:BC23) -> 0 | BD24: =SUM(BD9:BD23) -> 0 | BE24: =SUM(BE9:BE23) -> 0 | ... BM24: =SUM(BM9:BM23) -> 0 | FD24: Zinco | FE24: Zn | FF24: mg/dia | FG24: 252.29 | FH24: 252.29 | FI24: 756.87 | FJ24: =FI24/FH24 -> 3 | FN24: Zinco | FO24: Zn | FP24: mg/dia | FQ24: 342.02 | FR24: 342.02 | FS24: 1026.05 | FT24: =FS24/FR24 -> 2.9999708 | FW24: Zinco | FX24: Zn | FY24: mg/dia | FZ24: 346.88 | GA24: 346.88 | GB24: 1040.63 | GC24: =GB24/GA24 -> 2.9999712 | GO24: Concentrados Energéticos | GP24: Soja Casca | GQ24: 90.1 | GR24: 2.22 | GS24: 12.67 | GT24: 73.11 | GU24: 60.98 | GV24: 0.52 | GW24: 0.16 | GX24: 0.34 | GY24: 0.87 | GZ24: 0.08 | HA24: 0.09 | HB24: 5.01 | HC24: 6.46 | HD24: 17.55 | HF24: 48.07
E25: =IFERROR("**consumo médio do suplemento de "&ROUND(C19*C8,3)&" kg/cab/dia","") | J25: Acréscimo de consumo de MS | L25: 0 | GO25: Concentrados Energéticos | GP25: Sorgo Grão | GQ25: 88.01 | GR25: 2.91 | GS25: 9.33 | GT25: 84.19 | GU25: 10.58 | GV25: 0.07 | GW25: 0.29 | GX25: 0.19 | GY25: 0.73 | GZ25: 0.03 | HA25: 0.03 | HB25: 0.04 | HC25: 4.87 | HD25: 17.14 | HE25: 0.06 | HF25: 15.5
GO26: Concentrados Proteicos | GP26: Algodão Caroço | GQ26: 90.66 | GR26: 20.06 | GS26: 22.94 | GT26: 95.62 | GU26: 41.7 | GV26: 0.27 | GW26: 0.74 | GX26: 0.52 | GY26: 0.91 | GZ26: 0.12
B27: BIBLIOTECA DE ALIMENTOS | AW27: =AV24-AV9 -> 0 | AX27: =AW24-AW9 -> 0 | GO27: Concentrados Proteicos | GP27: Algodão Farelo 28%PB | GQ27: 89.71 | GR27: 1.99 | GS27: 31.48 | GT27: 77.08 | GU27: 33.26 | GV27: 0.26 | GW27: 0.78 | GX27: 0.54 | GY27: 1.27 | GZ27: 0.04 | HA27: 0.22 | HB27: 0.51 | HC27: 18.79 | HD27: 23.68 | HF27: 62.42
B28: Forragem | C28: M.S (%) | D28: NDT (% M.S) | E28: PB (% M.S) | F28: Ca (% M.S) | G28: P (% M.S) | H28: PDR (%M.S) | I28: FDN (%M.S) | J28: EE (%M.S) | K28: Mg (%M.S) | L28: Na (%M.S) | M28: K (%M.S) | N28: S (%M.S) | O28: Cu (mg/kg) | P28: Zn (mg/kg) | Q28: Fe (mg/kg) | R28: Mn (mg/kg) | S28: I (mg/kg) | T28: Co (mg/kg) | U28: Se (mg/kg) | GO28: Concentrados Proteicos | GP28: Algodão Farelo 38%PB | GQ28: 89.74 | GR28: 1.46 | GS28: 39.63 | GT28: 75.71 | GU28: 29.46 | GV28: 0.24 | GW28: 0.97 | HC28: 11.19 | HD28: 33.93 | HF28: 11.8
B29: Capim Andropogon | C29: 0.2555 | D29: 0.5356 | E29: 0.0449 | F29: 0.0004 | G29: 0 | I29: 0.7013 | J29: 0.0215 | K29: 0 | L29: 0 | M29: 0 | N29: 0 | O29: 0 | P29: 0 | R29: 0 | T29: 0 | GO29: Concentrados Proteicos | GP29: Algodão Torta | GQ29: 90.48 | GR29: 9.3 | GS29: 29.72 | GT29: 81.88 | GU29: 45.21 | GV29: 0.28 | GW29: 0.58
B30: Braquiária Brizantha | C30: 0.3409 | D30: 0.5668 | E30: 0.0691 | F30: 0.0031 | G30: 0.0011 | I30: 0.6384 | J30: 0.0196 | K30: 0.0041 | L30: 0.0002 | M30: 0.0165 | N30: 0.0009 | O30: 3.48 | P30: 26.4 | R30: 103.19 | T30: 0.07 | GO30: Concentrados Proteicos | GP30: Grão de Destilaria Seco (DDG 18%) | GQ30: 89.28 | GR30: 8.61 | GS30: 17.93 | GT30: 81.09 | GU30: 42.67 | GV30: 0.04 | GW30: 0.67
B31: Marandu | C31: 0.3324 | D31: 0.5552 | E31: 0.0768 | F31: 0.0028 | G31: 0.0009 | I31: 0.6415 | J31: 0.0195 | K31: 0.001 | L31: 0.0002 | M31: 0.0072 | N31: 0.0003 | O31: 15 | P31: 10 | R31: 56 | T31: 0.46 | GO31: Concentrados Proteicos | GP31: Grão de Destilaria Seco (DDG 30%) | GQ31: 88.56 | GR31: 5.28 | GS31: 32.27 | GT31: 74.09 | GU31: 52.39 | GV31: 2.25 | GW31: 0.34
B32: Decumbens | C32: 0.2849 | D32: 0.5533 | E32: 0.0674 | F32: 0.004 | G32: 0.001 | I32: 0.6638 | J32: 0.0181 | K32: 0.0009 | L32: 0.0001 | M32: 0.0094 | N32: 0.0004 | O32: 3.8 | P32: 28 | R32: 85 | T32: 0.28 | CL32: 0.3 | GO32: Concentrados Proteicos | GP32: Soja Farelo | GQ32: 88.65 | GR32: 1.93 | GS32: 48.85 | GT32: 79.45 | GU32: 13.1 | GV32: 0.34 | GW32: 0.59 | GX32: 0.29 | GY32: 2.02 | GZ32: 0.06 | HA32: 0.26 | HB32: 0.27 | HC32: 18.96 | HD32: 35.38 | HE32: 0.13 | HF32: 53.79
B33: Humidícola | C33: 0.2812 | D33: 0.5661 | E33: 0.0738 | F33: 0.0038 | G33: 0.0012 | I33: 0.7186 | J33: 0.0245 | K33: 0.002 | L33: 0.0002 | M33: 0.0199 | N33: 0.0004 | O33: 13.32 | P33: 19 | R33: 93.82 | T33: 0.09 | BM33: ELm | BN33: =IF(C13="Pasto",0.075*BJ70^0.75,IF(C10="Zebuíno",0.075*BJ70^0.75,0.075*BJ70^0.75)) -> #VALUE! | BO33: Mcal | CL33: =((120*K10)+(BN58-(120*K10)*0.64)/0.8)/1000 -> #VALUE! | CM33: =-53.07 + (304.89 * (CL33)) + (90.79 *K10) - (3.13 * K10*K10) -> #VALUE! | GO33: Concentrados Proteicos | GP33: Soja Farelo Extrusado | GQ33: 96.73 | GR33: 10.6 | GS33: 40.98 | GT33: 88.76 | GU33: 11.8 | GV33: 0.07 | GW33: 0.57 | GY33: 1.9 | GZ33: 0.06
B34: Capim Gordura | C34: 0.2772 | D34: 0.5668 | E34: 0.0692 | F34: 0.0024 | G34: 0.0007 | I34: 0.7229 | J34: 0.013 | K34: 0.0014 | L34: 0.0002 | M34: 0.0067 | N34: 0 | O34: 0 | P34: 0 | R34: 0 | T34: 0 | BM34: Elg | BN34: =IF(C13="pasto",BJ79,BJ78) -> #VALUE! | BO34: Mcal | CL34: =(CM33+(BN58-(CM33*0.64))/0.8)/1000 -> #VALUE! | CM34: =-53.07 + (304.89 * (CL34)) + (90.79 *K10) - (3.13 * K10*K10) -> #VALUE! | GO34: Fontes Minerais | GP34: Fosfato Supersimples | GQ34: 100 | GV34: 20.53 | GW34: 9.77
B35: Capim Massai | C35: 0.2948 | D35: 0.562 | E35: 0.0799 | F35: 0 | G35: 0 | I35: 0.7002 | J35: 0.0206 | K35: 0 | L35: 0 | M35: 0 | N35: 0 | O35: 0 | P35: 0 | R35: 0 | T35: 0 | BM35: EL | BN35: =BN34+BN33 -> #VALUE! | BO35: Mcal | CL35: =(CM34+(BN58-(CM34*0.64))/0.8)/1000 -> #VALUE! | CM35: =-53.07 + (304.89 * (CL35)) + (90.79 *K10) - (3.13 * K10*K10) -> #VALUE! | GO35: Fontes Minerais | GP35: Fosfato Supertriplo | GQ35: 100 | GW35: 15.31 | GX35: 20.27
B36: Capim Mombaça | C36: 0.27 | D36: 0.59 | E36: 0.12 | F36: 0.0074 | G36: 0.0019 | I36: 0.55 | J36: 0.0173 | K36: 0.002 | L36: 0.0001 | M36: 0.0274 | N36: 0.0014 | O36: 10.07 | P36: 26.81 | R36: 99.99 | T36: 0.41 | BM36: EMm | BN36: =BN33/BJ86 -> #VALUE! | BO36: Mcal | CE36: AMINOÁCIDOS* | CL36: =(CM35+(BN58-(CM35*0.64))/0.8)/1000 -> #VALUE! | CM36: =-53.07 + (304.89 * (CL36)) + (90.79 *K10) - (3.13 * K10*K10) -> #VALUE! | GO36: Fontes Minerais | GP36: Sal Comum | GQ36: 99.02 | GX36: 0.3 | GZ36: 0.06 | HA36: 39.55 | HD36: 1.34 | HE36: 2.71
B37: Capim Tifton 85 | C37: 0.2696 | D37: 0.5623 | E37: 0.1291 | F37: 0.0054 | G37: 0.005 | I37: 0.4883 | J37: 0.02 | K37: 0.0017 | L37: 0 | M37: 0.0128 | N37: 0.0018 | O37: 10.35 | P37: 32.22 | R37: 305 | T37: 0 | BM37: EMg | BN37: =BN34/BJ83 -> #VALUE! | BO37: Mcal | CL37: =(CM36+(BN58-(CM36*0.64))/0.8)/1000 -> #VALUE! | CM37: =-53.07 + (304.89 * (CL37)) + (90.79 *K10) - (3.13 * K10*K10) -> #VALUE!
B38: Milheto | C38: 0.1983 | D38: 0.5877 | E38: 0.1223 | F38: 0.0072 | G38: 0.0026 | I38: 0.6362 | J38: 0.0306 | K38: 0 | L38: 0 | M38: 0 | N38: 0 | O38: 0 | P38: 0 | R38: 0 | T38: 0 | BM38: EM | BN38: =BN37+BN36 -> #VALUE! | BO38: Mcal | CE38: Essenciais | CF38: Arg | CG38: Efi. Util. | CH38: =BJ211 -> #VALUE! | CI38: g | CL38: =(CM37+(BN58-(CM37*0.64))/0.8)/1000 -> #VALUE! | CM38: =-53.07 + (304.89 * (CL38)) + (90.79 *K10) - (3.13 * K10*K10) -> #VALUE! | HG38: 9.94
B39: Sorgo Forrageiro | C39: 0.2411 | D39: 0.579 | E39: 0.0684 | F39: 0.0013 | G39: 0.0013 | I39: 0.6335 | J39: 0.0304 | K39: 0.0026 | L39: 0 | M39: 0 | N39: 0 | O39: 0 | P39: 0 | R39: 0 | T39: 0 | CG39: 0.56 | CL39: =(CM38+(BN58-(CM38*0.64))/0.8)/1000 -> #VALUE! | CM39: =-53.07 + (304.89 * (CL39)) + (90.79 *K10) - (3.13 * K10*K10) -> #VALUE!
BM40: Ca | BN40: 0.568 | CF40: His | CG40: Efi. Util. | CH40: =BJ216 -> #VALUE! | CI40: g | CL40: =(CM39+(BN58-(CM39*0.64))/0.8)/1000 -> #VALUE! | CM40: =-53.07 + (304.89 * (CL40)) + (90.79 *K10) - (3.13 * K10*K10) -> #VALUE!
BM41: P | BN41: 0.678 | CG41: 0.62 | CL41: =(CM40+(BN58-(CM40*0.64))/0.8)/1000 -> #VALUE! | CM41: =-53.07 + (304.89 * (CL41)) + (90.79 *K10) - (3.13 * K10*K10) -> #VALUE!
B42: Concentrados | C42: M.S (% M.S) | D42: NDT (% M.S) | E42: PB (% M.S) | F42: Ca (% M.S) | G42: P (% M.S) | H42: PDR (% M.S) | I42: FDN (% M.S) | J42: EE (% M.S) | K42: Mg (% M.S) | L42: Na (% M.S) | M42: K(% M.S) | N42: S (% M.S) | O42: Cu (mg) | P42: Zn (mg) | Q42: Fe (mg) | R42: Mn (mg) | S42: I (mg) | T42: Co (mg) | U42: Se (mg) | V42: R$/kg | W42: R$/NDT | X42: R$/PB | BM42: Mg | BN42: 0.355 | CF42: Ile | CG42: Efi. Util. | CH42: =BJ221 -> #VALUE! | CI42: g | CL42: =(CM41+(BN58-(CM41*0.64))/0.8)/1000 -> #VALUE! | CM42: =-53.07 + (304.89 * (CL42)) + (90.79 *K10) - (3.13 * K10*K10) -> #VALUE!
B43: Milho | C43: 0.8788 | D43: 0.8692 | E43: 0.0896 | F43: 0.0003 | G43: 0.0026 | I43: 0.1239 | J43: 0.04 | K43: 0.0011 | L43: 0.0003 | M43: 0.0035 | N43: 0.0004 | O43: 3.48 | P43: 18.85 | R43: 8.8 | T43: 0.02 | U43: 0.07 | W43: =IFERROR(IF(V43/D43=0,"",V43/D43),"") | X43: =IFERROR(IF(V43/E43=0,"",V43/E43),"") | BM43: Na | BN43: 0.371 | CG43: 0.3 | CL43: =(CM42+(BN58-(CM42*0.64))/0.8)/1000 -> #VALUE! | CM43: =-53.07 + (304.89 * (CL43)) + (90.79 *K10) - (3.13 * K10*K10) -> #VALUE!
B44: Soja Casca | C44: 0.901 | D44: 0.7311 | E44: 0.1267 | F44: 0.0052 | G44: 0.0016 | I44: 0.6098 | J44: 0.0222 | K44: 0.0034 | L44: 0.0008 | M44: 0.0087 | N44: 0.0009 | O44: 6.46 | P44: 48.07 | R44: 17.55 | T44: 5.01 | W44: =IFERROR(IF(V44/D44=0,"",V44/D44),"") | X44: =IFERROR(IF(V44/E44=0,"",V44/E44),"") | BM44: K | BN44: 0.484 | CF44: Leu | CG44: Efi. Util. | CH44: =BJ226 -> #VALUE! | CI44: g | CL44: =(CM43+(BN58-(CM43*0.64))/0.8)/1000 -> #VALUE! | CM44: =-53.07 + (304.89 * (CL44)) + (90.79 *K10) - (3.13 * K10*K10) -> #VALUE!
B45: Sorgo Grão | C45: 0.8801 | D45: 0.8419 | E45: 0.0933 | F45: 0.0007 | G45: 0.0029 | I45: 0.1058 | J45: 0.0291 | K45: 0.0019 | L45: 0.0003 | M45: 0.0073 | N45: 0.0003 | O45: 4.87 | P45: 15.5 | R45: 17.14 | T45: 0.04 | U45: 0.06 | W45: =IFERROR(IF(V45/D45=0,"",V45/D45),"") | X45: =IFERROR(IF(V45/E45=0,"",V45/E45),"") | BM45: S | BN45: 0.773 | CG45: 0.3 | CL45: =(CM44+(BN58-(CM44*0.64))/0.8)/1000 -> #VALUE! | CM45: =-53.07 + (304.89 * (CL45)) + (90.79 *K10) - (3.13 * K10*K10) -> #VALUE!
B46: Algodão Caroço | C46: 0.9066 | D46: 0.9562 | E46: 0.2294 | F46: 0.0027 | G46: 0.0074 | I46: 0.417 | J46: 0.2006 | K46: 0.0052 | L46: 0.0012 | M46: 0.0091 | N46: 0 | W46: =IFERROR(IF(V46/D46=0,"",V46/D46),"") | X46: =IFERROR(IF(V46/E46=0,"",V46/E46),"") | BM46: Cu | BN46: 0.735 | CF46: Lys | CG46: Efi. Util. | CH46: =BJ231 -> #VALUE! | CI46: g | CL46: =(CM45+(BN58-(CM45*0.64))/0.8)/1000 -> #VALUE! | CM46: =-53.07 + (304.89 * (CL46)) + (90.79 *K10) - (3.13 * K10*K10) -> #VALUE!
B47: Algodão Farelo 28%PB | C47: 0.8971 | D47: 0.7708 | E47: 0.3148 | F47: 0.0026 | G47: 0.0078 | I47: 0.3326 | J47: 0.0199 | K47: 0.0054 | L47: 0.0004 | M47: 0.0127 | N47: 0.0022 | O47: 18.79 | P47: 62.42 | R47: 23.68 | T47: 0.51 | W47: =IFERROR(IF(V47/D47=0,"",V47/D47),"") | X47: =IFERROR(IF(V47/E47=0,"",V47/E47),"") | BM47: Co | BN47: 0.868 | CG47: 0.37 | CL47: =(CM46+(BN58-(CM46*0.64))/0.8)/1000 -> #VALUE! | CM47: =-53.07 + (304.89 * (CL47)) + (90.79 *K10) - (3.13 * K10*K10) -> #VALUE!
B48: Algodão Farelo 38%PB | C48: 0.8974 | D48: 0.7571 | E48: 0.3963 | F48: 0.0024 | G48: 0.0097 | I48: 0.2946 | J48: 0.0146 | O48: 11.19 | P48: 11.8 | R48: 33.93 | W48: =IFERROR(IF(V48/D48=0,"",V48/D48),"") | X48: =IFERROR(IF(V48/E48=0,"",V48/E48),"") | BM48: Cr | BN48: 0.784 | CF48: Met | CG48: Efi. Util. | CH48: =BJ236 -> #VALUE! | CI48: g | CL48: =(CM47+(BN58-(CM47*0.64))/0.8)/1000 -> #VALUE! | CM48: =-53.07 + (304.89 * (CL48)) + (90.79 *K10) - (3.13 * K10*K10) -> #VALUE!
B49: Algodão Torta | C49: 0.9048 | D49: 0.8188 | E49: 0.2972 | F49: 0.0028 | G49: 0.0058 | I49: 0.4521 | J49: 0.093 | W49: =IFERROR(IF(V49/D49=0,"",V49/D49),"") | X49: =IFERROR(IF(V49/E49=0,"",V49/E49),"") | BM49: Fe | BN49: 0.734 | CG49: 0.58 | CL49: =(CM48+(BN58-(CM48*0.64))/0.8)/1000 -> #VALUE! | CM49: =-53.07 + (304.89 * (CL49)) + (90.79 *K10) - (3.13 * K10*K10) -> #VALUE!
B50: DDG 18% | C50: 0.8928 | D50: 0.8109 | E50: 0.1793 | F50: 0.0004 | G50: 0.0067 | I50: 0.4267 | J50: 0.0861 | W50: =IFERROR(IF(V50/D50=0,"",V50/D50),"") | X50: =IFERROR(IF(V50/E50=0,"",V50/E50),"") | BM50: Mn | BN50: 0.439 | CF50: Phe | CG50: Efi. Util. | CH50: =BJ241 -> #VALUE! | CI50: g | CL50: =(CM49+(BN58-(CM49*0.64))/0.8)/1000 -> #VALUE! | CM50: =-53.07 + (304.89 * (CL50)) + (90.79 *K10) - (3.13 * K10*K10) -> #VALUE!
B51: DDG 30% | C51: 0.8856 | D51: 0.7409 | E51: 0.3227 | F51: 0.0225 | G51: 0.0034 | I51: 0.5239 | J51: 0.0528 | W51: =IFERROR(IF(V51/D51=0,"",V51/D51),"") | X51: =IFERROR(IF(V51/E51=0,"",V51/E51),"") | BM51: Mo | BN51: 0.497 | CG51: 0.31 | CL51: =(CM50+(BN58-(CM50*0.64))/0.8)/1000 -> #VALUE! | CM51: =-53.07 + (304.89 * (CL51)) + (90.79 *K10) - (3.13 * K10*K10) -> #VALUE!
B52: Soja Farelo | C52: 0.8865 | D52: 0.7945 | E52: 0.4885 | F52: 0.0034 | G52: 0.0059 | I52: 0.131 | J52: 0.0193 | K52: 0.0029 | L52: 0.0006 | M52: 0.0202 | N52: 0.0026 | O52: 18.96 | P52: 53.79 | R52: 35.38 | T52: 0.27 | U52: 0.13 | W52: =IFERROR(IF(V52/D52=0,"",V52/D52),"") | X52: =IFERROR(IF(V52/E52=0,"",V52/E52),"") | BM52: Se | BN52: 0.487 | CF52: Thr | CG52: Efi. Util. | CH52: =BJ246 -> #VALUE! | CI52: g | CL52: =(CM51+(BN58-(CM51*0.64))/0.8)/1000 -> #VALUE! | CM52: =-53.07 + (304.89 * (CL52)) + (90.79 *K10) - (3.13 * K10*K10) -> #VALUE!
B53: Sal comum | C53: 0.99 | L53: 0.39 | O53: 1.34 | P53: 9.9 | R53: 2.71 | W53: =IFERROR(IF(V53/D53=0,"",V53/D53),"") | X53: =IFERROR(IF(V53/E53=0,"",V53/E53),"") | BM53: Zn | BN53: 0.668 | CG53: 0.34 | CL53: =(CM52+(BN58-(CM52*0.64))/0.8)/1000 -> #VALUE! | CM53: =-53.07 + (304.89 * (CL53)) + (90.79 *K10) - (3.13 * K10*K10) -> #VALUE!
W54: =IFERROR(IF(V54/D54=0,"",V54/D54),"") | X54: =IFERROR(IF(V54/E54=0,"",V54/E54),"") | CF54: Trp | CG54: Efi. Util. | CH54: =BJ251 -> #VALUE! | CI54: g | CL54: =(CM53+(BN58-(CM53*0.64))/0.8)/1000 -> #VALUE! | CM54: =-53.07 + (304.89 * (CL54)) + (90.79 *K10) - (3.13 * K10*K10) -> #VALUE!
B55: Ureia | BM55: PMm | BN55: =IF(C13="Pasto",3.9*BJ69^0.75,3.6*BJ69^0.75) -> #VALUE! | BO55: g | CG55: 0.39 | CL55: =(CM54+(BN58-(CM54*0.64))/0.8)/1000 -> #VALUE! | CM55: =-53.07 + (304.89 * (CL55)) + (90.79 *K10) - (3.13 * K10*K10) -> #VALUE!
B56: Mineral/núcleo | C56: M.S (g/kg) | D56: NDT (g/kg) | E56: PB (g/kg) | F56: Ca (g/kg) | G56: P (g/kg) | H56: PDR (g/kg) | I56: FDN (g/kg) | J56: EE (g/kg) | K56: Mg (g/kg) | L56: Na (g/kg) | M56: K (g/kg) | N56: S (g/kg) | O56: Cu (mg/kg) | P56: Zn (mg/kg) | Q56: Fe (g/kg) | R56: Mn (mg/kg) | S56: I (mg/kg) | T56: Co (mg/kg) | U56: Se (mg/kg) | V56: NNP (g/kg) | W56: % ureia | BM56: PLg | BN56: =176.01*BJ71-0.381*BJ75^0.75*BJ71^1.035 -> #VALUE! | BO56: g | CF56: Val | CG56: Efi. Util. | CH56: =BJ256 -> #VALUE! | CI56: g | CL56: =(CM55+(BN58-(CM55*0.64))/0.8)/1000 -> #VALUE! | CM56: =-53.07 + (304.89 * (CL56)) + (90.79 *K10) - (3.13 * K10*K10) -> #VALUE!
B57: Fosbovi boi verde | C57: 1 | F57: 160 | G57: 120 | N57: 80 | O57: 1250 | P57: 5000 | R57: 2500 | S57: 0.62 | T57: 12.5 | U57: 25 | W57: =IF('Formulação de suplemento'!$V57/28.125/100=0,"",'Formulação de suplemento'!$V57/28.125/100) | BM57: PMg | BN57: =BN56/IF(BJ69<=340,84.665-0.1179*BJ75,47.4)*100 -> #VALUE! | BO57: g | CG57: 0.4 | CL57: =(CM56+(BN58-(CM56*0.64))/0.8)/1000 -> #VALUE! | CM57: =-53.07 + (304.89 * (CL57)) + (90.79 *K10) - (3.13 * K10*K10) -> #VALUE!
B58: Fortumix +engorda SP | C58: 1 | F58: 180 | G58: 29 | K58: 10 | N58: 10 | O58: 1000 | P58: 3000 | R58: 300 | S58: 50 | T58: 90 | U58: 6.6 | W58: =IF('Formulação de suplemento'!$V58/28.125/100=0,"",'Formulação de suplemento'!$V58/28.125/100) | BM58: PM | BN58: =BN57+BN55 -> #VALUE! | BO58: g | CL58: =(CM57+(BN58-(CM57*0.64))/0.8)/1000 -> #VALUE! | CM58: =-53.07 + (304.89 * (CL58)) + (90.79 *K10) - (3.13 * K10*K10) -> #VALUE!
W59: =IF('Formulação de suplemento'!$V59/28.125/100=0,"",'Formulação de suplemento'!$V59/28.125/100) | BM59: PBmic | BN59: =CM132 -> #VALUE! | BO59: g | CE59: Não Essenciais | CF59: Ala | CG59: Efi. Util. | CH59: =BJ261 -> #VALUE! | CI59: g | CL59: =(CM58+(BN58-(CM58*0.64))/0.8)/1000 -> #VALUE! | CM59: =-53.07 + (304.89 * (CL59)) + (90.79 *K10) - (3.13 * K10*K10) -> #VALUE!
W60: =IF('Formulação de suplemento'!$V60/28.125/100=0,"",'Formulação de suplemento'!$V60/28.125/100) | BM60: PDR | BN60: =BN59 -> #VALUE! | BO60: g | CG60: 0.35 | CL60: =(CM59+(BN58-(CM59*0.64))/0.8)/1000 -> #VALUE! | CM60: =-53.07 + (304.89 * (CL60)) + (90.79 *K10) - (3.13 * K10*K10) -> #VALUE!
W61: =IF('Formulação de suplemento'!$V61/28.125/100=0,"",'Formulação de suplemento'!$V61/28.125/100) | BM61: PNDR | BN61: =(BN58-(BN59*0.64))/0.8 -> #VALUE! | BO61: g | CF61: Asp | CG61: Efi. Util. | CH61: =BJ266 -> #VALUE! | CI61: g | CL61: =(CM60+(BN58-(CM60*0.64))/0.8)/1000 -> #VALUE! | CM61: =-53.07 + (304.89 * (CL61)) + (90.79 *K10) - (3.13 * K10*K10) -> #VALUE!
W62: =IF('Formulação de suplemento'!$V62/28.125/100=0,"",'Formulação de suplemento'!$V62/28.125/100) | CG62: 0.26 | CL62: =(CM61+(BN58-(CM61*0.64))/0.8)/1000 -> #VALUE! | CM62: =-53.07 + (304.89 * (CL62)) + (90.79 *K10) - (3.13 * K10*K10) -> #VALUE!
W63: =IF('Formulação de suplemento'!$V63/28.125/100=0,"",'Formulação de suplemento'!$V63/28.125/100) | CF63: Cys | CG63: Efi. Util. | CH63: =BJ281 -> #VALUE! | CI63: g | CL63: =(CM62+(BN58-(CM62*0.64))/0.8)/1000 -> #VALUE! | CM63: =-53.07 + (304.89 * (CL63)) + (90.79 *K10) - (3.13 * K10*K10) -> #VALUE!
W64: =IF('Formulação de suplemento'!$V64/28.125/100=0,"",'Formulação de suplemento'!$V64/28.125/100) | CG64: 0.18 | CL64: =(CM63+(BN58-(CM63*0.64))/0.8)/1000 -> #VALUE! | CM64: =-53.07 + (304.89 * (CL64)) + (90.79 *K10) - (3.13 * K10*K10) -> #VALUE!
W65: =IF('Formulação de suplemento'!$V65/28.125/100=0,"",'Formulação de suplemento'!$V65/28.125/100) | CF65: Glu | CG65: Efi. Util. | CH65: =BJ276 -> #VALUE! | CI65: g | CL65: =(CM64+(BN58-(CM64*0.64))/0.8)/1000 -> #VALUE! | CM65: =-53.07 + (304.89 * (CL65)) + (90.79 *K10) - (3.13 * K10*K10) -> #VALUE!
W66: =IF('Formulação de suplemento'!$V66/28.125/100=0,"",'Formulação de suplemento'!$V66/28.125/100) | CG66: 0.67 | CL66: =(CM65+(BN58-(CM65*0.64))/0.8)/1000 -> #VALUE! | CM66: =-53.07 + (304.89 * (CL66)) + (90.79 *K10) - (3.13 * K10*K10) -> #VALUE!
W67: =IF('Formulação de suplemento'!$V67/28.125/100=0,"",'Formulação de suplemento'!$V67/28.125/100) | CF67: Gly | CG67: Efi. Util. | CH67: =BJ281 -> #VALUE! | CI67: g | CL67: =(CM66+(BN58-(CM66*0.64))/0.8)/1000 -> #VALUE! | CM67: =-53.07 + (304.89 * (CL67)) + (90.79 *K10) - (3.13 * K10*K10) -> #VALUE!
W68: =IF('Formulação de suplemento'!$V68/28.125/100=0,"",'Formulação de suplemento'!$V68/28.125/100) | CG68: 0.63 | CL68: =(CM67+(BN58-(CM67*0.64))/0.8)/1000 -> #VALUE! | CM68: =-53.07 + (304.89 * (CL68)) + (90.79 *K10) - (3.13 * K10*K10) -> #VALUE!
BI69: Peso vivo | BJ69: =IF(C10="Cruzado",IF(C11="Leite",0.9247*C8^1.0085,0.8915*C8^1.0151),0.8915*C8^1.0151) -> #VALUE! | CF69: Pro | CG69: Efi. Util. | CH69: =BJ286 -> #VALUE! | CI69: g | CL69: =(CM68+(BN58-(CM68*0.64))/0.8)/1000 -> #VALUE! | CM69: =-53.07 + (304.89 * (CL69)) + (90.79 *K10) - (3.13 * K10*K10) -> #VALUE!
BI70: PCVZ | BJ70: =IF(C13="confinamento",IF(C10="Zebuíno",(IF(C12="Macho não castrado",0.8126*BJ69^1.0134,IF(C12="macho castrado",0.6241*BJ69^1.0608,0.611*BJ69^1.0667))),(IF(C12="Macho não castrado",0.7248*BJ69^1.0314,IF(C12="macho castrado",0.6586*BJ69^1.0499,0.6314*BJ69^1.0602)))),0.8507*BJ69^1.0002) -> #VALUE! | CG70: 0.43 | CL70: =(CM69+(BN58-(CM69*0.64))/0.8)/1000 -> #VALUE! | CM70: =-53.07 + (304.89 * (CL70)) + (90.79 *K10) - (3.13 * K10*K10) -> #VALUE!
B71: Atenção: | BI71: GPCVZ | BJ71: =0.963*C9^1.0151 -> 0 | CF71: Ser | CG71: Efi. Util. | CH71: =BJ291 -> #VALUE! | CI71: g | CL71: =(CM70+(BN58-(CM70*0.64))/0.8)/1000 -> #VALUE! | CM71: =-53.07 + (304.89 * (CL71)) + (90.79 *K10) - (3.13 * K10*K10) -> #VALUE!
B72: - Essa planilha é de uso exclusivo dos alunos do Programa Acelerador de Arrobas, não podendo ser compartilhada ou vendida separadamente. | BH72: PCVZequivalente | BI72: Zebuíno | BJ72: =IF(C12="Macho não castrado",(BJ70/517)*517,IF(C12="macho castrado",(BJ70/433)*517,(BJ70/402)*517)) -> #VALUE! | CG72: 0.31 | CL72: =(CM71+(BN58-(CM71*0.64))/0.8)/1000 -> #VALUE! | CM72: =-53.07 + (304.89 * (CL72)) + (90.79 *K10) - (3.13 * K10*K10) -> #VALUE!
B73: - Os dados gerados e coletados aqui não garantem resultado, visto que o mesmo depende de diversos outros fatores, como ensinado nas aulas. | BI73: CruzCorte | BJ73: =IF(C12="Macho não castrado",(BJ70/560)*517,IF(C12="macho castrado",(BJ70/482)*517,(BJ70/417)*517)) -> #VALUE! | CF73: Tyr | CG73: Efi. Util. | CH73: =BJ296 -> #VALUE! | CI73: g | CL73: =(CM72+(BN58-(CM72*0.64))/0.8)/1000 -> #VALUE! | CM73: =-53.07 + (304.89 * (CL73)) + (90.79 *K10) - (3.13 * K10*K10) -> #VALUE!
B74: - Essa planilha não se responsabiliza por falhas na nutrição, visto que a mesam depende de diversos outros fatores para falhar ou alcançar o sucesso, como ensinado nas aulas. | BI74: CruzLeite | BJ74: =IF(C12="Macho não castrado",(BJ70/616)*517,IF(C12="macho castrado",(BJ70/532)*517,(BJ70/493)*517)) -> #VALUE! | CG74: 0.26 | CL74: =(CM73+(BN58-(CM73*0.64))/0.8)/1000 -> #VALUE! | CM74: =-53.07 + (304.89 * (CL74)) + (90.79 *K10) - (3.13 * K10*K10) -> #VALUE!
B75: - Os alimentos inseridos na biblioteca não representam a realidade de todos os locais. Sempre faça análise bromatológica e peça os níveis de garantia. | BI75: PCVZeq | BJ75: =IF(C10="Zebuíno",BJ72,IF(C11="corte",BJ73,BJ74)) -> #VALUE! | CL75: =(CM74+(BN58-(CM74*0.64))/0.8)/1000 -> #VALUE! | CM75: =-53.07 + (304.89 * (CL75)) + (90.79 *K10) - (3.13 * K10*K10) -> #VALUE!
B76: - Essa planilha é para formulações simples, que tem capim em pastejo como base da dieta. | BI76: CMS | CL76: =(CM75+(BN58-(CM75*0.64))/0.8)/1000 -> #VALUE! | CM76: =-53.07 + (304.89 * (CL76)) + (90.79 *K10) - (3.13 * K10*K10) -> #VALUE!
BH77: Energia | BI77: ELm | CL77: =(CM76+(BN58-(CM76*0.64))/0.8)/1000 -> #VALUE! | CM77: =-53.07 + (304.89 * (CL77)) + (90.79 *K10) - (3.13 * K10*K10) -> #VALUE!
BI78: ELg conf | BJ78: =IF(C10="Zebuíno",0.061*BJ75^0.75*BJ71^1.035,IF(C11="corte",0.061*BJ75^0.75*BJ71^1.035,0.061*BJ75^0.75*BJ71^1.035)) -> #VALUE! | CL78: =(CM77+(BN58-(CM77*0.64))/0.8)/1000 -> #VALUE! | CM78: =-53.07 + (304.89 * (CL78)) + (90.79 *K10) - (3.13 * K10*K10) -> #VALUE!
BI79: ELg past | BJ79: =IF(C10="Zebuíno",0.052*BJ75^0.75*BJ71^1.062,IF(C11="corte",0.052*BJ75^0.75*BJ71^1.062,0.052*BJ75^0.75*BJ71^1.062)) -> #VALUE! | CL79: =(CM78+(BN58-(CM78*0.64))/0.8)/1000 -> #VALUE! | CM79: =-53.07 + (304.89 * (CL79)) + (90.79 *K10) - (3.13 * K10*K10) -> #VALUE!
BI80: Elg | CL80: =(CM79+(BN58-(CM79*0.64))/0.8)/1000 -> #VALUE! | CM80: =-53.07 + (304.89 * (CL80)) + (90.79 *K10) - (3.13 * K10*K10) -> #VALUE!
BI81: EL | CL81: =(CM80+(BN58-(CM80*0.64))/0.8)/1000 -> #VALUE! | CM81: =-53.07 + (304.89 * (CL81)) + (90.79 *K10) - (3.13 * K10*K10) -> #VALUE!
BI82: ERp | BJ82: =1.14*(BN34/BJ71)^-1.137 -> #VALUE! | CL82: =(CM81+(BN58-(CM81*0.64))/0.8)/1000 -> #VALUE! | CM82: =-53.07 + (304.89 * (CL82)) + (90.79 *K10) - (3.13 * K10*K10) -> #VALUE!
BI83: kg | BJ83: =0.327/(0.539+(1.14*(BN34/BJ71)^-1.137)) -> #VALUE! | CL83: =(CM82+(BN58-(CM82*0.64))/0.8)/1000 -> #VALUE! | CM83: =-53.07 + (304.89 * (CL83)) + (90.79 *K10) - (3.13 * K10*K10) -> #VALUE!
BI84: km conf | BJ84: =IF(C10="Cruzado",IF(C11="corte",0.513+0.173*BJ83+0.073*BJ71,0.513+0.173*BJ83+0.01*BJ71),0.513+0.173*BJ83+0.1*BJ71) -> #VALUE! | CL84: =(CM83+(BN58-(CM83*0.64))/0.8)/1000 -> #VALUE! | CM84: =-53.07 + (304.89 * (CL84)) + (90.79 *K10) - (3.13 * K10*K10) -> #VALUE!
BI85: km pasto | BJ85: =(0.513+0.173*BJ83+0.1*BJ71)*0.92 -> #VALUE! | CL85: =(CM84+(BN58-(CM84*0.64))/0.8)/1000 -> #VALUE! | CM85: =-53.07 + (304.89 * (CL85)) + (90.79 *K10) - (3.13 * K10*K10) -> #VALUE!
BI86: km | BJ86: =IF(C13="Pasto",BJ85,BJ84) -> #VALUE! | CL86: =(CM85+(BN58-(CM85*0.64))/0.8)/1000 -> #VALUE! | CM86: =-53.07 + (304.89 * (CL86)) + (90.79 *K10) - (3.13 * K10*K10) -> #VALUE!
BI87: EMm | CL87: =(CM86+(BN58-(CM86*0.64))/0.8)/1000 -> #VALUE! | CM87: =-53.07 + (304.89 * (CL87)) + (90.79 *K10) - (3.13 * K10*K10) -> #VALUE!
BI88: EMg | CL88: =(CM87+(BN58-(CM87*0.64))/0.8)/1000 -> #VALUE! | CM88: =-53.07 + (304.89 * (CL88)) + (90.79 *K10) - (3.13 * K10*K10) -> #VALUE!
BI89: EM | CL89: =(CM88+(BN58-(CM88*0.64))/0.8)/1000 -> #VALUE! | CM89: =-53.07 + (304.89 * (CL89)) + (90.79 *K10) - (3.13 * K10*K10) -> #VALUE!
BI90: ED | BJ90: =(((BN38/K7)+0.3032)/0.9455)*K7 -> #VALUE! | CL90: =(CM89+(BN58-(CM89*0.64))/0.8)/1000 -> #VALUE! | CM90: =-53.07 + (304.89 * (CL90)) + (90.79 *K10) - (3.13 * K10*K10) -> #VALUE!
BI91: NDT | CL91: =(CM90+(BN58-(CM90*0.64))/0.8)/1000 -> #VALUE! | CM91: =-53.07 + (304.89 * (CL91)) + (90.79 *K10) - (3.13 * K10*K10) -> #VALUE!
BI92: NDT, % | CL92: =(CM91+(BN58-(CM91*0.64))/0.8)/1000 -> #VALUE! | CM92: =-53.07 + (304.89 * (CL92)) + (90.79 *K10) - (3.13 * K10*K10) -> #VALUE!
CL93: =(CM92+(BN58-(CM92*0.64))/0.8)/1000 -> #VALUE! | CM93: =-53.07 + (304.89 * (CL93)) + (90.79 *K10) - (3.13 * K10*K10) -> #VALUE!
BH94: Proteína | BI94: PMm | CL94: =(CM93+(BN58-(CM93*0.64))/0.8)/1000 -> #VALUE! | CM94: =-53.07 + (304.89 * (CL94)) + (90.79 *K10) - (3.13 * K10*K10) -> #VALUE!
BI95: PLg | CL95: =(CM94+(BN58-(CM94*0.64))/0.8)/1000 -> #VALUE! | CM95: =-53.07 + (304.89 * (CL95)) + (90.79 *K10) - (3.13 * K10*K10) -> #VALUE!
BI96: PMg | CL96: =(CM95+(BN58-(CM95*0.64))/0.8)/1000 -> #VALUE! | CM96: =-53.07 + (304.89 * (CL96)) + (90.79 *K10) - (3.13 * K10*K10) -> #VALUE!
BI97: PM | CL97: =(CM96+(BN58-(CM96*0.64))/0.8)/1000 -> #VALUE! | CM97: =-53.07 + (304.89 * (CL97)) + (90.79 *K10) - (3.13 * K10*K10) -> #VALUE!
BI98: PBmic | CL98: =(CM97+(BN58-(CM97*0.64))/0.8)/1000 -> #VALUE! | CM98: =-53.07 + (304.89 * (CL98)) + (90.79 *K10) - (3.13 * K10*K10) -> #VALUE!
BI99: Ef.Mic. | BJ99: =BN59/K10 -> #VALUE! | CL99: =(CM98+(BN58-(CM98*0.64))/0.8)/1000 -> #VALUE! | CM99: =-53.07 + (304.89 * (CL99)) + (90.79 *K10) - (3.13 * K10*K10) -> #VALUE!
BI100: PDR | CL100: =(CM99+(BN58-(CM99*0.64))/0.8)/1000 -> #VALUE! | CM100: =-53.07 + (304.89 * (CL100)) + (90.79 *K10) - (3.13 * K10*K10) -> #VALUE!
BI101: PNDR | CL101: =(CM100+(BN58-(CM100*0.64))/0.8)/1000 -> #VALUE! | CM101: =-53.07 + (304.89 * (CL101)) + (90.79 *K10) - (3.13 * K10*K10) -> #VALUE!
...

Sheet Relatório de suplementação
A1: ESTIMATIVA SUPLEMENTAÇÃO
B3: 01 - Informações gerais
B4: ="O suplemento formulado abaixo, são para animais com peso médio de "&'Formulação de suplemento'!C8&" kg (iniciando com "&'Formulação de suplemento'!C6&" kg e finalizando com "&'Formulação de suplemento'!C7&" kg) com estimativa de GMD de "&'Formulação de suplemento'!C9&" kg/dia, para pastos com a qualidade informada pelo aluno." -> O suplemento formulado abaixo, são para animais com peso médio de kg (iniciando com kg e finalizando com kg) com estimativa de GMD de kg/dia, para pastos com a qualidade informada pelo aluno.
B6: 02 - Informações gerais do suplemento
B7: A tabela abaixo apresenta a % de cada ingrediente que tem que constar na suplementação diária do seu animal, ou seja, essa será a batida realizada.
B9: TABELA DO SUPLEMENTO FORMULADO
B10: ='Formulação de suplemento'!E6 -> Ingrediente | D10: ='Formulação de suplemento'!F6 -> % | F10: ='Formulação de suplemento'!G6 -> R$/kg | H10: ='Formulação de suplemento'!H6 -> R$
B11: =IF('Formulação de suplemento'!E7=0,"Ocultar",'Formulação de suplemento'!E7) -> Ocultar | D11: =IF('Formulação de suplemento'!F7=0,"Ocultar",'Formulação de suplemento'!F7) -> Ocultar | F11: =IF('Formulação de suplemento'!G7=0,"Ocultar",'Formulação de suplemento'!G7) -> Ocultar | H11: =IF('Formulação de suplemento'!H7=0,"Ocultar",'Formulação de suplemento'!H7) -> Ocultar
B12: =IF('Formulação de suplemento'!E8=0,"Ocultar",'Formulação de suplemento'!E8) -> Ocultar | D12: =IF('Formulação de suplemento'!F8=0,"Ocultar",'Formulação de suplemento'!F8) -> Ocultar | F12: =IF('Formulação de suplemento'!G8=0,"Ocultar",'Formulação de suplemento'!G8) -> Ocultar | H12: =IF('Formulação de suplemento'!H8=0,"Ocultar",'Formulação de suplemento'!H8) -> Ocultar
B13: =IF('Formulação de suplemento'!E9=0,"Ocultar",'Formulação de suplemento'!E9) -> Ocultar | D13: =IF('Formulação de suplemento'!F9=0,"Ocultar",'Formulação de suplemento'!F9) -> Ocultar | F13: =IF('Formulação de suplemento'!G9=0,"Ocultar",'Formulação de suplemento'!G9) -> Ocultar | H13: =IF('Formulação de suplemento'!H9=0,"Ocultar",'Formulação de suplemento'!H9) -> Ocultar
B14: =IF('Formulação de suplemento'!E10=0,"Ocultar",'Formulação de suplemento'!E10) -> Ocultar | D14: =IF('Formulação de suplemento'!F10=0,"Ocultar",'Formulação de suplemento'!F10) -> Ocultar | F14: =IF('Formulação de suplemento'!G10=0,"Ocultar",'Formulação de suplemento'!G10) -> Ocultar | H14: =IF('Formulação de suplemento'!H10=0,"Ocultar",'Formulação de suplemento'!H10) -> Ocultar
B15: =IF('Formulação de suplemento'!E11=0,"Ocultar",'Formulação de suplemento'!E11) -> Ocultar | D15: =IF('Formulação de suplemento'!F11=0,"Ocultar",'Formulação de suplemento'!F11) -> Ocultar | F15: =IF('Formulação de suplemento'!G11=0,"Ocultar",'Formulação de suplemento'!G11) -> Ocultar | H15: =IF('Formulação de suplemento'!H11=0,"Ocultar",'Formulação de suplemento'!H11) -> Ocultar
B16: =IF('Formulação de suplemento'!E12=0,"Ocultar",'Formulação de suplemento'!E12) -> Ocultar | D16: =IF('Formulação de suplemento'!F12=0,"Ocultar",'Formulação de suplemento'!F12) -> Ocultar | F16: =IF('Formulação de suplemento'!G12=0,"Ocultar",'Formulação de suplemento'!G12) -> Ocultar | H16: =IF('Formulação de suplemento'!H12=0,"Ocultar",'Formulação de suplemento'!H12) -> Ocultar
B17: =IF('Formulação de suplemento'!E13=0,"Ocultar",'Formulação de suplemento'!E13) -> Ocultar | D17: =IF('Formulação de suplemento'!F13=0,"Ocultar",'Formulação de suplemento'!F13) -> Ocultar | F17: =IF('Formulação de suplemento'!G13=0,"Ocultar",'Formulação de suplemento'!G13) -> Ocultar | H17: =IF('Formulação de suplemento'!H13=0,"Ocultar",'Formulação de suplemento'!H13) -> Ocultar
B18: =IF('Formulação de suplemento'!E14=0,"Ocultar",'Formulação de suplemento'!E14) -> Ocultar | D18: =IF('Formulação de suplemento'!F14=0,"Ocultar",'Formulação de suplemento'!F14) -> Ocultar | F18: =IF('Formulação de suplemento'!G14=0,"Ocultar",'Formulação de suplemento'!G14) -> Ocultar | H18: =IF('Formulação de suplemento'!H14=0,"Ocultar",'Formulação de suplemento'!H14) -> Ocultar
B19: =IF('Formulação de suplemento'!E15=0,"Ocultar",'Formulação de suplemento'!E15) -> Ocultar | D19: =IF('Formulação de suplemento'!F15=0,"Ocultar",'Formulação de suplemento'!F15) -> Ocultar | F19: =IF('Formulação de suplemento'!G15=0,"Ocultar",'Formulação de suplemento'!G15) -> Ocultar | H19: =IF('Formulação de suplemento'!H15=0,"Ocultar",'Formulação de suplemento'!H15) -> Ocultar
B20: =IF('Formulação de suplemento'!E16=0,"Ocultar",'Formulação de suplemento'!E16) -> Ocultar | D20: =IF('Formulação de suplemento'!F16=0,"Ocultar",'Formulação de suplemento'!F16) -> Ocultar | F20: =IF('Formulação de suplemento'!G16=0,"Ocultar",'Formulação de suplemento'!G16) -> Ocultar | H20: =IF('Formulação de suplemento'!H16=0,"Ocultar",'Formulação de suplemento'!H16) -> Ocultar
B21: =IF('Formulação de suplemento'!E17=0,"Ocultar",'Formulação de suplemento'!E17) -> Ocultar | D21: =IF('Formulação de suplemento'!F17=0,"Ocultar",'Formulação de suplemento'!F17) -> Ocultar | F21: =IF('Formulação de suplemento'!G17=0,"Ocultar",'Formulação de suplemento'!G17) -> Ocultar | H21: =IF('Formulação de suplemento'!H17=0,"Ocultar",'Formulação de suplemento'!H17) -> Ocultar
B22: =IF('Formulação de suplemento'!E18=0,"Ocultar",'Formulação de suplemento'!E18) -> Ocultar | D22: =IF('Formulação de suplemento'!F18=0,"Ocultar",'Formulação de suplemento'!F18) -> Ocultar | F22: =IF('Formulação de suplemento'!G18=0,"Ocultar",'Formulação de suplemento'!G18) -> Ocultar | H22: =IF('Formulação de suplemento'!H18=0,"Ocultar",'Formulação de suplemento'!H18) -> Ocultar
B23: =IF('Formulação de suplemento'!E19=0,"Ocultar",'Formulação de suplemento'!E19) -> Ocultar | D23: =IF('Formulação de suplemento'!F19=0,"Ocultar",'Formulação de suplemento'!F19) -> Ocultar | F23: =IF('Formulação de suplemento'!G19=0,"Ocultar",'Formulação de suplemento'!G19) -> Ocultar | H23: =IF('Formulação de suplemento'!H19=0,"Ocultar",'Formulação de suplemento'!H19) -> Ocultar
B24: ='Formulação de suplemento'!E21 -> Total | D24: ='Formulação de suplemento'!F21 -> 0 | F24: R$/kg ingredientes | H24: ='Formulação de suplemento'!H21 -> 0
F25: ='Formulação de suplemento'!E23 -> R$/kg mão de obra | H25: ='Formulação de suplemento'!F23 -> 0
F26: ='Formulação de suplemento'!G23 -> R$/kg final | H26: ='Formulação de suplemento'!H23 -> 0
B28: ="- O suplemento acima foi formulado para um consumo de "&'Formulação de suplemento'!C19*100&"% do peso vivo dos animais que irão consumir. Como o peso médio informado desses animais é de "&'Formulação de suplemento'!C8&" kg, o consumo diário de cada animal deve ser de "&'Formulação de suplemento'!AB7&" kg por dia. Para saber a quantidade que deve ser colocada no cocho para o lote todo, basta multiplicar esse consumo de kg por dia, pela quantidade de cabeças no lote. Exemplo: se o lote tem "&'Formulação de suplemento'!C20&" cabeças, o consumo seria de: "&'Formulação de suplemento'!C20&" x "&'Formulação de suplemento'!AB7&" = "&'Formulação de suplemento'!AB8&" kg/lote/dia." -> - O suplemento acima foi formulado para um consumo de 0% do peso vivo dos animais que irão consumir. Como o peso médio informado desses animais é de kg, o consumo diário de cada animal deve ser de kg por dia. Para saber a quantidade que deve ser colocada no cocho para o lote todo, basta multiplicar esse consumo de kg por dia, pela quantidade de cabeças no lote. Exemplo: se o lote tem cabeças, o consumo seria de: x = kg/lote/dia.
B29: *o consumo acima deve ir aumentando proporcionalmente conforme os animais ganham peso.
B31: 03 - informações da batida/mistura
B32: A tabela abaixo apresenta a quantidade em quilos de cada ingrediente devem ser colocados na batida/mistura, de acordo com o tamanho da sua batida/mistura.
B34: TABELA DE BATIDA
B35: =B10 -> Ingrediente | E35: 250 | F35: 500 | G35: 750 | H35: 1000 | I35: 1500
B36: =IF(B11=0,"Ocultar",B11) -> Ocultar | E36: =IF(IFERROR($D11*E$35,"Ocultar")=0,"Ocultar",IFERROR($D11*E$35,"Ocultar")) -> Ocultar | F36: =IF(IFERROR($D11*F$35,"Ocultar")=0,"Ocultar",IFERROR($D11*F$35,"Ocultar")) -> Ocultar | G36: =IF(IFERROR($D11*G$35,"Ocultar")=0,"Ocultar",IFERROR($D11*G$35,"Ocultar")) -> Ocultar | H36: =IF(IFERROR($D11*H$35,"Ocultar")=0,"Ocultar",IFERROR($D11*H$35,"Ocultar")) -> Ocultar | I36: =IF(IFERROR($D11*I$35,"Ocultar")=0,"Ocultar",IFERROR($D11*I$35,"Ocultar")) -> Ocultar
B37: =IF(B12=0,"Ocultar",B12) -> Ocultar | E37: =IF(IFERROR($D12*E$35,"Ocultar")=0,"Ocultar",IFERROR($D12*E$35,"Ocultar")) -> Ocultar | F37: =IF(IFERROR($D12*F$35,"Ocultar")=0,"Ocultar",IFERROR($D12*F$35,"Ocultar")) -> Ocultar | G37: =IF(IFERROR($D12*G$35,"Ocultar")=0,"Ocultar",IFERROR($D12*G$35,"Ocultar")) -> Ocultar | H37: =IF(IFERROR($D12*H$35,"Ocultar")=0,"Ocultar",IFERROR($D12*H$35,"Ocultar")) -> Ocultar | I37: =IF(IFERROR($D12*I$35,"Ocultar")=0,"Ocultar",IFERROR($D12*I$35,"Ocultar")) -> Ocultar
B38: =IF(B13=0,"Ocultar",B13) -> Ocultar | E38: =IF(IFERROR($D13*E$35,"Ocultar")=0,"Ocultar",IFERROR($D13*E$35,"Ocultar")) -> Ocultar | F38: =IF(IFERROR($D13*F$35,"Ocultar")=0,"Ocultar",IFERROR($D13*F$35,"Ocultar")) -> Ocultar | G38: =IF(IFERROR($D13*G$35,"Ocultar")=0,"Ocultar",IFERROR($D13*G$35,"Ocultar")) -> Ocultar | H38: =IF(IFERROR($D13*H$35,"Ocultar")=0,"Ocultar",IFERROR($D13*H$35,"Ocultar")) -> Ocultar | I38: =IF(IFERROR($D13*I$35,"Ocultar")=0,"Ocultar",IFERROR($D13*I$35,"Ocultar")) -> Ocultar
B39: =IF(B14=0,"Ocultar",B14) -> Ocultar | E39: =IF(IFERROR($D14*E$35,"Ocultar")=0,"Ocultar",IFERROR($D14*E$35,"Ocultar")) -> Ocultar | F39: =IF(IFERROR($D14*F$35,"Ocultar")=0,"Ocultar",IFERROR($D14*F$35,"Ocultar")) -> Ocultar | G39: =IF(IFERROR($D14*G$35,"Ocultar")=0,"Ocultar",IFERROR($D14*G$35,"Ocultar")) -> Ocultar | H39: =IF(IFERROR($D14*H$35,"Ocultar")=0,"Ocultar",IFERROR($D14*H$35,"Ocultar")) -> Ocultar | I39: =IF(IFERROR($D14*I$35,"Ocultar")=0,"Ocultar",IFERROR($D14*I$35,"Ocultar")) -> Ocultar
B40: =IF(B15=0,"Ocultar",B15) -> Ocultar | E40: =IF(IFERROR($D15*E$35,"Ocultar")=0,"Ocultar",IFERROR($D15*E$35,"Ocultar")) -> Ocultar | F40: =IF(IFERROR($D15*F$35,"Ocultar")=0,"Ocultar",IFERROR($D15*F$35,"Ocultar")) -> Ocultar | G40: =IF(IFERROR($D15*G$35,"Ocultar")=0,"Ocultar",IFERROR($D15*G$35,"Ocultar")) -> Ocultar | H40: =IF(IFERROR($D15*H$35,"Ocultar")=0,"Ocultar",IFERROR($D15*H$35,"Ocultar")) -> Ocultar | I40: =IF(IFERROR($D15*I$35,"Ocultar")=0,"Ocultar",IFERROR($D15*I$35,"Ocultar")) -> Ocultar
B41: =IF(B16=0,"Ocultar",B16) -> Ocultar | E41: =IF(IFERROR($D16*E$35,"Ocultar")=0,"Ocultar",IFERROR($D16*E$35,"Ocultar")) -> Ocultar | F41: =IF(IFERROR($D16*F$35,"Ocultar")=0,"Ocultar",IFERROR($D16*F$35,"Ocultar")) -> Ocultar | G41: =IF(IFERROR($D16*G$35,"Ocultar")=0,"Ocultar",IFERROR($D16*G$35,"Ocultar")) -> Ocultar | H41: =IF(IFERROR($D16*H$35,"Ocultar")=0,"Ocultar",IFERROR($D16*H$35,"Ocultar")) -> Ocultar | I41: =IF(IFERROR($D16*I$35,"Ocultar")=0,"Ocultar",IFERROR($D16*I$35,"Ocultar")) -> Ocultar
B42: =IF(B17=0,"Ocultar",B17) -> Ocultar | E42: =IF(IFERROR($D17*E$35,"Ocultar")=0,"Ocultar",IFERROR($D17*E$35,"Ocultar")) -> Ocultar | F42: =IF(IFERROR($D17*F$35,"Ocultar")=0,"Ocultar",IFERROR($D17*F$35,"Ocultar")) -> Ocultar | G42: =IF(IFERROR($D17*G$35,"Ocultar")=0,"Ocultar",IFERROR($D17*G$35,"Ocultar")) -> Ocultar | H42: =IF(IFERROR($D17*H$35,"Ocultar")=0,"Ocultar",IFERROR($D17*H$35,"Ocultar")) -> Ocultar | I42: =IF(IFERROR($D17*I$35,"Ocultar")=0,"Ocultar",IFERROR($D17*I$35,"Ocultar")) -> Ocultar
B43: =IF(B18=0,"Ocultar",B18) -> Ocultar | E43: =IF(IFERROR($D18*E$35,"Ocultar")=0,"Ocultar",IFERROR($D18*E$35,"Ocultar")) -> Ocultar | F43: =IF(IFERROR($D18*F$35,"Ocultar")=0,"Ocultar",IFERROR($D18*F$35,"Ocultar")) -> Ocultar | G43: =IF(IFERROR($D18*G$35,"Ocultar")=0,"Ocultar",IFERROR($D18*G$35,"Ocultar")) -> Ocultar | H43: =IF(IFERROR($D18*H$35,"Ocultar")=0,"Ocultar",IFERROR($D18*H$35,"Ocultar")) -> Ocultar | I43: =IF(IFERROR($D18*I$35,"Ocultar")=0,"Ocultar",IFERROR($D18*I$35,"Ocultar")) -> Ocultar
B44: =IF(B19=0,"Ocultar",B19) -> Ocultar | E44: =IF(IFERROR($D19*E$35,"Ocultar")=0,"Ocultar",IFERROR($D19*E$35,"Ocultar")) -> Ocultar | F44: =IF(IFERROR($D19*F$35,"Ocultar")=0,"Ocultar",IFERROR($D19*F$35,"Ocultar")) -> Ocultar | G44: =IF(IFERROR($D19*G$35,"Ocultar")=0,"Ocultar",IFERROR($D19*G$35,"Ocultar")) -> Ocultar | H44: =IF(IFERROR($D19*H$35,"Ocultar")=0,"Ocultar",IFERROR($D19*H$35,"Ocultar")) -> Ocultar | I44: =IF(IFERROR($D19*I$35,"Ocultar")=0,"Ocultar",IFERROR($D19*I$35,"Ocultar")) -> Ocultar
B45: =IF(B20=0,"Ocultar",B20) -> Ocultar | E45: =IF(IFERROR($D20*E$35,"Ocultar")=0,"Ocultar",IFERROR($D20*E$35,"Ocultar")) -> Ocultar | F45: =IF(IFERROR($D20*F$35,"Ocultar")=0,"Ocultar",IFERROR($D20*F$35,"Ocultar")) -> Ocultar | G45: =IF(IFERROR($D20*G$35,"Ocultar")=0,"Ocultar",IFERROR($D20*G$35,"Ocultar")) -> Ocultar | H45: =IF(IFERROR($D20*H$35,"Ocultar")=0,"Ocultar",IFERROR($D20*H$35,"Ocultar")) -> Ocultar | I45: =IF(IFERROR($D20*I$35,"Ocultar")=0,"Ocultar",IFERROR($D20*I$35,"Ocultar")) -> Ocultar
B46: =IF(B21=0,"Ocultar",B21) -> Ocultar | E46: =IF(IFERROR($D21*E$35,"Ocultar")=0,"Ocultar",IFERROR($D21*E$35,"Ocultar")) -> Ocultar | F46: =IF(IFERROR($D21*F$35,"Ocultar")=0,"Ocultar",IFERROR($D21*F$35,"Ocultar")) -> Ocultar | G46: =IF(IFERROR($D21*G$35,"Ocultar")=0,"Ocultar",IFERROR($D21*G$35,"Ocultar")) -> Ocultar | H46: =IF(IFERROR($D21*H$35,"Ocultar")=0,"Ocultar",IFERROR($D21*H$35,"Ocultar")) -> Ocultar | I46: =IF(IFERROR($D21*I$35,"Ocultar")=0,"Ocultar",IFERROR($D21*I$35,"Ocultar")) -> Ocultar
B47: =IF(B22=0,"Ocultar",B22) -> Ocultar | E47: =IF(IFERROR($D22*E$35,"Ocultar")=0,"Ocultar",IFERROR($D22*E$35,"Ocultar")) -> Ocultar | F47: =IF(IFERROR($D22*F$35,"Ocultar")=0,"Ocultar",IFERROR($D22*F$35,"Ocultar")) -> Ocultar | G47: =IF(IFERROR($D22*G$35,"Ocultar")=0,"Ocultar",IFERROR($D22*G$35,"Ocultar")) -> Ocultar | H47: =IF(IFERROR($D22*H$35,"Ocultar")=0,"Ocultar",IFERROR($D22*H$35,"Ocultar")) -> Ocultar | I47: =IF(IFERROR($D22*I$35,"Ocultar")=0,"Ocultar",IFERROR($D22*I$35,"Ocultar")) -> Ocultar
B48: =IF(B23=0,"Ocultar",B23) -> Ocultar | E48: =IF(IFERROR($D23*E$35,"Ocultar")=0,"Ocultar",IFERROR($D23*E$35,"Ocultar")) -> Ocultar | F48: =IF(IFERROR($D23*F$35,"Ocultar")=0,"Ocultar",IFERROR($D23*F$35,"Ocultar")) -> Ocultar | G48: =IF(IFERROR($D23*G$35,"Ocultar")=0,"Ocultar",IFERROR($D23*G$35,"Ocultar")) -> Ocultar | H48: =IF(IFERROR($D23*H$35,"Ocultar")=0,"Ocultar",IFERROR($D23*H$35,"Ocultar")) -> Ocultar | I48: =IF(IFERROR($D23*I$35,"Ocultar")=0,"Ocultar",IFERROR($D23*I$35,"Ocultar")) -> Ocultar
B49: =B24 -> Total | E49: =SUM(E36:E48) -> 0 | F49: =SUM(F36:F48) -> 0 | G49: =SUM(G36:G48) -> 0 | H49: =SUM(H36:H48) -> 0 | I49: =SUM(I36:I48) -> 0
B51: 04 - Informações da dieta total
B52: ="A tabela abaixo apresenta a quantidade em quilos de cada ingrediente que cada animal e o lote todo ("&'Formulação de suplemento'!C20&" cabeças) deve ingerir por dia." -> A tabela abaixo apresenta a quantidade em quilos de cada ingrediente que cada animal e o lote todo ( cabeças) deve ingerir por dia.
B54: TABELA DA DIETA TOTAL
B55: Alimentos | E55: Qnt./cab/dia | G55: Qnt./lote/dia
B56: Pasto | E56: =IFERROR('Formulação de suplemento'!S7,"Ocultar") | G56: =IFERROR('Formulação de suplemento'!$C$20*'Relatório de suplementação'!E56,"Ocultar") -> Ocultar
B57: =IF('Formulação de suplemento'!R8="","Ocultar",'Formulação de suplemento'!R8) -> Ocultar | E57: =IFERROR('Formulação de suplemento'!S8,"Ocultar") | G57: =IFERROR('Formulação de suplemento'!$C$20*'Relatório de suplementação'!E57,"Ocultar") -> Ocultar
B58: =IF('Formulação de suplemento'!R9="","Ocultar",'Formulação de suplemento'!R9) -> Ocultar | E58: =IFERROR('Formulação de suplemento'!S9,"Ocultar") | G58: =IFERROR('Formulação de suplemento'!$C$20*'Relatório de suplementação'!E58,"Ocultar") -> Ocultar
B59: =IF('Formulação de suplemento'!R10="","Ocultar",'Formulação de suplemento'!R10) -> Ocultar | E59: =IFERROR('Formulação de suplemento'!S10,"Ocultar") | G59: =IFERROR('Formulação de suplemento'!$C$20*'Relatório de suplementação'!E59,"Ocultar") -> Ocultar
B60: =IF('Formulação de suplemento'!R11="","Ocultar",'Formulação de suplemento'!R11) -> Ocultar | E60: =IFERROR('Formulação de suplemento'!S11,"Ocultar") | G60: =IFERROR('Formulação de suplemento'!$C$20*'Relatório de suplementação'!E60,"Ocultar") -> Ocultar
B61: =IF('Formulação de suplemento'!R12="","Ocultar",'Formulação de suplemento'!R12) -> Ocultar | E61: =IFERROR('Formulação de suplemento'!S12,"Ocultar") | G61: =IFERROR('Formulação de suplemento'!$C$20*'Relatório de suplementação'!E61,"Ocultar") -> Ocultar
B62: =IF('Formulação de suplemento'!R13="","Ocultar",'Formulação de suplemento'!R13) -> Ocultar | E62: =IFERROR('Formulação de suplemento'!S13,"Ocultar") | G62: =IFERROR('Formulação de suplemento'!$C$20*'Relatório de suplementação'!E62,"Ocultar") -> Ocultar
B63: =IF('Formulação de suplemento'!R14="","Ocultar",'Formulação de suplemento'!R14) -> Ocultar | E63: =IFERROR('Formulação de suplemento'!S14,"Ocultar") | G63: =IFERROR('Formulação de suplemento'!$C$20*'Relatório de suplementação'!E63,"Ocultar") -> Ocultar
B64: =IF('Formulação de suplemento'!R15="","Ocultar",'Formulação de suplemento'!R15) -> Ocultar | E64: =IFERROR('Formulação de suplemento'!S15,"Ocultar") | G64: =IFERROR('Formulação de suplemento'!$C$20*'Relatório de suplementação'!E64,"Ocultar") -> Ocultar
B65: =IF('Formulação de suplemento'!R16="","Ocultar",'Formulação de suplemento'!R16) -> Ocultar | E65: =IFERROR('Formulação de suplemento'!S16,"Ocultar") | G65: =IFERROR('Formulação de suplemento'!$C$20*'Relatório de suplementação'!E65,"Ocultar") -> Ocultar
B66: =IF('Formulação de suplemento'!R17="","Ocultar",'Formulação de suplemento'!R17) -> Ocultar | E66: =IFERROR('Formulação de suplemento'!S17,"Ocultar") | G66: =IFERROR('Formulação de suplemento'!$C$20*'Relatório de suplementação'!E66,"Ocultar") -> Ocultar
B67: =IF('Formulação de suplemento'!R18="","Ocultar",'Formulação de suplemento'!R18) -> Ocultar | E67: =IFERROR('Formulação de suplemento'!S18,"Ocultar") | G67: =IFERROR('Formulação de suplemento'!$C$20*'Relatório de suplementação'!E67,"Ocultar") -> Ocultar
B68: =IF('Formulação de suplemento'!R19="","Ocultar",'Formulação de suplemento'!R19) -> Ocultar | E68: =IFERROR('Formulação de suplemento'!S19,"Ocultar") | G68: =IFERROR('Formulação de suplemento'!$C$20*'Relatório de suplementação'!E68,"Ocultar") -> Ocultar
B69: Total | E69: =SUM(E56:F68) -> 0 | G69: =SUM(G56:H68) -> 0
B71: *na prática, sabemos que mensurar o consumo de pasto para animais em pastejo é praticamente impossível. Portanto, a quantidade de capim acima serve como baliza. Caso não tenha essa oferta de pasto na qualidade informada, o GMD alvo não será atingido.
B73: ="- A tabela abaixo mostra o consumo total dos itens da dieta, considerando que o consumo esteja travado no peso médio do lote de "&'Formulação de suplemento'!C8&" kg, com um total de "&'Formulação de suplemento'!C20&" cabeças e que o período de trato é de "&'Formulação de suplemento'!C16&" dias, conforme informado." -> - A tabela abaixo mostra o consumo total dos itens da dieta, considerando que o consumo esteja travado no peso médio do lote de kg, com um total de cabeças e que o período de trato é de dias, conforme informado.
B75: TABELA DE CONSUMO TOTAL
B76: =B55 -> Alimentos | E76: ="Qnt. Consumida em "&'Formulação de suplemento'!C16&" dias" -> Qnt. Consumida em dias
B77: =B56 -> Pasto | E77: =IF(B77="Ocultar","Ocultar", G56*'Formulação de suplemento'!$C$16) -> #VALUE!
B78: =B57 -> Ocultar | E78: =IF(B78="Ocultar","Ocultar", G57*'Formulação de suplemento'!$C$16) -> Ocultar
B79: =B58 -> Ocultar | E79: =IF(B79="Ocultar","Ocultar", G58*'Formulação de suplemento'!$C$16) -> Ocultar
B80: =B59 -> Ocultar | E80: =IF(B80="Ocultar","Ocultar", G59*'Formulação de suplemento'!$C$16) -> Ocultar
B81: =B60 -> Ocultar | E81: =IF(B81="Ocultar","Ocultar", G60*'Formulação de suplemento'!$C$16) -> Ocultar
B82: =B61 -> Ocultar | E82: =IF(B82="Ocultar","Ocultar", G61*'Formulação de suplemento'!$C$16) -> Ocultar
B83: =B62 -> Ocultar | E83: =IF(B83="Ocultar","Ocultar", G62*'Formulação de suplemento'!$C$16) -> Ocultar
B84: =B63 -> Ocultar | E84: =IF(B84="Ocultar","Ocultar", G63*'Formulação de suplemento'!$C$16) -> Ocultar
B85: =B64 -> Ocultar | E85: =IF(B85="Ocultar","Ocultar", G64*'Formulação de suplemento'!$C$16) -> Ocultar
B86: =B65 -> Ocultar | E86: =IF(B86="Ocultar","Ocultar", G65*'Formulação de suplemento'!$C$16) -> Ocultar
B87: =B66 -> Ocultar | E87: =IF(B87="Ocultar","Ocultar", G66*'Formulação de suplemento'!$C$16) -> Ocultar
B88: =B67 -> Ocultar | E88: =IF(B88="Ocultar","Ocultar", G67*'Formulação de suplemento'!$C$16) -> Ocultar
B89: =B68 -> Ocultar | E89: =IF(B89="Ocultar","Ocultar", G68*'Formulação de suplemento'!$C$16) -> Ocultar
B90: =B69 -> Total | E90: =SUM(E77:G89) -> #VALUE!
B92: *como o peso dos animais deve ser corrigido conforme o ganho de peso, essa quantidade pode mudar, servindo apenas com um parâmetro inicial.
B94: ='Formulação de suplemento'!Z5 -> OUTRAS INFORMAÇÕES
B95: ='Formulação de suplemento'!Z6 -> Descrição | C95: ='Formulação de suplemento'!AA6 -> 0 | F95: ='Formulação de suplemento'!AB6 -> Resultado
B96: ='Formulação de suplemento'!Z7 -> Consumo de supl. diário/cab | F96: ='Formulação de suplemento'!AB7
B97: ='Formulação de suplemento'!Z8 -> Consumo de supl. diário no lote | F97: ='Formulação de suplemento'!AB8
B98: ='Formulação de suplemento'!Z9 -> Consumo de supl. total no período | F98: ='Formulação de suplemento'!AB9
B99: ='Formulação de suplemento'!Z10 -> Diária do suplemento (R$/cab) | F99: ='Formulação de suplemento'!AB10
B100: ='Formulação de suplemento'!Z11 -> Diária total (R$/cab) | F100: ='Formulação de suplemento'!AB11
B101: ='Formulação de suplemento'!Z12 -> Desembolso (R$/cab/mês) | F101: ='Formulação de suplemento'!AB12
B102: ='Formulação de suplemento'!Z13 -> GMD de equilíbrio | F102: ='Formulação de suplemento'!AB13
B103: ='Formulação de suplemento'!Z14 -> GMC de equilíbrio | F103: ='Formulação de suplemento'!AB14
B104: ='Formulação de suplemento'!Z15 -> Custo da @ produzia (R$) | F104: ='Formulação de suplemento'!AB15
B105: ='Formulação de suplemento'!Z16 -> Dias para produzir 1@ | F105: ='Formulação de suplemento'!AB16
B106: ='Formulação de suplemento'!Z17 -> R$ produzidos/cab/dia | F106: ='Formulação de suplemento'!AB17 -> 0
B107: ='Formulação de suplemento'!Z18 -> Margem de produção/cab/dia | F107: ='Formulação de suplemento'!AB18
B108: ='Formulação de suplemento'!Z19 -> Margem R$/cab/mês | F108: ='Formulação de suplemento'!AB19

Sheet Resumo suplementação
A1: ESTIMATIVA SUPLEMENTAÇÃO
B3: Preço do kg do seu suplemento | D3: ='Formulação de suplemento'!H23 -> 0 | E3: > informação já puxada da formulação
B4: Consumo em %P.V do suplmento | D4: ='Formulação de suplemento'!C19 -> 0 | E4: > informação já puxada da formulação
B6: Informações dos animais
B7: Peso de entrada | C7: ='Vamos ver'!$C$6 -> 0 | D7: > informação já puxada do "VAMOS VER"
B8: Peso de saída | C8: ='Vamos ver'!$C$8 -> 0 | D8: > informação já puxada do "VAMOS VER"
B9: Dias de utilização | C9: ='Vamos ver'!$C$7 -> 0 | D9: > informação já puxada do "VAMOS VER"
B10: Qnt. Cabeças | C10: ='Vamos ver'!$C$5 -> 0 | D10: > informação já puxada do "VAMOS VER"
B12: Resultados
B13: Variação | C13: Inicial
B14: Consumo estimado | C14: =C10*AVERAGE(C8,C7)*C9*D4 -> 0 | D14: > total em kg que o lote irá consumir na recria
B15: Consumo diário | C15: =IFERROR(C14/Metas!C7,0) -> 0 | D15: > na média, o lote irá consumir isso por dia
B16: R$ estimado | C16: =C14*D3 -> 0 | D16: > valor que você vai gastar com suplementos
B17: R$ por cabeça | C17: =IFERROR(C16/C10,0) -> 0 | D17: > na média, cada cabeça irá gastar isso com supl.
B18: Diária | C18: =IFERROR(C17/C9,0) -> 0 | D18: > na média, essa será a diária gasta com supl.
B21: Ingrediente | D21: % batida | E21: Qnt. total
B22: =IF('Formulação de suplemento'!E7="","",'Formulação de suplemento'!E7) | D22: =IF('Formulação de suplemento'!F7="","",'Formulação de suplemento'!F7) | E22: =IF(D22="","", D22*$C$14)
B23: {=IF('Formulação de suplemento'!E8:E8="","",'Formulação de suplemento'!E8:E8)} | D23: =IF('Formulação de suplemento'!F8="","",'Formulação de suplemento'!F8) | E23: =IF(D23="","", D23*$C$14)
B24: {=IF('Formulação de suplemento'!E9:E9="","",'Formulação de suplemento'!E9:E9)} | D24: =IF('Formulação de suplemento'!F9="","",'Formulação de suplemento'!F9) | E24: =IF(D24="","", D24*$C$14)
B25: {=IF('Formulação de suplemento'!E10:E10="","",'Formulação de suplemento'!E10:E10)} | D25: =IF('Formulação de suplemento'!F10="","",'Formulação de suplemento'!F10) | E25: =IF(D25="","", D25*$C$14)
B26: {=IF('Formulação de suplemento'!E11:E11="","",'Formulação de suplemento'!E11:E11)} | D26: =IF('Formulação de suplemento'!F11="","",'Formulação de suplemento'!F11) | E26: =IF(D26="","", D26*$C$14)
B27: {=IF('Formulação de suplemento'!E13:E13="","",'Formulação de suplemento'!E13:E13)} | D27: =IF('Formulação de suplemento'!F13="","",'Formulação de suplemento'!F13) | E27: =IF(D27="","", D27*$C$14)
B28: {=IF('Formulação de suplemento'!E14:E14="","",'Formulação de suplemento'!E14:E14)} | D28: =IF('Formulação de suplemento'!F14="","",'Formulação de suplemento'!F14) | E28: =IF(D28="","", D28*$C$14)
B29: {=IF('Formulação de suplemento'!E15:E15="","",'Formulação de suplemento'!E15:E15)} | D29: =IF('Formulação de suplemento'!F15="","",'Formulação de suplemento'!F15) | E29: =IF(D29="","", D29*$C$14)
B30: {=IF('Formulação de suplemento'!E16:E16="","",'Formulação de suplemento'!E16:E16)} | D30: =IF('Formulação de suplemento'!F16="","",'Formulação de suplemento'!F16) | E30: =IF(D30="","", D30*$C$14)
B31: {=IF('Formulação de suplemento'!E17:E17="","",'Formulação de suplemento'!E17:E17)} | D31: =IF('Formulação de suplemento'!F17="","",'Formulação de suplemento'!F17) | E31: =IF(D31="","", D31*$C$14)
B32: {=IF('Formulação de suplemento'!E18:E18="","",'Formulação de suplemento'!E18:E18)} | D32: =IF('Formulação de suplemento'!F18="","",'Formulação de suplemento'!F18) | E32: =IF(D32="","", D32*$C$14)
B33: {=IF('Formulação de suplemento'!E19:E19="","",'Formulação de suplemento'!E19:E19)} | D33: =IF('Formulação de suplemento'!F19="","",'Formulação de suplemento'!F19) | E33: =IF(D33="","", D33*$C$14)
B34: {=IF('Formulação de suplemento'!E20:E20="","",'Formulação de suplemento'!E20:E20)} | D34: =IF('Formulação de suplemento'!F20="","",'Formulação de suplemento'!F20) | E34: =IF(D34="","", D34*$C$14)

Sheet Resumo materiais
A1: ESTIMATIVA MATERIAIS
B3: CERCA ELÉTRICA | J3: CERCA CONVENCIONAL | R3: ÁGUA ENCANADA
C5: Estimativa de materiais | F5: Resultados | K5: Estimativa de materiais | N5: Resultados
C6: Comprimento total da cerca (m) | F6: Total de lascas (un.) | G6: =D6/D7 -> #DIV/0! | K6: Comprimento total da cerca (m) | N6: Total de lascas (un.) | O6: =L6/L7 -> #DIV/0!
C7: Espaçamento entre lasca | F7: Total de arame (m) | G7: =D6*D8 -> 0 | K7: Espaçamento entre lasca | N7: Total de arame (m) | O7: =L6*L8 -> 0
C8: Quantidade de fios | F8: Estimativa de palanques | G8: =(D9*2)+IF(D10="Sim",4*D11,0) -> 0 | K8: Quantidade de fios | N8: Estimativa de palanques | O8: =(L9*2)+(O9*2)+IF(L10="Sim",4*L11,0) -> 0
C9: Número de piquetes | F9: Estimativa de porteiras de choque | G9: =D9 -> 0 | K9: Número de piquetes | N9: Estimativa de porteiras | O9: =L9+IF(L10="Sim",2*L11,0) -> 0
C10: Tem praça de alimentação? | F10: Estimativa de porteiras convencional | G10: =IF(D10="Sim",2*D11,0) -> 0 | K10: Tem praça de alimentação?
C11: Quantas praças de alimentação | F11: Potência eletrificador (J) | G11: =ROUNDUP(D6/3000,0) -> 0 | K11: Quantas praças de alimentação
F12: Isolador W (un.) | G12: =G6 -> #DIV/0!
F13: Hastes de aterramento | G13: =IF(G11<=3,3,G11) -> 3
C15: LISTA DE MATERIAIS | K15: LISTA DE MATERIAIS | S15: LISTA DE MATERIAIS
C16: Foto | D16: Item | E16: Preço un. | F16: Qnt. Necessária | G16: R$ Total | K16: Foto | L16: Item | M16: Preço un. | N16: Qnt. Necessária | O16: R$ Total | S16: Foto | T16: Item | U16: Preço un. | V16: Qnt. Necessária | W16: R$ Total
D17: Lasca | F17: =G6 -> #DIV/0! | G17: =F17*E17 -> #DIV/0! | L17: Lasca | N17: =O6 -> #DIV/0! | O17: =N17*M17 -> #DIV/0! | T17: Cano 50mm PN60 | W17: =V17*U17 -> 0
D18: Arame liso | F18: =G7 -> 0 | G18: =F18*E18 -> 0 | L18: Arame liso | N18: =O7 -> 0 | O18: =N18*M18 -> 0 | T18: Bebedouros | W18: =V18*U18 -> 0
D19: Porteira convencional | F19: =G10 -> 0 | G19: =F19*E19 -> 0 | L19: Porteira convencional | N19: =O9 -> 0 | O19: =N19*M19 -> 0 | T19: Boia p/ bebedouros (vazão total) | W19: =V19*U19 -> 0
D20: Palanque | F20: =G8 -> 0 | G20: =F20*E20 -> 0 | L20: Palanque | N20: =O8 -> 0 | O20: =N20*M20 -> 0 | T20: Tê 50mm | W20: =V20*U20 -> 0
D21: Porteira de choque | F21: =G9 -> 0 | G21: =F21*E21 -> 0 | L21: Mão de obra (km) | N21: =L6/1000 -> 0 | O21: =N21*M21 -> 0 | T21: Cotovelo | W21: =V21*U21 -> 0
D22: Castanha | F22: =F20*2.5 -> 0 | G22: =F22*E22 -> 0 | O22: =N22*M22 -> 0 | T22: Registros | W22: =V22*U22 -> 0
D23: Isolador W | F23: =F17 -> #DIV/0! | G23: =F23*E23 -> #DIV/0! | O23: =N23*M23 -> 0 | T23: Cola para canos | W23: =V23*U23 -> 0
D24: ="Eletrificador "&G11&"J" -> Eletrificador 0J | F24: 1 | G24: =F24*E24 -> 0 | O24: =N24*M24 -> 0 | T24: Abertura de valetas | W24: =V24*U24 -> 0
D25: Hastes aterramento | F25: =$G$13 -> 3 | G25: =F25*E25 -> 0 | O25: =N25*M25 -> 0 | T25: Mão de obra | W25: =V25*U25 -> 0
D26: Fio encapado | F26: =(($G$9+$G$10)*5)+($G$8*1) -> 0 | G26: =F26*E26 -> 0 | O26: =N26*M26 -> 0 | T26: Reservatório | W26: =V26*U26 -> 0
D27: Mão de obra (km) | F27: =$D$6/1000 -> 0 | G27: =F27*E27 -> 0 | O27: =N27*M27 -> 0 | W27: =V27*U27 -> 0
G28: =F28*E28 -> 0 | O28: =N28*M28 -> 0 | W28: =V28*U28 -> 0
G29: =F29*E29 -> 0 | O29: =N29*M29 -> 0 | W29: =V29*U29 -> 0
C30: Total | G30: =SUM(G17:G29) -> #DIV/0! | K30: Total | O30: =SUM(O17:O29) -> #DIV/0! | S30: Total | W30: =SUM(W17:W29) -> 0

Sheet Vamos ver
B1: A HORA DO VAMOS VER
E3: AVISOS
B4: SISTEMA
B5: Qnt. Cabeças | E5: =IF(C5<=250,"Quantas cabeças quer rodar nesse sistema? (no máximo 250 por lote).","REDUZIR TAMANHO DO LOTE, SEJA POR REDUÇÃO NA ÁREA OU DIMINUINDO A META DE LOTAÇÃO!") -> Quantas cabeças quer rodar nesse sistema? (no máximo 250 por lote).
B6: Peso de entrada (kg) | E6: Quanto maior esse peso, maior vai ser a lotação média e mais vai gastar com adubação. Porém, um animal que entra leve pode não ter peso de saída adequado no final do período.
B7: Dias de uso | D7: =C7/30 -> 0 | E7: Essa informação foi levantada no diagnóstico. Se não se lembra, volte as aulas.
B8: Peso de saída (kg) | E8: Garanta que com esse peso seu animal tenha mercado para venda, entrada no confinamento ou qualquer outra ação para aliviar pasto. Isso pode ser ajustado com o GMD ou peso de entrada.
B9: GMD (kg/dia) | C9: =IFERROR((C8-C6)/C7,"") | E9: O GMD tem que ser suficiente para que o animal tenha peso de saída no final do periodo. Não recomendo ultrapassar demais 1 kg/dia.
B10: Data de entrada | E10: Tente aproveitar o máximo possível do período de chuva. Para isso, tenha certeza que essa data está próximo ao início da estação de capim verde. Pode iniciar no final da seca se tiver massa.
B11: Data de saída | C11: =IFERROR(((C8-C6)/C9)+C10,"") | E11: A sua região tem que ter chuva suficiente para ter capim verde (ou em transição para a seca) ainda nessa data. Caso não tenha, diminua o período ou aumente o GMD para garantir que o animal saia antes.
B12: Área disponível (ha) | E12: Quantos hectares quer disponibilizar para esse sistema? Caso não saiba, vá ajustando o tamanho da área e o tamanho do lote de acordo com a lotação.
B13: Cabeças/ha | C13: =IFERROR(C5/C12,"")
B14: Lotação entrada (U.A/ha) | C14: =IFERROR((C13*C6)/450,"") | E14: =IF(C14="","",IF(C14>4,"Cuidado, essa lotação de entrada está alta. Para que ela aconteça, o capim já deve estar alto no início do período, ou com uma boa fertilidade inicial.","Ok"))
B15: Lotação média (U.A/ha) | C15: =IFERROR(AVERAGE(C14,C16),"") | E15: =IF(C15="","",IF(C15>ROUND(C7/30.3,0),"Pelo período de chuva disponível em sua região, você não conseguirá intensificar nesse nível. Diminua a meta de produção ou aumente os dias de capim verde (se for possível). Seu limite é de "&ROUND(C7/30.3,0)&" U.A/ha",IF(C15>5,"Cuidado, essa lotação média está alta. Recomendo que seu rotacionado tenha pelo menos 8 piquetes para aproveitar melhor o capim. Você aprenderá isso na aula sobre rotacionado.","Ok")))
B16: Lotação saída (U.A/ha) | C16: =IFERROR((C13*C8)/450,"") | E16: =IF(C16="","",IF(C16>6,"Cuidado, essa lotação de saída está alta. Garanta que seus animais tenham o GMD necessário para sair até final de chuva, já que provavelmente não será possível usar esse pasto na seca","Ok"))
B18: FINANCEIRO
B19: R$/@ compra | E19: Quanto está pagando na @ dos animais que rodarão no sistema
B20: R$/@ venda | E20: Quanto receberá pela @ desse animal na hora da venda? Caso não saiba, use o preço de hoje. Você também pode usar esse campo para simular uma possível queda.
B21: Desembolso (R$/cab/mês) | C21: =IFERROR((C24/C5/(C7/30)),"")
B22: R$ compra do lote | C22: =(C6/30)*C5*C19 -> 0
B23: R$ compra por cabeça | C23: =IFERROR(C22/C5,"")
B24: Custo operacional total | E24: Quanto você vai gastar de operacional, somando adubação e suplementação.
B25: Custo operacional/cab | C25: =IFERROR(C24/C5,0) -> 0 | E25: Esse valor significa quanto você gastará por cabeça para desenvolver ela nesse sistema.
B26: Custo operacional/ha | C26: =IFERROR(C24/C12,0) -> 0 | E26: Esse valor significa quanto você gastará por hectare para desenvolver ela nesse sistema.
B27: Custo total total | C27: =(C22+C24) -> 0
B28: Custo total/cab | C28: =IFERROR(C27/C5,0) -> 0 | E28: Esse valor significa quanto custará seu animal no final do sistema (compra de animais + operacional)
B29: Custo total/ha | C29: =IFERROR(C27/C12,0) -> 0 | E29: Esse valor significa quanto você irá investir por hectare (compra de animais + operacional)
B30: Faturamento total | C30: =(C8/30)*C5*C20 -> 0
B31: Faturamento/cab | C31: =IFERROR(C30/C5,0) -> 0 | E31: Valor que irá receber por cada animal
B32: Faturamento/ha | C32: =IFERROR(C30/C12,0) -> 0 | E32: Valor que irá receber por hectare
B33: Margem total | C33: =C30-C27 -> 0 | E33: Esse valor sobrará no seu bolso no final do período, após a venda dos animais, caso tudo ocorra como planejado.
B34: Margem/cab | C34: =IFERROR(C33/C5,0) -> 0 | E34: Esse valor significa quanto cada cabeça deu de lucro no período.
B35: Margem/ha | C35: =IFERROR(C33/C12,0) -> 0 | E35: Esse valor significa quanto você terá de lucro por hectare. A pecuária média tem apenas R$500-600. Como saber o que é bom pra você? Custo de oportunidade: arrendamento? Juros?
B36: Rentabilidade a.m | C36: =IFERROR((C33/C27)/D7,0) -> 0 | E36: Essa é a rentabilidade AO MÊS do seu sistema. Sempre compare com a taxa de juros atual do Brasil. Se estiver acima da taxa de juros, é porque está sendo um bom negócio.
B38: ZOOTÉCNICO
B39: @ produzidas | C39: =((C8-C6)/30)*C5 -> 0
B40: @ produzidas/hectare | C40: =IFERROR(C39/C12,0) -> 0 | E40: A média brasileira é de 6 @/ha por ano.
B41: Custo da @ produzida | C41: =IFERROR(C24/C39,0) -> 0
B43: INVESTIMENTOS
B44: Cercas
B45: Água
B46: Cochos
B47: Outros
B48: Total | C48: =C47+C46+C45+C44 -> 0
B49: Anos p/ pagar | C49: =IFERROR((C27+C48)/C30,"") | E49: É a quantidade de anos que você precisa para que seu investimento seja "retornado".
E50: Se for próximo ou menor que 1, é porque seu módulo já foi "pago" dentro de 01 ano, o que é ótimo, já que já te permite criar outro módulo com o lucro, ou quitar um financiamento. Entre 1 e 2 é bom. Acima de 2, revise seus custos e produção.
B51: Margem/ha nesse ano | C51: =IFERROR((C33-C48)/C12,"")
B52: Margem/há próx. ano | C52: =C35 -> 0

Sheet Fechamento
B1: A HORA DO VAMOS VER
E3: AVISOS
B4: SISTEMA
B5: Qnt. Cabeças | E5: =IF(C5<=250,"Quantas cabeças quer rodar nesse sistema? (no máximo 250 por lote).","REDUZIR TAMANHO DO LOTE, SEJA POR REDUÇÃO NA ÁREA OU DIMINUINDO A META DE LOTAÇÃO!") -> Quantas cabeças quer rodar nesse sistema? (no máximo 250 por lote).
B6: Peso de entrada (kg) | E6: Quanto maior esse peso, maior vai ser a lotação média e mais vai gastar com adubação. Porém, um animal que entra leve pode não ter peso de saída adequado no final do período.
B7: Dias de uso | D7: =C7/30 -> 0 | E7: Essa informação foi levantada no diagnóstico. Se não se lembra, volte as aulas.
B8: Peso de saída (kg) | E8: Garanta que com esse peso seu animal tenha mercado para venda, entrada no confinamento ou qualquer outra ação para aliviar pasto. Isso pode ser ajustado com o GMD ou peso de entrada.
B9: GMD (kg/dia) | C9: =IFERROR((C8-C6)/C7,"") | E9: O GMD tem que ser suficiente para que o animal tenha peso de saída no final do periodo. Não recomendo ultrapassar demais 1 kg/dia.
B10: Data de entrada | E10: Tente aproveitar o máximo possível do período de chuva. Para isso, tenha certeza que essa data está próximo ao início da estação de capim verde. Pode iniciar no final da seca se tiver massa.
B11: Data de saída | C11: =IFERROR(((C8-C6)/C9)+C10,"") | E11: A sua região tem que ter chuva suficiente para ter capim verde (ou em transição para a seca) ainda nessa data. Caso não tenha, diminua o período ou aumente o GMD para garantir que o animal saia antes.
B12: Área disponível (ha) | E12: Quantos hectares quer disponibilizar para esse sistema? Caso não saiba, vá ajustando o tamanho da área e o tamanho do lote de acordo com a lotação.
B13: Cabeças/ha | C13: =IFERROR(C5/C12,"")
B14: Lotação entrada (U.A/ha) | C14: =IFERROR((C13*C6)/450,"") | E14: =IF(C14="","",IF(C14>4,"Cuidado, essa lotação de entrada está alta. Para que ela aconteça, o capim já deve estar alto no início do período, ou com uma boa fertilidade inicial.","Ok"))
B15: Lotação média (U.A/ha) | C15: =IFERROR(AVERAGE(C14,C16),"") | E15: =IF(C15="","",IF(C15>ROUND(C7/30.3,0),"Pelo período de chuva disponível em sua região, você não conseguirá intensificar nesse nível. Diminua a meta de produção ou aumente os dias de capim verde (se for possível). Seu limite é de "&ROUND(C7/30.3,0)&" U.A/ha",IF(C15>5,"Cuidado, essa lotação média está alta. Recomendo que seu rotacionado tenha pelo menos 8 piquetes para aproveitar melhor o capim. Você aprenderá isso na aula sobre rotacionado.","Ok")))
B16: Lotação saída (U.A/ha) | C16: =IFERROR((C13*C8)/450,"") | E16: =IF(C16="","",IF(C16>6,"Cuidado, essa lotação de saída está alta. Garanta que seus animais tenham o GMD necessário para sair até final de chuva, já que provavelmente não será possível usar esse pasto na seca","Ok"))
B18: FINANCEIRO
B19: R$/@ compra | E19: Quanto está pagando na @ dos animais que rodarão no sistema
B20: R$/@ venda | E20: Quanto receberá pela @ desse animal na hora da venda? Caso não saiba, use o preço de hoje. Você também pode usar esse campo para simular uma possível queda.
B21: Desembolso (R$/cab/mês) | C21: =IFERROR((C24/C5/(C7/30)),"")
B22: R$ compra do lote | C22: =(C6/30)*C5*C19 -> 0
B23: R$ compra por cabeça | C23: =IFERROR(C22/C5,"")
B24: Custo operacional total | E24: Quanto você vai gastar de operacional, somando adubação e suplementação.
B25: Custo operacional/cab | C25: =IFERROR(C24/C5,0) -> 0 | E25: Esse valor significa quanto você gastará por cabeça para desenvolver ela nesse sistema.
B26: Custo operacional/ha | C26: =IFERROR(C24/C12,0) -> 0 | E26: Esse valor significa quanto você gastará por hectare para desenvolver ela nesse sistema.
B27: Custo total total | C27: =(C22+C24) -> 0
B28: Custo total/cab | C28: =IFERROR(C27/C5,0) -> 0 | E28: Esse valor significa quanto custará seu animal no final do sistema (compra de animais + operacional)
B29: Custo total/ha | C29: =IFERROR(C27/C12,0) -> 0 | E29: Esse valor significa quanto você irá investir por hectare (compra de animais + operacional)
B30: Faturamento total | C30: =(C8/30)*C5*C20 -> 0
B31: Faturamento/cab | C31: =IFERROR(C30/C5,0) -> 0 | E31: Valor que irá receber por cada animal
B32: Faturamento/ha | C32: =IFERROR(C30/C12,0) -> 0 | E32: Valor que irá receber por hectare
B33: Margem total | C33: =C30-C27 -> 0 | E33: Esse valor sobrará no seu bolso no final do período, após a venda dos animais, caso tudo ocorra como planejado.
B34: Margem/cab | C34: =IFERROR(C33/C5,0) -> 0 | E34: Esse valor significa quanto cada cabeça deu de lucro no período.
B35: Margem/ha | C35: =IFERROR(C33/C12,0) -> 0 | E35: Esse valor significa quanto você terá de lucro por hectare. A pecuária média tem apenas R$500-600. Como saber o que é bom pra você? Custo de oportunidade: arrendamento? Juros?
B36: Rentabilidade a.m | C36: =IFERROR((C33/C27)/D7,0) -> 0 | E36: Essa é a rentabilidade AO MÊS do seu sistema. Sempre compare com a taxa de juros atual do Brasil. Se estiver acima da taxa de juros, é porque está sendo um bom negócio.
B38: ZOOTÉCNICO
B39: @ produzidas | C39: =((C8-C6)/30)*C5 -> 0
B40: @ produzidas/hectare | C40: =IFERROR(C39/C12,0) -> 0 | E40: A média brasileira é de 6 @/ha por ano.
B41: Custo da @ produzida | C41: =IFERROR(C24/C39,0) -> 0
B43: INVESTIMENTOS
B44: Cercas
B45: Água
B46: Cochos
B47: Outros
B48: Total | C48: =C47+C46+C45+C44 -> 0
B49: Anos p/ pagar | C49: =IFERROR((C27+C48)/C30,"") | E49: É a quantidade de anos que você precisa para que seu investimento seja "retornado".
E50: Se for próximo ou menor que 1, é porque seu módulo já foi "pago" dentro de 01 ano, o que é ótimo, já que já te permite criar outro módulo com o lucro, ou quitar um financiamento. Entre 1 e 2 é bom. Acima de 2, revise seus custos e produção.
B51: Margem/ha nesse ano | C51: =IFERROR((C33-C48)/C12,"")
B52: Margem/há próx. ano | C52: =C35 -> 0

Sheet Acompanhamento de lotação e sup
B1: PLANILHA PARA ACOMPANHAMENTO
A3: Datas | D3: Peso médio por animal | F3: Consumo de suplemento | K3: Lotação no pasto | M3: Produção total
A4: Data inicial | B4: Data final | C4: Dias corridos | D4: Peso incial | E4: Peso final | F4: Consumo médio | I4: Previsto total | J4: Realizado total | K4: Lotação média | L4: Lotação saída | M4: @ produzidas | N4: @ produzidas/ha
A5: =C9 -> 45931 | B5: =VLOOKUP(LARGE(S:S,1),S:U,2,0) -> 46295 | C5: =B5-A5 -> 364 | D5: =F9 -> 200 | E5: =VLOOKUP(LARGE(S:S,1),S:U,3,0) -> 527.6 | F5: =IFERROR(AVERAGE(N9:N374),"") | I5: =SUM(J9:J374) -> 92950.9 | J5: =SUM(K9:K374) -> 0 | K5: =AVERAGE(V9:V374) -> 7.3494949 | L5: =VLOOKUP(LARGE(S:S,1),S:V,4,0) -> 10.658586 | M5: =(((VLOOKUP(LARGE(S9:S373,1),A9:F373,6,0)*(VLOOKUP(LARGE(S9:S373,1),A9:F373,4,0))/30)))-((D9*F9)/30)+SUM(W9:W173) -> 1092 | N5: =M5/AVERAGE(B9:B374) -> 99.272727
A7: Lançamento e acompanhamento | P7: Movimentação
A8: Dias corridos | B8: Área (ha) | C8: Data | D8: Cabeças | E8: GMD (kg/dia) | F8: Peso (kg) | G8: Leitura | I8: Consumo (%P.V) | J8: Consumo (kg) | K8: Realizado (kg) | L8: Lotação (U.A/ha) | M8: Lotação (Cab/ha) | N8: %P.V real | P8: Saída | Q8: Entrada | R8: Validação dia | S8: Dia | T8: Data final | U8: Peso | V8: lotação | W8: Saldo @ | X8: Saída | Y8: Entrada
A9: 1 | B9: 11 | C9: 45931 | D9: 100 | E9: 0.9 | F9: 200 | H9: =I9+G9 -> 0.007 | I9: 0.007 | J9: =H9*F9*D9 -> 140 | L9: =(D9*F9)/450/B9 -> 4.040404 | M9: =D9/B9 -> 9.0909091 | N9: =IFERROR(IF(K9="","",K9/F9/D9),"") | R9: =IF(C9<=TODAY(),"Ok","Não") -> Ok | S9: =IF(R9="Não","",COUNTIFS(R9,"Ok")) -> 1 | T9: =IF(R9="Ok",C9,"") -> 45931 | U9: =IF(R9="Ok",F9,"") -> 200 | V9: =IF(R9="Ok", L9,"") -> 4.040404 | W9: =((-(P9*F9)+(Q9*F9))/30)*-1 -> 0 | X9: =IFERROR((P9*$F9)/30,"") -> 0 | Y9: =IFERROR((Q9*$F9)/30,"") -> 0
A10: =IF(OR(D10=0,D10=""),"",A9+1) -> 2 | B10: =IFERROR(IF(C10="","",B9),"") -> 11 | C10: =IF(OR(D10=0,D10=""),"",C9+1) -> 45932 | D10: =D9-P10+Q10 -> 100 | E10: =IFERROR(IF(C10="","",E9),"") -> 0.9 | F10: =IFERROR(IF(D10="","",IF(C10="","",F9+E9)),"") -> 200.9 | H10: =H9+G10 -> 0.007 | I10: =IFERROR(IF(F10="","",IF(C10="","",I9)),"") -> 0.007 | J10: =H10*F10*D10 -> 140.63 | L10: =IFERROR(IF(D10="","",IF(C10="","",(D10*F10)/450/B10)),"") -> 4.0585859 | M10: =IFERROR(IF(D10="","",IF(C10="","",D10/B10)),"") -> 9.0909091 | N10: =IFERROR(IF(K10="","",K10/F10/D10),"") | R10: =IF(C10<=TODAY(),"Ok","Não") -> Ok | S10: =IF(R10="Não","",COUNTIFS($R$9:R10,"Ok")) -> 2 | T10: =IF(R10="Ok",C10,"") -> 45932 | U10: =IF(R10="Ok",F10,"") -> 200.9 | V10: =IF(R10="Ok", L10,"") -> 4.0585859 | W10: =((-(P10*F10)+(Q10*F10))/30)*-1 -> 0 | X10: =IFERROR((P10*$F10)/30,"") -> 0 | Y10: =IFERROR((Q10*$F10)/30,"") -> 0
A11: =IF(OR(D11=0,D11=""),"",A10+1) -> 3 | B11: =IFERROR(IF(C11="","",B10),"") -> 11 | C11: =IF(OR(D11=0,D11=""),"",C10+1) -> 45933 | D11: =D10-P11+Q11 -> 100 | E11: =IFERROR(IF(C11="","",E10),"") -> 0.9 | F11: =IFERROR(IF(D11="","",IF(C11="","",F10+E10)),"") -> 201.8 | H11: =H10+G11 -> 0.007 | I11: =IFERROR(IF(F11="","",IF(C11="","",I10)),"") -> 0.007 | J11: =H11*F11*D11 -> 141.26 | L11: =IFERROR(IF(D11="","",IF(C11="","",(D11*F11)/450/B11)),"") -> 4.0767677 | M11: =IFERROR(IF(D11="","",IF(C11="","",D11/B11)),"") -> 9.0909091 | N11: =IFERROR(IF(K11="","",K11/F11/D11),"") | R11: =IF(C11<=TODAY(),"Ok","Não") -> Ok | S11: =IF(R11="Não","",COUNTIFS($R$9:R11,"Ok")) -> 3 | T11: =IF(R11="Ok",C11,"") -> 45933 | U11: =IF(R11="Ok",F11,"") -> 201.8 | V11: =IF(R11="Ok", L11,"") -> 4.0767677 | W11: =((-(P11*F11)+(Q11*F11))/30)*-1 -> 0 | X11: =IFERROR((P11*$F11)/30,"") -> 0 | Y11: =IFERROR((Q11*$F11)/30,"") -> 0
A12: =IF(OR(D12=0,D12=""),"",A11+1) -> 4 | B12: =IFERROR(IF(C12="","",B11),"") -> 11 | C12: =IF(OR(D12=0,D12=""),"",C11+1) -> 45934 | D12: =D11-P12+Q12 -> 100 | E12: =IFERROR(IF(C12="","",E11),"") -> 0.9 | F12: =IFERROR(IF(D12="","",IF(C12="","",F11+E11)),"") -> 202.7 | H12: =H11+G12 -> 0.007 | I12: =IFERROR(IF(F12="","",IF(C12="","",I11)),"") -> 0.007 | J12: =H12*F12*D12 -> 141.89 | L12: =IFERROR(IF(D12="","",IF(C12="","",(D12*F12)/450/B12)),"") -> 4.0949495 | M12: =IFERROR(IF(D12="","",IF(C12="","",D12/B12)),"") -> 9.0909091 | N12: =IFERROR(IF(K12="","",K12/F12/D12),"") | R12: =IF(C12<=TODAY(),"Ok","Não") -> Ok | S12: =IF(R12="Não","",COUNTIFS($R$9:R12,"Ok")) -> 4 | T12: =IF(R12="Ok",C12,"") -> 45934 | U12: =IF(R12="Ok",F12,"") -> 202.7 | V12: =IF(R12="Ok", L12,"") -> 4.0949495 | W12: =((-(P12*F12)+(Q12*F12))/30)*-1 -> 0 | X12: =IFERROR((P12*$F12)/30,"") -> 0 | Y12: =IFERROR((Q12*$F12)/30,"") -> 0
A13: =IF(OR(D13=0,D13=""),"",A12+1) -> 5 | B13: =IFERROR(IF(C13="","",B12),"") -> 11 | C13: =IF(OR(D13=0,D13=""),"",C12+1) -> 45935 | D13: =D12-P13+Q13 -> 100 | E13: =IFERROR(IF(C13="","",E12),"") -> 0.9 | F13: =IFERROR(IF(D13="","",IF(C13="","",F12+E12)),"") -> 203.6 | H13: =H12+G13 -> 0.007 | I13: =IFERROR(IF(F13="","",IF(C13="","",I12)),"") -> 0.007 | J13: =H13*F13*D13 -> 142.52 | L13: =IFERROR(IF(D13="","",IF(C13="","",(D13*F13)/450/B13)),"") -> 4.1131313 | M13: =IFERROR(IF(D13="","",IF(C13="","",D13/B13)),"") -> 9.0909091 | N13: =IFERROR(IF(K13="","",K13/F13/D13),"") | R13: =IF(C13<=TODAY(),"Ok","Não") -> Ok | S13: =IF(R13="Não","",COUNTIFS($R$9:R13,"Ok")) -> 5 | T13: =IF(R13="Ok",C13,"") -> 45935 | U13: =IF(R13="Ok",F13,"") -> 203.6 | V13: =IF(R13="Ok", L13,"") -> 4.1131313 | W13: =((-(P13*F13)+(Q13*F13))/30)*-1 -> 0 | X13: =IFERROR((P13*$F13)/30,"") -> 0 | Y13: =IFERROR((Q13*$F13)/30,"") -> 0
A14: =IF(OR(D14=0,D14=""),"",A13+1) -> 6 | B14: =IFERROR(IF(C14="","",B13),"") -> 11 | C14: =IF(OR(D14=0,D14=""),"",C13+1) -> 45936 | D14: =D13-P14+Q14 -> 100 | E14: =IFERROR(IF(C14="","",E13),"") -> 0.9 | F14: =IFERROR(IF(D14="","",IF(C14="","",F13+E13)),"") -> 204.5 | H14: =H13+G14 -> 0.007 | I14: =IFERROR(IF(F14="","",IF(C14="","",I13)),"") -> 0.007 | J14: =H14*F14*D14 -> 143.15 | L14: =IFERROR(IF(D14="","",IF(C14="","",(D14*F14)/450/B14)),"") -> 4.1313131 | M14: =IFERROR(IF(D14="","",IF(C14="","",D14/B14)),"") -> 9.0909091 | N14: =IFERROR(IF(K14="","",K14/F14/D14),"") | R14: =IF(C14<=TODAY(),"Ok","Não") -> Ok | S14: =IF(R14="Não","",COUNTIFS($R$9:R14,"Ok")) -> 6 | T14: =IF(R14="Ok",C14,"") -> 45936 | U14: =IF(R14="Ok",F14,"") -> 204.5 | V14: =IF(R14="Ok", L14,"") -> 4.1313131 | W14: =((-(P14*F14)+(Q14*F14))/30)*-1 -> 0 | X14: =IFERROR((P14*$F14)/30,"") -> 0 | Y14: =IFERROR((Q14*$F14)/30,"") -> 0
A15: =IF(OR(D15=0,D15=""),"",A14+1) -> 7 | B15: =IFERROR(IF(C15="","",B14),"") -> 11 | C15: =IF(OR(D15=0,D15=""),"",C14+1) -> 45937 | D15: =D14-P15+Q15 -> 100 | E15: =IFERROR(IF(C15="","",E14),"") -> 0.9 | F15: =IFERROR(IF(D15="","",IF(C15="","",F14+E14)),"") -> 205.4 | H15: =H14+G15 -> 0.007 | I15: =IFERROR(IF(F15="","",IF(C15="","",I14)),"") -> 0.007 | J15: =H15*F15*D15 -> 143.78 | L15: =IFERROR(IF(D15="","",IF(C15="","",(D15*F15)/450/B15)),"") -> 4.1494949 | M15: =IFERROR(IF(D15="","",IF(C15="","",D15/B15)),"") -> 9.0909091 | N15: =IFERROR(IF(K15="","",K15/F15/D15),"") | R15: =IF(C15<=TODAY(),"Ok","Não") -> Ok | S15: =IF(R15="Não","",COUNTIFS($R$9:R15,"Ok")) -> 7 | T15: =IF(R15="Ok",C15,"") -> 45937 | U15: =IF(R15="Ok",F15,"") -> 205.4 | V15: =IF(R15="Ok", L15,"") -> 4.1494949 | W15: =((-(P15*F15)+(Q15*F15))/30)*-1 -> 0 | X15: =IFERROR((P15*$F15)/30,"") -> 0 | Y15: =IFERROR((Q15*$F15)/30,"") -> 0
A16: =IF(OR(D16=0,D16=""),"",A15+1) -> 8 | B16: =IFERROR(IF(C16="","",B15),"") -> 11 | C16: =IF(OR(D16=0,D16=""),"",C15+1) -> 45938 | D16: =D15-P16+Q16 -> 100 | E16: =IFERROR(IF(C16="","",E15),"") -> 0.9 | F16: =IFERROR(IF(D16="","",IF(C16="","",F15+E15)),"") -> 206.3 | H16: =H15+G16 -> 0.007 | I16: =IFERROR(IF(F16="","",IF(C16="","",I15)),"") -> 0.007 | J16: =H16*F16*D16 -> 144.41 | L16: =IFERROR(IF(D16="","",IF(C16="","",(D16*F16)/450/B16)),"") -> 4.1676768 | M16: =IFERROR(IF(D16="","",IF(C16="","",D16/B16)),"") -> 9.0909091 | N16: =IFERROR(IF(K16="","",K16/F16/D16),"") | R16: =IF(C16<=TODAY(),"Ok","Não") -> Ok | S16: =IF(R16="Não","",COUNTIFS($R$9:R16,"Ok")) -> 8 | T16: =IF(R16="Ok",C16,"") -> 45938 | U16: =IF(R16="Ok",F16,"") -> 206.3 | V16: =IF(R16="Ok", L16,"") -> 4.1676768 | W16: =((-(P16*F16)+(Q16*F16))/30)*-1 -> 0 | X16: =IFERROR((P16*$F16)/30,"") -> 0 | Y16: =IFERROR((Q16*$F16)/30,"") -> 0
A17: =IF(OR(D17=0,D17=""),"",A16+1) -> 9 | B17: =IFERROR(IF(C17="","",B16),"") -> 11 | C17: =IF(OR(D17=0,D17=""),"",C16+1) -> 45939 | D17: =D16-P17+Q17 -> 100 | E17: =IFERROR(IF(C17="","",E16),"") -> 0.9 | F17: =IFERROR(IF(D17="","",IF(C17="","",F16+E16)),"") -> 207.2 | H17: =H16+G17 -> 0.007 | I17: =IFERROR(IF(F17="","",IF(C17="","",I16)),"") -> 0.007 | J17: =H17*F17*D17 -> 145.04 | L17: =IFERROR(IF(D17="","",IF(C17="","",(D17*F17)/450/B17)),"") -> 4.1858586 | M17: =IFERROR(IF(D17="","",IF(C17="","",D17/B17)),"") -> 9.0909091 | N17: =IFERROR(IF(K17="","",K17/F17/D17),"") | R17: =IF(C17<=TODAY(),"Ok","Não") -> Ok | S17: =IF(R17="Não","",COUNTIFS($R$9:R17,"Ok")) -> 9 | T17: =IF(R17="Ok",C17,"") -> 45939 | U17: =IF(R17="Ok",F17,"") -> 207.2 | V17: =IF(R17="Ok", L17,"") -> 4.1858586 | W17: =((-(P17*F17)+(Q17*F17))/30)*-1 -> 0 | X17: =IFERROR((P17*$F17)/30,"") -> 0 | Y17: =IFERROR((Q17*$F17)/30,"") -> 0
A18: =IF(OR(D18=0,D18=""),"",A17+1) -> 10 | B18: =IFERROR(IF(C18="","",B17),"") -> 11 | C18: =IF(OR(D18=0,D18=""),"",C17+1) -> 45940 | D18: =D17-P18+Q18 -> 100 | E18: =IFERROR(IF(C18="","",E17),"") -> 0.9 | F18: =IFERROR(IF(D18="","",IF(C18="","",F17+E17)),"") -> 208.1 | H18: =H17+G18 -> 0.007 | I18: =IFERROR(IF(F18="","",IF(C18="","",I17)),"") -> 0.007 | J18: =H18*F18*D18 -> 145.67 | L18: =IFERROR(IF(D18="","",IF(C18="","",(D18*F18)/450/B18)),"") -> 4.2040404 | M18: =IFERROR(IF(D18="","",IF(C18="","",D18/B18)),"") -> 9.0909091 | N18: =IFERROR(IF(K18="","",K18/F18/D18),"") | R18: =IF(C18<=TODAY(),"Ok","Não") -> Ok | S18: =IF(R18="Não","",COUNTIFS($R$9:R18,"Ok")) -> 10 | T18: =IF(R18="Ok",C18,"") -> 45940 | U18: =IF(R18="Ok",F18,"") -> 208.1 | V18: =IF(R18="Ok", L18,"") -> 4.2040404 | W18: =((-(P18*F18)+(Q18*F18))/30)*-1 -> 0 | X18: =IFERROR((P18*$F18)/30,"") -> 0 | Y18: =IFERROR((Q18*$F18)/30,"") -> 0
A19: =IF(OR(D19=0,D19=""),"",A18+1) -> 11 | B19: =IFERROR(IF(C19="","",B18),"") -> 11 | C19: =IF(OR(D19=0,D19=""),"",C18+1) -> 45941 | D19: =D18-P19+Q19 -> 100 | E19: =IFERROR(IF(C19="","",E18),"") -> 0.9 | F19: =IFERROR(IF(D19="","",IF(C19="","",F18+E18)),"") -> 209 | H19: =H18+G19 -> 0.007 | I19: =IFERROR(IF(F19="","",IF(C19="","",I18)),"") -> 0.007 | J19: =H19*F19*D19 -> 146.3 | L19: =IFERROR(IF(D19="","",IF(C19="","",(D19*F19)/450/B19)),"") -> 4.2222222 | M19: =IFERROR(IF(D19="","",IF(C19="","",D19/B19)),"") -> 9.0909091 | N19: =IFERROR(IF(K19="","",K19/F19/D19),"") | R19: =IF(C19<=TODAY(),"Ok","Não") -> Ok | S19: =IF(R19="Não","",COUNTIFS($R$9:R19,"Ok")) -> 11 | T19: =IF(R19="Ok",C19,"") -> 45941 | U19: =IF(R19="Ok",F19,"") -> 209 | V19: =IF(R19="Ok", L19,"") -> 4.2222222 | W19: =((-(P19*F19)+(Q19*F19))/30)*-1 -> 0 | X19: =IFERROR((P19*$F19)/30,"") -> 0 | Y19: =IFERROR((Q19*$F19)/30,"") -> 0
A20: =IF(OR(D20=0,D20=""),"",A19+1) -> 12 | B20: =IFERROR(IF(C20="","",B19),"") -> 11 | C20: =IF(OR(D20=0,D20=""),"",C19+1) -> 45942 | D20: =D19-P20+Q20 -> 100 | E20: =IFERROR(IF(C20="","",E19),"") -> 0.9 | F20: =IFERROR(IF(D20="","",IF(C20="","",F19+E19)),"") -> 209.9 | H20: =H19+G20 -> 0.007 | I20: =IFERROR(IF(F20="","",IF(C20="","",I19)),"") -> 0.007 | J20: =H20*F20*D20 -> 146.93 | L20: =IFERROR(IF(D20="","",IF(C20="","",(D20*F20)/450/B20)),"") -> 4.240404 | M20: =IFERROR(IF(D20="","",IF(C20="","",D20/B20)),"") -> 9.0909091 | N20: =IFERROR(IF(K20="","",K20/F20/D20),"") | R20: =IF(C20<=TODAY(),"Ok","Não") -> Ok | S20: =IF(R20="Não","",COUNTIFS($R$9:R20,"Ok")) -> 12 | T20: =IF(R20="Ok",C20,"") -> 45942 | U20: =IF(R20="Ok",F20,"") -> 209.9 | V20: =IF(R20="Ok", L20,"") -> 4.240404 | W20: =((-(P20*F20)+(Q20*F20))/30)*-1 -> 0 | X20: =IFERROR((P20*$F20)/30,"") -> 0 | Y20: =IFERROR((Q20*$F20)/30,"") -> 0
A21: =IF(OR(D21=0,D21=""),"",A20+1) -> 13 | B21: =IFERROR(IF(C21="","",B20),"") -> 11 | C21: =IF(OR(D21=0,D21=""),"",C20+1) -> 45943 | D21: =D20-P21+Q21 -> 100 | E21: =IFERROR(IF(C21="","",E20),"") -> 0.9 | F21: =IFERROR(IF(D21="","",IF(C21="","",F20+E20)),"") -> 210.8 | H21: =H20+G21 -> 0.007 | I21: =IFERROR(IF(F21="","",IF(C21="","",I20)),"") -> 0.007 | J21: =H21*F21*D21 -> 147.56 | L21: =IFERROR(IF(D21="","",IF(C21="","",(D21*F21)/450/B21)),"") -> 4.2585859 | M21: =IFERROR(IF(D21="","",IF(C21="","",D21/B21)),"") -> 9.0909091 | N21: =IFERROR(IF(K21="","",K21/F21/D21),"") | R21: =IF(C21<=TODAY(),"Ok","Não") -> Ok | S21: =IF(R21="Não","",COUNTIFS($R$9:R21,"Ok")) -> 13 | T21: =IF(R21="Ok",C21,"") -> 45943 | U21: =IF(R21="Ok",F21,"") -> 210.8 | V21: =IF(R21="Ok", L21,"") -> 4.2585859 | W21: =((-(P21*F21)+(Q21*F21))/30)*-1 -> 0 | X21: =IFERROR((P21*$F21)/30,"") -> 0 | Y21: =IFERROR((Q21*$F21)/30,"") -> 0
... A373: =IF(OR(D373=0,D373=""),"",A372+1) -> 365 | B373: =IFERROR(IF(C373="","",B372),"") -> 11 | C373: =IF(OR(D373=0,D373=""),"",C372+1) -> 46295 | D373: =D372-P373+Q373 -> 100 | E373: =IFERROR(IF(C373="","",E372),"") -> 0.9 | F373: =IFERROR(IF(D373="","",IF(C373="","",F372+E372)),"") -> 527.6 | H373: =H372+G373 -> 0.007 | I373: =IFERROR(IF(F373="","",IF(C373="","",I372)),"") -> 0.007 | J373: =H373*F373*D373 -> 369.32 | L373: =IFERROR(IF(D373="","",IF(C373="","",(D373*F373)/450/B373)),"") -> 10.658586 | M373: =IFERROR(IF(D373="","",IF(C373="","",D373/B373)),"") -> 9.0909091 | N373: =IFERROR(IF(K373="","",K373/F373/D373),"") | R373: =IF(C373<=TODAY(),"Ok","Não") -> Ok | S373: =IF(R373="Não","",COUNTIFS($R$9:R373,"Ok")) -> 365 | T373: =IF(R373="Ok",C373,"") -> 46295 | U373: =IF(R373="Ok",F373,"") -> 527.6 | V373: =IF(R373="Ok", L373,"") -> 10.658586 | W373: =((-(P373*F373)+(Q373*F373))/30)*-1 -> 0 | X373: =IFERROR((P373*$F373)/30,"") -> 0 | Y373: =IFERROR((Q373*$F373)/30,"") -> 0
T374: =IF(R374="Ok",C374,"") | U374: =IF(R374="Ok",F374,"") | V374: =IF(R374="Ok", L374,"") | W374: =((-(P374*F374)+(Q374*F374))/30)*-1 -> 0 | X374: =IFERROR((P374*$F374)/30,"") -> 0 | Y374: =IFERROR((Q374*$F374)/30,"") -> 0
